{
  "type": "Feature",
  "properties": {
    "gn:admin1_code":"81",
    "gn:asciiname":"Kroue Golikro",
    "gn:country_code":"CI",
    "gn:dem":149,
    "gn:feature_class":"P",
    "gn:feature_code":"PPL",
    "gn:name":"Krou\u00e9 Golikro",
    "gn:population":0,
    "gn:timezone":"Africa/Abidjan",
    "iso:country":"CI",
    "name:und_x_variant":[
        "Krou\u00e9 Golikro",
        "Krou\u00e9-Ndolikro"
    ],
    "wof:name":"Kroue Golikro",
    "wof:placetype":"locality"
},
  "geometry": {"coordinates":[-4.67073,7.1636],"type":"Point"}
}