{
  "type": "Feature",
  "properties": {
    "gn:admin1_code":"92",
    "gn:asciiname":"Sorobo",
    "gn:country_code":"CI",
    "gn:dem":422,
    "gn:feature_class":"P",
    "gn:feature_code":"PPL",
    "gn:name":"Sorobo",
    "gn:population":0,
    "gn:timezone":"Africa/Abidjan",
    "iso:country":"CI",
    "name:und_x_variant":[
        "Sogobo",
        "Sorobo"
    ],
    "wof:name":"Sorobo",
    "wof:placetype":"locality"
},
  "geometry": {"coordinates":[-2.9787,8.08276],"type":"Point"}
}