{
  "type": "Feature",
  "properties": {
    "gn:admin1_code":"78",
    "gn:asciiname":"Tyonle",
    "gn:country_code":"CI",
    "gn:dem":270,
    "gn:feature_class":"P",
    "gn:feature_code":"PPL",
    "gn:name":"Tyonl\u00e9",
    "gn:population":0,
    "gn:timezone":"Africa/Abidjan",
    "iso:country":"CI",
    "name:und_x_variant":[
        "Toucl\u00e9",
        "Tiol\u00e9",
        "Tionl\u00e9",
        "Tyonl\u00e9"
    ],
    "wof:name":"Tyonle",
    "wof:placetype":"locality"
},
  "geometry": {"coordinates":[-7.66649,7.0564],"type":"Point"}
}