{
  "type": "Feature",
  "properties": {
    "gn:admin1_code":"77",
    "gn:asciiname":"Minignan",
    "gn:country_code":"CI",
    "gn:dem":408,
    "gn:feature_class":"P",
    "gn:feature_code":"PPLA2",
    "gn:name":"Minignan",
    "gn:population":0,
    "gn:timezone":"Africa/Abidjan",
    "iso:country":"CI",
    "name:und_x_variant":[
        "Maniniam",
        "Maninian",
        "Minignan"
    ],
    "wof:name":"Minignan",
    "wof:placetype":"locality"
},
  "geometry": {"coordinates":[-7.83593,9.99744],"type":"Point"}
}