{
  "type": "Feature",
  "properties": {
    "gn:admin1_code":"77",
    "gn:asciiname":"Minignan",
    "gn:country_code":"CI",
    "gn:dem":408,
    "gn:feature_class":"P",
    "gn:feature_code":"PPLA2",
    "gn:name":"Minignan",
    "gn:population":0,
    "gn:timezone":"Africa/Abidjan",
    "iso:country":"CI",
    "name:fra_x_preferred":[
        "Minignan"
    ],
    "name:ita_x_preferred":[
        "Minignan"
    ],
    "name:msa_x_preferred":[
        "Minignan"
    ],
    "name:ron_x_preferred":[
        "Minignan"
    ],
    "name:spa_x_preferred":[
        "Minignan"
    ],
    "name:und_x_variant":[
        "Maniniam",
        "Maninian",
        "Minignan"
    ],
    "name:urd_x_preferred":[
        "\u0645\u06cc\u0646\u06cc\u06af\u0646\u0627\u0646"
    ],
    "wof:name":"Minignan",
    "wof:placetype":"locality"
},
  "geometry": {"coordinates":[-7.83593,9.99744],"type":"Point"}
}