{
  "type": "Feature",
  "properties": {
    "gn:admin1_code":"78",
    "gn:asciiname":"Zobire",
    "gn:country_code":"CI",
    "gn:dem":271,
    "gn:feature_class":"P",
    "gn:feature_code":"PPL",
    "gn:name":"Zobir\u00e9",
    "gn:population":0,
    "gn:timezone":"Africa/Abidjan",
    "iso:country":"CI",
    "wof:name":"Zobire",
    "wof:placetype":"locality"
},
  "geometry": {"coordinates":[-7.34694,7.00278],"type":"Point"}
}