{
  "type": "Feature",
  "properties": {
    "gn:admin1_code":"90",
    "gn:asciiname":"Segele",
    "gn:country_code":"CI",
    "gn:dem":297,
    "gn:feature_class":"P",
    "gn:feature_code":"PPL",
    "gn:name":"S\u00e9g\u00e9l\u00e9",
    "gn:population":0,
    "gn:timezone":"Africa/Abidjan",
    "iso:country":"CI",
    "name:und_x_variant":[
        "S\u00e9gar\u00e9",
        "S\u00e9gu\u00e9l\u00e9",
        "S\u00e9g\u00e9l\u00e9"
    ],
    "wof:name":"Segele",
    "wof:placetype":"locality"
},
  "geometry": {"coordinates":[-5.26948,8.42822],"type":"Point"}
}