{
  "type": "Feature",
  "properties": {
    "gn:admin1_code":"94",
    "gn:asciiname":"Kouameziankro",
    "gn:country_code":"CI",
    "gn:dem":225,
    "gn:feature_class":"P",
    "gn:feature_code":"PPL",
    "gn:name":"Kouam\u00e9ziankro",
    "gn:population":0,
    "gn:timezone":"Africa/Abidjan",
    "iso:country":"CI",
    "wof:name":"Kouameziankro",
    "wof:placetype":"locality"
},
  "geometry": {"coordinates":[-3.38227,7.02899],"type":"Point"}
}