{
  "type": "Feature",
  "properties": {
    "gn:admin1_code":"93.0",
    "gn:asciiname":"Sonitra",
    "gn:country_code":"CI",
    "gn:dem":81,
    "gn:feature_class":"P",
    "gn:feature_code":"PPL",
    "gn:name":"Sonitra",
    "gn:population":0,
    "gn:timezone":"Africa/Abidjan",
    "iso:country":"CI",
    "wof:name":"Sonitra",
    "wof:placetype":"locality"
},
  "geometry": {"coordinates":[-4.02126,5.37996],"type":"Point"}
}