{
  "type": "Feature",
  "properties": {
    "gn:admin1_code":"81.0",
    "gn:asciiname":"Golikro Nzinoua",
    "gn:country_code":"CI",
    "gn:dem":95,
    "gn:feature_class":"P",
    "gn:feature_code":"PPL",
    "gn:name":"Golikro Nzinoua",
    "gn:population":0,
    "gn:timezone":"Africa/Abidjan",
    "iso:country":"CI",
    "wof:name":"Golikro Nzinoua",
    "wof:placetype":"locality"
},
  "geometry": {"coordinates":[-4.43333,6.91667],"type":"Point"}
}