{
  "type": "Feature",
  "properties": {
    "gn:admin1_code":"90",
    "gn:asciiname":"Tyakwenekaha",
    "gn:country_code":"CI",
    "gn:dem":421,
    "gn:feature_class":"P",
    "gn:feature_code":"PPL",
    "gn:name":"Tyakw\u00e9n\u00e9kaha",
    "gn:population":0,
    "gn:timezone":"Africa/Abidjan",
    "iso:country":"CI",
    "name:und_x_variant":[
        "Tiagouanakaha",
        "Tyakw\u00e9n\u00e9kaha"
    ],
    "wof:name":"Tyakwenekaha",
    "wof:placetype":"locality"
},
  "geometry": {"coordinates":[-5.12805,9.16052],"type":"Point"}
}