{
  "type": "Feature",
  "properties": {
    "gn:admin1_code":"81.0",
    "gn:asciiname":"Broukro",
    "gn:country_code":"CI",
    "gn:dem":203,
    "gn:feature_class":"P",
    "gn:feature_code":"PPL",
    "gn:name":"Broukro",
    "gn:population":0,
    "gn:timezone":"Africa/Abidjan",
    "iso:country":"CI",
    "wof:name":"Broukro",
    "wof:placetype":"locality"
},
  "geometry": {"coordinates":[-4.22305,6.6464],"type":"Point"}
}