{
  "type": "Feature",
  "properties": {
    "gn:admin1_code":"94",
    "gn:asciiname":"Yakasse",
    "gn:country_code":"CI",
    "gn:dem":273,
    "gn:feature_class":"P",
    "gn:feature_code":"PPL",
    "gn:name":"Yakass\u00e9",
    "gn:population":0,
    "gn:timezone":"Africa/Abidjan",
    "iso:country":"CI",
    "wof:name":"Yakasse",
    "wof:placetype":"locality"
},
  "geometry": {"coordinates":[-3.4126,6.9557],"type":"Point"}
}