{
  "type": "Feature",
  "properties": {
    "gn:admin1_code":"97.0",
    "gn:asciiname":"Geso Bondoso",
    "gn:country_code":"CI",
    "gn:dem":332,
    "gn:feature_class":"P",
    "gn:feature_code":"PPL",
    "gn:name":"Geso Bondoso",
    "gn:population":0,
    "gn:timezone":"Africa/Abidjan",
    "iso:country":"CI",
    "name:und_x_variant":[
        "Gu\u00e9sso-Bondosso",
        "Geso Bondoso"
    ],
    "wof:name":"Geso Bondoso",
    "wof:placetype":"locality"
},
  "geometry": {"coordinates":[-5.65933,8.27729],"type":"Point"}
}