{
  "type": "Feature",
  "properties": {
    "gn:admin1_code":"81",
    "gn:asciiname":"Setindra",
    "gn:country_code":"CI",
    "gn:dem":208,
    "gn:feature_class":"P",
    "gn:feature_code":"PPL",
    "gn:name":"S\u00e9tindra",
    "gn:population":0,
    "gn:timezone":"Africa/Abidjan",
    "iso:country":"CI",
    "wof:name":"Setindra",
    "wof:placetype":"locality"
},
  "geometry": {"coordinates":[-3.71667,7.56667],"type":"Point"}
}