{
  "type": "Feature",
  "properties": {
    "gn:admin1_code":"97",
    "gn:asciiname":"Siano",
    "gn:country_code":"CI",
    "gn:dem":468,
    "gn:feature_class":"P",
    "gn:feature_code":"PPL",
    "gn:name":"Siano",
    "gn:population":0,
    "gn:timezone":"Africa/Abidjan",
    "iso:country":"CI",
    "wof:name":"Siano",
    "wof:placetype":"locality"
},
  "geometry": {"coordinates":[-7.61979,8.2639],"type":"Point"}
}