{
  "type": "Feature",
  "properties": {
    "gn:admin1_code":"97",
    "gn:asciiname":"Siano",
    "gn:country_code":"CI",
    "gn:dem":468,
    "gn:feature_class":"P",
    "gn:feature_code":"PPL",
    "gn:name":"Siano",
    "gn:population":0,
    "gn:timezone":"Africa/Abidjan",
    "iso:country":"CI",
    "name:azb_x_preferred":[
        "\u0633\u06cc\u0627\u0646\u0648"
    ],
    "name:bar_x_preferred":[
        "Siano"
    ],
    "name:bul_x_preferred":[
        "\u0421\u0438\u0430\u043d\u043e"
    ],
    "name:ceb_x_preferred":[
        "Siano"
    ],
    "name:deu_x_preferred":[
        "Siano"
    ],
    "name:epo_x_preferred":[
        "Siano"
    ],
    "name:eus_x_preferred":[
        "Siano"
    ],
    "name:fas_x_preferred":[
        "\u0633\u06cc\u0627\u0646\u0648"
    ],
    "name:fra_x_preferred":[
        "Siano"
    ],
    "name:hun_x_preferred":[
        "Siano"
    ],
    "name:hye_x_preferred":[
        "\u054d\u056b\u0561\u0576\u0578"
    ],
    "name:ina_x_preferred":[
        "Siano"
    ],
    "name:ita_x_preferred":[
        "Siano"
    ],
    "name:jpn_x_preferred":[
        "\u30b7\u30a2\u30fc\u30ce"
    ],
    "name:kaz_x_preferred":[
        "\u0421\u0438\u0430\u043d\u043e"
    ],
    "name:kor_x_preferred":[
        "\uc2dc\uc544\ub178"
    ],
    "name:lat_x_preferred":[
        "Sianum"
    ],
    "name:lmo_x_preferred":[
        "Siano"
    ],
    "name:msa_x_preferred":[
        "Siano"
    ],
    "name:nap_x_preferred":[
        "Siano"
    ],
    "name:nld_x_preferred":[
        "Siano"
    ],
    "name:pms_x_preferred":[
        "Siano"
    ],
    "name:pol_x_preferred":[
        "Siano"
    ],
    "name:por_x_preferred":[
        "Siano"
    ],
    "name:ron_x_preferred":[
        "Siano"
    ],
    "name:rus_x_preferred":[
        "\u0421\u0438\u0430\u043d\u043e"
    ],
    "name:scn_x_preferred":[
        "Sianu"
    ],
    "name:spa_x_preferred":[
        "Siano"
    ],
    "name:srp_x_preferred":[
        "\u0421\u0458\u0430\u043d\u043e"
    ],
    "name:tur_x_preferred":[
        "Siano"
    ],
    "name:ukr_x_preferred":[
        "\u0421\u0456\u0430\u043d\u043e"
    ],
    "name:uzb_x_preferred":[
        "Siano"
    ],
    "name:vec_x_preferred":[
        "Siano"
    ],
    "name:vie_x_preferred":[
        "Siano"
    ],
    "name:vol_x_preferred":[
        "Siano"
    ],
    "name:war_x_preferred":[
        "Siano"
    ],
    "wof:name":"Siano",
    "wof:placetype":"locality"
},
  "geometry": {"coordinates":[-7.61979,8.2639],"type":"Point"}
}