{
  "type": "Feature",
  "properties": {
    "gn:admin1_code":"87",
    "gn:asciiname":"Tyemelekaha",
    "gn:country_code":"CI",
    "gn:dem":350,
    "gn:feature_class":"P",
    "gn:feature_code":"PPL",
    "gn:name":"Ty\u00e9m\u00e9l\u00e9kaha",
    "gn:population":0,
    "gn:timezone":"Africa/Abidjan",
    "iso:country":"CI",
    "name:und_x_variant":[
        "Ti\u00e9m\u00e9l\u00e9kaha",
        "Ty\u00e9m\u00e9l\u00e9kaha"
    ],
    "wof:name":"Tyemelekaha",
    "wof:placetype":"locality"
},
  "geometry": {"coordinates":[-5.53333,9.55],"type":"Point"}
}