{
  "type": "Feature",
  "properties": {
    "gn:admin1_code":"92.0",
    "gn:asciiname":"Dinbara",
    "gn:country_code":"CI",
    "gn:dem":315,
    "gn:feature_class":"P",
    "gn:feature_code":"PPL",
    "gn:name":"Dinbara",
    "gn:population":0,
    "gn:timezone":"Africa/Abidjan",
    "iso:country":"CI",
    "wof:name":"Dinbara",
    "wof:placetype":"locality"
},
  "geometry": {"coordinates":[-2.94066,9.5312],"type":"Point"}
}