{
  "type": "Feature",
  "properties": {
    "gn:admin1_code":"81.0",
    "gn:asciiname":"Befelemamoue",
    "gn:country_code":"CI",
    "gn:dem":166,
    "gn:feature_class":"P",
    "gn:feature_code":"PPL",
    "gn:name":"B\u00e9f\u00e9l\u00e9mamou\u00e9",
    "gn:population":0,
    "gn:timezone":"Africa/Abidjan",
    "iso:country":"CI",
    "wof:name":"Befelemamoue",
    "wof:placetype":"locality"
},
  "geometry": {"coordinates":[-4.43333,7.38333],"type":"Point"}
}