{
  "type": "Feature",
  "properties": {
    "gn:admin1_code":"81.0",
    "gn:asciiname":"Ehukro",
    "gn:country_code":"CI",
    "gn:dem":179,
    "gn:feature_class":"P",
    "gn:feature_code":"PPL",
    "gn:name":"Ehukro",
    "gn:population":0,
    "gn:timezone":"Africa/Abidjan",
    "iso:country":"CI",
    "wof:name":"Ehukro",
    "wof:placetype":"locality"
},
  "geometry": {"coordinates":[-4.16864,6.65089],"type":"Point"}
}