{
  "type": "Feature",
  "properties": {
    "gn:admin1_code":"90",
    "gn:asciiname":"Loniene",
    "gn:country_code":"CI",
    "gn:dem":317,
    "gn:feature_class":"P",
    "gn:feature_code":"PPL",
    "gn:name":"Loni\u00e9n\u00e9",
    "gn:population":0,
    "gn:timezone":"Africa/Abidjan",
    "iso:country":"CI",
    "wof:name":"Loniene",
    "wof:placetype":"locality"
},
  "geometry": {"coordinates":[-4.74665,8.31164],"type":"Point"}
}