{
  "type": "Feature",
  "properties": {
    "gn:admin1_code":"81.0",
    "gn:asciiname":"Angban Broukro",
    "gn:country_code":"CI",
    "gn:dem":198,
    "gn:feature_class":"P",
    "gn:feature_code":"PPL",
    "gn:name":"Angban Broukro",
    "gn:population":0,
    "gn:timezone":"Africa/Abidjan",
    "iso:country":"CI",
    "wof:name":"Angban Broukro",
    "wof:placetype":"locality"
},
  "geometry": {"coordinates":[-4.42094,7.81171],"type":"Point"}
}