{
  "type": "Feature",
  "properties": {
    "gn:admin1_code":"90.0",
    "gn:asciiname":"Kanzi",
    "gn:country_code":"CI",
    "gn:dem":200,
    "gn:feature_class":"P",
    "gn:feature_code":"PPL",
    "gn:name":"Kanzi",
    "gn:population":0,
    "gn:timezone":"Africa/Abidjan",
    "iso:country":"CI",
    "name:deu_x_preferred":[
        "Kanzi"
    ],
    "name:fin_x_preferred":[
        "Kanzi"
    ],
    "name:fra_x_preferred":[
        "Kanzi"
    ],
    "name:glg_x_preferred":[
        "Kanzi"
    ],
    "name:ita_x_preferred":[
        "Kanzi"
    ],
    "name:rus_x_preferred":[
        "\u041a\u0430\u043d\u0437\u0438"
    ],
    "name:spa_x_preferred":[
        "Kanzi"
    ],
    "name:ukr_x_preferred":[
        "\u041a\u0430\u043d\u0437\u0456"
    ],
    "name:und_x_variant":[
        "Aou\u00e9-Kansi"
    ],
    "wof:name":"Kanzi",
    "wof:placetype":"locality"
},
  "geometry": {"coordinates":[-5.21263,7.36723],"type":"Point"}
}