{
  "type": "Feature",
  "properties": {
    "gn:admin1_code":"90.0",
    "gn:asciiname":"Kanzi",
    "gn:country_code":"CI",
    "gn:dem":200,
    "gn:feature_class":"P",
    "gn:feature_code":"PPL",
    "gn:name":"Kanzi",
    "gn:population":0,
    "gn:timezone":"Africa/Abidjan",
    "iso:country":"CI",
    "name:und_x_variant":[
        "Aou\u00e9-Kansi"
    ],
    "wof:name":"Kanzi",
    "wof:placetype":"locality"
},
  "geometry": {"coordinates":[-5.21263,7.36723],"type":"Point"}
}