{
  "type": "Feature",
  "properties": {
    "gn:admin1_code":"92",
    "gn:asciiname":"Paimoko",
    "gn:country_code":"CI",
    "gn:dem":345,
    "gn:feature_class":"P",
    "gn:feature_code":"PPL",
    "gn:name":"Pa\u00efmoko",
    "gn:population":0,
    "gn:timezone":"Africa/Abidjan",
    "iso:country":"CI",
    "wof:name":"Paimoko",
    "wof:placetype":"locality"
},
  "geometry": {"coordinates":[-3.42036,9.50207],"type":"Point"}
}