{
  "type": "Feature",
  "properties": {
    "gn:admin1_code":"90",
    "gn:asciiname":"Kwaboukro",
    "gn:country_code":"CI",
    "gn:dem":254,
    "gn:feature_class":"P",
    "gn:feature_code":"PPL",
    "gn:name":"Kwaboukro",
    "gn:population":0,
    "gn:timezone":"Africa/Abidjan",
    "iso:country":"CI",
    "wof:name":"Kwaboukro",
    "wof:placetype":"locality"
},
  "geometry": {"coordinates":[-5.31909,8.0587],"type":"Point"}
}