{
  "type": "Feature",
  "properties": {
    "gn:admin1_code":"81.0",
    "gn:asciiname":"Attien Kouassikro",
    "gn:country_code":"CI",
    "gn:dem":191,
    "gn:feature_class":"P",
    "gn:feature_code":"PPL",
    "gn:name":"Attien Kouassikro",
    "gn:population":0,
    "gn:timezone":"Africa/Abidjan",
    "iso:country":"CI",
    "name:und_x_variant":[
        "Atien-Kouassikro"
    ],
    "wof:name":"Attien Kouassikro",
    "wof:placetype":"locality"
},
  "geometry": {"coordinates":[-4.87179,7.09887],"type":"Point"}
}