{
  "type": "Feature",
  "properties": {
    "gn:admin1_code":"78.0",
    "gn:asciiname":"Bepleu",
    "gn:country_code":"CI",
    "gn:dem":282,
    "gn:feature_class":"P",
    "gn:feature_code":"PPL",
    "gn:name":"Bepleu",
    "gn:population":0,
    "gn:timezone":"Africa/Abidjan",
    "iso:country":"CI",
    "wof:name":"Bepleu",
    "wof:placetype":"locality"
},
  "geometry": {"coordinates":[-8.04618,6.99987],"type":"Point"}
}