{
  "type": "Feature",
  "properties": {
    "gn:admin1_code":"81.0",
    "gn:asciiname":"Diangobo",
    "gn:country_code":"CI",
    "gn:dem":110,
    "gn:feature_class":"P",
    "gn:feature_code":"PPL",
    "gn:name":"Diangobo",
    "gn:population":0,
    "gn:timezone":"Africa/Abidjan",
    "iso:country":"CI",
    "wof:name":"Diangobo",
    "wof:placetype":"locality"
},
  "geometry": {"coordinates":[-4.53664,6.5201],"type":"Point"}
}