{
  "type": "Feature",
  "properties": {
    "gn:admin1_code":"87.0",
    "gn:asciiname":"Fonyege",
    "gn:country_code":"CI",
    "gn:dem":355,
    "gn:feature_class":"P",
    "gn:feature_code":"PPL",
    "gn:name":"Fony\u00e9g\u00e9",
    "gn:population":0,
    "gn:timezone":"Africa/Abidjan",
    "iso:country":"CI",
    "wof:name":"Fonyege",
    "wof:placetype":"locality"
},
  "geometry": {"coordinates":[-5.06247,9.51768],"type":"Point"}
}