{
  "type": "Feature",
  "properties": {
    "gn:admin1_code":"94.0",
    "gn:asciiname":"Hebe",
    "gn:country_code":"CI",
    "gn:dem":9,
    "gn:feature_class":"P",
    "gn:feature_code":"PPL",
    "gn:name":"H\u00e9b\u00e9",
    "gn:population":0,
    "gn:timezone":"Africa/Abidjan",
    "iso:country":"CI",
    "wof:name":"Hebe",
    "wof:placetype":"locality"
},
  "geometry": {"coordinates":[-3.52829,5.20066],"type":"Point"}
}