{
  "type": "Feature",
  "properties": {
    "gn:admin1_code":"94.0",
    "gn:asciiname":"Hebe",
    "gn:country_code":"CI",
    "gn:dem":9,
    "gn:feature_class":"P",
    "gn:feature_code":"PPL",
    "gn:name":"H\u00e9b\u00e9",
    "gn:population":0,
    "gn:timezone":"Africa/Abidjan",
    "iso:country":"CI",
    "name:aze_x_preferred":[
        "Hebe"
    ],
    "name:bos_x_preferred":[
        "Hebe"
    ],
    "name:bre_x_preferred":[
        "Hebe"
    ],
    "name:deu_x_preferred":[
        "Hebe"
    ],
    "name:ell_x_preferred":[
        "\u0389\u03b2\u03b7"
    ],
    "name:fra_x_preferred":[
        "H\u00e9b\u00e9"
    ],
    "name:glg_x_preferred":[
        "Hebe"
    ],
    "name:hrv_x_preferred":[
        "Hebe"
    ],
    "name:lat_x_preferred":[
        "Hebe"
    ],
    "name:ltz_x_preferred":[
        "Hebe"
    ],
    "name:nld_x_preferred":[
        "Hebe"
    ],
    "name:pol_x_preferred":[
        "Hebe"
    ],
    "name:por_x_preferred":[
        "Hebe"
    ],
    "name:ron_x_preferred":[
        "Hebe"
    ],
    "name:slv_x_preferred":[
        "Hebe"
    ],
    "name:spa_x_preferred":[
        "Hebe"
    ],
    "name:swe_x_preferred":[
        "Hebe"
    ],
    "wof:name":"Hebe",
    "wof:placetype":"locality"
},
  "geometry": {"coordinates":[-3.52829,5.20066],"type":"Point"}
}