{
  "type": "Feature",
  "properties": {
    "gn:admin1_code":"92.0",
    "gn:asciiname":"Bokatya",
    "gn:country_code":"CI",
    "gn:dem":264,
    "gn:feature_class":"P",
    "gn:feature_code":"PPL",
    "gn:name":"Bokatya",
    "gn:population":0,
    "gn:timezone":"Africa/Abidjan",
    "iso:country":"CI",
    "wof:name":"Bokatya",
    "wof:placetype":"locality"
},
  "geometry": {"coordinates":[-3.10855,7.80666],"type":"Point"}
}