{
  "type": "Feature",
  "properties": {
    "gn:admin1_code":"78.0",
    "gn:asciiname":"Dohouba",
    "gn:country_code":"CI",
    "gn:dem":389,
    "gn:feature_class":"P",
    "gn:feature_code":"PPL",
    "gn:name":"Dohouba",
    "gn:population":0,
    "gn:timezone":"Africa/Abidjan",
    "iso:country":"CI",
    "name:und_x_variant":[
        "Doba"
    ],
    "wof:name":"Dohouba",
    "wof:placetype":"locality"
},
  "geometry": {"coordinates":[-8.32798,7.34107],"type":"Point"}
}