{
  "type": "Feature",
  "properties": {
    "gn:admin1_code":"82",
    "gn:asciiname":"Pari",
    "gn:country_code":"CI",
    "gn:dem":100,
    "gn:feature_class":"P",
    "gn:feature_code":"PPL",
    "gn:name":"Pari",
    "gn:population":0,
    "gn:timezone":"Africa/Abidjan",
    "iso:country":"CI",
    "wof:name":"Pari",
    "wof:placetype":"locality"
},
  "geometry": {"coordinates":[-4.01531,6.08829],"type":"Point"}
}