{
  "type": "Feature",
  "properties": {
    "gn:admin1_code":"78",
    "gn:asciiname":"Zole",
    "gn:country_code":"CI",
    "gn:dem":356,
    "gn:feature_class":"P",
    "gn:feature_code":"PPL",
    "gn:name":"Zol\u00e9",
    "gn:population":0,
    "gn:timezone":"Africa/Abidjan",
    "iso:country":"CI",
    "name:fra_x_preferred":[
        "Zole"
    ],
    "name:lav_x_preferred":[
        "Zole"
    ],
    "name:rus_x_preferred":[
        "\u0417\u043e\u043b\u0435"
    ],
    "wof:name":"Zole",
    "wof:placetype":"locality"
},
  "geometry": {"coordinates":[-8.17315,7.19893],"type":"Point"}
}