{
  "type": "Feature",
  "properties": {
    "gn:admin1_code":"00",
    "gn:asciiname":"Ngata-Kouadio",
    "gn:country_code":"CI",
    "gn:dem":239,
    "gn:feature_class":"P",
    "gn:feature_code":"PPL",
    "gn:name":"Ngata-Kouadio",
    "gn:population":0,
    "gn:timezone":"Africa/Abidjan",
    "iso:country":"CI",
    "wof:name":"Ngata-Kouadio",
    "wof:placetype":"locality"
},
  "geometry": {"coordinates":[-5.35,7.96667],"type":"Point"}
}