{
  "type": "Feature",
  "properties": {
    "gn:admin1_code":"82.0",
    "gn:asciiname":"Samba Kone",
    "gn:country_code":"CI",
    "gn:dem":55,
    "gn:feature_class":"P",
    "gn:feature_code":"PPL",
    "gn:name":"Samba Kone",
    "gn:population":0,
    "gn:timezone":"Africa/Abidjan",
    "iso:country":"CI",
    "wof:name":"Samba Kone",
    "wof:placetype":"locality"
},
  "geometry": {"coordinates":[-4.22242,5.68999],"type":"Point"}
}