{
  "type": "Feature",
  "properties": {
    "gn:admin1_code":"95.0",
    "gn:asciiname":"Gueboua II",
    "gn:country_code":"CI",
    "gn:dem":217,
    "gn:feature_class":"P",
    "gn:feature_code":"PPL",
    "gn:name":"Gu\u00e9boua II",
    "gn:population":0,
    "gn:timezone":"Africa/Abidjan",
    "iso:country":"CI",
    "wof:name":"Gueboua II",
    "wof:placetype":"locality"
},
  "geometry": {"coordinates":[-5.68917,5.98814],"type":"Point"}
}