{
  "type": "Feature",
  "properties": {
    "gn:admin1_code":"78",
    "gn:asciiname":"Meantouo",
    "gn:country_code":"CI",
    "gn:dem":285,
    "gn:feature_class":"P",
    "gn:feature_code":"PPL",
    "gn:name":"M\u00e9antouo",
    "gn:population":0,
    "gn:timezone":"Africa/Abidjan",
    "iso:country":"CI",
    "name:und_x_variant":[
        "M\u00e9atouo",
        "M\u00e9antouo"
    ],
    "wof:name":"Meantouo",
    "wof:placetype":"locality"
},
  "geometry": {"coordinates":[-8.14283,6.8862],"type":"Point"}
}