{
  "type": "Feature",
  "properties": {
    "gn:admin1_code":"87",
    "gn:asciiname":"Koulobevogo",
    "gn:country_code":"CI",
    "gn:dem":375,
    "gn:feature_class":"P",
    "gn:feature_code":"PPL",
    "gn:name":"Koulob\u00e9vogo",
    "gn:population":0,
    "gn:timezone":"Africa/Abidjan",
    "iso:country":"CI",
    "wof:name":"Koulobevogo",
    "wof:placetype":"locality"
},
  "geometry": {"coordinates":[-5.53945,10.10551],"type":"Point"}
}