{
  "type": "Feature",
  "properties": {
    "gn:admin1_code":"93",
    "gn:asciiname":"Port-Bouet",
    "gn:country_code":"CI",
    "gn:dem":9,
    "gn:feature_class":"P",
    "gn:feature_code":"PPL",
    "gn:name":"Port-Bou\u00ebt",
    "gn:population":0,
    "gn:timezone":"Africa/Abidjan",
    "iso:country":"CI",
    "name:ceb_x_preferred":[
        "Port-Bou\u00ebt"
    ],
    "name:deu_x_preferred":[
        "Port-Bou\u00ebt"
    ],
    "name:fra_x_preferred":[
        "Port-Bou\u00ebt"
    ],
    "name:msa_x_preferred":[
        "Port-Bou\u00ebt"
    ],
    "name:ron_x_preferred":[
        "Port-Bou\u00ebt"
    ],
    "name:swe_x_preferred":[
        "Port-Bou\u00ebt"
    ],
    "name:und_x_variant":[
        "Pickaniny Bassam",
        "Port Buet",
        "Petit Bassam"
    ],
    "wof:name":"Port-Bouet",
    "wof:placetype":"locality"
},
  "geometry": {"coordinates":[-3.96299,5.25677],"type":"Point"}
}