{
  "type": "Feature",
  "properties": {
    "gn:admin1_code":"87",
    "gn:asciiname":"Sienre",
    "gn:country_code":"CI",
    "gn:dem":363,
    "gn:feature_class":"P",
    "gn:feature_code":"PPL",
    "gn:name":"Sienr\u00e9",
    "gn:population":0,
    "gn:timezone":"Africa/Abidjan",
    "iso:country":"CI",
    "name:und_x_variant":[
        "Syenr\u00e9",
        "Sienr\u00e9"
    ],
    "wof:name":"Sienre",
    "wof:placetype":"locality"
},
  "geometry": {"coordinates":[-6.0582,9.81453],"type":"Point"}
}