{
  "type": "Feature",
  "properties": {
    "gn:admin1_code":"92.0",
    "gn:asciiname":"Danbiro",
    "gn:country_code":"CI",
    "gn:dem":364,
    "gn:feature_class":"P",
    "gn:feature_code":"PPL",
    "gn:name":"Danbiro",
    "gn:population":0,
    "gn:timezone":"Africa/Abidjan",
    "iso:country":"CI",
    "wof:name":"Danbiro",
    "wof:placetype":"locality"
},
  "geometry": {"coordinates":[-3.59221,9.60759],"type":"Point"}
}