{
  "type": "Feature",
  "properties": {
    "gn:admin1_code":"90.0",
    "gn:asciiname":"Boukebo",
    "gn:country_code":"CI",
    "gn:dem":314,
    "gn:feature_class":"P",
    "gn:feature_code":"PPL",
    "gn:name":"Bouk\u00e9bo",
    "gn:population":0,
    "gn:timezone":"Africa/Abidjan",
    "iso:country":"CI",
    "wof:name":"Boukebo",
    "wof:placetype":"locality"
},
  "geometry": {"coordinates":[-5.32458,7.75456],"type":"Point"}
}