{
  "type": "Feature",
  "properties": {
    "gn:admin1_code":"90.0",
    "gn:asciiname":"Aouakro",
    "gn:country_code":"CI",
    "gn:dem":207,
    "gn:feature_class":"P",
    "gn:feature_code":"PPL",
    "gn:name":"Aouakro",
    "gn:population":0,
    "gn:timezone":"Africa/Abidjan",
    "iso:country":"CI",
    "name:und_x_variant":[
        "Aoukro"
    ],
    "wof:name":"Aouakro",
    "wof:placetype":"locality"
},
  "geometry": {"coordinates":[-5.41139,7.42249],"type":"Point"}
}