{
  "type": "Feature",
  "properties": {
    "gn:admin1_code":"94",
    "gn:asciiname":"Ahigbe Koffikro",
    "gn:country_code":"CI",
    "gn:dem":68,
    "gn:feature_class":"P",
    "gn:feature_code":"PPL",
    "gn:name":"Ahigb\u00e9 Koffikro",
    "gn:population":0,
    "gn:timezone":"Africa/Abidjan",
    "iso:country":"CI",
    "name:und_x_variant":[
        "Koffikro",
        "Kofikro",
        "Ahigb\u00e9 Koffikro"
    ],
    "wof:name":"Ahigbe Koffikro",
    "wof:placetype":"locality"
},
  "geometry": {"coordinates":[-3.38023,5.40755],"type":"Point"}
}