{
  "type": "Feature",
  "properties": {
    "gn:admin1_code":"77",
    "gn:asciiname":"N'gapye",
    "gn:country_code":"CI",
    "gn:dem":419,
    "gn:feature_class":"P",
    "gn:feature_code":"PPL",
    "gn:name":"N\u2019gapy\u00e9",
    "gn:population":0,
    "gn:timezone":"Africa/Abidjan",
    "iso:country":"CI",
    "name:und_x_variant":[
        "Gapy\u00e9",
        "Ngapi\u00e9",
        "N\u2019gapy\u00e9"
    ],
    "wof:name":"N'gapye",
    "wof:placetype":"locality"
},
  "geometry": {"coordinates":[-6.83151,9.58767],"type":"Point"}
}