{
  "type": "Feature",
  "properties": {
    "gn:admin1_code":"93.0",
    "gn:asciiname":"Atchi",
    "gn:country_code":"CI",
    "gn:dem":82,
    "gn:feature_class":"P",
    "gn:feature_code":"PPL",
    "gn:name":"Atchi",
    "gn:population":0,
    "gn:timezone":"Africa/Abidjan",
    "iso:country":"CI",
    "wof:name":"Atchi",
    "wof:placetype":"locality"
},
  "geometry": {"coordinates":[-4.07868,5.23946],"type":"Point"}
}