{
  "type": "Feature",
  "properties": {
    "gn:admin1_code":"87",
    "gn:asciiname":"Sakouelle",
    "gn:country_code":"CI",
    "gn:dem":378,
    "gn:feature_class":"P",
    "gn:feature_code":"PPL",
    "gn:name":"Sakou\u00e9ll\u00e9",
    "gn:population":0,
    "gn:timezone":"Africa/Abidjan",
    "iso:country":"CI",
    "name:und_x_variant":[
        "Sakpel\u00e9",
        "Sakpou\u00e9l\u00e9",
        "Sakou\u00e9ll\u00e9"
    ],
    "wof:name":"Sakouelle",
    "wof:placetype":"locality"
},
  "geometry": {"coordinates":[-6.01903,9.22978],"type":"Point"}
}