{
  "type": "Feature",
  "properties": {
    "gn:admin1_code":"76",
    "gn:asciiname":"Niahougou",
    "gn:country_code":"CI",
    "gn:dem":100,
    "gn:feature_class":"P",
    "gn:feature_code":"PPL",
    "gn:name":"Niahougou",
    "gn:population":0,
    "gn:timezone":"Africa/Abidjan",
    "iso:country":"CI",
    "wof:name":"Niahougou",
    "wof:placetype":"locality"
},
  "geometry": {"coordinates":[-6.8408,5.25112],"type":"Point"}
}