{
  "type": "Feature",
  "properties": {
    "gn:admin1_code":"82.0",
    "gn:asciiname":"Aoussi Kouachi",
    "gn:country_code":"CI",
    "gn:dem":103,
    "gn:feature_class":"P",
    "gn:feature_code":"PPL",
    "gn:name":"Aoussi Kouachi",
    "gn:population":0,
    "gn:timezone":"Africa/Abidjan",
    "iso:country":"CI",
    "wof:name":"Aoussi Kouachi",
    "wof:placetype":"locality"
},
  "geometry": {"coordinates":[-3.58041,5.81895],"type":"Point"}
}