{
  "type": "Feature",
  "properties": {
    "gn:admin1_code":"76",
    "gn:asciiname":"Ouro",
    "gn:country_code":"CI",
    "gn:dem":9,
    "gn:feature_class":"P",
    "gn:feature_code":"PPL",
    "gn:name":"Ouro",
    "gn:population":0,
    "gn:timezone":"Africa/Abidjan",
    "iso:country":"CI",
    "wof:name":"Ouro",
    "wof:placetype":"locality"
},
  "geometry": {"coordinates":[-6.87837,4.67314],"type":"Point"}
}