{
  "type": "Feature",
  "properties": {
    "gn:admin1_code":"82.0",
    "gn:asciiname":"Andre Soboua",
    "gn:country_code":"CI",
    "gn:dem":60,
    "gn:feature_class":"P",
    "gn:feature_code":"PPL",
    "gn:name":"Andr\u00e9 Soboua",
    "gn:population":0,
    "gn:timezone":"Africa/Abidjan",
    "iso:country":"CI",
    "wof:name":"Andre Soboua",
    "wof:placetype":"locality"
},
  "geometry": {"coordinates":[-4.3765,5.79775],"type":"Point"}
}