{
  "type": "Feature",
  "properties": {
    "gn:admin1_code":"81",
    "gn:asciiname":"Kouandi-Ndakro",
    "gn:country_code":"CI",
    "gn:dem":199,
    "gn:feature_class":"P",
    "gn:feature_code":"PPL",
    "gn:name":"Kouandi-Ndakro",
    "gn:population":0,
    "gn:timezone":"Africa/Abidjan",
    "iso:country":"CI",
    "name:und_x_variant":[
        "Kouandi Dadougou",
        "Kouandi-Ndakro"
    ],
    "wof:name":"Kouandi-Ndakro",
    "wof:placetype":"locality"
},
  "geometry": {"coordinates":[-4.00099,7.57896],"type":"Point"}
}