{
  "type": "Feature",
  "properties": {
    "gn:admin1_code":"98.0",
    "gn:asciiname":"Assanou",
    "gn:country_code":"CI",
    "gn:dem":184,
    "gn:feature_class":"P",
    "gn:feature_code":"PPL",
    "gn:name":"Assanou",
    "gn:population":0,
    "gn:timezone":"Africa/Abidjan",
    "iso:country":"CI",
    "wof:name":"Assanou",
    "wof:placetype":"locality"
},
  "geometry": {"coordinates":[-5.15835,6.99442],"type":"Point"}
}