{
  "type": "Feature",
  "properties": {
    "gn:admin1_code":"97",
    "gn:asciiname":"Logbaso",
    "gn:country_code":"CI",
    "gn:dem":331,
    "gn:feature_class":"P",
    "gn:feature_code":"PPL",
    "gn:name":"Logbaso",
    "gn:population":0,
    "gn:timezone":"Africa/Abidjan",
    "iso:country":"CI",
    "name:und_x_variant":[
        "Lokouasso",
        "Logbaso"
    ],
    "wof:name":"Logbaso",
    "wof:placetype":"locality"
},
  "geometry": {"coordinates":[-5.79078,8.34432],"type":"Point"}
}