{
  "type": "Feature",
  "properties": {
    "gn:admin1_code":"87.0",
    "gn:asciiname":"Katyeri",
    "gn:country_code":"CI",
    "gn:dem":364,
    "gn:feature_class":"P",
    "gn:feature_code":"PPL",
    "gn:name":"Katy\u00e9ri",
    "gn:population":0,
    "gn:timezone":"Africa/Abidjan",
    "iso:country":"CI",
    "name:und_x_variant":[
        "Kati\u00e9ri",
        "Katy\u00e9ri"
    ],
    "wof:name":"Katyeri",
    "wof:placetype":"locality"
},
  "geometry": {"coordinates":[-5.41929,9.54605],"type":"Point"}
}