{
  "type": "Feature",
  "properties": {
    "gn:admin1_code":"90.0",
    "gn:asciiname":"Adioblessou",
    "gn:country_code":"CI",
    "gn:dem":244,
    "gn:feature_class":"P",
    "gn:feature_code":"PPL",
    "gn:name":"Adioblessou",
    "gn:population":0,
    "gn:timezone":"Africa/Abidjan",
    "iso:country":"CI",
    "name:und_x_variant":[
        "Adiolessou"
    ],
    "wof:name":"Adioblessou",
    "wof:placetype":"locality"
},
  "geometry": {"coordinates":[-5.34214,7.49068],"type":"Point"}
}