{
  "type": "Feature",
  "properties": {
    "gn:admin1_code":"78.0",
    "gn:asciiname":"Babli Yaya",
    "gn:country_code":"CI",
    "gn:dem":290,
    "gn:feature_class":"P",
    "gn:feature_code":"PPL",
    "gn:name":"Babli Yaya",
    "gn:population":0,
    "gn:timezone":"Africa/Abidjan",
    "iso:country":"CI",
    "wof:name":"Babli Yaya",
    "wof:placetype":"locality"
},
  "geometry": {"coordinates":[-8.15274,6.61234],"type":"Point"}
}