{
  "type": "Feature",
  "properties": {
    "gn:admin1_code":"78",
    "gn:asciiname":"Sohouba",
    "gn:country_code":"CI",
    "gn:dem":672,
    "gn:feature_class":"P",
    "gn:feature_code":"PPL",
    "gn:name":"Sohouba",
    "gn:population":0,
    "gn:timezone":"Africa/Abidjan",
    "iso:country":"CI",
    "wof:name":"Sohouba",
    "wof:placetype":"locality"
},
  "geometry": {"coordinates":[-7.39401,7.76178],"type":"Point"}
}