{
  "type": "Feature",
  "properties": {
    "gn:admin1_code":"93.0",
    "gn:asciiname":"L'habitat",
    "gn:country_code":"CI",
    "gn:dem":111,
    "gn:feature_class":"P",
    "gn:feature_code":"PPL",
    "gn:name":"L\u2019habitat",
    "gn:population":0,
    "gn:timezone":"Africa/Abidjan",
    "iso:country":"CI",
    "wof:name":"L'habitat",
    "wof:placetype":"locality"
},
  "geometry": {"coordinates":[-4.00951,5.4328],"type":"Point"}
}