{
  "type": "Feature",
  "properties": {
    "gn:admin1_code":"96.0",
    "gn:asciiname":"Bleda",
    "gn:country_code":"CI",
    "gn:dem":269,
    "gn:feature_class":"P",
    "gn:feature_code":"PPL",
    "gn:name":"Bl\u00e8da",
    "gn:population":0,
    "gn:timezone":"Africa/Abidjan",
    "iso:country":"CI",
    "name:aze_x_preferred":[
        "Bleda"
    ],
    "name:bel_x_preferred":[
        "\u0411\u043b\u0435\u0434\u0430"
    ],
    "name:bul_x_preferred":[
        "\u0411\u043b\u0435\u0434\u0430"
    ],
    "name:cat_x_preferred":[
        "Bleda"
    ],
    "name:dan_x_preferred":[
        "Bleda"
    ],
    "name:deu_x_preferred":[
        "Bleda"
    ],
    "name:fra_x_preferred":[
        "Bleda"
    ],
    "name:glg_x_preferred":[
        "Bleda"
    ],
    "name:heb_x_preferred":[
        "\u05d1\u05dc\u05d3\u05d4 \u05d4\u05d4\u05d5\u05e0\u05d9"
    ],
    "name:hun_x_preferred":[
        "Bleda"
    ],
    "name:ita_x_preferred":[
        "Bleda"
    ],
    "name:jpn_x_preferred":[
        "\u30d6\u30ec\u30c0"
    ],
    "name:kaz_x_preferred":[
        "\u0411\u043b\u0435\u0434\u0430"
    ],
    "name:nld_x_preferred":[
        "Bleda"
    ],
    "name:pol_x_preferred":[
        "Bleda"
    ],
    "name:por_x_preferred":[
        "Bleda"
    ],
    "name:rus_x_preferred":[
        "\u0411\u043b\u0435\u0434\u0430"
    ],
    "name:spa_x_preferred":[
        "Bleda"
    ],
    "name:srp_x_preferred":[
        "\u0411\u043b\u0435\u0434\u0430"
    ],
    "name:swe_x_preferred":[
        "Bleda"
    ],
    "name:tgl_x_preferred":[
        "Bleda"
    ],
    "name:tur_x_preferred":[
        "Bleda"
    ],
    "name:ukr_x_preferred":[
        "\u0411\u043b\u0435\u0434\u0430"
    ],
    "name:vie_x_preferred":[
        "Bleda"
    ],
    "name:zho_x_preferred":[
        "\u5e03\u5217\u9054"
    ],
    "wof:name":"Bleda",
    "wof:placetype":"locality"
},
  "geometry": {"coordinates":[-5.93868,7.65638],"type":"Point"}
}