{
  "type": "Feature",
  "properties": {
    "gn:admin1_code":"93.0",
    "gn:asciiname":"Loukoukrou Ekare",
    "gn:country_code":"CI",
    "gn:dem":19,
    "gn:feature_class":"P",
    "gn:feature_code":"PPL",
    "gn:name":"Loukoukrou Ekar\u00e9",
    "gn:population":0,
    "gn:timezone":"Africa/Abidjan",
    "iso:country":"CI",
    "wof:name":"Loukoukrou Ekare",
    "wof:placetype":"locality"
},
  "geometry": {"coordinates":[-4.04573,5.34342],"type":"Point"}
}