{
  "type": "Feature",
  "properties": {
    "gn:admin1_code":"94.0",
    "gn:asciiname":"Kouakoukro la-Limite",
    "gn:country_code":"CI",
    "gn:dem":101,
    "gn:feature_class":"P",
    "gn:feature_code":"PPL",
    "gn:name":"Kouakoukro la-Limit\u00e9",
    "gn:population":0,
    "gn:timezone":"Africa/Abidjan",
    "iso:country":"CI",
    "wof:name":"Kouakoukro la-Limite",
    "wof:placetype":"locality"
},
  "geometry": {"coordinates":[-3.4421,5.35818],"type":"Point"}
}