{
  "type": "Feature",
  "properties": {
    "gn:admin1_code":"87",
    "gn:asciiname":"Ponondougou",
    "gn:country_code":"CI",
    "gn:dem":368,
    "gn:feature_class":"P",
    "gn:feature_code":"PPL",
    "gn:name":"Ponondougou",
    "gn:population":0,
    "gn:timezone":"Africa/Abidjan",
    "iso:country":"CI",
    "name:fra_x_preferred":[
        "Ponondougou"
    ],
    "name:msa_x_preferred":[
        "Ponondougou"
    ],
    "name:und_x_variant":[
        "Panadougou",
        "Ponokaha",
        "Ponadongou",
        "Ponadougou"
    ],
    "wof:name":"Ponondougou",
    "wof:placetype":"locality"
},
  "geometry": {"coordinates":[-6.3236,9.51892],"type":"Point"}
}