{
  "type": "Feature",
  "properties": {
    "gn:admin1_code":"98.0",
    "gn:asciiname":"Gogkro",
    "gn:country_code":"CI",
    "gn:dem":162,
    "gn:feature_class":"P",
    "gn:feature_code":"PPL",
    "gn:name":"Gogkro",
    "gn:population":0,
    "gn:timezone":"Africa/Abidjan",
    "iso:country":"CI",
    "name:und_x_variant":[
        "Gogokro"
    ],
    "wof:name":"Gogkro",
    "wof:placetype":"locality"
},
  "geometry": {"coordinates":[-5.43459,6.82653],"type":"Point"}
}