{
  "type": "Feature",
  "properties": {
    "gn:admin1_code":"90",
    "gn:asciiname":"Kongouekro",
    "gn:country_code":"CI",
    "gn:dem":326,
    "gn:feature_class":"P",
    "gn:feature_code":"PPL",
    "gn:name":"Kongou\u00e9kro",
    "gn:population":0,
    "gn:timezone":"Africa/Abidjan",
    "iso:country":"CI",
    "wof:name":"Kongouekro",
    "wof:placetype":"locality"
},
  "geometry": {"coordinates":[-5.0301,7.76028],"type":"Point"}
}