{
  "type": "Feature",
  "properties": {
    "gn:admin1_code":"87",
    "gn:asciiname":"Korgokaha",
    "gn:country_code":"CI",
    "gn:dem":344,
    "gn:feature_class":"P",
    "gn:feature_code":"PPL",
    "gn:name":"Korgokaha",
    "gn:population":0,
    "gn:timezone":"Africa/Abidjan",
    "iso:country":"CI",
    "wof:name":"Korgokaha",
    "wof:placetype":"locality"
},
  "geometry": {"coordinates":[-5.52854,9.50225],"type":"Point"}
}