{
  "type": "Feature",
  "properties": {
    "gn:admin1_code":"94.0",
    "gn:asciiname":"Borobo",
    "gn:country_code":"CI",
    "gn:dem":171,
    "gn:feature_class":"P",
    "gn:feature_code":"PPL",
    "gn:name":"Borobo",
    "gn:population":0,
    "gn:timezone":"Africa/Abidjan",
    "iso:country":"CI",
    "wof:name":"Borobo",
    "wof:placetype":"locality"
},
  "geometry": {"coordinates":[-3.29209,6.19687],"type":"Point"}
}