{
  "type": "Feature",
  "properties": {
    "gn:admin1_code":"87",
    "gn:asciiname":"Torkaha",
    "gn:country_code":"CI",
    "gn:dem":371,
    "gn:feature_class":"P",
    "gn:feature_code":"PPL",
    "gn:name":"Torkaha",
    "gn:population":0,
    "gn:timezone":"Africa/Abidjan",
    "iso:country":"CI",
    "wof:name":"Torkaha",
    "wof:placetype":"locality"
},
  "geometry": {"coordinates":[-5.68832,9.3917],"type":"Point"}
}