{
  "type": "Feature",
  "properties": {
    "gn:admin1_code":"96",
    "gn:asciiname":"Zikagbeu",
    "gn:country_code":"CI",
    "gn:dem":243,
    "gn:feature_class":"P",
    "gn:feature_code":"PPL",
    "gn:name":"Zikagbeu",
    "gn:population":0,
    "gn:timezone":"Africa/Abidjan",
    "iso:country":"CI",
    "name:und_x_variant":[
        "Zikagbe",
        "Zikabou\u00e9"
    ],
    "wof:name":"Zikagbeu",
    "wof:placetype":"locality"
},
  "geometry": {"coordinates":[-6.89125,6.75608],"type":"Point"}
}