{
  "type": "Feature",
  "properties": {
    "gn:admin1_code":"77",
    "gn:asciiname":"Sandyougouna",
    "gn:country_code":"CI",
    "gn:dem":458,
    "gn:feature_class":"P",
    "gn:feature_code":"PPL",
    "gn:name":"Sandyougouna",
    "gn:population":0,
    "gn:timezone":"Africa/Abidjan",
    "iso:country":"CI",
    "name:und_x_variant":[
        "Sandiougouna",
        "Sandyougouna"
    ],
    "wof:name":"Sandyougouna",
    "wof:placetype":"locality"
},
  "geometry": {"coordinates":[-7.85182,9.61697],"type":"Point"}
}