{
  "type": "Feature",
  "properties": {
    "gn:admin1_code":"92.0",
    "gn:asciiname":"Biribieli",
    "gn:country_code":"CI",
    "gn:dem":322,
    "gn:feature_class":"P",
    "gn:feature_code":"PPL",
    "gn:name":"Biribi\u00e9li",
    "gn:population":0,
    "gn:timezone":"Africa/Abidjan",
    "iso:country":"CI",
    "wof:name":"Biribieli",
    "wof:placetype":"locality"
},
  "geometry": {"coordinates":[-3.33333,9.78333],"type":"Point"}
}