{
  "type": "Feature",
  "properties": {
    "gn:admin1_code":"78",
    "gn:asciiname":"Lotou",
    "gn:country_code":"CI",
    "gn:dem":282,
    "gn:feature_class":"P",
    "gn:feature_code":"PPL",
    "gn:name":"Lotou",
    "gn:population":0,
    "gn:timezone":"Africa/Abidjan",
    "iso:country":"CI",
    "name:und_x_variant":[
        "Latou",
        "Lotou"
    ],
    "wof:name":"Lotou",
    "wof:placetype":"locality"
},
  "geometry": {"coordinates":[-7.12509,7.83899],"type":"Point"}
}