{
  "type": "Feature",
  "properties": {
    "gn:admin1_code":"82",
    "gn:asciiname":"Yassap A",
    "gn:country_code":"CI",
    "gn:dem":59,
    "gn:feature_class":"P",
    "gn:feature_code":"PPL",
    "gn:name":"Yassap A",
    "gn:population":0,
    "gn:timezone":"Africa/Abidjan",
    "iso:country":"CI",
    "name:und_x_variant":[
        "Yassof",
        "Yassap",
        "Yassap A"
    ],
    "wof:name":"Yassap A",
    "wof:placetype":"locality"
},
  "geometry": {"coordinates":[-4.4261,5.41862],"type":"Point"}
}