{
  "type": "Feature",
  "properties": {
    "gn:admin1_code":"82.0",
    "gn:asciiname":"Akre Nguessandon",
    "gn:country_code":"CI",
    "gn:dem":8,
    "gn:feature_class":"P",
    "gn:feature_code":"PPL",
    "gn:name":"Akr\u00e9 Nguessandon",
    "gn:population":0,
    "gn:timezone":"Africa/Abidjan",
    "iso:country":"CI",
    "name:und_x_variant":[
        "Guessandan",
        "Akr\u00e9 Nguessandon"
    ],
    "wof:name":"Akre Nguessandon",
    "wof:placetype":"locality"
},
  "geometry": {"coordinates":[-4.81667,5.15],"type":"Point"}
}