{
  "type": "Feature",
  "properties": {
    "gn:admin1_code":"87",
    "gn:asciiname":"Samorossoba",
    "gn:country_code":"CI",
    "gn:dem":358,
    "gn:feature_class":"P",
    "gn:feature_code":"PPL",
    "gn:name":"Samorossoba",
    "gn:population":0,
    "gn:timezone":"Africa/Abidjan",
    "iso:country":"CI",
    "wof:name":"Samorossoba",
    "wof:placetype":"locality"
},
  "geometry": {"coordinates":[-6.38341,9.8691],"type":"Point"}
}