{
  "type": "Feature",
  "properties": {
    "gn:admin1_code":"81.0",
    "gn:asciiname":"Aerokro",
    "gn:country_code":"CI",
    "gn:dem":119,
    "gn:feature_class":"P",
    "gn:feature_code":"PPL",
    "gn:name":"A\u00e9rokro",
    "gn:population":0,
    "gn:timezone":"Africa/Abidjan",
    "iso:country":"CI",
    "wof:name":"Aerokro",
    "wof:placetype":"locality"
},
  "geometry": {"coordinates":[-4.54879,6.99017],"type":"Point"}
}