{
  "type": "Feature",
  "properties": {
    "gn:admin1_code":"97",
    "gn:asciiname":"Souloumana",
    "gn:country_code":"CI",
    "gn:dem":328,
    "gn:feature_class":"P",
    "gn:feature_code":"PPL",
    "gn:name":"Souloumana",
    "gn:population":0,
    "gn:timezone":"Africa/Abidjan",
    "iso:country":"CI",
    "wof:name":"Souloumana",
    "wof:placetype":"locality"
},
  "geometry": {"coordinates":[-6.39066,8.02068],"type":"Point"}
}