{
  "type": "Feature",
  "properties": {
    "gn:admin1_code":"82.0",
    "gn:asciiname":"Kotou Missako",
    "gn:country_code":"CI",
    "gn:dem":83,
    "gn:feature_class":"P",
    "gn:feature_code":"PPL",
    "gn:name":"Kotou Missako",
    "gn:population":0,
    "gn:timezone":"Africa/Abidjan",
    "iso:country":"CI",
    "wof:name":"Kotou Missako",
    "wof:placetype":"locality"
},
  "geometry": {"coordinates":[-4.27094,5.97668],"type":"Point"}
}