{
  "type": "Feature",
  "properties": {
    "gn:admin1_code":"81",
    "gn:asciiname":"Sakikrou",
    "gn:country_code":"CI",
    "gn:dem":149,
    "gn:feature_class":"P",
    "gn:feature_code":"PPL",
    "gn:name":"Sakikrou",
    "gn:population":0,
    "gn:timezone":"Africa/Abidjan",
    "iso:country":"CI",
    "wof:name":"Sakikrou",
    "wof:placetype":"locality"
},
  "geometry": {"coordinates":[-3.73333,7.68333],"type":"Point"}
}