{
  "type": "Feature",
  "properties": {
    "gn:admin1_code":"82.0",
    "gn:asciiname":"Kouame",
    "gn:country_code":"CI",
    "gn:dem":54,
    "gn:feature_class":"P",
    "gn:feature_code":"PPL",
    "gn:name":"Kouam\u00e9",
    "gn:population":0,
    "gn:timezone":"Africa/Abidjan",
    "iso:country":"CI",
    "wof:name":"Kouame",
    "wof:placetype":"locality"
},
  "geometry": {"coordinates":[-3.74702,5.89456],"type":"Point"}
}