{
  "type": "Feature",
  "properties": {
    "gn:admin1_code":"82",
    "gn:asciiname":"Tiebiessou",
    "gn:country_code":"CI",
    "gn:dem":13,
    "gn:feature_class":"P",
    "gn:feature_code":"PPL",
    "gn:name":"Ti\u00e9bi\u00e9ssou",
    "gn:population":0,
    "gn:timezone":"Africa/Abidjan",
    "iso:country":"CI",
    "name:und_x_variant":[
        "T\u00e9vi\u00e9ssou",
        "Ti\u00e9bi\u00e9ssou"
    ],
    "wof:name":"Tiebiessou",
    "wof:placetype":"locality"
},
  "geometry": {"coordinates":[-4.89056,5.3525],"type":"Point"}
}