{
  "type": "Feature",
  "properties": {
    "gn:admin1_code":"82.0",
    "gn:asciiname":"Ouamni",
    "gn:country_code":"CI",
    "gn:dem":67,
    "gn:feature_class":"P",
    "gn:feature_code":"PPL",
    "gn:name":"Ouamni",
    "gn:population":0,
    "gn:timezone":"Africa/Abidjan",
    "iso:country":"CI",
    "wof:name":"Ouamni",
    "wof:placetype":"locality"
},
  "geometry": {"coordinates":[-4.39128,5.9401],"type":"Point"}
}