{
  "type": "Feature",
  "properties": {
    "gn:admin1_code":"87.0",
    "gn:asciiname":"Baralokaha",
    "gn:country_code":"CI",
    "gn:dem":332,
    "gn:feature_class":"P",
    "gn:feature_code":"PPL",
    "gn:name":"Baralokaha",
    "gn:population":0,
    "gn:timezone":"Africa/Abidjan",
    "iso:country":"CI",
    "wof:name":"Baralokaha",
    "wof:placetype":"locality"
},
  "geometry": {"coordinates":[-5.35253,9.51167],"type":"Point"}
}