{
  "type": "Feature",
  "properties": {
    "gn:admin1_code":"97.0",
    "gn:asciiname":"Gbatosso",
    "gn:country_code":"CI",
    "gn:dem":369,
    "gn:feature_class":"P",
    "gn:feature_code":"PPL",
    "gn:name":"Gbatosso",
    "gn:population":0,
    "gn:timezone":"Africa/Abidjan",
    "iso:country":"CI",
    "name:und_x_variant":[
        "Gbatoso",
        "Gbatasso",
        "Gbatosso"
    ],
    "wof:name":"Gbatosso",
    "wof:placetype":"locality"
},
  "geometry": {"coordinates":[-6.27608,8.97252],"type":"Point"}
}