{
  "type": "Feature",
  "properties": {
    "gn:admin1_code":"87",
    "gn:asciiname":"Tyongofolokaha",
    "gn:country_code":"CI",
    "gn:dem":332,
    "gn:feature_class":"P",
    "gn:feature_code":"PPL",
    "gn:name":"Tyongofolokaha",
    "gn:population":0,
    "gn:timezone":"Africa/Abidjan",
    "iso:country":"CI",
    "name:und_x_variant":[
        "Tiongofolokaha",
        "Tyongofolokaha"
    ],
    "wof:name":"Tyongofolokaha",
    "wof:placetype":"locality"
},
  "geometry": {"coordinates":[-5.42972,9.63337],"type":"Point"}
}