{
  "type": "Feature",
  "properties": {
    "gn:admin1_code":"78",
    "gn:asciiname":"Kouepleu",
    "gn:country_code":"CI",
    "gn:dem":358,
    "gn:feature_class":"P",
    "gn:feature_code":"PPL",
    "gn:name":"Kou\u00e9pleu",
    "gn:population":0,
    "gn:timezone":"Africa/Abidjan",
    "iso:country":"CI",
    "wof:name":"Kouepleu",
    "wof:placetype":"locality"
},
  "geometry": {"coordinates":[-7.93696,7.20336],"type":"Point"}
}