{
  "type": "Feature",
  "properties": {
    "gn:admin1_code":"77",
    "gn:asciiname":"Tchigouela",
    "gn:country_code":"CI",
    "gn:dem":449,
    "gn:feature_class":"P",
    "gn:feature_code":"PPL",
    "gn:name":"Tchigou\u00e9la",
    "gn:population":0,
    "gn:timezone":"Africa/Abidjan",
    "iso:country":"CI",
    "wof:name":"Tchigouela",
    "wof:placetype":"locality"
},
  "geometry": {"coordinates":[-7.69015,9.14193],"type":"Point"}
}