{
  "type": "Feature",
  "properties": {
    "gn:admin1_code":"81.0",
    "gn:asciiname":"Adroukro",
    "gn:country_code":"CI",
    "gn:dem":266,
    "gn:feature_class":"P",
    "gn:feature_code":"PPL",
    "gn:name":"Adroukro",
    "gn:population":0,
    "gn:timezone":"Africa/Abidjan",
    "iso:country":"CI",
    "wof:name":"Adroukro",
    "wof:placetype":"locality"
},
  "geometry": {"coordinates":[-3.93789,7.52348],"type":"Point"}
}