{
  "type": "Feature",
  "properties": {
    "gn:admin1_code":"78",
    "gn:asciiname":"Zangagleu",
    "gn:country_code":"CI",
    "gn:dem":382,
    "gn:feature_class":"P",
    "gn:feature_code":"PPL",
    "gn:name":"Zangagleu",
    "gn:population":0,
    "gn:timezone":"Africa/Abidjan",
    "iso:country":"CI",
    "wof:name":"Zangagleu",
    "wof:placetype":"locality"
},
  "geometry": {"coordinates":[-8.30066,7.45466],"type":"Point"}
}