{
  "type": "Feature",
  "properties": {
    "gn:admin1_code":"92.0",
    "gn:asciiname":"Bassampounou",
    "gn:country_code":"CI",
    "gn:dem":233,
    "gn:feature_class":"P",
    "gn:feature_code":"PPL",
    "gn:name":"Bassampounou",
    "gn:population":0,
    "gn:timezone":"Africa/Abidjan",
    "iso:country":"CI",
    "wof:name":"Bassampounou",
    "wof:placetype":"locality"
},
  "geometry": {"coordinates":[-3.33414,7.82949],"type":"Point"}
}