{
  "type": "Feature",
  "properties": {
    "gn:admin1_code":"90",
    "gn:asciiname":"Kondorobo",
    "gn:country_code":"CI",
    "gn:dem":292,
    "gn:feature_class":"P",
    "gn:feature_code":"PPL",
    "gn:name":"Kondorobo",
    "gn:population":0,
    "gn:timezone":"Africa/Abidjan",
    "iso:country":"CI",
    "wof:name":"Kondorobo",
    "wof:placetype":"locality"
},
  "geometry": {"coordinates":[-5.74638,7.83335],"type":"Point"}
}