{
  "type": "Feature",
  "properties": {
    "gn:admin1_code":"76",
    "gn:asciiname":"Koreguhe",
    "gn:country_code":"CI",
    "gn:dem":190,
    "gn:feature_class":"P",
    "gn:feature_code":"PPL",
    "gn:name":"Kor\u00e9guh\u00e9",
    "gn:population":0,
    "gn:timezone":"Africa/Abidjan",
    "iso:country":"CI",
    "name:und_x_variant":[
        "Kor\u00e9guh\u00e9",
        "Kor\u00e9yo"
    ],
    "wof:name":"Koreguhe",
    "wof:placetype":"locality"
},
  "geometry": {"coordinates":[-6.65891,6.18859],"type":"Point"}
}