{
  "type": "Feature",
  "properties": {
    "gn:admin1_code":"81.0",
    "gn:asciiname":"Bofrebo",
    "gn:country_code":"CI",
    "gn:dem":91,
    "gn:feature_class":"P",
    "gn:feature_code":"PPL",
    "gn:name":"Bofr\u00e9bo",
    "gn:population":0,
    "gn:timezone":"Africa/Abidjan",
    "iso:country":"CI",
    "wof:name":"Bofrebo",
    "wof:placetype":"locality"
},
  "geometry": {"coordinates":[-4.81635,6.60946],"type":"Point"}
}