{
  "type": "Feature",
  "properties": {
    "gn:admin1_code":"82.0",
    "gn:asciiname":"Niamde Niams",
    "gn:country_code":"CI",
    "gn:dem":72,
    "gn:feature_class":"P",
    "gn:feature_code":"PPL",
    "gn:name":"Niamd\u00e9 Niams",
    "gn:population":0,
    "gn:timezone":"Africa/Abidjan",
    "iso:country":"CI",
    "wof:name":"Niamde Niams",
    "wof:placetype":"locality"
},
  "geometry": {"coordinates":[-4.50034,5.92935],"type":"Point"}
}