{
  "type": "Feature",
  "properties": {
    "gn:admin1_code":"81.0",
    "gn:asciiname":"Kra Krakro",
    "gn:country_code":"CI",
    "gn:dem":194,
    "gn:feature_class":"P",
    "gn:feature_code":"PPL",
    "gn:name":"Kra Krakro",
    "gn:population":0,
    "gn:timezone":"Africa/Abidjan",
    "iso:country":"CI",
    "name:und_x_variant":[
        "Karakor\u00e9"
    ],
    "wof:name":"Kra Krakro",
    "wof:placetype":"locality"
},
  "geometry": {"coordinates":[-4.46721,7.68559],"type":"Point"}
}