{
  "type": "Feature",
  "properties": {
    "gn:admin1_code":"76.0",
    "gn:asciiname":"Gnankoladji",
    "gn:country_code":"CI",
    "gn:dem":116,
    "gn:feature_class":"P",
    "gn:feature_code":"PPL",
    "gn:name":"Gnankoladji",
    "gn:population":0,
    "gn:timezone":"Africa/Abidjan",
    "iso:country":"CI",
    "name:und_x_variant":[
        "Gniankoladji",
        "Gnankoladji"
    ],
    "wof:name":"Gnankoladji",
    "wof:placetype":"locality"
},
  "geometry": {"coordinates":[-6.61377,5.69812],"type":"Point"}
}