{
  "type": "Feature",
  "properties": {
    "gn:admin1_code":"95",
    "gn:asciiname":"Kokoboue",
    "gn:country_code":"CI",
    "gn:dem":226,
    "gn:feature_class":"P",
    "gn:feature_code":"PPL",
    "gn:name":"Kokobou\u00e9",
    "gn:population":0,
    "gn:timezone":"Africa/Abidjan",
    "iso:country":"CI",
    "wof:name":"Kokoboue",
    "wof:placetype":"locality"
},
  "geometry": {"coordinates":[-5.75725,5.75026],"type":"Point"}
}