{
  "type": "Feature",
  "properties": {
    "gn:admin1_code":"97",
    "gn:asciiname":"Sarakabougou",
    "gn:country_code":"CI",
    "gn:dem":316,
    "gn:feature_class":"P",
    "gn:feature_code":"PPL",
    "gn:name":"Sarakabougou",
    "gn:population":0,
    "gn:timezone":"Africa/Abidjan",
    "iso:country":"CI",
    "wof:name":"Sarakabougou",
    "wof:placetype":"locality"
},
  "geometry": {"coordinates":[-7.14832,8.16104],"type":"Point"}
}