{
  "type": "Feature",
  "properties": {
    "gn:admin1_code":"90",
    "gn:asciiname":"Kouadiokro",
    "gn:country_code":"CI",
    "gn:dem":270,
    "gn:feature_class":"P",
    "gn:feature_code":"PPL",
    "gn:name":"Kouadiokro",
    "gn:population":0,
    "gn:timezone":"Africa/Abidjan",
    "iso:country":"CI",
    "name:fra_x_preferred":[
        "Kouadiokro"
    ],
    "name:msa_x_preferred":[
        "Kouadiokro"
    ],
    "wof:name":"Kouadiokro",
    "wof:placetype":"locality"
},
  "geometry": {"coordinates":[-5.43529,7.94482],"type":"Point"}
}