{
  "type": "Feature",
  "properties": {
    "gn:admin1_code":"96",
    "gn:asciiname":"Kribleguhe",
    "gn:country_code":"CI",
    "gn:dem":247,
    "gn:feature_class":"P",
    "gn:feature_code":"PPL",
    "gn:name":"Kribl\u00e9guh\u00e9",
    "gn:population":0,
    "gn:timezone":"Africa/Abidjan",
    "iso:country":"CI",
    "name:und_x_variant":[
        "Kipr\u00e9gu\u00e9",
        "Kribl\u00e9gu\u00e9",
        "Kribl\u00e9guh\u00e9"
    ],
    "wof:name":"Kribleguhe",
    "wof:placetype":"locality"
},
  "geometry": {"coordinates":[-6.2409,6.79354],"type":"Point"}
}