{
  "type": "Feature",
  "properties": {
    "gn:admin1_code":"97",
    "gn:asciiname":"Tyenfou",
    "gn:country_code":"CI",
    "gn:dem":418,
    "gn:feature_class":"P",
    "gn:feature_code":"PPL",
    "gn:name":"Ty\u00e8nfou",
    "gn:population":0,
    "gn:timezone":"Africa/Abidjan",
    "iso:country":"CI",
    "wof:name":"Tyenfou",
    "wof:placetype":"locality"
},
  "geometry": {"coordinates":[-7.36543,8.33616],"type":"Point"}
}