{
  "type": "Feature",
  "properties": {
    "gn:admin1_code":"95",
    "gn:asciiname":"Krikpoko",
    "gn:country_code":"CI",
    "gn:dem":256,
    "gn:feature_class":"P",
    "gn:feature_code":"PPL",
    "gn:name":"Krikpoko",
    "gn:population":0,
    "gn:timezone":"Africa/Abidjan",
    "iso:country":"CI",
    "name:und_x_variant":[
        "Kripoko"
    ],
    "wof:name":"Krikpoko",
    "wof:placetype":"locality"
},
  "geometry": {"coordinates":[-5.64466,6.19052],"type":"Point"}
}