{
  "type": "Feature",
  "properties": {
    "gn:admin1_code":"93.0",
    "gn:asciiname":"Ousmane Diallo",
    "gn:country_code":"CI",
    "gn:dem":97,
    "gn:feature_class":"P",
    "gn:feature_code":"PPL",
    "gn:name":"Ousmane Diallo",
    "gn:population":0,
    "gn:timezone":"Africa/Abidjan",
    "iso:country":"CI",
    "name:fra_x_preferred":[
        "Ousmane Diallo"
    ],
    "wof:name":"Ousmane Diallo",
    "wof:placetype":"locality"
},
  "geometry": {"coordinates":[-4.04768,5.56676],"type":"Point"}
}