{
  "type": "Feature",
  "properties": {
    "gn:admin1_code":"95",
    "gn:asciiname":"Zikriby",
    "gn:country_code":"CI",
    "gn:dem":160,
    "gn:feature_class":"P",
    "gn:feature_code":"PPL",
    "gn:name":"Zikriby",
    "gn:population":0,
    "gn:timezone":"Africa/Abidjan",
    "iso:country":"CI",
    "name:und_x_variant":[
        "Zikribi",
        "Zikriby"
    ],
    "wof:name":"Zikriby",
    "wof:placetype":"locality"
},
  "geometry": {"coordinates":[-5.42515,5.613],"type":"Point"}
}