{
  "type": "Feature",
  "properties": {
    "gn:admin1_code":"76",
    "gn:asciiname":"Tanie",
    "gn:country_code":"CI",
    "gn:dem":80,
    "gn:feature_class":"P",
    "gn:feature_code":"PPL",
    "gn:name":"Tani\u00e9",
    "gn:population":0,
    "gn:timezone":"Africa/Abidjan",
    "iso:country":"CI",
    "wof:name":"Tanie",
    "wof:placetype":"locality"
},
  "geometry": {"coordinates":[-7.45,5.06667],"type":"Point"}
}