{
  "type": "Feature",
  "properties": {
    "gn:admin1_code":"97.0",
    "gn:asciiname":"Fouanga",
    "gn:country_code":"CI",
    "gn:dem":254,
    "gn:feature_class":"P",
    "gn:feature_code":"PPL",
    "gn:name":"Fouanga",
    "gn:population":0,
    "gn:timezone":"Africa/Abidjan",
    "iso:country":"CI",
    "name:und_x_variant":[
        "Foanga",
        "Founga",
        "Fouanga"
    ],
    "wof:name":"Fouanga",
    "wof:placetype":"locality"
},
  "geometry": {"coordinates":[-6.08752,7.76316],"type":"Point"}
}