{
  "type": "Feature",
  "properties": {
    "gn:admin1_code":"78.0",
    "gn:asciiname":"Gezon",
    "gn:country_code":"CI",
    "gn:dem":356,
    "gn:feature_class":"P",
    "gn:feature_code":"PPL",
    "gn:name":"G\u00e9zon",
    "gn:population":0,
    "gn:timezone":"Africa/Abidjan",
    "iso:country":"CI",
    "name:und_x_variant":[
        "Guh\u00e9zon",
        "Gu\u00e9zon",
        "G\u00e9zon"
    ],
    "wof:name":"Gezon",
    "wof:placetype":"locality"
},
  "geometry": {"coordinates":[-7.18712,7.07641],"type":"Point"}
}