{
  "type": "Feature",
  "properties": {
    "gn:admin1_code":"98",
    "gn:asciiname":"Tenikro",
    "gn:country_code":"CI",
    "gn:dem":220,
    "gn:feature_class":"P",
    "gn:feature_code":"PPL",
    "gn:name":"T\u00e9nikro",
    "gn:population":0,
    "gn:timezone":"Africa/Abidjan",
    "iso:country":"CI",
    "wof:name":"Tenikro",
    "wof:placetype":"locality"
},
  "geometry": {"coordinates":[-5.37503,6.94919],"type":"Point"}
}