{
  "type": "Feature",
  "properties": {
    "gn:admin1_code":"90",
    "gn:asciiname":"Seouletie",
    "gn:country_code":"CI",
    "gn:dem":217,
    "gn:feature_class":"P",
    "gn:feature_code":"PPL",
    "gn:name":"S\u00e9oul\u00e9ti\u00e9",
    "gn:population":0,
    "gn:timezone":"Africa/Abidjan",
    "iso:country":"CI",
    "name:und_x_variant":[
        "S\u00e9oul\u00e9ti\u00e9",
        "Saour\u00e9ti\u00e9"
    ],
    "wof:name":"Seouletie",
    "wof:placetype":"locality"
},
  "geometry": {"coordinates":[-5.51053,7.76743],"type":"Point"}
}