{
  "type": "Feature",
  "properties": {
    "gn:admin1_code":"78",
    "gn:asciiname":"Pauleoula",
    "gn:country_code":"CI",
    "gn:dem":162,
    "gn:feature_class":"P",
    "gn:feature_code":"PPL",
    "gn:name":"Paul\u00e9oula",
    "gn:population":0,
    "gn:timezone":"Africa/Abidjan",
    "iso:country":"CI",
    "name:und_x_variant":[
        "Paul\u00e9oula"
    ],
    "wof:name":"Pauleoula",
    "wof:placetype":"locality"
},
  "geometry": {"coordinates":[-7.40143,5.82056],"type":"Point"}
}