{
  "type": "Feature",
  "properties": {
    "gn:admin1_code":"96",
    "gn:asciiname":"Niaourayo",
    "gn:country_code":"CI",
    "gn:dem":235,
    "gn:feature_class":"P",
    "gn:feature_code":"PPL",
    "gn:name":"Niaourayo",
    "gn:population":0,
    "gn:timezone":"Africa/Abidjan",
    "iso:country":"CI",
    "name:und_x_variant":[
        "Niahourahio"
    ],
    "wof:name":"Niaourayo",
    "wof:placetype":"locality"
},
  "geometry": {"coordinates":[-6.37793,6.49033],"type":"Point"}
}