{
  "type": "Feature",
  "properties": {
    "gn:admin1_code":"82.0",
    "gn:asciiname":"Chave Ekissi",
    "gn:country_code":"CI",
    "gn:dem":56,
    "gn:feature_class":"P",
    "gn:feature_code":"PPL",
    "gn:name":"Chav\u00e9 Ekissi",
    "gn:population":0,
    "gn:timezone":"Africa/Abidjan",
    "iso:country":"CI",
    "wof:name":"Chave Ekissi",
    "wof:placetype":"locality"
},
  "geometry": {"coordinates":[-4.22458,5.80449],"type":"Point"}
}