{
  "type": "Feature",
  "properties": {
    "gn:admin1_code":"82.0",
    "gn:asciiname":"Angoubekoua",
    "gn:country_code":"CI",
    "gn:dem":30,
    "gn:feature_class":"P",
    "gn:feature_code":"PPL",
    "gn:name":"Angoub\u00e9koua",
    "gn:population":0,
    "gn:timezone":"Africa/Abidjan",
    "iso:country":"CI",
    "wof:name":"Angoubekoua",
    "wof:placetype":"locality"
},
  "geometry": {"coordinates":[-3.91018,5.67193],"type":"Point"}
}