{
  "type": "Feature",
  "properties": {
    "gn:admin1_code":"82",
    "gn:asciiname":"Sassako-Begniny",
    "gn:country_code":"CI",
    "gn:dem":9,
    "gn:feature_class":"P",
    "gn:feature_code":"PPL",
    "gn:name":"Sassako-B\u00e9gniny",
    "gn:population":0,
    "gn:timezone":"Africa/Abidjan",
    "iso:country":"CI",
    "name:und_x_variant":[
        "Sassako B\u00e9nigny",
        "Sassako-B\u00e9gniny"
    ],
    "wof:name":"Sassako-Begniny",
    "wof:placetype":"locality"
},
  "geometry": {"coordinates":[-4.27736,5.21645],"type":"Point"}
}