{
  "type": "Feature",
  "properties": {
    "gn:admin1_code":"90",
    "gn:asciiname":"Wandarama",
    "gn:country_code":"CI",
    "gn:dem":287,
    "gn:feature_class":"P",
    "gn:feature_code":"PPL",
    "gn:name":"Wandarama",
    "gn:population":0,
    "gn:timezone":"Africa/Abidjan",
    "iso:country":"CI",
    "name:und_x_variant":[
        "Ouandarama",
        "Wandarama"
    ],
    "wof:name":"Wandarama",
    "wof:placetype":"locality"
},
  "geometry": {"coordinates":[-4.56987,8.24842],"type":"Point"}
}