{
  "type": "Feature",
  "properties": {
    "gn:admin1_code":"90.0",
    "gn:asciiname":"Konouan Mbadio",
    "gn:country_code":"CI",
    "gn:dem":216,
    "gn:feature_class":"P",
    "gn:feature_code":"PPL",
    "gn:name":"Konouan Mbadio",
    "gn:population":0,
    "gn:timezone":"Africa/Abidjan",
    "iso:country":"CI",
    "name:und_x_variant":[
        "Kanoua"
    ],
    "wof:name":"Konouan Mbadio",
    "wof:placetype":"locality"
},
  "geometry": {"coordinates":[-5.3985,7.5304],"type":"Point"}
}