{
  "type": "Feature",
  "properties": {
    "gn:admin1_code":"78",
    "gn:asciiname":"Trodapleu",
    "gn:country_code":"CI",
    "gn:dem":272,
    "gn:feature_class":"P",
    "gn:feature_code":"PPL",
    "gn:name":"Trodapleu",
    "gn:population":0,
    "gn:timezone":"Africa/Abidjan",
    "iso:country":"CI",
    "wof:name":"Trodapleu",
    "wof:placetype":"locality"
},
  "geometry": {"coordinates":[-8.13,6.99869],"type":"Point"}
}