{
  "type": "Feature",
  "properties": {
    "gn:admin1_code":"92",
    "gn:asciiname":"Kobinakourikro",
    "gn:country_code":"CI",
    "gn:dem":165,
    "gn:feature_class":"P",
    "gn:feature_code":"PPL",
    "gn:name":"Kobinakourikro",
    "gn:population":0,
    "gn:timezone":"Africa/Abidjan",
    "iso:country":"CI",
    "wof:name":"Kobinakourikro",
    "wof:placetype":"locality"
},
  "geometry": {"coordinates":[-3.53333,7.53333],"type":"Point"}
}