{
  "type": "Feature",
  "properties": {
    "gn:admin1_code":"93.0",
    "gn:asciiname":"Gonzagville",
    "gn:country_code":"CI",
    "gn:dem":87,
    "gn:feature_class":"P",
    "gn:feature_code":"PPL",
    "gn:name":"Gonzagville",
    "gn:population":0,
    "gn:timezone":"Africa/Abidjan",
    "iso:country":"CI",
    "name:und_x_variant":[
        "Gonzagueville"
    ],
    "wof:name":"Gonzagville",
    "wof:placetype":"locality"
},
  "geometry": {"coordinates":[-3.89843,5.23602],"type":"Point"}
}