{
  "type": "Feature",
  "properties": {
    "gn:admin1_code":"81",
    "gn:asciiname":"Tiaouabo",
    "gn:country_code":"CI",
    "gn:dem":199,
    "gn:feature_class":"P",
    "gn:feature_code":"PPL",
    "gn:name":"Tiaouabo",
    "gn:population":0,
    "gn:timezone":"Africa/Abidjan",
    "iso:country":"CI",
    "wof:name":"Tiaouabo",
    "wof:placetype":"locality"
},
  "geometry": {"coordinates":[-3.91667,7.83333],"type":"Point"}
}