{
  "type": "Feature",
  "properties": {
    "gn:admin1_code":"94.0",
    "gn:asciiname":"Mouhoua Aby",
    "gn:country_code":"CI",
    "gn:dem":6,
    "gn:feature_class":"P",
    "gn:feature_code":"PPL",
    "gn:name":"Mouhoua Aby",
    "gn:population":0,
    "gn:timezone":"Africa/Abidjan",
    "iso:country":"CI",
    "wof:name":"Mouhoua Aby",
    "wof:placetype":"locality"
},
  "geometry": {"coordinates":[-3.13022,5.14776],"type":"Point"}
}