{
  "type": "Feature",
  "properties": {
    "gn:admin1_code":"97",
    "gn:asciiname":"Kongaso",
    "gn:country_code":"CI",
    "gn:dem":286,
    "gn:feature_class":"P",
    "gn:feature_code":"PPL",
    "gn:name":"Kongaso",
    "gn:population":0,
    "gn:timezone":"Africa/Abidjan",
    "iso:country":"CI",
    "name:und_x_variant":[
        "Kongasso",
        "Kongaso"
    ],
    "wof:name":"Kongaso",
    "wof:placetype":"locality"
},
  "geometry": {"coordinates":[-6.07747,7.81533],"type":"Point"}
}