{
  "type": "Feature",
  "properties": {
    "gn:admin1_code":"92",
    "gn:asciiname":"Merei",
    "gn:country_code":"CI",
    "gn:dem":287,
    "gn:feature_class":"P",
    "gn:feature_code":"PPL",
    "gn:name":"M\u00e9r\u00e9\u00ef",
    "gn:population":0,
    "gn:timezone":"Africa/Abidjan",
    "iso:country":"CI",
    "name:ceb_x_preferred":[
        "Comuna Merei"
    ],
    "name:deu_x_preferred":[
        "Merei"
    ],
    "name:ita_x_preferred":[
        "Merei"
    ],
    "name:msa_x_preferred":[
        "Merei"
    ],
    "name:nld_x_preferred":[
        "Merei"
    ],
    "name:por_x_preferred":[
        "Merei"
    ],
    "name:ron_x_preferred":[
        "Comuna Merei"
    ],
    "name:srp_x_preferred":[
        "\u041e\u043f\u0448\u0442\u0438\u043d\u0430 \u041c\u0435\u0440\u0435\u0458"
    ],
    "name:ukr_x_preferred":[
        "\u041c\u0435\u0440\u0435\u0439"
    ],
    "name:vie_x_preferred":[
        "Merei"
    ],
    "name:vol_x_preferred":[
        "Merei"
    ],
    "name:zho_x_preferred":[
        "\u6885\u96f7\u4f0a\u9109"
    ],
    "wof:name":"Merei",
    "wof:placetype":"locality"
},
  "geometry": {"coordinates":[-2.74903,8.61493],"type":"Point"}
}