{
  "type": "Feature",
  "properties": {
    "gn:admin1_code":"92",
    "gn:asciiname":"Merei",
    "gn:country_code":"CI",
    "gn:dem":287,
    "gn:feature_class":"P",
    "gn:feature_code":"PPL",
    "gn:name":"M\u00e9r\u00e9\u00ef",
    "gn:population":0,
    "gn:timezone":"Africa/Abidjan",
    "iso:country":"CI",
    "wof:name":"Merei",
    "wof:placetype":"locality"
},
  "geometry": {"coordinates":[-2.74903,8.61493],"type":"Point"}
}