{
  "type": "Feature",
  "properties": {
    "gn:admin1_code":"82.0",
    "gn:asciiname":"Guana Tone",
    "gn:country_code":"CI",
    "gn:dem":65,
    "gn:feature_class":"P",
    "gn:feature_code":"PPL",
    "gn:name":"Guana Ton\u00e9",
    "gn:population":0,
    "gn:timezone":"Africa/Abidjan",
    "iso:country":"CI",
    "wof:name":"Guana Tone",
    "wof:placetype":"locality"
},
  "geometry": {"coordinates":[-4.29069,5.91057],"type":"Point"}
}