{
  "type": "Feature",
  "properties": {
    "gn:admin1_code":"96.0",
    "gn:asciiname":"Batrouan",
    "gn:country_code":"CI",
    "gn:dem":212,
    "gn:feature_class":"P",
    "gn:feature_code":"PPL",
    "gn:name":"Batrouan",
    "gn:population":0,
    "gn:timezone":"Africa/Abidjan",
    "iso:country":"CI",
    "wof:name":"Batrouan",
    "wof:placetype":"locality"
},
  "geometry": {"coordinates":[-6.63167,6.54258],"type":"Point"}
}