{
  "type": "Feature",
  "properties": {
    "gn:admin1_code":"90.0",
    "gn:asciiname":"Akokokro",
    "gn:country_code":"CI",
    "gn:dem":343,
    "gn:feature_class":"P",
    "gn:feature_code":"PPL",
    "gn:name":"Akokokro",
    "gn:population":0,
    "gn:timezone":"Africa/Abidjan",
    "iso:country":"CI",
    "wof:name":"Akokokro",
    "wof:placetype":"locality"
},
  "geometry": {"coordinates":[-5.23293,7.76991],"type":"Point"}
}