{
  "type": "Feature",
  "properties": {
    "gn:admin1_code":"78",
    "gn:asciiname":"Ouegouen",
    "gn:country_code":"CI",
    "gn:dem":335,
    "gn:feature_class":"P",
    "gn:feature_code":"PPL",
    "gn:name":"Ouegouen",
    "gn:population":0,
    "gn:timezone":"Africa/Abidjan",
    "iso:country":"CI",
    "name:und_x_variant":[
        "Ou\u00e9gouin",
        "Ouegouen"
    ],
    "wof:name":"Ouegouen",
    "wof:placetype":"locality"
},
  "geometry": {"coordinates":[-7.6175,7.35528],"type":"Point"}
}