{
  "type": "Feature",
  "properties": {
    "gn:admin1_code":"98.0",
    "gn:asciiname":"Duokro",
    "gn:country_code":"CI",
    "gn:dem":184,
    "gn:feature_class":"P",
    "gn:feature_code":"PPL",
    "gn:name":"Duokro",
    "gn:population":0,
    "gn:timezone":"Africa/Abidjan",
    "iso:country":"CI",
    "wof:name":"Duokro",
    "wof:placetype":"locality"
},
  "geometry": {"coordinates":[-5.23498,6.65903],"type":"Point"}
}