{
  "type": "Feature",
  "properties": {
    "gn:admin1_code":"93.0",
    "gn:asciiname":"Yao Kouassikro",
    "gn:country_code":"CI",
    "gn:dem":18,
    "gn:feature_class":"P",
    "gn:feature_code":"PPL",
    "gn:name":"Yao Kouassikro",
    "gn:population":0,
    "gn:timezone":"Africa/Abidjan",
    "iso:country":"CI",
    "wof:name":"Yao Kouassikro",
    "wof:placetype":"locality"
},
  "geometry": {"coordinates":[-4.29237,5.52178],"type":"Point"}
}