{
  "type": "Feature",
  "properties": {
    "gn:admin1_code":"94.0",
    "gn:asciiname":"Bernoikro",
    "gn:country_code":"CI",
    "gn:dem":37,
    "gn:feature_class":"P",
    "gn:feature_code":"PPL",
    "gn:name":"Bernoikro",
    "gn:population":0,
    "gn:timezone":"Africa/Abidjan",
    "iso:country":"CI",
    "wof:name":"Bernoikro",
    "wof:placetype":"locality"
},
  "geometry": {"coordinates":[-2.97953,5.27172],"type":"Point"}
}