{
  "type": "Feature",
  "properties": {
    "gn:admin1_code":"82.0",
    "gn:asciiname":"Kalila",
    "gn:country_code":"CI",
    "gn:dem":66,
    "gn:feature_class":"P",
    "gn:feature_code":"PPL",
    "gn:name":"Kalila",
    "gn:population":0,
    "gn:timezone":"Africa/Abidjan",
    "iso:country":"CI",
    "wof:name":"Kalila",
    "wof:placetype":"locality"
},
  "geometry": {"coordinates":[-4.30794,5.92221],"type":"Point"}
}