{
  "type": "Feature",
  "properties": {
    "gn:admin1_code":"78",
    "gn:asciiname":"Togbayourou",
    "gn:country_code":"CI",
    "gn:dem":322,
    "gn:feature_class":"P",
    "gn:feature_code":"PPL",
    "gn:name":"Togbayourou",
    "gn:population":0,
    "gn:timezone":"Africa/Abidjan",
    "iso:country":"CI",
    "wof:name":"Togbayourou",
    "wof:placetype":"locality"
},
  "geometry": {"coordinates":[-7.46667,7.31667],"type":"Point"}
}