{
  "type": "Feature",
  "properties": {
    "gn:admin1_code":"90",
    "gn:asciiname":"Nindo",
    "gn:country_code":"CI",
    "gn:dem":224,
    "gn:feature_class":"P",
    "gn:feature_code":"PPL",
    "gn:name":"Nindo",
    "gn:population":0,
    "gn:timezone":"Africa/Abidjan",
    "iso:country":"CI",
    "wof:name":"Nindo",
    "wof:placetype":"locality"
},
  "geometry": {"coordinates":[-5.64012,7.73723],"type":"Point"}
}