{
  "type": "Feature",
  "properties": {
    "gn:admin1_code":"78",
    "gn:asciiname":"Saebri",
    "gn:country_code":"CI",
    "gn:dem":252,
    "gn:feature_class":"P",
    "gn:feature_code":"PPL",
    "gn:name":"Saebri",
    "gn:population":0,
    "gn:timezone":"Africa/Abidjan",
    "iso:country":"CI",
    "wof:name":"Saebri",
    "wof:placetype":"locality"
},
  "geometry": {"coordinates":[-8.3383,6.57684],"type":"Point"}
}