{
  "type": "Feature",
  "properties": {
    "gn:admin1_code":"78.0",
    "gn:asciiname":"Gouakatouo",
    "gn:country_code":"CI",
    "gn:dem":288,
    "gn:feature_class":"P",
    "gn:feature_code":"PPL",
    "gn:name":"Gouakatouo",
    "gn:population":0,
    "gn:timezone":"Africa/Abidjan",
    "iso:country":"CI",
    "wof:name":"Gouakatouo",
    "wof:placetype":"locality"
},
  "geometry": {"coordinates":[-8.08426,6.97558],"type":"Point"}
}