{
  "type": "Feature",
  "properties": {
    "gn:admin1_code":"81.0",
    "gn:asciiname":"Assaoufoue",
    "gn:country_code":"CI",
    "gn:dem":160,
    "gn:feature_class":"P",
    "gn:feature_code":"PPL",
    "gn:name":"Assaoufou\u00e9",
    "gn:population":0,
    "gn:timezone":"Africa/Abidjan",
    "iso:country":"CI",
    "wof:name":"Assaoufoue",
    "wof:placetype":"locality"
},
  "geometry": {"coordinates":[-4.22405,6.57675],"type":"Point"}
}