{
  "type": "Feature",
  "properties": {
    "gn:admin1_code":"93.0",
    "gn:asciiname":"Les deux-Plateaux",
    "gn:country_code":"CI",
    "gn:dem":46,
    "gn:feature_class":"P",
    "gn:feature_code":"PPL",
    "gn:name":"Les deux-Plateaux",
    "gn:population":0,
    "gn:timezone":"Africa/Abidjan",
    "iso:country":"CI",
    "wof:name":"Les deux-Plateaux",
    "wof:placetype":"locality"
},
  "geometry": {"coordinates":[-4.00801,5.35324],"type":"Point"}
}