{
  "type": "Feature",
  "properties": {
    "gn:admin1_code":"98",
    "gn:asciiname":"Morokinkro",
    "gn:country_code":"CI",
    "gn:dem":167,
    "gn:elevation":"406.0",
    "gn:feature_class":"P",
    "gn:feature_code":"PPL",
    "gn:name":"Morokinkro",
    "gn:population":0,
    "gn:timezone":"Africa/Abidjan",
    "iso:country":"CI",
    "name:und_x_variant":[
        "Moro-Attienkro"
    ],
    "wof:name":"Morokinkro",
    "wof:placetype":"locality"
},
  "geometry": {"coordinates":[-4.99457,6.8166],"type":"Point"}
}