{
  "type": "Feature",
  "properties": {
    "gn:admin1_code":"78.0",
    "gn:asciiname":"Glongouen",
    "gn:country_code":"CI",
    "gn:dem":348,
    "gn:feature_class":"P",
    "gn:feature_code":"PPL",
    "gn:name":"Glongouen",
    "gn:population":0,
    "gn:timezone":"Africa/Abidjan",
    "iso:country":"CI",
    "name:und_x_variant":[
        "Glongoin",
        "Glangouin",
        "Glongoen",
        "Glongouen"
    ],
    "wof:name":"Glongouen",
    "wof:placetype":"locality"
},
  "geometry": {"coordinates":[-7.55119,7.4371],"type":"Point"}
}