{
  "type": "Feature",
  "properties": {
    "gn:admin1_code":"81",
    "gn:asciiname":"Lengoue",
    "gn:country_code":"CI",
    "gn:dem":147,
    "gn:feature_class":"P",
    "gn:feature_code":"PPL",
    "gn:name":"Lengou\u00e9",
    "gn:population":0,
    "gn:timezone":"Africa/Abidjan",
    "iso:country":"CI",
    "wof:name":"Lengoue",
    "wof:placetype":"locality"
},
  "geometry": {"coordinates":[-4.28333,7.33333],"type":"Point"}
}