{
  "type": "Feature",
  "properties": {
    "gn:admin1_code":"82.0",
    "gn:asciiname":"Boussoukro",
    "gn:country_code":"CI",
    "gn:dem":89,
    "gn:feature_class":"P",
    "gn:feature_code":"PPL",
    "gn:name":"Boussoukro",
    "gn:population":0,
    "gn:timezone":"Africa/Abidjan",
    "iso:country":"CI",
    "wof:name":"Boussoukro",
    "wof:placetype":"locality"
},
  "geometry": {"coordinates":[-4.69507,5.88398],"type":"Point"}
}