{
  "type": "Feature",
  "properties": {
    "gn:admin1_code":"87",
    "gn:asciiname":"Lomono",
    "gn:country_code":"CI",
    "gn:dem":288,
    "gn:feature_class":"P",
    "gn:feature_code":"PPL",
    "gn:name":"Lomono",
    "gn:population":0,
    "gn:timezone":"Africa/Abidjan",
    "iso:country":"CI",
    "name:und_x_variant":[
        "Lemono",
        "Lomono"
    ],
    "wof:name":"Lomono",
    "wof:placetype":"locality"
},
  "geometry": {"coordinates":[-4.60705,9.27642],"type":"Point"}
}