{
  "type": "Feature",
  "properties": {
    "gn:admin1_code":"87.0",
    "gn:asciiname":"Kayere-Kevogo",
    "gn:country_code":"CI",
    "gn:dem":350,
    "gn:feature_class":"P",
    "gn:feature_code":"PPL",
    "gn:name":"Kay\u00e9r\u00e9-K\u00e9vogo",
    "gn:population":0,
    "gn:timezone":"Africa/Abidjan",
    "iso:country":"CI",
    "wof:name":"Kayere-Kevogo",
    "wof:placetype":"locality"
},
  "geometry": {"coordinates":[-5.6097,10.12043],"type":"Point"}
}