{
  "type": "Feature",
  "properties": {
    "gn:admin1_code":"95.0",
    "gn:asciiname":"Agbaou",
    "gn:country_code":"CI",
    "gn:dem":205,
    "gn:feature_class":"P",
    "gn:feature_code":"PPL",
    "gn:name":"Agbaou",
    "gn:population":0,
    "gn:timezone":"Africa/Abidjan",
    "iso:country":"CI",
    "wof:name":"Agbaou",
    "wof:placetype":"locality"
},
  "geometry": {"coordinates":[-5.21515,6.0816],"type":"Point"}
}