{
  "type": "Feature",
  "properties": {
    "gn:admin1_code":"81.0",
    "gn:asciiname":"Anialesso",
    "gn:country_code":"CI",
    "gn:dem":145,
    "gn:feature_class":"P",
    "gn:feature_code":"PPL",
    "gn:name":"Anialesso",
    "gn:population":0,
    "gn:timezone":"Africa/Abidjan",
    "iso:country":"CI",
    "wof:name":"Anialesso",
    "wof:placetype":"locality"
},
  "geometry": {"coordinates":[-4.31897,6.52374],"type":"Point"}
}