{
  "type": "Feature",
  "properties": {
    "gn:admin1_code":"90",
    "gn:asciiname":"Kouassi Golikro",
    "gn:country_code":"CI",
    "gn:dem":326,
    "gn:feature_class":"P",
    "gn:feature_code":"PPL",
    "gn:name":"Kouassi Golikro",
    "gn:population":0,
    "gn:timezone":"Africa/Abidjan",
    "iso:country":"CI",
    "name:und_x_variant":[
        "Kouassi-Glikro",
        "Kouassi-Golikro"
    ],
    "wof:name":"Kouassi Golikro",
    "wof:placetype":"locality"
},
  "geometry": {"coordinates":[-5.19405,7.76003],"type":"Point"}
}