{
  "type": "Feature",
  "properties": {
    "gn:admin1_code":"78",
    "gn:asciiname":"Seambli",
    "gn:country_code":"CI",
    "gn:dem":344,
    "gn:feature_class":"P",
    "gn:feature_code":"PPL",
    "gn:name":"S\u00e9ambli",
    "gn:population":0,
    "gn:timezone":"Africa/Abidjan",
    "iso:country":"CI",
    "wof:name":"Seambli",
    "wof:placetype":"locality"
},
  "geometry": {"coordinates":[-7.34189,7.37003],"type":"Point"}
}