{
  "type": "Feature",
  "properties": {
    "gn:admin1_code":"90.0",
    "gn:asciiname":"Assan",
    "gn:country_code":"CI",
    "gn:dem":293,
    "gn:feature_class":"P",
    "gn:feature_code":"PPL",
    "gn:name":"Assan",
    "gn:population":0,
    "gn:timezone":"Africa/Abidjan",
    "iso:country":"CI",
    "wof:name":"Assan",
    "wof:placetype":"locality"
},
  "geometry": {"coordinates":[-5.05,7.81663],"type":"Point"}
}