{
  "type": "Feature",
  "properties": {
    "gn:admin1_code":"94.0",
    "gn:asciiname":"Toumanguie Sodepalm Deux",
    "gn:country_code":"CI",
    "gn:dem":74,
    "gn:feature_class":"P",
    "gn:feature_code":"PPL",
    "gn:name":"Toumangui\u00e9 Sodepalm Deux",
    "gn:population":0,
    "gn:timezone":"Africa/Abidjan",
    "iso:country":"CI",
    "wof:name":"Toumanguie Sodepalm Deux",
    "wof:placetype":"locality"
},
  "geometry": {"coordinates":[-3.38206,5.35522],"type":"Point"}
}