{
  "type": "Feature",
  "properties": {
    "gn:admin1_code":"94.0",
    "gn:asciiname":"Petit Koumassi",
    "gn:country_code":"CI",
    "gn:dem":103,
    "gn:feature_class":"P",
    "gn:feature_code":"PPL",
    "gn:name":"Petit Koumassi",
    "gn:population":0,
    "gn:timezone":"Africa/Abidjan",
    "iso:country":"CI",
    "wof:name":"Petit Koumassi",
    "wof:placetype":"locality"
},
  "geometry": {"coordinates":[-3.54724,5.53731],"type":"Point"}
}