{
  "type": "Feature",
  "properties": {
    "gn:admin1_code":"78",
    "gn:asciiname":"Kpangouen",
    "gn:country_code":"CI",
    "gn:dem":354,
    "gn:feature_class":"P",
    "gn:feature_code":"PPL",
    "gn:name":"Kpangouen",
    "gn:population":0,
    "gn:timezone":"Africa/Abidjan",
    "iso:country":"CI",
    "wof:name":"Kpangouen",
    "wof:placetype":"locality"
},
  "geometry": {"coordinates":[-7.5193,7.42898],"type":"Point"}
}