{
  "type": "Feature",
  "properties": {
    "gn:admin1_code":"76.0",
    "gn:asciiname":"Braguhe",
    "gn:country_code":"CI",
    "gn:dem":174,
    "gn:feature_class":"P",
    "gn:feature_code":"PPL",
    "gn:name":"Braguh\u00e9",
    "gn:population":0,
    "gn:timezone":"Africa/Abidjan",
    "iso:country":"CI",
    "wof:name":"Braguhe",
    "wof:placetype":"locality"
},
  "geometry": {"coordinates":[-6.79373,6.03294],"type":"Point"}
}