{
  "type": "Feature",
  "properties": {
    "gn:admin1_code":"90.0",
    "gn:asciiname":"Brongonzue",
    "gn:country_code":"CI",
    "gn:dem":223,
    "gn:feature_class":"P",
    "gn:feature_code":"PPL",
    "gn:name":"Brongonzu\u00e9",
    "gn:population":0,
    "gn:timezone":"Africa/Abidjan",
    "iso:country":"CI",
    "wof:name":"Brongonzue",
    "wof:placetype":"locality"
},
  "geometry": {"coordinates":[-5.66076,7.40517],"type":"Point"}
}