{
  "type": "Feature",
  "properties": {
    "gn:admin1_code":"93.0",
    "gn:asciiname":"Bonikro",
    "gn:country_code":"CI",
    "gn:dem":73,
    "gn:feature_class":"P",
    "gn:feature_code":"PPL",
    "gn:name":"Bonikro",
    "gn:population":0,
    "gn:timezone":"Africa/Abidjan",
    "iso:country":"CI",
    "name:fra_x_preferred":[
        "Bonikro"
    ],
    "name:ita_x_preferred":[
        "Bonikro"
    ],
    "name:msa_x_preferred":[
        "Bonikro"
    ],
    "wof:name":"Bonikro",
    "wof:placetype":"locality"
},
  "geometry": {"coordinates":[-4.10536,5.35086],"type":"Point"}
}