{
  "type": "Feature",
  "properties": {
    "gn:admin1_code":"78.0",
    "gn:asciiname":"Gbale",
    "gn:country_code":"CI",
    "gn:dem":584,
    "gn:feature_class":"P",
    "gn:feature_code":"PPL",
    "gn:name":"Gbal\u00e9",
    "gn:population":0,
    "gn:timezone":"Africa/Abidjan",
    "iso:country":"CI",
    "name:und_x_variant":[
        "Gbal\u00e9",
        "Gbal\u00e9 2"
    ],
    "wof:name":"Gbale",
    "wof:placetype":"locality"
},
  "geometry": {"coordinates":[-7.8965,7.51036],"type":"Point"}
}