{
  "type": "Feature",
  "properties": {
    "gn:admin1_code":"92.0",
    "gn:asciiname":"Bayana",
    "gn:country_code":"CI",
    "gn:dem":307,
    "gn:feature_class":"P",
    "gn:feature_code":"PPL",
    "gn:name":"Bayana",
    "gn:population":0,
    "gn:timezone":"Africa/Abidjan",
    "iso:country":"CI",
    "name:ben_x_preferred":[
        "\u09ac\u09be\u09af\u09bc\u09be\u09a8\u09be"
    ],
    "name:bpy_x_preferred":[
        "\u09ac\u09be\u09af\u09bc\u09be\u09a8\u09be"
    ],
    "name:cat_x_preferred":[
        "Bayana"
    ],
    "name:ceb_x_preferred":[
        "Bay\u0101na"
    ],
    "name:deu_x_preferred":[
        "Bayana"
    ],
    "name:hin_x_preferred":[
        "\u092c\u092f\u093e\u0928\u093e"
    ],
    "name:jpn_x_preferred":[
        "\u30d0\u30e4\u30fc\u30ca\u30fc"
    ],
    "name:mar_x_preferred":[
        "\u092c\u093e\u092f\u0928\u093e"
    ],
    "name:mlg_x_preferred":[
        "Bayana"
    ],
    "name:msa_x_preferred":[
        "Bayana"
    ],
    "name:nep_x_preferred":[
        "\u092c\u092f\u093e\u0928\u093e"
    ],
    "name:new_x_preferred":[
        "\u092c\u092f\u0928\u093e"
    ],
    "name:swe_x_preferred":[
        "Bay\u0101na"
    ],
    "name:vie_x_preferred":[
        "Bayana"
    ],
    "name:zho_x_preferred":[
        "\u5df4\u8036\u7eb3"
    ],
    "wof:name":"Bayana",
    "wof:placetype":"locality"
},
  "geometry": {"coordinates":[-3.06667,9.58333],"type":"Point"}
}