{
  "type": "Feature",
  "properties": {
    "gn:admin1_code":"92.0",
    "gn:asciiname":"Bayana",
    "gn:country_code":"CI",
    "gn:dem":307,
    "gn:feature_class":"P",
    "gn:feature_code":"PPL",
    "gn:name":"Bayana",
    "gn:population":0,
    "gn:timezone":"Africa/Abidjan",
    "iso:country":"CI",
    "wof:name":"Bayana",
    "wof:placetype":"locality"
},
  "geometry": {"coordinates":[-3.06667,9.58333],"type":"Point"}
}