{
  "type": "Feature",
  "properties": {
    "gn:admin1_code":"93.0",
    "gn:asciiname":"Adjifou",
    "gn:country_code":"CI",
    "gn:dem":9,
    "gn:feature_class":"P",
    "gn:feature_code":"PPL",
    "gn:name":"Adjifou",
    "gn:population":0,
    "gn:timezone":"Africa/Abidjan",
    "iso:country":"CI",
    "wof:name":"Adjifou",
    "wof:placetype":"locality"
},
  "geometry": {"coordinates":[-3.92619,5.28469],"type":"Point"}
}