{
  "type": "Feature",
  "properties": {
    "gn:admin1_code":"94.0",
    "gn:asciiname":"Toumanguie Sodepalm Un",
    "gn:country_code":"CI",
    "gn:dem":66,
    "gn:feature_class":"P",
    "gn:feature_code":"PPL",
    "gn:name":"Toumangui\u00e9 Sodepalm Un",
    "gn:population":0,
    "gn:timezone":"Africa/Abidjan",
    "iso:country":"CI",
    "wof:name":"Toumanguie Sodepalm Un",
    "wof:placetype":"locality"
},
  "geometry": {"coordinates":[-3.38685,5.37019],"type":"Point"}
}