{
  "type": "Feature",
  "properties": {
    "gn:admin1_code":"76.0",
    "gn:asciiname":"Gaouri",
    "gn:country_code":"CI",
    "gn:dem":68,
    "gn:feature_class":"P",
    "gn:feature_code":"PPL",
    "gn:name":"Gaouri",
    "gn:population":0,
    "gn:timezone":"Africa/Abidjan",
    "iso:country":"CI",
    "wof:name":"Gaouri",
    "wof:placetype":"locality"
},
  "geometry": {"coordinates":[-6.66667,5.16667],"type":"Point"}
}