{
  "type": "Feature",
  "properties": {
    "gn:admin1_code":"81",
    "gn:asciiname":"Kofikro",
    "gn:country_code":"CI",
    "gn:dem":194,
    "gn:feature_class":"P",
    "gn:feature_code":"PPL",
    "gn:name":"Kofikro",
    "gn:population":0,
    "gn:timezone":"Africa/Abidjan",
    "iso:country":"CI",
    "wof:name":"Kofikro",
    "wof:placetype":"locality"
},
  "geometry": {"coordinates":[-4.18333,7.36667],"type":"Point"}
}