{
  "type": "Feature",
  "properties": {
    "gn:admin1_code":"97.0",
    "gn:asciiname":"Diaso",
    "gn:country_code":"CI",
    "gn:dem":549,
    "gn:feature_class":"P",
    "gn:feature_code":"PPL",
    "gn:name":"Diaso",
    "gn:population":0,
    "gn:timezone":"Africa/Abidjan",
    "iso:country":"CI",
    "wof:name":"Diaso",
    "wof:placetype":"locality"
},
  "geometry": {"coordinates":[-7.53124,8.16303],"type":"Point"}
}