{
  "type": "Feature",
  "properties": {
    "gn:admin1_code":"81",
    "gn:asciiname":"Mbabrasso",
    "gn:country_code":"CI",
    "gn:dem":230,
    "gn:feature_class":"P",
    "gn:feature_code":"PPL",
    "gn:name":"Mbabrasso",
    "gn:population":0,
    "gn:timezone":"Africa/Abidjan",
    "iso:country":"CI",
    "wof:name":"Mbabrasso",
    "wof:placetype":"locality"
},
  "geometry": {"coordinates":[-4.01312,7.68457],"type":"Point"}
}