{
  "type": "Feature",
  "properties": {
    "gn:admin1_code":"96.0",
    "gn:asciiname":"Bidiouan",
    "gn:country_code":"CI",
    "gn:dem":253,
    "gn:feature_class":"P",
    "gn:feature_code":"PPL",
    "gn:name":"Bidiouan",
    "gn:population":0,
    "gn:timezone":"Africa/Abidjan",
    "iso:country":"CI",
    "name:und_x_variant":[
        "Bidihouan"
    ],
    "wof:name":"Bidiouan",
    "wof:placetype":"locality"
},
  "geometry": {"coordinates":[-6.23701,6.61531],"type":"Point"}
}