{
  "type": "Feature",
  "properties": {
    "gn:admin1_code":"95.0",
    "gn:asciiname":"Bigbie",
    "gn:country_code":"CI",
    "gn:dem":234,
    "gn:feature_class":"P",
    "gn:feature_code":"PPL",
    "gn:name":"Bigbi\u00e9",
    "gn:population":0,
    "gn:timezone":"Africa/Abidjan",
    "iso:country":"CI",
    "name:und_x_variant":[
        "Bigoi\u00e9",
        "Bigbi\u00e9",
        "Bigb\u00e9 I",
        "Bigbi\u00e9 II"
    ],
    "wof:name":"Bigbie",
    "wof:placetype":"locality"
},
  "geometry": {"coordinates":[-5.9606,6.39085],"type":"Point"}
}