{
  "type": "Feature",
  "properties": {
    "gn:admin1_code":"81",
    "gn:asciiname":"Pongokofikro",
    "gn:country_code":"CI",
    "gn:dem":196,
    "gn:feature_class":"P",
    "gn:feature_code":"PPL",
    "gn:name":"Pongokofikro",
    "gn:population":0,
    "gn:timezone":"Africa/Abidjan",
    "iso:country":"CI",
    "wof:name":"Pongokofikro",
    "wof:placetype":"locality"
},
  "geometry": {"coordinates":[-4.43333,7.78333],"type":"Point"}
}