{
  "type": "Feature",
  "properties": {
    "gn:admin1_code":"82",
    "gn:asciiname":"Orgaff",
    "gn:country_code":"CI",
    "gn:dem":24,
    "gn:feature_class":"P",
    "gn:feature_code":"PPL",
    "gn:name":"Orgaff",
    "gn:population":0,
    "gn:timezone":"Africa/Abidjan",
    "iso:country":"CI",
    "name:und_x_variant":[
        "Orgaf",
        "Orgaff"
    ],
    "wof:name":"Orgaff",
    "wof:placetype":"locality"
},
  "geometry": {"coordinates":[-4.35241,5.41866],"type":"Point"}
}