{
  "type": "Feature",
  "properties": {
    "gn:admin1_code":"76.0",
    "gn:asciiname":"Bokle",
    "gn:country_code":"CI",
    "gn:dem":29,
    "gn:feature_class":"P",
    "gn:feature_code":"PPL",
    "gn:name":"Bokl\u00e9",
    "gn:population":0,
    "gn:timezone":"Africa/Abidjan",
    "iso:country":"CI",
    "wof:name":"Bokle",
    "wof:placetype":"locality"
},
  "geometry": {"coordinates":[-7.56478,4.78821],"type":"Point"}
}