{
  "type": "Feature",
  "properties": {
    "gn:admin1_code":"76",
    "gn:asciiname":"Yonake",
    "gn:country_code":"CI",
    "gn:dem":13,
    "gn:feature_class":"P",
    "gn:feature_code":"PPL",
    "gn:name":"Yonak\u00e9",
    "gn:population":0,
    "gn:timezone":"Africa/Abidjan",
    "iso:country":"CI",
    "wof:name":"Yonake",
    "wof:placetype":"locality"
},
  "geometry": {"coordinates":[-7.3992,4.38722],"type":"Point"}
}