{
  "type": "Feature",
  "properties": {
    "gn:admin1_code":"82.0",
    "gn:asciiname":"Gnagnan Kassi",
    "gn:country_code":"CI",
    "gn:dem":86,
    "gn:feature_class":"P",
    "gn:feature_code":"PPL",
    "gn:name":"Gnagnan Kassi",
    "gn:population":0,
    "gn:timezone":"Africa/Abidjan",
    "iso:country":"CI",
    "wof:name":"Gnagnan Kassi",
    "wof:placetype":"locality"
},
  "geometry": {"coordinates":[-4.46141,5.65106],"type":"Point"}
}