{
  "type": "Feature",
  "properties": {
    "gn:admin1_code":"92.0",
    "gn:asciiname":"Aounzi",
    "gn:country_code":"CI",
    "gn:dem":166,
    "gn:feature_class":"P",
    "gn:feature_code":"PPL",
    "gn:name":"Aounzi",
    "gn:population":0,
    "gn:timezone":"Africa/Abidjan",
    "iso:country":"CI",
    "wof:name":"Aounzi",
    "wof:placetype":"locality"
},
  "geometry": {"coordinates":[-3.25,7.46667],"type":"Point"}
}