{
  "type": "Feature",
  "properties": {
    "gn:admin1_code":"90.0",
    "gn:asciiname":"Adiekro",
    "gn:country_code":"CI",
    "gn:dem":334,
    "gn:feature_class":"P",
    "gn:feature_code":"PPL",
    "gn:name":"Adi\u00e9kro",
    "gn:population":0,
    "gn:timezone":"Africa/Abidjan",
    "iso:country":"CI",
    "name:und_x_variant":[
        "Adi\u00e9kro",
        "Abi\u00e9kro"
    ],
    "wof:name":"Adiekro",
    "wof:placetype":"locality"
},
  "geometry": {"coordinates":[-5.19611,7.79953],"type":"Point"}
}