{
  "type": "Feature",
  "properties": {
    "gn:admin1_code":"76.0",
    "gn:asciiname":"Butubre I",
    "gn:country_code":"CI",
    "gn:dem":81,
    "gn:feature_class":"P",
    "gn:feature_code":"PPL",
    "gn:name":"Butubr\u00e9 I",
    "gn:population":0,
    "gn:timezone":"Africa/Abidjan",
    "iso:country":"CI",
    "name:und_x_variant":[
        "Broutoubr\u00e9",
        "Boutubr\u00e9",
        "Boutoubr\u00e9",
        "Butubr\u00e9 I"
    ],
    "wof:name":"Butubre I",
    "wof:placetype":"locality"
},
  "geometry": {"coordinates":[-6.44838,5.51071],"type":"Point"}
}