{
  "type": "Feature",
  "properties": {
    "gn:admin1_code":"94.0",
    "gn:asciiname":"Adounikro",
    "gn:country_code":"CI",
    "gn:dem":160,
    "gn:feature_class":"P",
    "gn:feature_code":"PPL",
    "gn:name":"Adounikro",
    "gn:population":0,
    "gn:timezone":"Africa/Abidjan",
    "iso:country":"CI",
    "wof:name":"Adounikro",
    "wof:placetype":"locality"
},
  "geometry": {"coordinates":[-3.56404,6.72245],"type":"Point"}
}