{
  "type": "Feature",
  "properties": {
    "gn:admin1_code":"82.0",
    "gn:asciiname":"Bacanda",
    "gn:country_code":"CI",
    "gn:dem":22,
    "gn:feature_class":"P",
    "gn:feature_code":"PPL",
    "gn:name":"Bacanda",
    "gn:population":0,
    "gn:timezone":"Africa/Abidjan",
    "iso:country":"CI",
    "name:fra_x_preferred":[
        "Bacanda"
    ],
    "name:ita_x_preferred":[
        "Bacanda"
    ],
    "name:msa_x_preferred":[
        "Bacanda"
    ],
    "name:und_x_variant":[
        "Bakanda",
        "Bacanda"
    ],
    "wof:name":"Bacanda",
    "wof:placetype":"locality"
},
  "geometry": {"coordinates":[-4.87758,5.63331],"type":"Point"}
}