{
  "type": "Feature",
  "properties": {
    "gn:admin1_code":"96.0",
    "gn:asciiname":"Angovia",
    "gn:country_code":"CI",
    "gn:dem":232,
    "gn:feature_class":"P",
    "gn:feature_code":"PPL",
    "gn:name":"Angovia",
    "gn:population":0,
    "gn:timezone":"Africa/Abidjan",
    "iso:country":"CI",
    "wof:name":"Angovia",
    "wof:placetype":"locality"
},
  "geometry": {"coordinates":[-5.53697,7.03305],"type":"Point"}
}