{
  "type": "Feature",
  "properties": {
    "gn:admin1_code":"95.0",
    "gn:asciiname":"Bougbouela",
    "gn:country_code":"CI",
    "gn:dem":220,
    "gn:feature_class":"P",
    "gn:feature_code":"PPL",
    "gn:name":"Bougbou\u00e9la",
    "gn:population":0,
    "gn:timezone":"Africa/Abidjan",
    "iso:country":"CI",
    "wof:name":"Bougbouela",
    "wof:placetype":"locality"
},
  "geometry": {"coordinates":[-6.01053,6.43187],"type":"Point"}
}