{
  "type": "Feature",
  "properties": {
    "gn:admin1_code":"78.0",
    "gn:asciiname":"Kassiogouine",
    "gn:country_code":"CI",
    "gn:dem":317,
    "gn:feature_class":"P",
    "gn:feature_code":"PPL",
    "gn:name":"Kassiogouin\u00e9",
    "gn:population":0,
    "gn:timezone":"Africa/Abidjan",
    "iso:country":"CI",
    "wof:name":"Kassiogouine",
    "wof:placetype":"locality"
},
  "geometry": {"coordinates":[-7.61844,7.16678],"type":"Point"}
}