{
  "type": "Feature",
  "properties": {
    "gn:admin1_code":"95",
    "gn:asciiname":"Payopa",
    "gn:country_code":"CI",
    "gn:dem":260,
    "gn:feature_class":"P",
    "gn:feature_code":"PPL",
    "gn:name":"Payopa",
    "gn:population":0,
    "gn:timezone":"Africa/Abidjan",
    "iso:country":"CI",
    "name:und_x_variant":[
        "Pa\u00efopa"
    ],
    "wof:name":"Payopa",
    "wof:placetype":"locality"
},
  "geometry": {"coordinates":[-5.75723,6.19473],"type":"Point"}
}