{
  "type": "Feature",
  "properties": {
    "gn:admin1_code":"93.0",
    "gn:asciiname":"Apichi Beke",
    "gn:country_code":"CI",
    "gn:dem":86,
    "gn:feature_class":"P",
    "gn:feature_code":"PPL",
    "gn:name":"Apichi Bek\u00e9",
    "gn:population":0,
    "gn:timezone":"Africa/Abidjan",
    "iso:country":"CI",
    "wof:name":"Apichi Beke",
    "wof:placetype":"locality"
},
  "geometry": {"coordinates":[-4.16233,5.43215],"type":"Point"}
}