{
  "type": "Feature",
  "properties": {
    "gn:admin1_code":"97",
    "gn:asciiname":"Magina",
    "gn:country_code":"CI",
    "gn:dem":366,
    "gn:feature_class":"P",
    "gn:feature_code":"PPL",
    "gn:name":"Magina",
    "gn:population":0,
    "gn:timezone":"Africa/Abidjan",
    "iso:country":"CI",
    "wof:name":"Magina",
    "wof:placetype":"locality"
},
  "geometry": {"coordinates":[-6.17301,8.07623],"type":"Point"}
}