{
  "type": "Feature",
  "properties": {
    "gn:admin1_code":"92",
    "gn:asciiname":"Kpon",
    "gn:country_code":"CI",
    "gn:dem":356,
    "gn:feature_class":"P",
    "gn:feature_code":"PPL",
    "gn:name":"Kpon",
    "gn:population":0,
    "gn:timezone":"Africa/Abidjan",
    "iso:country":"CI",
    "name:und_x_variant":[
        "Pon",
        "Kpon"
    ],
    "wof:name":"Kpon",
    "wof:placetype":"locality"
},
  "geometry": {"coordinates":[-3.49571,8.41663],"type":"Point"}
}