{
  "type": "Feature",
  "properties": {
    "gn:admin1_code":"76",
    "gn:asciiname":"Niaouriyo",
    "gn:country_code":"CI",
    "gn:dem":165,
    "gn:feature_class":"P",
    "gn:feature_code":"PPL",
    "gn:name":"Niaouriyo",
    "gn:population":0,
    "gn:timezone":"Africa/Abidjan",
    "iso:country":"CI",
    "name:und_x_variant":[
        "Niaouayo",
        "Niaouriyo"
    ],
    "wof:name":"Niaouriyo",
    "wof:placetype":"locality"
},
  "geometry": {"coordinates":[-6.11667,5.76667],"type":"Point"}
}