{
  "type": "Feature",
  "properties": {
    "gn:admin1_code":"77.0",
    "gn:asciiname":"Katiola",
    "gn:country_code":"CI",
    "gn:dem":398,
    "gn:feature_class":"P",
    "gn:feature_code":"PPL",
    "gn:name":"Katiola",
    "gn:population":0,
    "gn:timezone":"Africa/Abidjan",
    "iso:country":"CI",
    "name:und_x_variant":[
        "Kadiola",
        "Katiola"
    ],
    "wof:name":"Katiola",
    "wof:placetype":"locality"
},
  "geometry": {"coordinates":[-7.62195,9.65516],"type":"Point"}
}