{
  "type": "Feature",
  "properties": {
    "gn:admin1_code":"77.0",
    "gn:asciiname":"Katiola",
    "gn:country_code":"CI",
    "gn:dem":398,
    "gn:feature_class":"P",
    "gn:feature_code":"PPL",
    "gn:name":"Katiola",
    "gn:population":0,
    "gn:timezone":"Africa/Abidjan",
    "iso:country":"CI",
    "name:ceb_x_preferred":[
        "Katiola"
    ],
    "name:fra_x_preferred":[
        "Katiola"
    ],
    "name:ita_x_preferred":[
        "Katiola"
    ],
    "name:msa_x_preferred":[
        "Katiola"
    ],
    "name:pol_x_preferred":[
        "Katiola"
    ],
    "name:ron_x_preferred":[
        "Katiola"
    ],
    "name:rus_x_preferred":[
        "\u041a\u0430\u0442\u0438\u043e\u043b\u0430"
    ],
    "name:spa_x_preferred":[
        "Katiola"
    ],
    "name:swe_x_preferred":[
        "Katiola"
    ],
    "name:und_x_variant":[
        "Kadiola",
        "Katiola"
    ],
    "name:zho_x_preferred":[
        "\u5361\u8482\u5967\u62c9"
    ],
    "wof:name":"Katiola",
    "wof:placetype":"locality"
},
  "geometry": {"coordinates":[-7.62195,9.65516],"type":"Point"}
}