{
  "type": "Feature",
  "properties": {
    "gn:admin1_code":"95",
    "gn:asciiname":"Zeleayo",
    "gn:country_code":"CI",
    "gn:dem":236,
    "gn:feature_class":"P",
    "gn:feature_code":"PPL",
    "gn:name":"Z\u00e9l\u00e9ayo",
    "gn:population":0,
    "gn:timezone":"Africa/Abidjan",
    "iso:country":"CI",
    "name:und_x_variant":[
        "Z\u00e9l\u00e9ayo",
        "Z\u00e9r\u00e9ayo",
        "Z\u00e9l\u00e9ahio"
    ],
    "wof:name":"Zeleayo",
    "wof:placetype":"locality"
},
  "geometry": {"coordinates":[-6.33406,6.20457],"type":"Point"}
}