{
  "type": "Feature",
  "properties": {
    "gn:admin1_code":"76.0",
    "gn:asciiname":"Idioke",
    "gn:country_code":"CI",
    "gn:dem":36,
    "gn:feature_class":"P",
    "gn:feature_code":"PPL",
    "gn:name":"Idiok\u00e9",
    "gn:population":0,
    "gn:timezone":"Africa/Abidjan",
    "iso:country":"CI",
    "name:und_x_variant":[
        "Idio",
        "Idiok\u00e9"
    ],
    "wof:name":"Idioke",
    "wof:placetype":"locality"
},
  "geometry": {"coordinates":[-7.43095,4.61796],"type":"Point"}
}