{
  "type": "Feature",
  "properties": {
    "gn:admin1_code":"94.0",
    "gn:asciiname":"Adaou",
    "gn:country_code":"CI",
    "gn:dem":73,
    "gn:feature_class":"P",
    "gn:feature_code":"PPL",
    "gn:name":"Adaou",
    "gn:population":0,
    "gn:timezone":"Africa/Abidjan",
    "iso:country":"CI",
    "wof:name":"Adaou",
    "wof:placetype":"locality"
},
  "geometry": {"coordinates":[-3.26443,5.42783],"type":"Point"}
}