{
  "type": "Feature",
  "properties": {
    "gn:admin1_code":"92",
    "gn:asciiname":"Yanvo",
    "gn:country_code":"CI",
    "gn:dem":235,
    "gn:feature_class":"P",
    "gn:feature_code":"PPL",
    "gn:name":"Yanvo",
    "gn:population":0,
    "gn:timezone":"Africa/Abidjan",
    "iso:country":"CI",
    "wof:name":"Yanvo",
    "wof:placetype":"locality"
},
  "geometry": {"coordinates":[-3.11434,7.76292],"type":"Point"}
}