{
  "type": "Feature",
  "properties": {
    "gn:admin1_code":"77",
    "gn:asciiname":"Syola",
    "gn:country_code":"CI",
    "gn:dem":407,
    "gn:feature_class":"P",
    "gn:feature_code":"PPL",
    "gn:name":"Syola",
    "gn:population":0,
    "gn:timezone":"Africa/Abidjan",
    "iso:country":"CI",
    "name:che_x_preferred":[
        "\u0421\u0435\u043b\u0430"
    ],
    "name:rus_x_preferred":[
        "\u0421\u0451\u043b\u0430"
    ],
    "wof:name":"Syola",
    "wof:placetype":"locality"
},
  "geometry": {"coordinates":[-7.45153,9.861],"type":"Point"}
}