{
  "type": "Feature",
  "properties": {
    "gn:admin1_code":"81",
    "gn:asciiname":"Lagoukro",
    "gn:country_code":"CI",
    "gn:dem":170,
    "gn:feature_class":"P",
    "gn:feature_code":"PPL",
    "gn:name":"Lagoukro",
    "gn:population":0,
    "gn:timezone":"Africa/Abidjan",
    "iso:country":"CI",
    "wof:name":"Lagoukro",
    "wof:placetype":"locality"
},
  "geometry": {"coordinates":[-3.79261,7.05703],"type":"Point"}
}