{
  "type": "Feature",
  "properties": {
    "gn:admin1_code":"82.0",
    "gn:asciiname":"Bonikro",
    "gn:country_code":"CI",
    "gn:dem":58,
    "gn:feature_class":"P",
    "gn:feature_code":"PPL",
    "gn:name":"Bonikro",
    "gn:population":0,
    "gn:timezone":"Africa/Abidjan",
    "iso:country":"CI",
    "wof:name":"Bonikro",
    "wof:placetype":"locality"
},
  "geometry": {"coordinates":[-4.28898,5.94039],"type":"Point"}
}