{
  "type": "Feature",
  "properties": {
    "gn:admin1_code":"81",
    "gn:asciiname":"Kotoblinouan",
    "gn:country_code":"CI",
    "gn:dem":226,
    "gn:feature_class":"P",
    "gn:feature_code":"PPL",
    "gn:name":"Kotoblinouan",
    "gn:population":0,
    "gn:timezone":"Africa/Abidjan",
    "iso:country":"CI",
    "name:und_x_variant":[
        "Kotobrinoi"
    ],
    "wof:name":"Kotoblinouan",
    "wof:placetype":"locality"
},
  "geometry": {"coordinates":[-4.93787,7.36251],"type":"Point"}
}