{
  "type": "Feature",
  "properties": {
    "gn:admin1_code":"95",
    "gn:asciiname":"Nazia",
    "gn:country_code":"CI",
    "gn:dem":230,
    "gn:feature_class":"P",
    "gn:feature_code":"PPL",
    "gn:name":"Nazia",
    "gn:population":0,
    "gn:timezone":"Africa/Abidjan",
    "iso:country":"CI",
    "wof:name":"Nazia",
    "wof:placetype":"locality"
},
  "geometry": {"coordinates":[-6.02067,6.24358],"type":"Point"}
}