{
  "type": "Feature",
  "properties": {
    "gn:admin1_code":"95.0",
    "gn:asciiname":"Douyo-Mayo",
    "gn:country_code":"CI",
    "gn:dem":261,
    "gn:feature_class":"P",
    "gn:feature_code":"PPL",
    "gn:name":"Douyo-Mayo",
    "gn:population":0,
    "gn:timezone":"Africa/Abidjan",
    "iso:country":"CI",
    "wof:name":"Douyo-Mayo",
    "wof:placetype":"locality"
},
  "geometry": {"coordinates":[-5.94056,5.94111],"type":"Point"}
}