{
  "type": "Feature",
  "properties": {
    "gn:admin1_code":"82.0",
    "gn:asciiname":"Aboni",
    "gn:country_code":"CI",
    "gn:dem":83,
    "gn:feature_class":"P",
    "gn:feature_code":"PPL",
    "gn:name":"Aboni",
    "gn:population":0,
    "gn:timezone":"Africa/Abidjan",
    "iso:country":"CI",
    "wof:name":"Aboni",
    "wof:placetype":"locality"
},
  "geometry": {"coordinates":[-4.50132,5.92131],"type":"Point"}
}