{
  "type": "Feature",
  "properties": {
    "gn:admin1_code":"97.0",
    "gn:asciiname":"Bandadougou",
    "gn:country_code":"CI",
    "gn:dem":542,
    "gn:feature_class":"P",
    "gn:feature_code":"PPL",
    "gn:name":"Bandadougou",
    "gn:population":0,
    "gn:timezone":"Africa/Abidjan",
    "iso:country":"CI",
    "wof:name":"Bandadougou",
    "wof:placetype":"locality"
},
  "geometry": {"coordinates":[-7.82984,8.2014],"type":"Point"}
}