{
  "type": "Feature",
  "properties": {
    "gn:admin1_code":"95",
    "gn:asciiname":"Zizezom",
    "gn:country_code":"CI",
    "gn:dem":201,
    "gn:feature_class":"P",
    "gn:feature_code":"PPL",
    "gn:name":"Ziz\u00e9zom",
    "gn:population":0,
    "gn:timezone":"Africa/Abidjan",
    "iso:country":"CI",
    "name:und_x_variant":[
        "Ziz\u00e9zion",
        "Ziz\u00e9zom"
    ],
    "wof:name":"Zizezom",
    "wof:placetype":"locality"
},
  "geometry": {"coordinates":[-6.15,6.31667],"type":"Point"}
}