{
  "type": "Feature",
  "properties": {
    "gn:admin1_code":"96.0",
    "gn:asciiname":"Baluzon",
    "gn:country_code":"CI",
    "gn:dem":265,
    "gn:feature_class":"P",
    "gn:feature_code":"PPL",
    "gn:name":"Baluzon",
    "gn:population":0,
    "gn:timezone":"Africa/Abidjan",
    "iso:country":"CI",
    "wof:name":"Baluzon",
    "wof:placetype":"locality"
},
  "geometry": {"coordinates":[-6.42248,6.89654],"type":"Point"}
}