{
  "type": "Feature",
  "properties": {
    "gn:admin1_code":"81.0",
    "gn:asciiname":"Bouafoukro",
    "gn:country_code":"CI",
    "gn:dem":108,
    "gn:feature_class":"P",
    "gn:feature_code":"PPL",
    "gn:name":"Bouafoukro",
    "gn:population":0,
    "gn:timezone":"Africa/Abidjan",
    "iso:country":"CI",
    "name:und_x_variant":[
        "Bouaffoukro"
    ],
    "wof:name":"Bouafoukro",
    "wof:placetype":"locality"
},
  "geometry": {"coordinates":[-4.47453,6.67163],"type":"Point"}
}