{
  "type": "Feature",
  "properties": {
    "gn:admin1_code":"92",
    "gn:asciiname":"Yakro",
    "gn:country_code":"CI",
    "gn:dem":238,
    "gn:feature_class":"P",
    "gn:feature_code":"PPL",
    "gn:name":"Yakro",
    "gn:population":0,
    "gn:timezone":"Africa/Abidjan",
    "iso:country":"CI",
    "wof:name":"Yakro",
    "wof:placetype":"locality"
},
  "geometry": {"coordinates":[-3.69321,7.88261],"type":"Point"}
}