{
  "type": "Feature",
  "properties": {
    "gn:admin1_code":"89.0",
    "gn:asciiname":"Eliape",
    "gn:country_code":"CI",
    "gn:dem":17,
    "gn:feature_class":"P",
    "gn:feature_code":"PPL",
    "gn:name":"Eliap\u00e9",
    "gn:population":0,
    "gn:timezone":"Africa/Abidjan",
    "iso:country":"CI",
    "wof:name":"Eliape",
    "wof:placetype":"locality"
},
  "geometry": {"coordinates":[-3.18836,5.24853],"type":"Point"}
}