{
  "type": "Feature",
  "properties": {
    "gn:admin1_code":"87",
    "gn:asciiname":"Nechokaha",
    "gn:country_code":"CI",
    "gn:dem":358,
    "gn:feature_class":"P",
    "gn:feature_code":"PPL",
    "gn:name":"N\u00e9chokaha",
    "gn:population":0,
    "gn:timezone":"Africa/Abidjan",
    "iso:country":"CI",
    "wof:name":"Nechokaha",
    "wof:placetype":"locality"
},
  "geometry": {"coordinates":[-5.58333,9.28333],"type":"Point"}
}