{
  "type": "Feature",
  "properties": {
    "gn:admin1_code":"81",
    "gn:asciiname":"Kravassou",
    "gn:country_code":"CI",
    "gn:dem":74,
    "gn:feature_class":"P",
    "gn:feature_code":"PPL",
    "gn:name":"Kravassou",
    "gn:population":0,
    "gn:timezone":"Africa/Abidjan",
    "iso:country":"CI",
    "wof:name":"Kravassou",
    "wof:placetype":"locality"
},
  "geometry": {"coordinates":[-4.71457,6.26072],"type":"Point"}
}