{
  "type": "Feature",
  "properties": {
    "gn:admin1_code":"78.0",
    "gn:asciiname":"Diane",
    "gn:country_code":"CI",
    "gn:dem":418,
    "gn:feature_class":"P",
    "gn:feature_code":"PPL",
    "gn:name":"Dian\u00e9",
    "gn:population":0,
    "gn:timezone":"Africa/Abidjan",
    "iso:country":"CI",
    "name:bre_x_preferred":[
        "Diane"
    ],
    "name:fra_x_preferred":[
        "Diane"
    ],
    "name:jpn_x_preferred":[
        "\u30c0\u30a4\u30a2\u30f3"
    ],
    "name:nld_x_preferred":[
        "Diane"
    ],
    "name:spa_x_preferred":[
        "Diane"
    ],
    "wof:name":"Diane",
    "wof:placetype":"locality"
},
  "geometry": {"coordinates":[-7.43561,7.55709],"type":"Point"}
}