{
  "type": "Feature",
  "properties": {
    "gn:admin1_code":"82.0",
    "gn:asciiname":"Akobi",
    "gn:country_code":"CI",
    "gn:dem":82,
    "gn:feature_class":"P",
    "gn:feature_code":"PPL",
    "gn:name":"Akobi",
    "gn:population":0,
    "gn:timezone":"Africa/Abidjan",
    "iso:country":"CI",
    "wof:name":"Akobi",
    "wof:placetype":"locality"
},
  "geometry": {"coordinates":[-4.4212,5.94565],"type":"Point"}
}