{
  "type": "Feature",
  "properties": {
    "gn:admin1_code":"87",
    "gn:asciiname":"Nanpirgekaha",
    "gn:country_code":"CI",
    "gn:dem":335,
    "gn:feature_class":"P",
    "gn:feature_code":"PPL",
    "gn:name":"Nanpirg\u00e9kaha",
    "gn:population":0,
    "gn:timezone":"Africa/Abidjan",
    "iso:country":"CI",
    "name:und_x_variant":[
        "Nanpirgu\u00e9kaha",
        "Nanpirg\u00e9kaha"
    ],
    "wof:name":"Nanpirgekaha",
    "wof:placetype":"locality"
},
  "geometry": {"coordinates":[-5.39577,9.36598],"type":"Point"}
}