{
  "type": "Feature",
  "properties": {
    "gn:admin1_code":"82.0",
    "gn:asciiname":"Fetchi Adja",
    "gn:country_code":"CI",
    "gn:dem":48,
    "gn:feature_class":"P",
    "gn:feature_code":"PPL",
    "gn:name":"F\u00e9tchi Adja",
    "gn:population":0,
    "gn:timezone":"Africa/Abidjan",
    "iso:country":"CI",
    "wof:name":"Fetchi Adja",
    "wof:placetype":"locality"
},
  "geometry": {"coordinates":[-4.24624,5.8572],"type":"Point"}
}