{
  "type": "Feature",
  "properties": {
    "gn:admin1_code":"90",
    "gn:asciiname":"Sarakakro",
    "gn:country_code":"CI",
    "gn:dem":257,
    "gn:feature_class":"P",
    "gn:feature_code":"PPL",
    "gn:name":"Sarakakro",
    "gn:population":0,
    "gn:timezone":"Africa/Abidjan",
    "iso:country":"CI",
    "name:und_x_variant":[
        "Sarakro"
    ],
    "wof:name":"Sarakakro",
    "wof:placetype":"locality"
},
  "geometry": {"coordinates":[-5.05839,7.49546],"type":"Point"}
}