{
  "type": "Feature",
  "properties": {
    "gn:admin1_code":"76",
    "gn:asciiname":"Lekidou",
    "gn:country_code":"CI",
    "gn:dem":10,
    "gn:feature_class":"P",
    "gn:feature_code":"PPL",
    "gn:name":"L\u00e9kidou",
    "gn:population":0,
    "gn:timezone":"Africa/Abidjan",
    "iso:country":"CI",
    "wof:name":"Lekidou",
    "wof:placetype":"locality"
},
  "geometry": {"coordinates":[-6.12558,4.99229],"type":"Point"}
}