{
  "type": "Feature",
  "properties": {
    "gn:admin1_code":"78.0",
    "gn:asciiname":"Boyatro",
    "gn:country_code":"CI",
    "gn:dem":334,
    "gn:feature_class":"P",
    "gn:feature_code":"PPL",
    "gn:name":"Boyatro",
    "gn:population":0,
    "gn:timezone":"Africa/Abidjan",
    "iso:country":"CI",
    "wof:name":"Boyatro",
    "wof:placetype":"locality"
},
  "geometry": {"coordinates":[-8.34915,7.2443],"type":"Point"}
}