{
  "type": "Feature",
  "properties": {
    "gn:admin1_code":"78",
    "gn:asciiname":"Zoutouo",
    "gn:country_code":"CI",
    "gn:dem":271,
    "gn:feature_class":"P",
    "gn:feature_code":"PPL",
    "gn:name":"Zoutouo",
    "gn:population":0,
    "gn:timezone":"Africa/Abidjan",
    "iso:country":"CI",
    "name:und_x_variant":[
        "Zontouo",
        "Zoutouo"
    ],
    "wof:name":"Zoutouo",
    "wof:placetype":"locality"
},
  "geometry": {"coordinates":[-8.24212,7.00812],"type":"Point"}
}