{
  "type": "Feature",
  "properties": {
    "gn:admin1_code":"97",
    "gn:asciiname":"Tiebondougou",
    "gn:country_code":"CI",
    "gn:dem":434,
    "gn:feature_class":"P",
    "gn:feature_code":"PPL",
    "gn:name":"Tiebondougou",
    "gn:population":0,
    "gn:timezone":"Africa/Abidjan",
    "iso:country":"CI",
    "wof:name":"Tiebondougou",
    "wof:placetype":"locality"
},
  "geometry": {"coordinates":[-7.65188,8.79936],"type":"Point"}
}