{
  "type": "Feature",
  "properties": {
    "gn:admin1_code":"92.0",
    "gn:asciiname":"Boudi",
    "gn:country_code":"CI",
    "gn:dem":313,
    "gn:feature_class":"P",
    "gn:feature_code":"PPL",
    "gn:name":"Boudi",
    "gn:population":0,
    "gn:timezone":"Africa/Abidjan",
    "iso:country":"CI",
    "wof:name":"Boudi",
    "wof:placetype":"locality"
},
  "geometry": {"coordinates":[-2.90137,7.95198],"type":"Point"}
}