{
  "type": "Feature",
  "properties": {
    "gn:admin1_code":"93.0",
    "gn:asciiname":"Ancien Koumassi",
    "gn:country_code":"CI",
    "gn:dem":5,
    "gn:feature_class":"P",
    "gn:feature_code":"PPL",
    "gn:name":"Ancien Koumassi",
    "gn:population":0,
    "gn:timezone":"Africa/Abidjan",
    "iso:country":"CI",
    "wof:name":"Ancien Koumassi",
    "wof:placetype":"locality"
},
  "geometry": {"coordinates":[-3.96717,5.27486],"type":"Point"}
}