{
  "type": "Feature",
  "properties": {
    "gn:admin1_code":"78",
    "gn:asciiname":"Trodelepleu",
    "gn:country_code":"CI",
    "gn:dem":380,
    "gn:feature_class":"P",
    "gn:feature_code":"PPL",
    "gn:name":"Trodelepleu",
    "gn:population":0,
    "gn:timezone":"Africa/Abidjan",
    "iso:country":"CI",
    "wof:name":"Trodelepleu",
    "wof:placetype":"locality"
},
  "geometry": {"coordinates":[-8.17864,7.28951],"type":"Point"}
}