{
  "type": "Feature",
  "properties": {
    "gn:admin1_code":"96.0",
    "gn:asciiname":"Dema",
    "gn:country_code":"CI",
    "gn:dem":255,
    "gn:feature_class":"P",
    "gn:feature_code":"PPL",
    "gn:name":"D\u00e9ma",
    "gn:population":0,
    "gn:timezone":"Africa/Abidjan",
    "iso:country":"CI",
    "name:ceb_x_preferred":[
        "Dema"
    ],
    "name:deu_x_preferred":[
        "Dema"
    ],
    "name:fra_x_preferred":[
        "Dema"
    ],
    "name:ita_x_preferred":[
        "Dema"
    ],
    "name:swe_x_preferred":[
        "Dema"
    ],
    "wof:name":"Dema",
    "wof:placetype":"locality"
},
  "geometry": {"coordinates":[-6.48194,7.30833],"type":"Point"}
}