{
  "type": "Feature",
  "properties": {
    "gn:admin1_code":"81",
    "gn:asciiname":"Ngrikankro",
    "gn:country_code":"CI",
    "gn:dem":165,
    "gn:feature_class":"P",
    "gn:feature_code":"PPL",
    "gn:name":"Ngrikankro",
    "gn:population":0,
    "gn:timezone":"Africa/Abidjan",
    "iso:country":"CI",
    "wof:name":"Ngrikankro",
    "wof:placetype":"locality"
},
  "geometry": {"coordinates":[-4.12944,7.2875],"type":"Point"}
}