{
  "type": "Feature",
  "properties": {
    "gn:admin1_code":"93.0",
    "gn:asciiname":"Tape Issaka",
    "gn:country_code":"CI",
    "gn:dem":85,
    "gn:feature_class":"P",
    "gn:feature_code":"PPL",
    "gn:name":"Tap\u00e9 Issaka",
    "gn:population":0,
    "gn:timezone":"Africa/Abidjan",
    "iso:country":"CI",
    "wof:name":"Tape Issaka",
    "wof:placetype":"locality"
},
  "geometry": {"coordinates":[-4.22846,5.37155],"type":"Point"}
}