{
  "type": "Feature",
  "properties": {
    "gn:admin1_code":"96",
    "gn:asciiname":"Labia",
    "gn:country_code":"CI",
    "gn:dem":268,
    "gn:feature_class":"P",
    "gn:feature_code":"PPL",
    "gn:name":"Labia",
    "gn:population":0,
    "gn:timezone":"Africa/Abidjan",
    "iso:country":"CI",
    "name:als_x_preferred":[
        "Schamlippe"
    ],
    "name:ara_x_preferred":[
        "\u0634\u0641\u0631\u0627\u0646"
    ],
    "name:ben_x_preferred":[
        "\u09b2\u09c7\u09ac\u09bf\u09af\u09bc\u09be"
    ],
    "name:bul_x_preferred":[
        "\u0421\u0440\u0430\u043c\u043d\u0438 \u0443\u0441\u0442\u043d\u0438"
    ],
    "name:cat_x_preferred":[
        "Llavis"
    ],
    "name:ces_x_preferred":[
        "Stydk\u00e9 pysky"
    ],
    "name:cym_x_preferred":[
        "Labia"
    ],
    "name:dan_x_preferred":[
        "Skaml\u00e6ber"
    ],
    "name:deu_x_preferred":[
        "Schamlippen"
    ],
    "name:div_x_preferred":[
        "\u078a\u07a6\u0783\u07aa\u0796\u07aa\u078e\u07ac \u078c\u07aa\u0782\u07b0\u078a\u07a6\u078c\u07b0"
    ],
    "name:epo_x_preferred":[
        "Vulvaj lipoj"
    ],
    "name:eus_x_preferred":[
        "Ezpainak"
    ],
    "name:fas_x_preferred":[
        "\u0644\u0628\u0647"
    ],
    "name:fin_x_preferred":[
        "H\u00e4pyhuulet"
    ],
    "name:fra_x_preferred":[
        "L\u00e8vre vaginale"
    ],
    "name:glg_x_preferred":[
        "Labios"
    ],
    "name:heb_x_preferred":[
        "\u05e9\u05e4\u05ea\u05d9\u05d9\u05dd"
    ],
    "name:hin_x_preferred":[
        "\u092d\u0917\u094b\u0937\u094d\u0920"
    ],
    "name:isl_x_preferred":[
        "Skapabarmar"
    ],
    "name:kaz_x_preferred":[
        "\u0416\u044b\u043d\u044b\u0441 \u0435\u0440\u043d\u0435\u0443\u043b\u0435\u0440\u0456"
    ],
    "name:lit_x_preferred":[
        "Lytin\u0117s l\u016bpos"
    ],
    "name:nds_x_preferred":[
        "Schaamlippen"
    ],
    "name:nep_x_preferred":[
        "\u092d\u0917\u094b\u0937\u094d\u0920"
    ],
    "name:nld_x_preferred":[
        "Schaamlippen"
    ],
    "name:nno_x_preferred":[
        "Kj\u00f8nnslepper"
    ],
    "name:nor_x_preferred":[
        "Kvinnelige kj\u00f8nnslepper"
    ],
    "name:pol_x_preferred":[
        "Wargi sromowe"
    ],
    "name:por_x_preferred":[
        "L\u00e1bios"
    ],
    "name:ron_x_preferred":[
        "Labiile vaginale"
    ],
    "name:rus_x_preferred":[
        "\u041f\u043e\u043b\u043e\u0432\u044b\u0435 \u0433\u0443\u0431\u044b"
    ],
    "name:spa_x_preferred":[
        "Labios"
    ],
    "name:swe_x_preferred":[
        "Blygdl\u00e4ppar"
    ],
    "name:tam_x_preferred":[
        "\u0b87\u0ba4\u0bb4\u0bcd"
    ],
    "name:tgl_x_preferred":[
        "Labia"
    ],
    "name:tha_x_preferred":[
        "\u0e41\u0e04\u0e21"
    ],
    "name:tur_x_preferred":[
        "Labia"
    ],
    "name:ukr_x_preferred":[
        "\u0421\u0442\u0430\u0442\u0435\u0432\u0456 \u0433\u0443\u0431\u0438"
    ],
    "wof:name":"Labia",
    "wof:placetype":"locality"
},
  "geometry": {"coordinates":[-6.45833,6.88639],"type":"Point"}
}