{
  "type": "Feature",
  "properties": {
    "gn:admin1_code":"96",
    "gn:asciiname":"Labia",
    "gn:country_code":"CI",
    "gn:dem":268,
    "gn:feature_class":"P",
    "gn:feature_code":"PPL",
    "gn:name":"Labia",
    "gn:population":0,
    "gn:timezone":"Africa/Abidjan",
    "iso:country":"CI",
    "wof:name":"Labia",
    "wof:placetype":"locality"
},
  "geometry": {"coordinates":[-6.45833,6.88639],"type":"Point"}
}