{
  "type": "Feature",
  "properties": {
    "gn:admin1_code":"81.0",
    "gn:asciiname":"Eadiani-Kouadiokro",
    "gn:country_code":"CI",
    "gn:dem":230,
    "gn:feature_class":"P",
    "gn:feature_code":"PPL",
    "gn:name":"Eadiani-Kouadiokro",
    "gn:population":0,
    "gn:timezone":"Africa/Abidjan",
    "iso:country":"CI",
    "wof:name":"Eadiani-Kouadiokro",
    "wof:placetype":"locality"
},
  "geometry": {"coordinates":[-4.13333,7.36667],"type":"Point"}
}