{
  "type": "Feature",
  "properties": {
    "gn:admin1_code":"87.0",
    "gn:asciiname":"Forokouan",
    "gn:country_code":"CI",
    "gn:dem":346,
    "gn:feature_class":"P",
    "gn:feature_code":"PPL",
    "gn:name":"Forokouan",
    "gn:population":0,
    "gn:timezone":"Africa/Abidjan",
    "iso:country":"CI",
    "wof:name":"Forokouan",
    "wof:placetype":"locality"
},
  "geometry": {"coordinates":[-6.06799,9.98031],"type":"Point"}
}