{
  "type": "Feature",
  "properties": {
    "gn:admin1_code":"92",
    "gn:asciiname":"Konguidougou",
    "gn:country_code":"CI",
    "gn:dem":293,
    "gn:feature_class":"P",
    "gn:feature_code":"PPL",
    "gn:name":"Konguidougou",
    "gn:population":0,
    "gn:timezone":"Africa/Abidjan",
    "iso:country":"CI",
    "wof:name":"Konguidougou",
    "wof:placetype":"locality"
},
  "geometry": {"coordinates":[-3.00532,9.38164],"type":"Point"}
}