{
  "type": "Feature",
  "properties": {
    "gn:admin1_code":"87.0",
    "gn:asciiname":"Boyo",
    "gn:country_code":"CI",
    "gn:dem":354,
    "gn:feature_class":"P",
    "gn:feature_code":"PPL",
    "gn:name":"Boyo",
    "gn:population":0,
    "gn:timezone":"Africa/Abidjan",
    "iso:country":"CI",
    "name:und_x_variant":[
        "Podyo",
        "Boundiou",
        "Boyo"
    ],
    "wof:name":"Boyo",
    "wof:placetype":"locality"
},
  "geometry": {"coordinates":[-6.37826,9.95478],"type":"Point"}
}