{
  "type": "Feature",
  "properties": {
    "gn:admin1_code":"96.0",
    "gn:asciiname":"Tezie",
    "gn:country_code":"CI",
    "gn:dem":234,
    "gn:feature_class":"P",
    "gn:feature_code":"PPL",
    "gn:name":"T\u00e9zi\u00e9",
    "gn:population":0,
    "gn:timezone":"Africa/Abidjan",
    "iso:country":"CI",
    "name:azb_x_preferred":[
        "\u062a\u0632\u06cc\u0647"
    ],
    "name:fas_x_preferred":[
        "\u062a\u0632\u06cc\u0647"
    ],
    "name:fra_x_preferred":[
        "T\u00e9zi\u00e9"
    ],
    "name:msa_x_preferred":[
        "T\u00e9zi\u00e9"
    ],
    "name:und_x_variant":[
        "T\u00e9zi\u00e9"
    ],
    "wof:name":"Tezie",
    "wof:placetype":"locality"
},
  "geometry": {"coordinates":[-6.3025,6.3875],"type":"Point"}
}