{
  "type": "Feature",
  "properties": {
    "gn:admin1_code":"90.0",
    "gn:asciiname":"Kinkeledougou",
    "gn:country_code":"CI",
    "gn:dem":279,
    "gn:feature_class":"P",
    "gn:feature_code":"PPL",
    "gn:name":"Kink\u00e9l\u00e9dougou",
    "gn:population":0,
    "gn:timezone":"Africa/Abidjan",
    "iso:country":"CI",
    "wof:name":"Kinkeledougou",
    "wof:placetype":"locality"
},
  "geometry": {"coordinates":[-4.47825,8.34636],"type":"Point"}
}