{
  "type": "Feature",
  "properties": {
    "gn:admin1_code":"76",
    "gn:asciiname":"Tripoko",
    "gn:country_code":"CI",
    "gn:dem":150,
    "gn:feature_class":"P",
    "gn:feature_code":"PPL",
    "gn:name":"Tripoko",
    "gn:population":0,
    "gn:timezone":"Africa/Abidjan",
    "iso:country":"CI",
    "name:und_x_variant":[
        "Tiripoko",
        "Tripoko"
    ],
    "wof:name":"Tripoko",
    "wof:placetype":"locality"
},
  "geometry": {"coordinates":[-5.88108,5.42743],"type":"Point"}
}