{
  "type": "Feature",
  "properties": {
    "gn:admin1_code":"92.0",
    "gn:asciiname":"Balanfodougou",
    "gn:country_code":"CI",
    "gn:dem":239,
    "gn:feature_class":"P",
    "gn:feature_code":"PPL",
    "gn:name":"Balanfodougou",
    "gn:population":0,
    "gn:timezone":"Africa/Abidjan",
    "iso:country":"CI",
    "wof:name":"Balanfodougou",
    "wof:placetype":"locality"
},
  "geometry": {"coordinates":[-4.28333,9.61667],"type":"Point"}
}