{
  "type": "Feature",
  "properties": {
    "gn:admin1_code":"78.0",
    "gn:asciiname":"Gbehigui",
    "gn:country_code":"CI",
    "gn:dem":882,
    "gn:feature_class":"P",
    "gn:feature_code":"PPL",
    "gn:name":"Gb\u00e9higui",
    "gn:population":0,
    "gn:timezone":"Africa/Abidjan",
    "iso:country":"CI",
    "name:und_x_variant":[
        "Gb\u00e9higui",
        "B\u00e9igi"
    ],
    "wof:name":"Gbehigui",
    "wof:placetype":"locality"
},
  "geometry": {"coordinates":[-7.46778,7.72083],"type":"Point"}
}