{
  "type": "Feature",
  "properties": {
    "gn:admin1_code":"81",
    "gn:asciiname":"Kofi Kouassikro",
    "gn:country_code":"CI",
    "gn:dem":211,
    "gn:feature_class":"P",
    "gn:feature_code":"PPL",
    "gn:name":"Kofi Kouassikro",
    "gn:population":0,
    "gn:timezone":"Africa/Abidjan",
    "iso:country":"CI",
    "wof:name":"Kofi Kouassikro",
    "wof:placetype":"locality"
},
  "geometry": {"coordinates":[-5.18821,7.19597],"type":"Point"}
}