{
  "type": "Feature",
  "properties": {
    "gn:admin1_code":"90",
    "gn:asciiname":"Ngatakro",
    "gn:country_code":"CI",
    "gn:dem":248,
    "gn:feature_class":"P",
    "gn:feature_code":"PPL",
    "gn:name":"Ngatakro",
    "gn:population":0,
    "gn:timezone":"Africa/Abidjan",
    "iso:country":"CI",
    "name:und_x_variant":[
        "Lombo-Ngatakro"
    ],
    "wof:name":"Ngatakro",
    "wof:placetype":"locality"
},
  "geometry": {"coordinates":[-5.34618,7.52941],"type":"Point"}
}