{
  "type": "Feature",
  "properties": {
    "gn:admin1_code":"93.0",
    "gn:asciiname":"Audoin Beugreto",
    "gn:country_code":"CI",
    "gn:dem":8,
    "gn:feature_class":"P",
    "gn:feature_code":"PPL",
    "gn:name":"Audoin Beugr\u00e9to",
    "gn:population":0,
    "gn:timezone":"Africa/Abidjan",
    "iso:country":"CI",
    "wof:name":"Audoin Beugreto",
    "wof:placetype":"locality"
},
  "geometry": {"coordinates":[-4.14011,5.29201],"type":"Point"}
}