{
  "type": "Feature",
  "properties": {
    "gn:admin1_code":"97.0",
    "gn:asciiname":"Gwarana",
    "gn:country_code":"CI",
    "gn:dem":305,
    "gn:feature_class":"P",
    "gn:feature_code":"PPL",
    "gn:name":"Gwarana",
    "gn:population":0,
    "gn:timezone":"Africa/Abidjan",
    "iso:country":"CI",
    "wof:name":"Gwarana",
    "wof:placetype":"locality"
},
  "geometry": {"coordinates":[-6.2099,8.07444],"type":"Point"}
}