{
  "type": "Feature",
  "properties": {
    "gn:admin1_code":"94.0",
    "gn:asciiname":"Bagreben",
    "gn:country_code":"CI",
    "gn:dem":77,
    "gn:feature_class":"P",
    "gn:feature_code":"PPL",
    "gn:name":"Bagr\u00e9ben",
    "gn:population":0,
    "gn:timezone":"Africa/Abidjan",
    "iso:country":"CI",
    "wof:name":"Bagreben",
    "wof:placetype":"locality"
},
  "geometry": {"coordinates":[-3.12,5.58917],"type":"Point"}
}