{
  "type": "Feature",
  "properties": {
    "gn:admin1_code":"87",
    "gn:asciiname":"Pouniakele",
    "gn:country_code":"CI",
    "gn:dem":357,
    "gn:feature_class":"P",
    "gn:feature_code":"PPL",
    "gn:name":"Pouniak\u00e9l\u00e9",
    "gn:population":0,
    "gn:timezone":"Africa/Abidjan",
    "iso:country":"CI",
    "wof:name":"Pouniakele",
    "wof:placetype":"locality"
},
  "geometry": {"coordinates":[-6.51719,10.13331],"type":"Point"}
}