{
  "type": "Feature",
  "properties": {
    "gn:admin1_code":"96",
    "gn:asciiname":"Tetia",
    "gn:country_code":"CI",
    "gn:dem":196,
    "gn:feature_class":"P",
    "gn:feature_code":"PPL",
    "gn:name":"T\u00e9tia",
    "gn:population":0,
    "gn:timezone":"Africa/Abidjan",
    "iso:country":"CI",
    "wof:name":"Tetia",
    "wof:placetype":"locality"
},
  "geometry": {"coordinates":[-6.53806,6.41611],"type":"Point"}
}