{
  "type": "Feature",
  "properties": {
    "gn:admin1_code":"81.0",
    "gn:asciiname":"Adjiebo",
    "gn:country_code":"CI",
    "gn:dem":182,
    "gn:feature_class":"P",
    "gn:feature_code":"PPL",
    "gn:name":"Adjiebo",
    "gn:population":0,
    "gn:timezone":"Africa/Abidjan",
    "iso:country":"CI",
    "name:und_x_variant":[
        "Adi\u00e9bo"
    ],
    "wof:name":"Adjiebo",
    "wof:placetype":"locality"
},
  "geometry": {"coordinates":[-4.81184,7.30396],"type":"Point"}
}