{
  "type": "Feature",
  "properties": {
    "gn:admin1_code":"78",
    "gn:asciiname":"Krikouma",
    "gn:country_code":"CI",
    "gn:dem":353,
    "gn:feature_class":"P",
    "gn:feature_code":"PPL",
    "gn:name":"Krikouma",
    "gn:population":0,
    "gn:timezone":"Africa/Abidjan",
    "iso:country":"CI",
    "wof:name":"Krikouma",
    "wof:placetype":"locality"
},
  "geometry": {"coordinates":[-7.49732,7.4074],"type":"Point"}
}