{
  "type": "Feature",
  "properties": {
    "gn:admin1_code":"90.0",
    "gn:asciiname":"Gomo",
    "gn:country_code":"CI",
    "gn:dem":259,
    "gn:feature_class":"P",
    "gn:feature_code":"PPL",
    "gn:name":"Gomo",
    "gn:population":0,
    "gn:timezone":"Africa/Abidjan",
    "iso:country":"CI",
    "name:ceb_x_preferred":[
        "Gomo"
    ],
    "name:por_x_preferred":[
        "Gomo"
    ],
    "name:swe_x_preferred":[
        "Gomo"
    ],
    "name:und_x_variant":[
        "Goma"
    ],
    "wof:name":"Gomo",
    "wof:placetype":"locality"
},
  "geometry": {"coordinates":[-5.0725,7.42341],"type":"Point"}
}