{
  "type": "Feature",
  "properties": {
    "gn:admin1_code":"92",
    "gn:asciiname":"Kofikokourokouro",
    "gn:country_code":"CI",
    "gn:dem":228,
    "gn:feature_class":"P",
    "gn:feature_code":"PPL",
    "gn:name":"Kofikokourokouro",
    "gn:population":0,
    "gn:timezone":"Africa/Abidjan",
    "iso:country":"CI",
    "wof:name":"Kofikokourokouro",
    "wof:placetype":"locality"
},
  "geometry": {"coordinates":[-3.16955,7.22826],"type":"Point"}
}