{
  "type": "Feature",
  "properties": {
    "gn:admin1_code":"81",
    "gn:asciiname":"Mekro",
    "gn:country_code":"CI",
    "gn:dem":137,
    "gn:feature_class":"P",
    "gn:feature_code":"PPL",
    "gn:name":"M\u00e9kro",
    "gn:population":0,
    "gn:timezone":"Africa/Abidjan",
    "iso:country":"CI",
    "wof:name":"Mekro",
    "wof:placetype":"locality"
},
  "geometry": {"coordinates":[-4.26667,6.75],"type":"Point"}
}