{
  "type": "Feature",
  "properties": {
    "gn:admin1_code":"90",
    "gn:asciiname":"Sanderekro",
    "gn:country_code":"CI",
    "gn:dem":245,
    "gn:feature_class":"P",
    "gn:feature_code":"PPL",
    "gn:name":"Sand\u00e9r\u00e9kro",
    "gn:population":0,
    "gn:timezone":"Africa/Abidjan",
    "iso:country":"CI",
    "wof:name":"Sanderekro",
    "wof:placetype":"locality"
},
  "geometry": {"coordinates":[-4.68541,7.99401],"type":"Point"}
}