{
  "type": "Feature",
  "properties": {
    "gn:admin1_code":"95",
    "gn:asciiname":"Mahibouo",
    "gn:country_code":"CI",
    "gn:dem":231,
    "gn:feature_class":"P",
    "gn:feature_code":"PPL",
    "gn:name":"Mahibouo",
    "gn:population":0,
    "gn:timezone":"Africa/Abidjan",
    "iso:country":"CI",
    "name:und_x_variant":[
        "Mahiboua"
    ],
    "wof:name":"Mahibouo",
    "wof:placetype":"locality"
},
  "geometry": {"coordinates":[-5.9215,6.04896],"type":"Point"}
}