{
  "type": "Feature",
  "properties": {
    "gn:admin1_code":"90",
    "gn:asciiname":"Kouassiblekro",
    "gn:country_code":"CI",
    "gn:dem":257,
    "gn:feature_class":"P",
    "gn:feature_code":"PPL",
    "gn:name":"Kouassibl\u00e9kro",
    "gn:population":0,
    "gn:timezone":"Africa/Abidjan",
    "iso:country":"CI",
    "wof:name":"Kouassiblekro",
    "wof:placetype":"locality"
},
  "geometry": {"coordinates":[-4.94633,7.67272],"type":"Point"}
}