{
  "type": "Feature",
  "properties": {
    "gn:admin1_code":"78.0",
    "gn:asciiname":"Bouempleu",
    "gn:country_code":"CI",
    "gn:dem":366,
    "gn:feature_class":"P",
    "gn:feature_code":"PPL",
    "gn:name":"Bouempleu",
    "gn:population":0,
    "gn:timezone":"Africa/Abidjan",
    "iso:country":"CI",
    "wof:name":"Bouempleu",
    "wof:placetype":"locality"
},
  "geometry": {"coordinates":[-8.17069,7.17858],"type":"Point"}
}