{
  "type": "Feature",
  "properties": {
    "gn:admin1_code":"78.0",
    "gn:asciiname":"Gbapleu",
    "gn:country_code":"CI",
    "gn:dem":344,
    "gn:feature_class":"P",
    "gn:feature_code":"PPL",
    "gn:name":"Gbapleu",
    "gn:population":0,
    "gn:timezone":"Africa/Abidjan",
    "iso:country":"CI",
    "wof:name":"Gbapleu",
    "wof:placetype":"locality"
},
  "geometry": {"coordinates":[-7.52887,7.40723],"type":"Point"}
}