{
  "type": "Feature",
  "properties": {
    "gn:admin1_code":"77",
    "gn:asciiname":"Ouayere",
    "gn:country_code":"CI",
    "gn:dem":364,
    "gn:feature_class":"P",
    "gn:feature_code":"PPL",
    "gn:name":"Ouay\u00e9r\u00e9",
    "gn:population":0,
    "gn:timezone":"Africa/Abidjan",
    "iso:country":"CI",
    "name:und_x_variant":[
        "Wahir\u00e9",
        "Ouahir\u00e9",
        "Ouay\u00e9r\u00e9"
    ],
    "wof:name":"Ouayere",
    "wof:placetype":"locality"
},
  "geometry": {"coordinates":[-6.91722,10.11944],"type":"Point"}
}