{
  "type": "Feature",
  "properties": {
    "gn:admin1_code":"95",
    "gn:asciiname":"Zahililie",
    "gn:country_code":"CI",
    "gn:dem":216,
    "gn:feature_class":"P",
    "gn:feature_code":"PPL",
    "gn:name":"Zahilili\u00e9",
    "gn:population":0,
    "gn:timezone":"Africa/Abidjan",
    "iso:country":"CI",
    "wof:name":"Zahililie",
    "wof:placetype":"locality"
},
  "geometry": {"coordinates":[-5.63186,5.82937],"type":"Point"}
}