{
  "type": "Feature",
  "properties": {
    "gn:admin1_code":"92",
    "gn:asciiname":"Tabagne",
    "gn:country_code":"CI",
    "gn:dem":292,
    "gn:feature_class":"P",
    "gn:feature_code":"PPL",
    "gn:name":"Tabagn\u00e9",
    "gn:population":0,
    "gn:timezone":"Africa/Abidjan",
    "iso:country":"CI",
    "name:fra_x_preferred":[
        "Tabagne"
    ],
    "name:ita_x_preferred":[
        "Tabagne"
    ],
    "name:msa_x_preferred":[
        "Tabagne"
    ],
    "name:und_x_variant":[
        "Tabagui",
        "Tabanye",
        "Tabagn\u00e9"
    ],
    "wof:name":"Tabagne",
    "wof:placetype":"locality"
},
  "geometry": {"coordinates":[-3.06871,7.99104],"type":"Point"}
}