{
  "type": "Feature",
  "properties": {
    "gn:admin1_code":"76",
    "gn:asciiname":"Okrouyo",
    "gn:country_code":"CI",
    "gn:dem":158,
    "gn:feature_class":"P",
    "gn:feature_code":"PPL",
    "gn:name":"Okrouyo",
    "gn:population":0,
    "gn:timezone":"Africa/Abidjan",
    "iso:country":"CI",
    "wof:name":"Okrouyo",
    "wof:placetype":"locality"
},
  "geometry": {"coordinates":[-6.40785,5.76443],"type":"Point"}
}