{
  "type": "Feature",
  "properties": {
    "gn:admin1_code":"77.0",
    "gn:asciiname":"Bengo",
    "gn:country_code":"CI",
    "gn:dem":474,
    "gn:feature_class":"P",
    "gn:feature_code":"PPL",
    "gn:name":"B\u00e8ngo",
    "gn:population":0,
    "gn:timezone":"Africa/Abidjan",
    "iso:country":"CI",
    "name:ceb_x_preferred":[
        "Bengo"
    ],
    "name:deu_x_preferred":[
        "Bengo"
    ],
    "name:ita_x_preferred":[
        "Bengo"
    ],
    "name:swe_x_preferred":[
        "Bengo"
    ],
    "wof:name":"Bengo",
    "wof:placetype":"locality"
},
  "geometry": {"coordinates":[-7.79492,9.16581],"type":"Point"}
}