{
  "type": "Feature",
  "properties": {
    "gn:admin1_code":"93.0",
    "gn:asciiname":"Anon",
    "gn:country_code":"CI",
    "gn:dem":33,
    "gn:feature_class":"P",
    "gn:feature_code":"PPL",
    "gn:name":"Anon",
    "gn:population":0,
    "gn:timezone":"Africa/Abidjan",
    "iso:country":"CI",
    "name:ceb_x_preferred":[
        "Anon"
    ],
    "name:deu_x_preferred":[
        "Anon"
    ],
    "name:fra_x_preferred":[
        "Anon"
    ],
    "name:ita_x_preferred":[
        "Anon"
    ],
    "name:nld_x_preferred":[
        "Anon"
    ],
    "name:rus_x_preferred":[
        "\u0410\u043d\u043e\u043d"
    ],
    "name:spa_x_preferred":[
        "An\u00f3n"
    ],
    "name:swe_x_preferred":[
        "Anon"
    ],
    "wof:name":"Anon",
    "wof:placetype":"locality"
},
  "geometry": {"coordinates":[-4.37132,5.52108],"type":"Point"}
}