{
  "type": "Feature",
  "properties": {
    "gn:admin1_code":"96",
    "gn:asciiname":"Zahirogbeu",
    "gn:country_code":"CI",
    "gn:dem":247,
    "gn:feature_class":"P",
    "gn:feature_code":"PPL",
    "gn:name":"Zahirogbeu",
    "gn:population":0,
    "gn:timezone":"Africa/Abidjan",
    "iso:country":"CI",
    "name:und_x_variant":[
        "Zairogbe"
    ],
    "wof:name":"Zahirogbeu",
    "wof:placetype":"locality"
},
  "geometry": {"coordinates":[-6.88421,6.76219],"type":"Point"}
}