{
  "type": "Feature",
  "properties": {
    "gn:admin1_code":"76",
    "gn:asciiname":"To-So",
    "gn:country_code":"CI",
    "gn:dem":130,
    "gn:feature_class":"P",
    "gn:feature_code":"PPL",
    "gn:name":"T\u00f4-S\u00f4",
    "gn:population":0,
    "gn:timezone":"Africa/Abidjan",
    "iso:country":"CI",
    "wof:name":"To-So",
    "wof:placetype":"locality"
},
  "geometry": {"coordinates":[-6.85,5.23333],"type":"Point"}
}