{
  "type": "Feature",
  "properties": {
    "gn:admin1_code":"82.0",
    "gn:asciiname":"Ncho",
    "gn:country_code":"CI",
    "gn:dem":73,
    "gn:feature_class":"P",
    "gn:feature_code":"PPL",
    "gn:name":"Ncho",
    "gn:population":0,
    "gn:timezone":"Africa/Abidjan",
    "iso:country":"CI",
    "wof:name":"Ncho",
    "wof:placetype":"locality"
},
  "geometry": {"coordinates":[-3.72158,5.66433],"type":"Point"}
}