{
  "type": "Feature",
  "properties": {
    "gn:admin1_code":"78",
    "gn:asciiname":"Zodri",
    "gn:country_code":"CI",
    "gn:dem":272,
    "gn:feature_class":"P",
    "gn:feature_code":"PPL",
    "gn:name":"Zodri",
    "gn:population":0,
    "gn:timezone":"Africa/Abidjan",
    "iso:country":"CI",
    "name:und_x_variant":[
        "Zoud\u00e9pleu"
    ],
    "wof:name":"Zodri",
    "wof:placetype":"locality"
},
  "geometry": {"coordinates":[-7.75593,7.00079],"type":"Point"}
}