{
  "type": "Feature",
  "properties": {
    "gn:admin1_code":"77",
    "gn:asciiname":"Ouelle",
    "gn:country_code":"CI",
    "gn:dem":351,
    "gn:feature_class":"P",
    "gn:feature_code":"PPL",
    "gn:name":"Ouell\u00e9",
    "gn:population":0,
    "gn:timezone":"Africa/Abidjan",
    "iso:country":"CI",
    "name:und_x_variant":[
        "W\u00e9l\u00e9",
        "Ouell\u00e9"
    ],
    "wof:name":"Ouelle",
    "wof:placetype":"locality"
},
  "geometry": {"coordinates":[-6.80896,10.35602],"type":"Point"}
}