{
  "type": "Feature",
  "properties": {
    "gn:admin1_code":"95.0",
    "gn:asciiname":"Gohouboua",
    "gn:country_code":"CI",
    "gn:dem":210,
    "gn:feature_class":"P",
    "gn:feature_code":"PPL",
    "gn:name":"Gohouboua",
    "gn:population":0,
    "gn:timezone":"Africa/Abidjan",
    "iso:country":"CI",
    "name:und_x_variant":[
        "Gouboua"
    ],
    "wof:name":"Gohouboua",
    "wof:placetype":"locality"
},
  "geometry": {"coordinates":[-5.56986,6.09257],"type":"Point"}
}