{
  "type": "Feature",
  "properties": {
    "gn:admin1_code":"90.0",
    "gn:asciiname":"Assenze",
    "gn:country_code":"CI",
    "gn:dem":302,
    "gn:feature_class":"P",
    "gn:feature_code":"PPL",
    "gn:name":"Assenz\u00e9",
    "gn:population":0,
    "gn:timezone":"Africa/Abidjan",
    "iso:country":"CI",
    "name:und_x_variant":[
        "Assenz\u00e9",
        "Asenz\u00e9"
    ],
    "wof:name":"Assenze",
    "wof:placetype":"locality"
},
  "geometry": {"coordinates":[-5.25843,7.67542],"type":"Point"}
}