{
  "type": "Feature",
  "properties": {
    "gn:admin1_code":"97",
    "gn:asciiname":"Manandougou",
    "gn:country_code":"CI",
    "gn:dem":348,
    "gn:feature_class":"P",
    "gn:feature_code":"PPL",
    "gn:name":"Manandougou",
    "gn:population":0,
    "gn:timezone":"Africa/Abidjan",
    "iso:country":"CI",
    "wof:name":"Manandougou",
    "wof:placetype":"locality"
},
  "geometry": {"coordinates":[-6.40647,9.02085],"type":"Point"}
}