{
  "type": "Feature",
  "properties": {
    "gn:admin1_code":"92",
    "gn:asciiname":"Pedi",
    "gn:country_code":"CI",
    "gn:dem":299,
    "gn:feature_class":"P",
    "gn:feature_code":"PPL",
    "gn:name":"P\u00e9di",
    "gn:population":0,
    "gn:timezone":"Africa/Abidjan",
    "iso:country":"CI",
    "name:afr_x_preferred":[
        "Pedi"
    ],
    "name:cat_x_preferred":[
        "Pedi"
    ],
    "name:ceb_x_preferred":[
        "Pedi"
    ],
    "name:eus_x_preferred":[
        "Pedi"
    ],
    "name:fra_x_preferred":[
        "Pedi"
    ],
    "name:ita_x_preferred":[
        "Pedi"
    ],
    "name:scn_x_preferred":[
        "Pedi"
    ],
    "name:swe_x_preferred":[
        "Sepedi"
    ],
    "wof:name":"Pedi",
    "wof:placetype":"locality"
},
  "geometry": {"coordinates":[-2.79896,8.44676],"type":"Point"}
}