{
  "type": "Feature",
  "properties": {
    "gn:admin1_code":"92.0",
    "gn:asciiname":"Ataram",
    "gn:country_code":"CI",
    "gn:dem":294,
    "gn:feature_class":"P",
    "gn:feature_code":"PPL",
    "gn:name":"Ataram",
    "gn:population":0,
    "gn:timezone":"Africa/Abidjan",
    "iso:country":"CI",
    "wof:name":"Ataram",
    "wof:placetype":"locality"
},
  "geometry": {"coordinates":[-3.00728,7.93677],"type":"Point"}
}