{
  "type": "Feature",
  "properties": {
    "gn:admin1_code":"96",
    "gn:asciiname":"Sobedoufla",
    "gn:country_code":"CI",
    "gn:dem":314,
    "gn:feature_class":"P",
    "gn:feature_code":"PPL",
    "gn:name":"Sob\u00e9doufla",
    "gn:population":0,
    "gn:timezone":"Africa/Abidjan",
    "iso:country":"CI",
    "name:fra_x_preferred":[
        "S\u00e9b\u00e9doufla"
    ],
    "name:msa_x_preferred":[
        "S\u00e9b\u00e9doufla"
    ],
    "name:und_x_variant":[
        "S\u00e9b\u00e9doufla",
        "S\u00e9d\u00e9boufla",
        "Sob\u00e9doufla"
    ],
    "wof:name":"Sobedoufla",
    "wof:placetype":"locality"
},
  "geometry": {"coordinates":[-6.40209,7.73504],"type":"Point"}
}