{
  "type": "Feature",
  "properties": {
    "gn:admin1_code":"78.0",
    "gn:asciiname":"Baoubli",
    "gn:country_code":"CI",
    "gn:dem":254,
    "gn:feature_class":"P",
    "gn:feature_code":"PPL",
    "gn:name":"Baoubli",
    "gn:population":0,
    "gn:timezone":"Africa/Abidjan",
    "iso:country":"CI",
    "wof:name":"Baoubli",
    "wof:placetype":"locality"
},
  "geometry": {"coordinates":[-7.39931,6.80566],"type":"Point"}
}