{
  "type": "Feature",
  "properties": {
    "gn:admin1_code":"82.0",
    "gn:asciiname":"Breti",
    "gn:country_code":"CI",
    "gn:dem":21,
    "gn:feature_class":"P",
    "gn:feature_code":"PPL",
    "gn:name":"Br\u00e9ti",
    "gn:population":0,
    "gn:timezone":"Africa/Abidjan",
    "iso:country":"CI",
    "name:und_x_variant":[
        "Mbr\u00e9ti-Bakanda",
        "M\u2019Brett\u00e9",
        "Br\u00e9ti"
    ],
    "wof:name":"Breti",
    "wof:placetype":"locality"
},
  "geometry": {"coordinates":[-4.86619,5.61631],"type":"Point"}
}