{
  "type": "Feature",
  "properties": {
    "gn:admin1_code":"78.0",
    "gn:asciiname":"Batyebli",
    "gn:country_code":"CI",
    "gn:dem":313,
    "gn:feature_class":"P",
    "gn:feature_code":"PPL",
    "gn:name":"Baty\u00e9bli",
    "gn:population":0,
    "gn:timezone":"Africa/Abidjan",
    "iso:country":"CI",
    "wof:name":"Batyebli",
    "wof:placetype":"locality"
},
  "geometry": {"coordinates":[-7.27051,7.268],"type":"Point"}
}