{
  "type": "Feature",
  "properties": {
    "gn:admin1_code":"82.0",
    "gn:asciiname":"Kambo",
    "gn:country_code":"CI",
    "gn:dem":55,
    "gn:feature_class":"P",
    "gn:feature_code":"PPL",
    "gn:name":"Kambo",
    "gn:population":0,
    "gn:timezone":"Africa/Abidjan",
    "iso:country":"CI",
    "wof:name":"Kambo",
    "wof:placetype":"locality"
},
  "geometry": {"coordinates":[-3.96322,5.85279],"type":"Point"}
}