{
  "type": "Feature",
  "properties": {
    "gn:admin1_code":"95",
    "gn:asciiname":"Zadiayo",
    "gn:country_code":"CI",
    "gn:dem":213,
    "gn:feature_class":"P",
    "gn:feature_code":"PPL",
    "gn:name":"Zadiayo",
    "gn:population":0,
    "gn:timezone":"Africa/Abidjan",
    "iso:country":"CI",
    "name:und_x_variant":[
        "Zadiahio"
    ],
    "wof:name":"Zadiayo",
    "wof:placetype":"locality"
},
  "geometry": {"coordinates":[-6.24583,6.15696],"type":"Point"}
}