{
  "type": "Feature",
  "properties": {
    "gn:admin1_code":"92",
    "gn:asciiname":"Yaou-Ngatiakrou",
    "gn:country_code":"CI",
    "gn:dem":183,
    "gn:feature_class":"P",
    "gn:feature_code":"PPL",
    "gn:name":"Yaou-Ngatiakrou",
    "gn:population":0,
    "gn:timezone":"Africa/Abidjan",
    "iso:country":"CI",
    "name:und_x_variant":[
        "Yao N\u2019Gatakrou",
        "Yao-Ngatiakrou",
        "Yaou-Ngatiakrou"
    ],
    "wof:name":"Yaou-Ngatiakrou",
    "wof:placetype":"locality"
},
  "geometry": {"coordinates":[-3.21911,7.29809],"type":"Point"}
}