{
  "type": "Feature",
  "properties": {
    "gn:admin1_code":"82.0",
    "gn:asciiname":"Osma Offo",
    "gn:country_code":"CI",
    "gn:dem":81,
    "gn:feature_class":"P",
    "gn:feature_code":"PPL",
    "gn:name":"Osma Offo",
    "gn:population":0,
    "gn:timezone":"Africa/Abidjan",
    "iso:country":"CI",
    "wof:name":"Osma Offo",
    "wof:placetype":"locality"
},
  "geometry": {"coordinates":[-4.29047,5.89647],"type":"Point"}
}