{
  "type": "Feature",
  "properties": {
    "gn:admin1_code":"87.0",
    "gn:asciiname":"Bele",
    "gn:country_code":"CI",
    "gn:dem":367,
    "gn:feature_class":"P",
    "gn:feature_code":"PPL",
    "gn:name":"B\u00e9l\u00e9",
    "gn:population":0,
    "gn:timezone":"Africa/Abidjan",
    "iso:country":"CI",
    "name:ceb_x_preferred":[
        "Bele"
    ],
    "name:swe_x_preferred":[
        "Bele"
    ],
    "name:und_x_variant":[
        "Mb\u00e9l\u00e9",
        "B\u00e9l\u00e9"
    ],
    "wof:name":"Bele",
    "wof:placetype":"locality"
},
  "geometry": {"coordinates":[-6.57508,10.28008],"type":"Point"}
}