{
  "type": "Feature",
  "properties": {
    "gn:admin1_code":"89.0",
    "gn:asciiname":"Adjouan",
    "gn:country_code":"CI",
    "gn:dem":45,
    "gn:feature_class":"P",
    "gn:feature_code":"PPL",
    "gn:name":"Adjouan",
    "gn:population":0,
    "gn:timezone":"Africa/Abidjan",
    "iso:country":"CI",
    "name:und_x_variant":[
        "Adjouhan",
        "Ajwa",
        "Adjouan"
    ],
    "wof:name":"Adjouan",
    "wof:placetype":"locality"
},
  "geometry": {"coordinates":[-3.15232,5.30995],"type":"Point"}
}