{
  "type": "Feature",
  "properties": {
    "gn:admin1_code":"76",
    "gn:admin2_code":"11153077.0",
    "gn:admin3_code":"2281118.0",
    "gn:asciiname":"Grand Tabu",
    "gn:country_code":"CI",
    "gn:dem":115,
    "gn:feature_class":"P",
    "gn:feature_code":"PPL",
    "gn:name":"Grand Tabu",
    "gn:population":0,
    "gn:timezone":"Africa/Abidjan",
    "iso:country":"CI",
    "name:eng_x_historical":[
        "Segre"
    ],
    "name:eng_x_preferred":[
        "Segre"
    ],
    "name:und_x_variant":[
        "S\u00e9kr\u00e9t\u00e9",
        "Grand Tabou",
        "S\u00e9kr\u00e9k\u00e9"
    ],
    "wof:name":"Grand Tabu",
    "wof:placetype":"locality"
},
  "geometry": {"coordinates":[-7.30802,4.4513],"type":"Point"}
}