{
  "type": "Feature",
  "properties": {
    "gn:admin1_code":"78.0",
    "gn:asciiname":"Birma",
    "gn:country_code":"CI",
    "gn:dem":467,
    "gn:feature_class":"P",
    "gn:feature_code":"PPL",
    "gn:name":"Birma",
    "gn:population":0,
    "gn:timezone":"Africa/Abidjan",
    "iso:country":"CI",
    "wof:name":"Birma",
    "wof:placetype":"locality"
},
  "geometry": {"coordinates":[-7.41099,8.01329],"type":"Point"}
}