{
  "type": "Feature",
  "properties": {
    "gn:admin1_code":"90.0",
    "gn:asciiname":"Beou",
    "gn:country_code":"CI",
    "gn:dem":327,
    "gn:feature_class":"P",
    "gn:feature_code":"PPL",
    "gn:name":"B\u00e9ou",
    "gn:population":0,
    "gn:timezone":"Africa/Abidjan",
    "iso:country":"CI",
    "wof:name":"Beou",
    "wof:placetype":"locality"
},
  "geometry": {"coordinates":[-5.07268,7.59544],"type":"Point"}
}