{
  "type": "Feature",
  "properties": {
    "gn:admin1_code":"78.0",
    "gn:asciiname":"Guedoloupleu",
    "gn:country_code":"CI",
    "gn:dem":320,
    "gn:feature_class":"P",
    "gn:feature_code":"PPL",
    "gn:name":"Gu\u00e9doloupleu",
    "gn:population":0,
    "gn:timezone":"Africa/Abidjan",
    "iso:country":"CI",
    "name:und_x_variant":[
        "Godoloupleu",
        "Guedoloupleu",
        "Gu\u00e9doloupleu"
    ],
    "wof:name":"Guedoloupleu",
    "wof:placetype":"locality"
},
  "geometry": {"coordinates":[-8.28808,7.14096],"type":"Point"}
}