{
  "type": "Feature",
  "properties": {
    "gn:admin1_code":"96",
    "gn:asciiname":"Zobia",
    "gn:country_code":"CI",
    "gn:dem":217,
    "gn:feature_class":"P",
    "gn:feature_code":"PPL",
    "gn:name":"Zobia",
    "gn:population":0,
    "gn:timezone":"Africa/Abidjan",
    "iso:country":"CI",
    "name:vie_x_preferred":[
        "Zobia"
    ],
    "wof:name":"Zobia",
    "wof:placetype":"locality"
},
  "geometry": {"coordinates":[-6.60487,6.47976],"type":"Point"}
}