{
  "type": "Feature",
  "properties": {
    "gn:admin1_code":"97.0",
    "gn:asciiname":"Bogoba",
    "gn:country_code":"CI",
    "gn:dem":402,
    "gn:feature_class":"P",
    "gn:feature_code":"PPL",
    "gn:name":"Bogoba",
    "gn:population":0,
    "gn:timezone":"Africa/Abidjan",
    "iso:country":"CI",
    "name:und_x_variant":[
        "Booba",
        "Boroba",
        "Bogoba"
    ],
    "wof:name":"Bogoba",
    "wof:placetype":"locality"
},
  "geometry": {"coordinates":[-6.91083,8.22667],"type":"Point"}
}