{
  "type": "Feature",
  "properties": {
    "gn:admin1_code":"94.0",
    "gn:asciiname":"Korouako",
    "gn:country_code":"CI",
    "gn:dem":37,
    "gn:feature_class":"P",
    "gn:feature_code":"PPL",
    "gn:name":"Korouako",
    "gn:population":0,
    "gn:timezone":"Africa/Abidjan",
    "iso:country":"CI",
    "wof:name":"Korouako",
    "wof:placetype":"locality"
},
  "geometry": {"coordinates":[-3.37736,5.50475],"type":"Point"}
}