{
  "type": "Feature",
  "properties": {
    "gn:admin1_code":"81.0",
    "gn:asciiname":"Gangoro",
    "gn:country_code":"CI",
    "gn:dem":128,
    "gn:feature_class":"P",
    "gn:feature_code":"PPL",
    "gn:name":"Gangoro",
    "gn:population":0,
    "gn:timezone":"Africa/Abidjan",
    "iso:country":"CI",
    "wof:name":"Gangoro",
    "wof:placetype":"locality"
},
  "geometry": {"coordinates":[-4.86667,6.73333],"type":"Point"}
}