{
  "type": "Feature",
  "properties": {
    "gn:admin1_code":"87",
    "gn:asciiname":"Koroufon",
    "gn:country_code":"CI",
    "gn:dem":333,
    "gn:feature_class":"P",
    "gn:feature_code":"PPL",
    "gn:name":"Koroufon",
    "gn:population":0,
    "gn:timezone":"Africa/Abidjan",
    "iso:country":"CI",
    "wof:name":"Koroufon",
    "wof:placetype":"locality"
},
  "geometry": {"coordinates":[-5.65762,10.26023],"type":"Point"}
}