{
  "type": "Feature",
  "properties": {
    "gn:admin1_code":"87",
    "gn:asciiname":"Niangbrasso",
    "gn:country_code":"CI",
    "gn:dem":349,
    "gn:feature_class":"P",
    "gn:feature_code":"PPL",
    "gn:name":"Niangbrasso",
    "gn:population":0,
    "gn:timezone":"Africa/Abidjan",
    "iso:country":"CI",
    "name:und_x_variant":[
        "Niangbarasso",
        "Niangbrasso"
    ],
    "wof:name":"Niangbrasso",
    "wof:placetype":"locality"
},
  "geometry": {"coordinates":[-5.62695,10.15673],"type":"Point"}
}