{
  "type": "Feature",
  "properties": {
    "gn:admin1_code":"97.0",
    "gn:asciiname":"Barhana",
    "gn:country_code":"CI",
    "gn:dem":344,
    "gn:feature_class":"P",
    "gn:feature_code":"PPL",
    "gn:name":"Barhana",
    "gn:population":0,
    "gn:timezone":"Africa/Abidjan",
    "iso:country":"CI",
    "wof:name":"Barhana",
    "wof:placetype":"locality"
},
  "geometry": {"coordinates":[-6.81278,8.17194],"type":"Point"}
}