{
  "type": "Feature",
  "properties": {
    "gn:admin1_code":"76",
    "gn:asciiname":"Para",
    "gn:country_code":"CI",
    "gn:dem":145,
    "gn:feature_class":"P",
    "gn:feature_code":"PPL",
    "gn:name":"Para",
    "gn:population":0,
    "gn:timezone":"Africa/Abidjan",
    "iso:country":"CI",
    "wof:name":"Para",
    "wof:placetype":"locality"
},
  "geometry": {"coordinates":[-7.32755,5.51956],"type":"Point"}
}