{
  "type": "Feature",
  "properties": {
    "gn:admin1_code":"87",
    "gn:asciiname":"Nonfoun",
    "gn:country_code":"CI",
    "gn:dem":392,
    "gn:feature_class":"P",
    "gn:feature_code":"PPL",
    "gn:name":"Nonfoun",
    "gn:population":0,
    "gn:timezone":"Africa/Abidjan",
    "iso:country":"CI",
    "wof:name":"Nonfoun",
    "wof:placetype":"locality"
},
  "geometry": {"coordinates":[-5.75,9.55],"type":"Point"}
}