{
  "type": "Feature",
  "properties": {
    "gn:admin1_code":"90.0",
    "gn:asciiname":"Brobo",
    "gn:country_code":"CI",
    "gn:dem":267,
    "gn:feature_class":"P",
    "gn:feature_code":"PPL",
    "gn:name":"Brobo",
    "gn:population":0,
    "gn:timezone":"Africa/Abidjan",
    "iso:country":"CI",
    "name:fra_x_preferred":[
        "Brobo"
    ],
    "name:ita_x_preferred":[
        "Brobo"
    ],
    "name:msa_x_preferred":[
        "Brobo"
    ],
    "name:ron_x_preferred":[
        "Brobo"
    ],
    "name:und_x_variant":[
        "Kouadio Priko",
        "Kouadio Prikro",
        "Gorobo"
    ],
    "wof:name":"Brobo",
    "wof:placetype":"locality"
},
  "geometry": {"coordinates":[-4.82541,7.64026],"type":"Point"}
}