{
  "type": "Feature",
  "properties": {
    "gn:admin1_code":"90.0",
    "gn:asciiname":"Aloukro Diekro",
    "gn:country_code":"CI",
    "gn:dem":232,
    "gn:feature_class":"P",
    "gn:feature_code":"PPL",
    "gn:name":"Aloukro Di\u00e9kro",
    "gn:population":0,
    "gn:timezone":"Africa/Abidjan",
    "iso:country":"CI",
    "name:und_x_variant":[
        "Aloukro Di\u00e9kro",
        "Aloukro Dr\u00e9kro"
    ],
    "wof:name":"Aloukro Diekro",
    "wof:placetype":"locality"
},
  "geometry": {"coordinates":[-5.25833,7.34681],"type":"Point"}
}