{
  "type": "Feature",
  "properties": {
    "gn:admin1_code":"82.0",
    "gn:asciiname":"N'guessan Seka",
    "gn:country_code":"CI",
    "gn:dem":74,
    "gn:feature_class":"P",
    "gn:feature_code":"PPL",
    "gn:name":"N\u2019guessan Seka",
    "gn:population":0,
    "gn:timezone":"Africa/Abidjan",
    "iso:country":"CI",
    "wof:name":"N'guessan Seka",
    "wof:placetype":"locality"
},
  "geometry": {"coordinates":[-3.88574,5.96659],"type":"Point"}
}