{
  "type": "Feature",
  "properties": {
    "gn:admin1_code":"78",
    "gn:asciiname":"Tyapleu",
    "gn:country_code":"CI",
    "gn:dem":315,
    "gn:feature_class":"P",
    "gn:feature_code":"PPL",
    "gn:name":"Tyapleu",
    "gn:population":0,
    "gn:timezone":"Africa/Abidjan",
    "iso:country":"CI",
    "name:und_x_variant":[
        "Tyopleu"
    ],
    "wof:name":"Tyapleu",
    "wof:placetype":"locality"
},
  "geometry": {"coordinates":[-7.73593,7.19248],"type":"Point"}
}