{
  "type": "Feature",
  "properties": {
    "gn:admin1_code":"96",
    "gn:asciiname":"Traonfla",
    "gn:country_code":"CI",
    "gn:dem":263,
    "gn:feature_class":"P",
    "gn:feature_code":"PPL",
    "gn:name":"Traonfla",
    "gn:population":0,
    "gn:timezone":"Africa/Abidjan",
    "iso:country":"CI",
    "name:und_x_variant":[
        "Trahonfla",
        "Traonfla"
    ],
    "wof:name":"Traonfla",
    "wof:placetype":"locality"
},
  "geometry": {"coordinates":[-6.17658,7.46084],"type":"Point"}
}