{
  "type": "Feature",
  "properties": {
    "gn:admin1_code":"87.0",
    "gn:asciiname":"Ganon",
    "gn:country_code":"CI",
    "gn:dem":372,
    "gn:feature_class":"P",
    "gn:feature_code":"PPL",
    "gn:name":"Ganon",
    "gn:population":0,
    "gn:timezone":"Africa/Abidjan",
    "iso:country":"CI",
    "name:und_x_variant":[
        "Nganon",
        "Ganon"
    ],
    "wof:name":"Ganon",
    "wof:placetype":"locality"
},
  "geometry": {"coordinates":[-5.81228,9.35876],"type":"Point"}
}