{
  "type": "Feature",
  "properties": {
    "gn:admin1_code":"87.0",
    "gn:asciiname":"Ganon",
    "gn:country_code":"CI",
    "gn:dem":372,
    "gn:feature_class":"P",
    "gn:feature_code":"PPL",
    "gn:name":"Ganon",
    "gn:population":0,
    "gn:timezone":"Africa/Abidjan",
    "iso:country":"CI",
    "name:ara_x_preferred":[
        "\u062c\u0627\u0646\u0648\u0646"
    ],
    "name:ast_x_preferred":[
        "Ganondorf"
    ],
    "name:cat_x_preferred":[
        "Ganon"
    ],
    "name:dan_x_preferred":[
        "Ganon"
    ],
    "name:fin_x_preferred":[
        "Ganon"
    ],
    "name:fra_x_preferred":[
        "Ganon"
    ],
    "name:ita_x_preferred":[
        "Ganondorf"
    ],
    "name:jpn_x_preferred":[
        "\u30ac\u30ce\u30f3\u30c9\u30ed\u30d5"
    ],
    "name:kor_x_preferred":[
        "\uac00\ub17c\ub3cc\ud504"
    ],
    "name:lat_x_preferred":[
        "Ganon"
    ],
    "name:nld_x_preferred":[
        "Ganon"
    ],
    "name:nor_x_preferred":[
        "Ganon"
    ],
    "name:por_x_preferred":[
        "Ganondorf"
    ],
    "name:rus_x_preferred":[
        "\u0413\u044d\u043d\u043e\u043d"
    ],
    "name:spa_x_preferred":[
        "Ganondorf"
    ],
    "name:swe_x_preferred":[
        "Ganon"
    ],
    "name:und_x_variant":[
        "Nganon"
    ],
    "wof:name":"Ganon",
    "wof:placetype":"locality"
},
  "geometry": {"coordinates":[-5.81228,9.35876],"type":"Point"}
}