{
  "type": "Feature",
  "properties": {
    "gn:admin1_code":"82.0",
    "gn:asciiname":"Grand Motcho",
    "gn:country_code":"CI",
    "gn:dem":86,
    "gn:feature_class":"P",
    "gn:feature_code":"PPL",
    "gn:name":"Grand Motcho",
    "gn:population":0,
    "gn:timezone":"Africa/Abidjan",
    "iso:country":"CI",
    "wof:name":"Grand Motcho",
    "wof:placetype":"locality"
},
  "geometry": {"coordinates":[-4.1625,5.95032],"type":"Point"}
}