{
  "type": "Feature",
  "properties": {
    "gn:admin1_code":"77.0",
    "gn:asciiname":"Seme",
    "gn:country_code":"CI",
    "gn:dem":392,
    "gn:feature_class":"P",
    "gn:feature_code":"PPL",
    "gn:name":"S\u00e9m\u00e9",
    "gn:population":0,
    "gn:timezone":"Africa/Abidjan",
    "iso:country":"CI",
    "name:ceb_x_preferred":[
        "Seme"
    ],
    "name:ita_x_preferred":[
        "Seme"
    ],
    "name:slv_x_preferred":[
        "Seme"
    ],
    "name:swe_x_preferred":[
        "Seme"
    ],
    "wof:name":"Seme",
    "wof:placetype":"locality"
},
  "geometry": {"coordinates":[-6.94751,10.15919],"type":"Point"}
}