{
  "type": "Feature",
  "properties": {
    "gn:admin1_code":"96.0",
    "gn:asciiname":"Bobreguhe",
    "gn:country_code":"CI",
    "gn:dem":241,
    "gn:feature_class":"P",
    "gn:feature_code":"PPL",
    "gn:name":"Bobr\u00e9guh\u00e9",
    "gn:population":0,
    "gn:timezone":"Africa/Abidjan",
    "iso:country":"CI",
    "name:und_x_variant":[
        "Bobr\u00e9gu\u00e9",
        "Bobr\u00e9guh\u00e9"
    ],
    "wof:name":"Bobreguhe",
    "wof:placetype":"locality"
},
  "geometry": {"coordinates":[-6.56718,6.53851],"type":"Point"}
}