{
  "type": "Feature",
  "properties": {
    "gn:admin1_code":"81.0",
    "gn:asciiname":"Adiakouemi",
    "gn:country_code":"CI",
    "gn:dem":213,
    "gn:feature_class":"P",
    "gn:feature_code":"PPL",
    "gn:name":"Adiakou\u00e9mi",
    "gn:population":0,
    "gn:timezone":"Africa/Abidjan",
    "iso:country":"CI",
    "wof:name":"Adiakouemi",
    "wof:placetype":"locality"
},
  "geometry": {"coordinates":[-4.11982,7.38485],"type":"Point"}
}