{
  "type": "Feature",
  "properties": {
    "gn:admin1_code":"96",
    "gn:asciiname":"Sinfla",
    "gn:country_code":"CI",
    "gn:dem":240,
    "gn:feature_class":"P",
    "gn:feature_code":"PPL",
    "gn:name":"Sinfla",
    "gn:population":0,
    "gn:timezone":"Africa/Abidjan",
    "iso:country":"CI",
    "wof:name":"Sinfla",
    "wof:placetype":"locality"
},
  "geometry": {"coordinates":[-5.71597,6.84408],"type":"Point"}
}