{
  "type": "Feature",
  "properties": {
    "gn:admin1_code":"92",
    "gn:asciiname":"Kolia",
    "gn:country_code":"CI",
    "gn:dem":187,
    "gn:feature_class":"P",
    "gn:feature_code":"PPL",
    "gn:name":"Kolia",
    "gn:population":0,
    "gn:timezone":"Africa/Abidjan",
    "iso:country":"CI",
    "wof:name":"Kolia",
    "wof:placetype":"locality"
},
  "geometry": {"coordinates":[-3.22063,7.49869],"type":"Point"}
}