{
  "type": "Feature",
  "properties": {
    "gn:admin1_code":"76",
    "gn:asciiname":"Saoui",
    "gn:country_code":"CI",
    "gn:dem":36,
    "gn:feature_class":"P",
    "gn:feature_code":"PPL",
    "gn:name":"Saoui",
    "gn:population":0,
    "gn:timezone":"Africa/Abidjan",
    "iso:country":"CI",
    "name:und_x_variant":[
        "Sahouy",
        "Saoui"
    ],
    "wof:name":"Saoui",
    "wof:placetype":"locality"
},
  "geometry": {"coordinates":[-6.76501,4.89259],"type":"Point"}
}