{
  "type": "Feature",
  "properties": {
    "gn:admin1_code":"98",
    "gn:asciiname":"Lugbakro",
    "gn:country_code":"CI",
    "gn:dem":195,
    "gn:feature_class":"P",
    "gn:feature_code":"PPL",
    "gn:name":"Lugbakro",
    "gn:population":0,
    "gn:timezone":"Africa/Abidjan",
    "iso:country":"CI",
    "wof:name":"Lugbakro",
    "wof:placetype":"locality"
},
  "geometry": {"coordinates":[-5.20166,6.72607],"type":"Point"}
}