{
  "type": "Feature",
  "properties": {
    "gn:admin1_code":"82.0",
    "gn:asciiname":"Tabot Avagou",
    "gn:country_code":"CI",
    "gn:dem":8,
    "gn:feature_class":"P",
    "gn:feature_code":"PPL",
    "gn:name":"Tabot Avagou",
    "gn:population":0,
    "gn:timezone":"Africa/Abidjan",
    "iso:country":"CI",
    "name:und_x_variant":[
        "Tabot",
        "Avagon",
        "Avagou Tabot",
        "Tabot Avagou"
    ],
    "wof:name":"Tabot Avagou",
    "wof:placetype":"locality"
},
  "geometry": {"coordinates":[-4.32917,5.25916],"type":"Point"}
}