{
  "type": "Feature",
  "properties": {
    "gn:admin1_code":"81.0",
    "gn:asciiname":"Gouromnankro",
    "gn:country_code":"CI",
    "gn:dem":182,
    "gn:feature_class":"P",
    "gn:feature_code":"PPL",
    "gn:name":"Gouromnankro",
    "gn:population":0,
    "gn:timezone":"Africa/Abidjan",
    "iso:country":"CI",
    "name:und_x_variant":[
        "Gouroumankro",
        "Gurumankro",
        "Gouromankro",
        "Gouroum\u00e9nankro",
        "Gouromnankro"
    ],
    "wof:name":"Gouromnankro",
    "wof:placetype":"locality"
},
  "geometry": {"coordinates":[-5.17103,6.71437],"type":"Point"}
}