{
  "type": "Feature",
  "properties": {
    "gn:admin1_code":"82.0",
    "gn:asciiname":"Ohoue Okoin",
    "gn:country_code":"CI",
    "gn:dem":70,
    "gn:feature_class":"P",
    "gn:feature_code":"PPL",
    "gn:name":"Ohou\u00e9 Okoin",
    "gn:population":0,
    "gn:timezone":"Africa/Abidjan",
    "iso:country":"CI",
    "wof:name":"Ohoue Okoin",
    "wof:placetype":"locality"
},
  "geometry": {"coordinates":[-4.0069,5.88183],"type":"Point"}
}