{
  "type": "Feature",
  "properties": {
    "gn:admin1_code":"82.0",
    "gn:asciiname":"Tuto",
    "gn:country_code":"CI",
    "gn:dem":69,
    "gn:feature_class":"P",
    "gn:feature_code":"PPL",
    "gn:name":"Tuto",
    "gn:population":0,
    "gn:timezone":"Africa/Abidjan",
    "iso:country":"CI",
    "name:ara_x_preferred":[
        "\u062a\u0633\u0648\u062a\u0648"
    ],
    "name:azb_x_preferred":[
        "\u062a\u0648\u062a\u0648"
    ],
    "name:dan_x_preferred":[
        "Livonir Ruschel"
    ],
    "name:eus_x_preferred":[
        "Livonir Ruschel"
    ],
    "name:fas_x_preferred":[
        "\u062a\u0648\u062a\u0648"
    ],
    "name:fra_x_preferred":[
        "Livonir Ruschel"
    ],
    "name:ind_x_preferred":[
        "Livonir Ruschel"
    ],
    "name:jpn_x_preferred":[
        "\u30ea\u30dc\u30cb\u30fc\u30eb\u30fb\u30eb\u30c3\u30b7\u30a7\u30eb"
    ],
    "name:msa_x_preferred":[
        "Livonir Ruschel"
    ],
    "name:nld_x_preferred":[
        "Tuto"
    ],
    "name:nno_x_preferred":[
        "Livonir Ruschel"
    ],
    "name:pol_x_preferred":[
        "Livonir Ruschel"
    ],
    "name:spa_x_preferred":[
        "Livonir Ruschel"
    ],
    "name:swe_x_preferred":[
        "Livonir Ruschel"
    ],
    "name:tgl_x_preferred":[
        "Livonir Ruschel"
    ],
    "name:tur_x_preferred":[
        "Livonir Ruschel"
    ],
    "name:vie_x_preferred":[
        "Livonir Ruschel"
    ],
    "wof:name":"Tuto",
    "wof:placetype":"locality"
},
  "geometry": {"coordinates":[-3.71346,5.64451],"type":"Point"}
}