{
  "type": "Feature",
  "properties": {
    "gn:admin1_code":"82.0",
    "gn:asciiname":"Tuto",
    "gn:country_code":"CI",
    "gn:dem":69,
    "gn:feature_class":"P",
    "gn:feature_code":"PPL",
    "gn:name":"Tuto",
    "gn:population":0,
    "gn:timezone":"Africa/Abidjan",
    "iso:country":"CI",
    "wof:name":"Tuto",
    "wof:placetype":"locality"
},
  "geometry": {"coordinates":[-3.71346,5.64451],"type":"Point"}
}