{
  "type": "Feature",
  "properties": {
    "gn:admin1_code":"87",
    "gn:asciiname":"Kodala",
    "gn:country_code":"CI",
    "gn:dem":288,
    "gn:feature_class":"P",
    "gn:feature_code":"PPL",
    "gn:name":"Kodala",
    "gn:population":0,
    "gn:timezone":"Africa/Abidjan",
    "iso:country":"CI",
    "name:ben_x_preferred":[
        "\u0995\u09cb\u09a6\u09be\u09b2\u09be"
    ],
    "name:bpy_x_preferred":[
        "\u0995\u09cb\u09a6\u09be\u09b2\u09be"
    ],
    "name:ceb_x_preferred":[
        "Kodala"
    ],
    "name:ita_x_preferred":[
        "Kodala"
    ],
    "name:msa_x_preferred":[
        "Kodala"
    ],
    "name:nld_x_preferred":[
        "Kodala"
    ],
    "name:ori_x_preferred":[
        "\u0b15\u0b4b\u0b26\u0b33\u0b3e"
    ],
    "name:por_x_preferred":[
        "Kodala"
    ],
    "name:swe_x_preferred":[
        "Kodala"
    ],
    "name:vie_x_preferred":[
        "Kodala"
    ],
    "name:zho_x_preferred":[
        "\u79d1\u8fbe\u62c9"
    ],
    "wof:name":"Kodala",
    "wof:placetype":"locality"
},
  "geometry": {"coordinates":[-4.74373,9.38121],"type":"Point"}
}