{
  "type": "Feature",
  "properties": {
    "gn:admin1_code":"87",
    "gn:asciiname":"Kodala",
    "gn:country_code":"CI",
    "gn:dem":288,
    "gn:feature_class":"P",
    "gn:feature_code":"PPL",
    "gn:name":"Kodala",
    "gn:population":0,
    "gn:timezone":"Africa/Abidjan",
    "iso:country":"CI",
    "wof:name":"Kodala",
    "wof:placetype":"locality"
},
  "geometry": {"coordinates":[-4.74373,9.38121],"type":"Point"}
}