{
  "type": "Feature",
  "properties": {
    "gn:admin1_code":"82.0",
    "gn:asciiname":"Marintcho",
    "gn:country_code":"CI",
    "gn:dem":33,
    "gn:feature_class":"P",
    "gn:feature_code":"PPL",
    "gn:name":"Marintcho",
    "gn:population":0,
    "gn:timezone":"Africa/Abidjan",
    "iso:country":"CI",
    "wof:name":"Marintcho",
    "wof:placetype":"locality"
},
  "geometry": {"coordinates":[-3.69265,5.52132],"type":"Point"}
}