{
  "type": "Feature",
  "properties": {
    "gn:admin1_code":"82.0",
    "gn:asciiname":"Addah",
    "gn:country_code":"CI",
    "gn:dem":8,
    "gn:feature_class":"P",
    "gn:feature_code":"PPL",
    "gn:name":"Addah",
    "gn:population":0,
    "gn:timezone":"Africa/Abidjan",
    "iso:country":"CI",
    "name:fas_x_preferred":[
        "\u0627\u062f\u0627\u0647"
    ],
    "name:fra_x_preferred":[
        "Addah"
    ],
    "name:msa_x_preferred":[
        "Addah"
    ],
    "name:ron_x_preferred":[
        "Addah"
    ],
    "name:swe_x_preferred":[
        "Addah"
    ],
    "name:und_x_variant":[
        "Adda",
        "Addah"
    ],
    "wof:name":"Addah",
    "wof:placetype":"locality"
},
  "geometry": {"coordinates":[-4.6507,5.17483],"type":"Point"}
}