{
  "type": "Feature",
  "properties": {
    "gn:admin1_code":"96.0",
    "gn:asciiname":"Goulaonfla",
    "gn:country_code":"CI",
    "gn:dem":298,
    "gn:feature_class":"P",
    "gn:feature_code":"PPL",
    "gn:name":"Goulaonfla",
    "gn:population":0,
    "gn:timezone":"Africa/Abidjan",
    "iso:country":"CI",
    "name:und_x_variant":[
        "Goulahoufla",
        "Goulaonfla"
    ],
    "wof:name":"Goulaonfla",
    "wof:placetype":"locality"
},
  "geometry": {"coordinates":[-6.54254,7.67736],"type":"Point"}
}