{
  "type": "Feature",
  "properties": {
    "gn:admin1_code":"87.0",
    "gn:asciiname":"Kaloa",
    "gn:country_code":"CI",
    "gn:dem":348,
    "gn:feature_class":"P",
    "gn:feature_code":"PPL",
    "gn:name":"Kaloa",
    "gn:population":0,
    "gn:timezone":"Africa/Abidjan",
    "iso:country":"CI",
    "name:fra_x_preferred":[
        "Kaloa"
    ],
    "name:msa_x_preferred":[
        "Kaloa"
    ],
    "name:und_x_variant":[
        "Kaloona",
        "Kaloa"
    ],
    "wof:name":"Kaloa",
    "wof:placetype":"locality"
},
  "geometry": {"coordinates":[-6.05002,10.00277],"type":"Point"}
}