{
  "type": "Feature",
  "properties": {
    "gn:admin1_code":"90",
    "gn:asciiname":"Kounon",
    "gn:country_code":"CI",
    "gn:dem":339,
    "gn:feature_class":"P",
    "gn:feature_code":"PPL",
    "gn:name":"Kounon",
    "gn:population":0,
    "gn:timezone":"Africa/Abidjan",
    "iso:country":"CI",
    "wof:name":"Kounon",
    "wof:placetype":"locality"
},
  "geometry": {"coordinates":[-5.22142,9.37691],"type":"Point"}
}