{
  "type": "Feature",
  "properties": {
    "gn:admin1_code":"82.0",
    "gn:asciiname":"Mene",
    "gn:country_code":"CI",
    "gn:dem":59,
    "gn:feature_class":"P",
    "gn:feature_code":"PPL",
    "gn:name":"M\u00e9n\u00e9",
    "gn:population":0,
    "gn:timezone":"Africa/Abidjan",
    "iso:country":"CI",
    "wof:name":"Mene",
    "wof:placetype":"locality"
},
  "geometry": {"coordinates":[-4.37654,5.7964],"type":"Point"}
}