{
  "type": "Feature",
  "properties": {
    "gn:admin1_code":"81",
    "gn:asciiname":"Sereme",
    "gn:country_code":"CI",
    "gn:dem":215,
    "gn:feature_class":"P",
    "gn:feature_code":"PPL",
    "gn:name":"S\u00e9r\u00e9m\u00e9",
    "gn:population":0,
    "gn:timezone":"Africa/Abidjan",
    "iso:country":"CI",
    "wof:name":"Sereme",
    "wof:placetype":"locality"
},
  "geometry": {"coordinates":[-5.20789,6.57332],"type":"Point"}
}