{
  "type": "Feature",
  "properties": {
    "gn:admin1_code":"90",
    "gn:asciiname":"Suibonou",
    "gn:country_code":"CI",
    "gn:dem":254,
    "gn:feature_class":"P",
    "gn:feature_code":"PPL",
    "gn:name":"Suibonou",
    "gn:population":0,
    "gn:timezone":"Africa/Abidjan",
    "iso:country":"CI",
    "name:und_x_variant":[
        "Soubonou"
    ],
    "wof:name":"Suibonou",
    "wof:placetype":"locality"
},
  "geometry": {"coordinates":[-5.14915,7.53496],"type":"Point"}
}