{
  "type": "Feature",
  "properties": {
    "gn:admin1_code":"97",
    "gn:asciiname":"Vamoso",
    "gn:country_code":"CI",
    "gn:dem":450,
    "gn:feature_class":"P",
    "gn:feature_code":"PPL",
    "gn:name":"Vamoso",
    "gn:population":0,
    "gn:timezone":"Africa/Abidjan",
    "iso:country":"CI",
    "wof:name":"Vamoso",
    "wof:placetype":"locality"
},
  "geometry": {"coordinates":[-7.5296,8.06944],"type":"Point"}
}