{
  "type": "Feature",
  "properties": {
    "gn:admin1_code":"92.0",
    "gn:asciiname":"Binie",
    "gn:country_code":"CI",
    "gn:dem":366,
    "gn:feature_class":"P",
    "gn:feature_code":"PPL",
    "gn:name":"Bini\u00e9",
    "gn:population":0,
    "gn:timezone":"Africa/Abidjan",
    "iso:country":"CI",
    "wof:name":"Binie",
    "wof:placetype":"locality"
},
  "geometry": {"coordinates":[-3.51551,9.66074],"type":"Point"}
}