{
  "type": "Feature",
  "properties": {
    "gn:admin1_code":"95",
    "gn:asciiname":"Kraakou",
    "gn:country_code":"CI",
    "gn:dem":191,
    "gn:feature_class":"P",
    "gn:feature_code":"PPL",
    "gn:name":"Kraakou",
    "gn:population":0,
    "gn:timezone":"Africa/Abidjan",
    "iso:country":"CI",
    "name:und_x_variant":[
        "Krakou"
    ],
    "wof:name":"Kraakou",
    "wof:placetype":"locality"
},
  "geometry": {"coordinates":[-5.41866,6.38895],"type":"Point"}
}