{
  "type": "Feature",
  "properties": {
    "gn:admin1_code":"87.0",
    "gn:asciiname":"Beniasso",
    "gn:country_code":"CI",
    "gn:dem":350,
    "gn:feature_class":"P",
    "gn:feature_code":"PPL",
    "gn:name":"B\u00e9niasso",
    "gn:population":0,
    "gn:timezone":"Africa/Abidjan",
    "iso:country":"CI",
    "name:und_x_variant":[
        "B\u00e9gniasso",
        "B\u00e9niasso"
    ],
    "wof:name":"Beniasso",
    "wof:placetype":"locality"
},
  "geometry": {"coordinates":[-6.58577,10.48004],"type":"Point"}
}