{
  "type": "Feature",
  "properties": {
    "gn:admin1_code":"76",
    "gn:asciiname":"Wedjere",
    "gn:country_code":"CI",
    "gn:dem":24,
    "gn:feature_class":"P",
    "gn:feature_code":"PPL",
    "gn:name":"Wedj\u00e9r\u00e9",
    "gn:population":0,
    "gn:timezone":"Africa/Abidjan",
    "iso:country":"CI",
    "name:und_x_variant":[
        "Ou\u00e9gr\u00e9",
        "Wegire",
        "W\u00e9gr\u00e9",
        "Wedj\u00e9r\u00e9"
    ],
    "wof:name":"Wedjere",
    "wof:placetype":"locality"
},
  "geometry": {"coordinates":[-7.31729,4.56087],"type":"Point"}
}