{
  "type": "Feature",
  "properties": {
    "gn:admin1_code":"81",
    "gn:asciiname":"Kroukroubo",
    "gn:country_code":"CI",
    "gn:dem":170,
    "gn:feature_class":"P",
    "gn:feature_code":"PPL",
    "gn:name":"Kroukroubo",
    "gn:population":0,
    "gn:timezone":"Africa/Abidjan",
    "iso:country":"CI",
    "wof:name":"Kroukroubo",
    "wof:placetype":"locality"
},
  "geometry": {"coordinates":[-5.29033,6.61521],"type":"Point"}
}