{
  "type": "Feature",
  "properties": {
    "gn:admin1_code":"78.0",
    "gn:asciiname":"Boyapleu I",
    "gn:country_code":"CI",
    "gn:dem":297,
    "gn:feature_class":"P",
    "gn:feature_code":"PPL",
    "gn:name":"Boyapleu I",
    "gn:population":0,
    "gn:timezone":"Africa/Abidjan",
    "iso:country":"CI",
    "name:und_x_variant":[
        "Boyapleu",
        "Boy\u00e9pleu",
        "Boyapleu I"
    ],
    "wof:name":"Boyapleu I",
    "wof:placetype":"locality"
},
  "geometry": {"coordinates":[-8.12665,7.05241],"type":"Point"}
}