{
  "type": "Feature",
  "properties": {
    "gn:admin1_code":"76.0",
    "gn:asciiname":"Graouro",
    "gn:country_code":"CI",
    "gn:dem":84,
    "gn:feature_class":"P",
    "gn:feature_code":"PPL",
    "gn:name":"Graouro",
    "gn:population":0,
    "gn:timezone":"Africa/Abidjan",
    "iso:country":"CI",
    "wof:name":"Graouro",
    "wof:placetype":"locality"
},
  "geometry": {"coordinates":[-7.43116,4.37611],"type":"Point"}
}