{
  "type": "Feature",
  "properties": {
    "gn:admin1_code":"96.0",
    "gn:asciiname":"Gouetifla",
    "gn:country_code":"CI",
    "gn:dem":283,
    "gn:feature_class":"P",
    "gn:feature_code":"PPL",
    "gn:name":"Gou\u00e9tifla",
    "gn:population":0,
    "gn:timezone":"Africa/Abidjan",
    "iso:country":"CI",
    "name:und_x_variant":[
        "Goudifla",
        "Gou\u00e9tifla"
    ],
    "wof:name":"Gouetifla",
    "wof:placetype":"locality"
},
  "geometry": {"coordinates":[-6.29014,7.60749],"type":"Point"}
}