{
  "type": "Feature",
  "properties": {
    "gn:admin1_code":"90",
    "gn:asciiname":"Mangrekan",
    "gn:country_code":"CI",
    "gn:dem":252,
    "gn:feature_class":"P",
    "gn:feature_code":"PPL",
    "gn:name":"Mangr\u00e9kan",
    "gn:population":0,
    "gn:timezone":"Africa/Abidjan",
    "iso:country":"CI",
    "name:und_x_variant":[
        "Mangr\u00e9",
        "Mangr\u00e9kan"
    ],
    "wof:name":"Mangrekan",
    "wof:placetype":"locality"
},
  "geometry": {"coordinates":[-5.46241,7.74144],"type":"Point"}
}