{
  "type": "Feature",
  "properties": {
    "gn:admin1_code":"96.0",
    "gn:asciiname":"Guedjigbeu II",
    "gn:country_code":"CI",
    "gn:dem":243,
    "gn:feature_class":"P",
    "gn:feature_code":"PPL",
    "gn:name":"Guedjigbeu II",
    "gn:population":0,
    "gn:timezone":"Africa/Abidjan",
    "iso:country":"CI",
    "name:und_x_variant":[
        "Guedjigbe II"
    ],
    "wof:name":"Guedjigbeu II",
    "wof:placetype":"locality"
},
  "geometry": {"coordinates":[-6.78183,6.79017],"type":"Point"}
}