{
  "type": "Feature",
  "properties": {
    "gn:admin1_code":"82.0",
    "gn:asciiname":"Ahuakre",
    "gn:country_code":"CI",
    "gn:dem":29,
    "gn:feature_class":"P",
    "gn:feature_code":"PPL",
    "gn:name":"Ahuakr\u00e9",
    "gn:population":0,
    "gn:timezone":"Africa/Abidjan",
    "iso:country":"CI",
    "name:und_x_variant":[
        "Ahuacr\u00e9",
        "Ahuakr\u00e9"
    ],
    "wof:name":"Ahuakre",
    "wof:placetype":"locality"
},
  "geometry": {"coordinates":[-4.85505,5.60697],"type":"Point"}
}