{
  "type": "Feature",
  "properties": {
    "gn:admin1_code":"90",
    "gn:asciiname":"Nikolo",
    "gn:country_code":"CI",
    "gn:dem":268,
    "gn:feature_class":"P",
    "gn:feature_code":"PPL",
    "gn:name":"Nikolo",
    "gn:population":0,
    "gn:timezone":"Africa/Abidjan",
    "iso:country":"CI",
    "wof:name":"Nikolo",
    "wof:placetype":"locality"
},
  "geometry": {"coordinates":[-5.07084,8.19677],"type":"Point"}
}