{
  "type": "Feature",
  "properties": {
    "gn:admin1_code":"96.0",
    "gn:asciiname":"Dyeifla",
    "gn:country_code":"CI",
    "gn:dem":284,
    "gn:feature_class":"P",
    "gn:feature_code":"PPL",
    "gn:name":"Dy\u00e9ifla",
    "gn:population":0,
    "gn:timezone":"Africa/Abidjan",
    "iso:country":"CI",
    "name:und_x_variant":[
        "Di\u00e9ifla",
        "Dy\u00e9ifla"
    ],
    "wof:name":"Dyeifla",
    "wof:placetype":"locality"
},
  "geometry": {"coordinates":[-6.00154,7.71736],"type":"Point"}
}