{
  "type": "Feature",
  "properties": {
    "gn:admin1_code":"81",
    "gn:asciiname":"Kouassi Nzikro",
    "gn:country_code":"CI",
    "gn:dem":115,
    "gn:feature_class":"P",
    "gn:feature_code":"PPL",
    "gn:name":"Kouassi Nzikro",
    "gn:population":0,
    "gn:timezone":"Africa/Abidjan",
    "iso:country":"CI",
    "wof:name":"Kouassi Nzikro",
    "wof:placetype":"locality"
},
  "geometry": {"coordinates":[-4.30267,6.94638],"type":"Point"}
}