{
  "type": "Feature",
  "properties": {
    "gn:admin1_code":"82.0",
    "gn:asciiname":"Atoupo Iago",
    "gn:country_code":"CI",
    "gn:dem":86,
    "gn:feature_class":"P",
    "gn:feature_code":"PPL",
    "gn:name":"Atoupo Iago",
    "gn:population":0,
    "gn:timezone":"Africa/Abidjan",
    "iso:country":"CI",
    "wof:name":"Atoupo Iago",
    "wof:placetype":"locality"
},
  "geometry": {"coordinates":[-3.89102,5.98137],"type":"Point"}
}