{
  "type": "Feature",
  "properties": {
    "gn:admin1_code":"87",
    "gn:asciiname":"Lafokpokaha",
    "gn:country_code":"CI",
    "gn:dem":364,
    "gn:feature_class":"P",
    "gn:feature_code":"PPL",
    "gn:name":"Lafokpokaha",
    "gn:population":0,
    "gn:timezone":"Africa/Abidjan",
    "iso:country":"CI",
    "name:fra_x_preferred":[
        "Lafokpokaha"
    ],
    "name:msa_x_preferred":[
        "Lafokpokaha"
    ],
    "name:und_x_variant":[
        "Lafopokaha"
    ],
    "name:urd_x_preferred":[
        "\u0644\u0627\u0641\u0648\u06a9\u067e\u0648\u06a9\u0627\u06c1\u0627"
    ],
    "wof:name":"Lafokpokaha",
    "wof:placetype":"locality"
},
  "geometry": {"coordinates":[-5.06764,9.59728],"type":"Point"}
}