{
  "type": "Feature",
  "properties": {
    "gn:admin1_code":"87.0",
    "gn:asciiname":"Fononvogo",
    "gn:country_code":"CI",
    "gn:dem":346,
    "gn:feature_class":"P",
    "gn:feature_code":"PPL",
    "gn:name":"Fononvogo",
    "gn:population":0,
    "gn:timezone":"Africa/Abidjan",
    "iso:country":"CI",
    "name:und_x_variant":[
        "Fonovogo",
        "Fononvogo"
    ],
    "wof:name":"Fononvogo",
    "wof:placetype":"locality"
},
  "geometry": {"coordinates":[-5.53737,9.66804],"type":"Point"}
}