{
  "type": "Feature",
  "properties": {
    "gn:admin1_code":"87",
    "gn:asciiname":"Mohouele",
    "gn:country_code":"CI",
    "gn:dem":419,
    "gn:feature_class":"P",
    "gn:feature_code":"PPL",
    "gn:name":"Mohou\u00e9l\u00e9",
    "gn:population":0,
    "gn:timezone":"Africa/Abidjan",
    "iso:country":"CI",
    "name:und_x_variant":[
        "Monou\u00e9l\u00e9",
        "Mohou\u00e9l\u00e9"
    ],
    "wof:name":"Mohouele",
    "wof:placetype":"locality"
},
  "geometry": {"coordinates":[-6.25777,9.4968],"type":"Point"}
}