{
  "type": "Feature",
  "properties": {
    "gn:admin1_code":"96.0",
    "gn:asciiname":"Goetifla",
    "gn:country_code":"CI",
    "gn:dem":272,
    "gn:feature_class":"P",
    "gn:feature_code":"PPL",
    "gn:name":"Go\u00e9tifla",
    "gn:population":0,
    "gn:timezone":"Africa/Abidjan",
    "iso:country":"CI",
    "name:und_x_variant":[
        "Gou\u00e9tifla",
        "Go\u00e9tifla"
    ],
    "wof:name":"Goetifla",
    "wof:placetype":"locality"
},
  "geometry": {"coordinates":[-6.18637,7.46904],"type":"Point"}
}