{
  "type": "Feature",
  "properties": {
    "gn:admin1_code":"78.0",
    "gn:asciiname":"Diourouzon",
    "gn:country_code":"CI",
    "gn:dem":248,
    "gn:feature_class":"P",
    "gn:feature_code":"PPL",
    "gn:name":"Diourouzon",
    "gn:population":0,
    "gn:timezone":"Africa/Abidjan",
    "iso:country":"CI",
    "name:fra_x_preferred":[
        "Diourouzon"
    ],
    "name:msa_x_preferred":[
        "Diourouzon"
    ],
    "name:und_x_variant":[
        "Dieouzon"
    ],
    "wof:name":"Diourouzon",
    "wof:placetype":"locality"
},
  "geometry": {"coordinates":[-7.51952,6.88922],"type":"Point"}
}