{
  "type": "Feature",
  "properties": {
    "gn:admin1_code":"97",
    "gn:asciiname":"Siana",
    "gn:country_code":"CI",
    "gn:dem":321,
    "gn:feature_class":"P",
    "gn:feature_code":"PPL",
    "gn:name":"Siana",
    "gn:population":0,
    "gn:timezone":"Africa/Abidjan",
    "iso:country":"CI",
    "name:und_x_variant":[
        "Syana",
        "Siana"
    ],
    "wof:name":"Siana",
    "wof:placetype":"locality"
},
  "geometry": {"coordinates":[-6.55699,8.05368],"type":"Point"}
}