{
  "type": "Feature",
  "properties": {
    "gn:admin1_code":"97",
    "gn:asciiname":"Siana",
    "gn:country_code":"CI",
    "gn:dem":321,
    "gn:feature_class":"P",
    "gn:feature_code":"PPL",
    "gn:name":"Siana",
    "gn:population":0,
    "gn:timezone":"Africa/Abidjan",
    "iso:country":"CI",
    "name:bpy_x_preferred":[
        "\u09b8\u09bf\u09af\u09bc\u09be\u09a8\u09be"
    ],
    "name:ita_x_preferred":[
        "Siana"
    ],
    "name:msa_x_preferred":[
        "Siana"
    ],
    "name:nld_x_preferred":[
        "Siana"
    ],
    "name:ori_x_preferred":[
        "\u0b38\u0b3f\u0b05\u0b28\u0b3e"
    ],
    "name:pnb_x_preferred":[
        "\u0633\u06cc\u0627\u0646\u0627"
    ],
    "name:pol_x_preferred":[
        "Siana"
    ],
    "name:por_x_preferred":[
        "Siana"
    ],
    "name:und_x_variant":[
        "Syana"
    ],
    "name:urd_x_preferred":[
        "\u0633\u06cc\u0627\u0646\u0627"
    ],
    "name:vie_x_preferred":[
        "Siana"
    ],
    "wof:name":"Siana",
    "wof:placetype":"locality"
},
  "geometry": {"coordinates":[-6.55699,8.05368],"type":"Point"}
}