{
  "type": "Feature",
  "properties": {
    "gn:admin1_code":"87",
    "gn:asciiname":"Nadyelakaha",
    "gn:country_code":"CI",
    "gn:dem":347,
    "gn:feature_class":"P",
    "gn:feature_code":"PPL",
    "gn:name":"Nady\u00e8lakaha",
    "gn:population":0,
    "gn:timezone":"Africa/Abidjan",
    "iso:country":"CI",
    "name:und_x_variant":[
        "Nadi\u00e9lakaha",
        "Nady\u00e8lakaha"
    ],
    "wof:name":"Nadyelakaha",
    "wof:placetype":"locality"
},
  "geometry": {"coordinates":[-5.58333,9.25],"type":"Point"}
}