{
  "type": "Feature",
  "properties": {
    "gn:admin1_code":"78",
    "gn:asciiname":"Kpanleu",
    "gn:country_code":"CI",
    "gn:dem":249,
    "gn:feature_class":"P",
    "gn:feature_code":"PPL",
    "gn:name":"Kpanleu",
    "gn:population":0,
    "gn:timezone":"Africa/Abidjan",
    "iso:country":"CI",
    "name:und_x_variant":[
        "Kplompleu",
        "Kplonleu",
        "Kpanleu"
    ],
    "wof:name":"Kpanleu",
    "wof:placetype":"locality"
},
  "geometry": {"coordinates":[-8.35343,6.71273],"type":"Point"}
}