{
  "type": "Feature",
  "properties": {
    "gn:admin1_code":"97",
    "gn:asciiname":"Konkoudougou",
    "gn:country_code":"CI",
    "gn:dem":307,
    "gn:feature_class":"P",
    "gn:feature_code":"PPL",
    "gn:name":"Konkoudougou",
    "gn:population":0,
    "gn:timezone":"Africa/Abidjan",
    "iso:country":"CI",
    "wof:name":"Konkoudougou",
    "wof:placetype":"locality"
},
  "geometry": {"coordinates":[-5.74846,8.24785],"type":"Point"}
}