{
  "type": "Feature",
  "properties": {
    "gn:admin1_code":"82",
    "gn:asciiname":"Tiaha",
    "gn:country_code":"CI",
    "gn:dem":30,
    "gn:feature_class":"P",
    "gn:feature_code":"PPL",
    "gn:name":"Tiaha",
    "gn:population":0,
    "gn:timezone":"Africa/Abidjan",
    "iso:country":"CI",
    "wof:name":"Tiaha",
    "wof:placetype":"locality"
},
  "geometry": {"coordinates":[-4.48319,5.29427],"type":"Point"}
}