{
  "type": "Feature",
  "properties": {
    "gn:admin1_code":"94.0",
    "gn:asciiname":"Ebakro",
    "gn:country_code":"CI",
    "gn:dem":20,
    "gn:feature_class":"P",
    "gn:feature_code":"PPL",
    "gn:name":"\u00c9bakro",
    "gn:population":0,
    "gn:timezone":"Africa/Abidjan",
    "iso:country":"CI",
    "name:und_x_variant":[
        "Adi\u00e9krou",
        "Abakro",
        "\u00c9bakro"
    ],
    "wof:name":"Ebakro",
    "wof:placetype":"locality"
},
  "geometry": {"coordinates":[-3.22976,5.41425],"type":"Point"}
}