{
  "type": "Feature",
  "properties": {
    "gn:admin1_code":"92",
    "gn:asciiname":"Noa",
    "gn:country_code":"CI",
    "gn:dem":228,
    "gn:feature_class":"P",
    "gn:feature_code":"PPL",
    "gn:name":"Noa",
    "gn:population":0,
    "gn:timezone":"Africa/Abidjan",
    "iso:country":"CI",
    "name:und_x_variant":[
        "Nao",
        "Noa"
    ],
    "wof:name":"Noa",
    "wof:placetype":"locality"
},
  "geometry": {"coordinates":[-3.02778,7.79361],"type":"Point"}
}