{
  "type": "Feature",
  "properties": {
    "gn:admin1_code":"78",
    "gn:asciiname":"Pane",
    "gn:country_code":"CI",
    "gn:dem":328,
    "gn:feature_class":"P",
    "gn:feature_code":"PPL",
    "gn:name":"Pan\u00e9",
    "gn:population":0,
    "gn:timezone":"Africa/Abidjan",
    "iso:country":"CI",
    "wof:name":"Pane",
    "wof:placetype":"locality"
},
  "geometry": {"coordinates":[-7.46447,7.29404],"type":"Point"}
}