{
  "type": "Feature",
  "properties": {
    "gn:admin1_code":"92",
    "gn:asciiname":"Yakokoroko",
    "gn:country_code":"CI",
    "gn:dem":335,
    "gn:feature_class":"P",
    "gn:feature_code":"PPL",
    "gn:name":"Yakokoroko",
    "gn:population":0,
    "gn:timezone":"Africa/Abidjan",
    "iso:country":"CI",
    "wof:name":"Yakokoroko",
    "wof:placetype":"locality"
},
  "geometry": {"coordinates":[-3.08349,8.07117],"type":"Point"}
}