{
  "type": "Feature",
  "properties": {
    "gn:admin1_code":"78",
    "gn:asciiname":"Sangoue",
    "gn:country_code":"CI",
    "gn:dem":427,
    "gn:feature_class":"P",
    "gn:feature_code":"PPL",
    "gn:name":"Sangou\u00e9",
    "gn:population":0,
    "gn:timezone":"Africa/Abidjan",
    "iso:country":"CI",
    "wof:name":"Sangoue",
    "wof:placetype":"locality"
},
  "geometry": {"coordinates":[-7.47343,7.48398],"type":"Point"}
}