{
  "type": "Feature",
  "properties": {
    "gn:admin1_code":"78",
    "gn:asciiname":"Koulaere",
    "gn:country_code":"CI",
    "gn:dem":320,
    "gn:feature_class":"P",
    "gn:feature_code":"PPL",
    "gn:name":"Koula\u00e9r\u00e9",
    "gn:population":0,
    "gn:timezone":"Africa/Abidjan",
    "iso:country":"CI",
    "wof:name":"Koulaere",
    "wof:placetype":"locality"
},
  "geometry": {"coordinates":[-7.20568,7.38303],"type":"Point"}
}