{
  "type": "Feature",
  "properties": {
    "gn:admin1_code":"94.0",
    "gn:asciiname":"Samo",
    "gn:country_code":"CI",
    "gn:dem":61,
    "gn:feature_class":"P",
    "gn:feature_code":"PPL",
    "gn:name":"Samo",
    "gn:population":0,
    "gn:timezone":"Africa/Abidjan",
    "iso:country":"CI",
    "wof:name":"Samo",
    "wof:placetype":"locality"
},
  "geometry": {"coordinates":[-3.51785,5.284],"type":"Point"}
}