{
  "type": "Feature",
  "properties": {
    "gn:admin1_code":"90",
    "gn:asciiname":"Tonfoin",
    "gn:country_code":"CI",
    "gn:dem":394,
    "gn:feature_class":"P",
    "gn:feature_code":"PPL",
    "gn:name":"Tonfoin",
    "gn:population":0,
    "gn:timezone":"Africa/Abidjan",
    "iso:country":"CI",
    "wof:name":"Tonfoin",
    "wof:placetype":"locality"
},
  "geometry": {"coordinates":[-4.23333,8.11667],"type":"Point"}
}