{
  "type": "Feature",
  "properties": {
    "gn:admin1_code":"92.0",
    "gn:asciiname":"Amouatene",
    "gn:country_code":"CI",
    "gn:dem":329,
    "gn:feature_class":"P",
    "gn:feature_code":"PPL",
    "gn:name":"Amouat\u00e9n\u00e9",
    "gn:population":0,
    "gn:timezone":"Africa/Abidjan",
    "iso:country":"CI",
    "wof:name":"Amouatene",
    "wof:placetype":"locality"
},
  "geometry": {"coordinates":[-3.08454,8.09665],"type":"Point"}
}