{
  "type": "Feature",
  "properties": {
    "gn:admin1_code":"97",
    "gn:asciiname":"Konogo",
    "gn:country_code":"CI",
    "gn:dem":399,
    "gn:feature_class":"P",
    "gn:feature_code":"PPL",
    "gn:name":"Konogo",
    "gn:population":0,
    "gn:timezone":"Africa/Abidjan",
    "iso:country":"CI",
    "wof:name":"Konogo",
    "wof:placetype":"locality"
},
  "geometry": {"coordinates":[-6.93623,8.53284],"type":"Point"}
}