{
  "type": "Feature",
  "properties": {
    "gn:admin1_code":"97",
    "gn:asciiname":"Sakouaso",
    "gn:country_code":"CI",
    "gn:dem":361,
    "gn:feature_class":"P",
    "gn:feature_code":"PPL",
    "gn:name":"Sakouaso",
    "gn:population":0,
    "gn:timezone":"Africa/Abidjan",
    "iso:country":"CI",
    "name:und_x_variant":[
        "Sakouasso",
        "Sakouaso"
    ],
    "wof:name":"Sakouaso",
    "wof:placetype":"locality"
},
  "geometry": {"coordinates":[-6.66667,7.83333],"type":"Point"}
}