{
  "type": "Feature",
  "properties": {
    "gn:admin1_code":"90",
    "gn:asciiname":"Nda Guessankro",
    "gn:country_code":"CI",
    "gn:dem":285,
    "gn:feature_class":"P",
    "gn:feature_code":"PPL",
    "gn:name":"Nda Guessankro",
    "gn:population":0,
    "gn:timezone":"Africa/Abidjan",
    "iso:country":"CI",
    "wof:name":"Nda Guessankro",
    "wof:placetype":"locality"
},
  "geometry": {"coordinates":[-5.12058,7.88194],"type":"Point"}
}