{
  "type": "Feature",
  "properties": {
    "gn:admin1_code":"90.0",
    "gn:asciiname":"Diedou Ahounze",
    "gn:country_code":"CI",
    "gn:dem":255,
    "gn:feature_class":"P",
    "gn:feature_code":"PPL",
    "gn:name":"Di\u00e9dou Ahounz\u00e9",
    "gn:population":0,
    "gn:timezone":"Africa/Abidjan",
    "iso:country":"CI",
    "name:und_x_variant":[
        "Di\u00e9dou Ahounz\u00e9",
        "Di\u00e9dou Aounz\u00e9"
    ],
    "wof:name":"Diedou Ahounze",
    "wof:placetype":"locality"
},
  "geometry": {"coordinates":[-5.33331,7.8737],"type":"Point"}
}