{
  "type": "Feature",
  "properties": {
    "gn:admin1_code":"96.0",
    "gn:asciiname":"Beoumasso",
    "gn:country_code":"CI",
    "gn:dem":228,
    "gn:feature_class":"P",
    "gn:feature_code":"PPL",
    "gn:name":"B\u00e9oumasso",
    "gn:population":0,
    "gn:timezone":"Africa/Abidjan",
    "iso:country":"CI",
    "wof:name":"Beoumasso",
    "wof:placetype":"locality"
},
  "geometry": {"coordinates":[-5.95,7.68333],"type":"Point"}
}