{
  "type": "Feature",
  "properties": {
    "gn:admin1_code":"90.0",
    "gn:asciiname":"Aliboti",
    "gn:country_code":"CI",
    "gn:dem":278,
    "gn:feature_class":"P",
    "gn:feature_code":"PPL",
    "gn:name":"Aliboti",
    "gn:population":0,
    "gn:timezone":"Africa/Abidjan",
    "iso:country":"CI",
    "wof:name":"Aliboti",
    "wof:placetype":"locality"
},
  "geometry": {"coordinates":[-5.24468,7.58416],"type":"Point"}
}