{
  "type": "Feature",
  "properties": {
    "gn:admin1_code":"81.0",
    "gn:asciiname":"Akanguissakro",
    "gn:country_code":"CI",
    "gn:dem":171,
    "gn:feature_class":"P",
    "gn:feature_code":"PPL",
    "gn:name":"Akanguissakro",
    "gn:population":0,
    "gn:timezone":"Africa/Abidjan",
    "iso:country":"CI",
    "wof:name":"Akanguissakro",
    "wof:placetype":"locality"
},
  "geometry": {"coordinates":[-3.87611,7.79333],"type":"Point"}
}