{
  "type": "Feature",
  "properties": {
    "gn:admin1_code":"82.0",
    "gn:asciiname":"Ogou Moussan",
    "gn:country_code":"CI",
    "gn:dem":75,
    "gn:feature_class":"P",
    "gn:feature_code":"PPL",
    "gn:name":"Ogou Moussan",
    "gn:population":0,
    "gn:timezone":"Africa/Abidjan",
    "iso:country":"CI",
    "wof:name":"Ogou Moussan",
    "wof:placetype":"locality"
},
  "geometry": {"coordinates":[-4.26038,5.99255],"type":"Point"}
}