{
  "type": "Feature",
  "properties": {
    "gn:admin1_code":"81.0",
    "gn:asciiname":"Guissakouassi",
    "gn:country_code":"CI",
    "gn:dem":197,
    "gn:feature_class":"P",
    "gn:feature_code":"PPL",
    "gn:name":"Guissakouassi",
    "gn:population":0,
    "gn:timezone":"Africa/Abidjan",
    "iso:country":"CI",
    "wof:name":"Guissakouassi",
    "wof:placetype":"locality"
},
  "geometry": {"coordinates":[-3.93333,7.03333],"type":"Point"}
}