{
  "type": "Feature",
  "properties": {
    "gn:admin1_code":"90",
    "gn:asciiname":"Ofyakaha",
    "gn:country_code":"CI",
    "gn:dem":330,
    "gn:feature_class":"P",
    "gn:feature_code":"PPL",
    "gn:name":"Ofyakaha",
    "gn:population":0,
    "gn:timezone":"Africa/Abidjan",
    "iso:country":"CI",
    "name:und_x_variant":[
        "Ofiakaha",
        "Ofyakaha"
    ],
    "wof:name":"Ofyakaha",
    "wof:placetype":"locality"
},
  "geometry": {"coordinates":[-5.13169,8.21364],"type":"Point"}
}