{
  "type": "Feature",
  "properties": {
    "gn:admin1_code":"97",
    "gn:asciiname":"Monyimasou",
    "gn:country_code":"CI",
    "gn:dem":370,
    "gn:feature_class":"P",
    "gn:feature_code":"PPL",
    "gn:name":"Monyimasou",
    "gn:population":0,
    "gn:timezone":"Africa/Abidjan",
    "iso:country":"CI",
    "wof:name":"Monyimasou",
    "wof:placetype":"locality"
},
  "geometry": {"coordinates":[-6.87286,8.19113],"type":"Point"}
}