{
  "type": "Feature",
  "properties": {
    "gn:admin1_code":"78.0",
    "gn:asciiname":"Gbonleu",
    "gn:country_code":"CI",
    "gn:dem":290,
    "gn:feature_class":"P",
    "gn:feature_code":"PPL",
    "gn:name":"Gbonleu",
    "gn:population":0,
    "gn:timezone":"Africa/Abidjan",
    "iso:country":"CI",
    "name:und_x_variant":[
        "Bonleu",
        "Gbonleu",
        "Ganleu"
    ],
    "wof:name":"Gbonleu",
    "wof:placetype":"locality"
},
  "geometry": {"coordinates":[-8.02773,7.10717],"type":"Point"}
}