{
  "type": "Feature",
  "properties": {
    "gn:admin1_code":"90.0",
    "gn:asciiname":"Ando",
    "gn:country_code":"CI",
    "gn:dem":179,
    "gn:feature_class":"P",
    "gn:feature_code":"PPL",
    "gn:name":"Ando",
    "gn:population":0,
    "gn:timezone":"Africa/Abidjan",
    "iso:country":"CI",
    "name:ceb_x_preferred":[
        "Ando"
    ],
    "name:deu_x_preferred":[
        "Ando"
    ],
    "name:fra_x_preferred":[
        "Ando"
    ],
    "name:heb_x_preferred":[
        "\u05d0\u05e0\u05d3\u05d5"
    ],
    "name:ita_x_preferred":[
        "Ando"
    ],
    "name:rus_x_preferred":[
        "\u0410\u043d\u0434\u043e"
    ],
    "name:swe_x_preferred":[
        "Ando"
    ],
    "name:ukr_x_preferred":[
        "\u0410\u043d\u0434\u043e"
    ],
    "wof:name":"Ando",
    "wof:placetype":"locality"
},
  "geometry": {"coordinates":[-4.73189,7.91235],"type":"Point"}
}