{
  "type": "Feature",
  "properties": {
    "gn:admin1_code":"90.0",
    "gn:asciiname":"Ando",
    "gn:country_code":"CI",
    "gn:dem":179,
    "gn:feature_class":"P",
    "gn:feature_code":"PPL",
    "gn:name":"Ando",
    "gn:population":0,
    "gn:timezone":"Africa/Abidjan",
    "iso:country":"CI",
    "wof:name":"Ando",
    "wof:placetype":"locality"
},
  "geometry": {"coordinates":[-4.73189,7.91235],"type":"Point"}
}