{
  "type": "Feature",
  "properties": {
    "gn:admin1_code":"87",
    "gn:asciiname":"Sityorikaha",
    "gn:country_code":"CI",
    "gn:dem":351,
    "gn:feature_class":"P",
    "gn:feature_code":"PPL",
    "gn:name":"Sityorikaha",
    "gn:population":0,
    "gn:timezone":"Africa/Abidjan",
    "iso:country":"CI",
    "name:und_x_variant":[
        "Sitiorikaha",
        "Sityorikaha"
    ],
    "wof:name":"Sityorikaha",
    "wof:placetype":"locality"
},
  "geometry": {"coordinates":[-5.37664,9.51561],"type":"Point"}
}