{
  "type": "Feature",
  "properties": {
    "gn:admin1_code":"92",
    "gn:asciiname":"Nioumassi",
    "gn:country_code":"CI",
    "gn:dem":202,
    "gn:feature_class":"P",
    "gn:feature_code":"PPL",
    "gn:name":"Nioumassi",
    "gn:population":0,
    "gn:timezone":"Africa/Abidjan",
    "iso:country":"CI",
    "wof:name":"Nioumassi",
    "wof:placetype":"locality"
},
  "geometry": {"coordinates":[-2.96668,7.5392],"type":"Point"}
}