{
  "type": "Feature",
  "properties": {
    "gn:admin1_code":"96.0",
    "gn:asciiname":"Deriboua",
    "gn:country_code":"CI",
    "gn:dem":215,
    "gn:feature_class":"P",
    "gn:feature_code":"PPL",
    "gn:name":"D\u00e9riboua",
    "gn:population":0,
    "gn:timezone":"Africa/Abidjan",
    "iso:country":"CI",
    "wof:name":"Deriboua",
    "wof:placetype":"locality"
},
  "geometry": {"coordinates":[-6.713,6.38613],"type":"Point"}
}