{
  "type": "Feature",
  "properties": {
    "gn:admin1_code":"92.0",
    "gn:asciiname":"Dingbi",
    "gn:country_code":"CI",
    "gn:dem":378,
    "gn:feature_class":"P",
    "gn:feature_code":"PPL",
    "gn:name":"Dingbi",
    "gn:population":0,
    "gn:timezone":"Africa/Abidjan",
    "iso:country":"CI",
    "name:fra_x_preferred":[
        "Dingbi"
    ],
    "name:msa_x_preferred":[
        "Dingbi"
    ],
    "name:und_x_variant":[
        "Dimbi",
        "Dinbi",
        "Dingbi"
    ],
    "wof:name":"Dingbi",
    "wof:placetype":"locality"
},
  "geometry": {"coordinates":[-3.03738,8.10391],"type":"Point"}
}