{
  "type": "Feature",
  "properties": {
    "gn:admin1_code":"82.0",
    "gn:asciiname":"Varle",
    "gn:country_code":"CI",
    "gn:dem":16,
    "gn:feature_class":"P",
    "gn:feature_code":"PPL",
    "gn:name":"Varl\u00e9",
    "gn:population":0,
    "gn:timezone":"Africa/Abidjan",
    "iso:country":"CI",
    "wof:name":"Varle",
    "wof:placetype":"locality"
},
  "geometry": {"coordinates":[-3.77888,5.25106],"type":"Point"}
}