{
  "type": "Feature",
  "properties": {
    "gn:admin1_code":"82.0",
    "gn:asciiname":"Gegboudougou",
    "gn:country_code":"CI",
    "gn:dem":18,
    "gn:feature_class":"P",
    "gn:feature_code":"PPL",
    "gn:name":"G\u00e9gboudougou",
    "gn:population":0,
    "gn:timezone":"Africa/Abidjan",
    "iso:country":"CI",
    "name:und_x_variant":[
        "Digb\u00e9dougou",
        "Guegboudoukou",
        "Doubou\u00e9dou",
        "Doubou\u00e9don",
        "G\u00e9gboudougou"
    ],
    "wof:name":"Gegboudougou",
    "wof:placetype":"locality"
},
  "geometry": {"coordinates":[-5.14037,5.2146],"type":"Point"}
}