{
  "type": "Feature",
  "properties": {
    "gn:admin1_code":"82.0",
    "gn:asciiname":"Achi",
    "gn:country_code":"CI",
    "gn:dem":65,
    "gn:feature_class":"P",
    "gn:feature_code":"PPL",
    "gn:name":"Achi",
    "gn:population":0,
    "gn:timezone":"Africa/Abidjan",
    "iso:country":"CI",
    "name:ceb_x_preferred":[
        "Achi"
    ],
    "name:deu_x_preferred":[
        "Achi"
    ],
    "name:lim_x_preferred":[
        "Achi"
    ],
    "name:nld_x_preferred":[
        "Achi"
    ],
    "name:por_x_preferred":[
        "Achi"
    ],
    "name:spa_x_preferred":[
        "Ach\u00ed"
    ],
    "name:swe_x_preferred":[
        "Achi"
    ],
    "name:tur_x_preferred":[
        "A\u00e7i"
    ],
    "wof:name":"Achi",
    "wof:placetype":"locality"
},
  "geometry": {"coordinates":[-3.84953,5.91678],"type":"Point"}
}