{
  "type": "Feature",
  "properties": {
    "gn:admin1_code":"87.0",
    "gn:asciiname":"Fonfongodougou",
    "gn:country_code":"CI",
    "gn:dem":340,
    "gn:feature_class":"P",
    "gn:feature_code":"PPL",
    "gn:name":"Fonfongodougou",
    "gn:population":0,
    "gn:timezone":"Africa/Abidjan",
    "iso:country":"CI",
    "wof:name":"Fonfongodougou",
    "wof:placetype":"locality"
},
  "geometry": {"coordinates":[-5.35,10.15],"type":"Point"}
}