{
  "type": "Feature",
  "properties": {
    "gn:admin1_code":"90",
    "gn:asciiname":"Koloko Sakassou",
    "gn:country_code":"CI",
    "gn:dem":215,
    "gn:feature_class":"P",
    "gn:feature_code":"PPL",
    "gn:name":"Koloko Sakassou",
    "gn:population":0,
    "gn:timezone":"Africa/Abidjan",
    "iso:country":"CI",
    "wof:name":"Koloko Sakassou",
    "wof:placetype":"locality"
},
  "geometry": {"coordinates":[-5.33685,7.30997],"type":"Point"}
}