{
  "type": "Feature",
  "properties": {
    "gn:admin1_code":"77",
    "gn:asciiname":"Kounboueni",
    "gn:country_code":"CI",
    "gn:dem":417,
    "gn:feature_class":"P",
    "gn:feature_code":"PPL",
    "gn:name":"Kounbou\u00e8ni",
    "gn:population":0,
    "gn:timezone":"Africa/Abidjan",
    "iso:country":"CI",
    "name:und_x_variant":[
        "Koungou\u00e9ni",
        "Kounbou\u00e8ni"
    ],
    "wof:name":"Kounboueni",
    "wof:placetype":"locality"
},
  "geometry": {"coordinates":[-7.39286,9.15062],"type":"Point"}
}