{
  "type": "Feature",
  "properties": {
    "gn:admin1_code":"82.0",
    "gn:asciiname":"Ndri",
    "gn:country_code":"CI",
    "gn:dem":27,
    "gn:feature_class":"P",
    "gn:feature_code":"PPL",
    "gn:name":"Ndri",
    "gn:population":0,
    "gn:timezone":"Africa/Abidjan",
    "iso:country":"CI",
    "wof:name":"Ndri",
    "wof:placetype":"locality"
},
  "geometry": {"coordinates":[-4.25533,5.85056],"type":"Point"}
}