{
  "type": "Feature",
  "properties": {
    "gn:admin1_code":"82.0",
    "gn:asciiname":"Ake",
    "gn:country_code":"CI",
    "gn:dem":37,
    "gn:feature_class":"P",
    "gn:feature_code":"PPL",
    "gn:name":"Ak\u00e9",
    "gn:population":0,
    "gn:timezone":"Africa/Abidjan",
    "iso:country":"CI",
    "name:deu_x_preferred":[
        "Ak\u00e9"
    ],
    "name:eus_x_preferred":[
        "Ak\u00e9"
    ],
    "name:fra_x_preferred":[
        "Ake"
    ],
    "name:hun_x_preferred":[
        "Ak\u00e9"
    ],
    "name:ita_x_preferred":[
        "Ak\u00e9"
    ],
    "name:mkd_x_preferred":[
        "\u0410\u043a\u0435"
    ],
    "name:spa_x_preferred":[
        "Ak\u00e9"
    ],
    "wof:name":"Ake",
    "wof:placetype":"locality"
},
  "geometry": {"coordinates":[-3.70669,5.53085],"type":"Point"}
}