{
  "type": "Feature",
  "properties": {
    "iso:country":"CI",
    "name:ceb_x_preferred":[
        "Zu\u00e9noula"
    ],
    "name:eng_x_preferred":[
        "Zu\u00e9noula Department"
    ],
    "name:est_x_preferred":[
        "Zu\u00e9noula"
    ],
    "name:fre_x_preferred":[
        "Zu\u00e9noula"
    ],
    "name:may_x_preferred":[
        "Zu\u00e9noula"
    ],
    "name:rum_x_preferred":[
        "Zu\u00e9noula"
    ],
    "name:swa_x_preferred":[
        "Wilaya ya Zu\u00e9noula"
    ],
    "name:swe_x_preferred":[
        "Zu\u00e9noula"
    ],
    "name:unk_x_variant":[
        "Z\u00e9noula"
    ],
    "qs:gn_country":"CI",
    "qs:gn_fcode":"PPL",
    "qs:gn_pop":34435,
    "qs:name":"Zuenoula",
    "qs:name_adm0":"C\u00f4te d\u00b4Ivoire",
    "qs:name_adm1":"Marahou\u00e9",
    "qs:photos":0,
    "qs:photos_1k":0,
    "qs:photos_9k":0,
    "qs:photos_9r":0,
    "qs:photos_all":0,
    "qs:photos_sr":0,
    "qs:placetype":"Town",
    "qs:pop_sr":"7",
    "qs:woe_adm0":23424854,
    "wd:wordcount":39,
    "wof:name":"Zuenoula",
    "wof:placetype":"locality",
    "wof:population":34435
},
  "geometry": {"coordinates":[-6.05054,7.43027],"type":"Point"}
}