{
  "type": "Feature",
  "properties": {
    "gn:admin1_code":"87",
    "gn:asciiname":"Ziekanha",
    "gn:country_code":"CI",
    "gn:dem":360,
    "gn:feature_class":"P",
    "gn:feature_code":"PPL",
    "gn:name":"Zi\u00e9kanha",
    "gn:population":0,
    "gn:timezone":"Africa/Abidjan",
    "iso:country":"CI",
    "wof:name":"Ziekanha",
    "wof:placetype":"locality"
},
  "geometry": {"coordinates":[-5.91981,10.15408],"type":"Point"}
}