{
  "type": "Feature",
  "properties": {
    "gn:admin1_code":"90",
    "gn:asciiname":"Pkontara",
    "gn:country_code":"CI",
    "gn:dem":305,
    "gn:feature_class":"P",
    "gn:feature_code":"PPL",
    "gn:name":"Pkontara",
    "gn:population":0,
    "gn:timezone":"Africa/Abidjan",
    "iso:country":"CI",
    "wof:name":"Pkontara",
    "wof:placetype":"locality"
},
  "geometry": {"coordinates":[-5.48333,8.66667],"type":"Point"}
}