{
  "type": "Feature",
  "properties": {
    "gn:admin1_code":"92",
    "gn:asciiname":"Poubonaoure",
    "gn:country_code":"CI",
    "gn:dem":357,
    "gn:feature_class":"P",
    "gn:feature_code":"PPL",
    "gn:name":"Poubonaour\u00e9",
    "gn:population":0,
    "gn:timezone":"Africa/Abidjan",
    "iso:country":"CI",
    "wof:name":"Poubonaoure",
    "wof:placetype":"locality"
},
  "geometry": {"coordinates":[-3.26942,9.62064],"type":"Point"}
}