{
  "type": "Feature",
  "properties": {
    "gn:admin1_code":"94.0",
    "gn:asciiname":"Eniambo",
    "gn:country_code":"CI",
    "gn:dem":65,
    "gn:feature_class":"P",
    "gn:feature_code":"PPL",
    "gn:name":"Eniambo",
    "gn:population":0,
    "gn:timezone":"Africa/Abidjan",
    "iso:country":"CI",
    "name:und_x_variant":[
        "Enuiambo",
        "Eniambo"
    ],
    "wof:name":"Eniambo",
    "wof:placetype":"locality"
},
  "geometry": {"coordinates":[-3.4125,5.59306],"type":"Point"}
}