{
  "type": "Feature",
  "properties": {
    "gn:admin1_code":"87",
    "gn:asciiname":"Sero",
    "gn:country_code":"CI",
    "gn:dem":343,
    "gn:feature_class":"P",
    "gn:feature_code":"PPL",
    "gn:name":"S\u00e9ro",
    "gn:population":0,
    "gn:timezone":"Africa/Abidjan",
    "iso:country":"CI",
    "name:ido_x_preferred":[
        "Sero"
    ],
    "name:srp_x_preferred":[
        "Sero"
    ],
    "name:und_x_variant":[
        "Z\u00e9h\u00e9roho",
        "S\u00e9ro"
    ],
    "wof:name":"Sero",
    "wof:placetype":"locality"
},
  "geometry": {"coordinates":[-6.01508,9.85491],"type":"Point"}
}