{
  "type": "Feature",
  "properties": {
    "gn:admin1_code":"95.0",
    "gn:asciiname":"Bibiepa",
    "gn:country_code":"CI",
    "gn:dem":261,
    "gn:feature_class":"P",
    "gn:feature_code":"PPL",
    "gn:name":"Bibi\u00e9pa",
    "gn:population":0,
    "gn:timezone":"Africa/Abidjan",
    "iso:country":"CI",
    "wof:name":"Bibiepa",
    "wof:placetype":"locality"
},
  "geometry": {"coordinates":[-5.89796,6.34341],"type":"Point"}
}