{
  "type": "Feature",
  "properties": {
    "gn:admin1_code":"82.0",
    "gn:asciiname":"Kragbokro",
    "gn:country_code":"CI",
    "gn:dem":80,
    "gn:feature_class":"P",
    "gn:feature_code":"PPL",
    "gn:name":"Kragbokro",
    "gn:population":0,
    "gn:timezone":"Africa/Abidjan",
    "iso:country":"CI",
    "wof:name":"Kragbokro",
    "wof:placetype":"locality"
},
  "geometry": {"coordinates":[-4.27653,5.9809],"type":"Point"}
}