{
  "type": "Feature",
  "properties": {
    "gn:admin1_code":"94.0",
    "gn:asciiname":"Kohourou",
    "gn:country_code":"CI",
    "gn:dem":49,
    "gn:feature_class":"P",
    "gn:feature_code":"PPL",
    "gn:name":"Kohourou",
    "gn:population":0,
    "gn:timezone":"Africa/Abidjan",
    "iso:country":"CI",
    "wof:name":"Kohourou",
    "wof:placetype":"locality"
},
  "geometry": {"coordinates":[-3.32856,5.47964],"type":"Point"}
}