{
  "type": "Feature",
  "properties": {
    "gn:admin1_code":"93.0",
    "gn:asciiname":"Adjame",
    "gn:country_code":"CI",
    "gn:dem":51,
    "gn:feature_class":"P",
    "gn:feature_code":"PPL",
    "gn:name":"Adjam\u00e9",
    "gn:population":0,
    "gn:timezone":"Africa/Abidjan",
    "iso:country":"CI",
    "wof:name":"Adjame",
    "wof:placetype":"locality"
},
  "geometry": {"coordinates":[-3.87196,5.34558],"type":"Point"}
}