{
  "type": "Feature",
  "properties": {
    "gn:admin1_code":"97",
    "gn:asciiname":"Ousougoula",
    "gn:country_code":"CI",
    "gn:dem":304,
    "gn:feature_class":"P",
    "gn:feature_code":"PPL",
    "gn:name":"Ousougoula",
    "gn:population":0,
    "gn:timezone":"Africa/Abidjan",
    "iso:country":"CI",
    "name:und_x_variant":[
        "Oussougoula",
        "Ousougoula"
    ],
    "wof:name":"Ousougoula",
    "wof:placetype":"locality"
},
  "geometry": {"coordinates":[-6.63355,8.08767],"type":"Point"}
}