{
  "type": "Feature",
  "properties": {
    "gn:admin1_code":"87",
    "gn:asciiname":"Soukouroula",
    "gn:country_code":"CI",
    "gn:dem":341,
    "gn:feature_class":"P",
    "gn:feature_code":"PPL",
    "gn:name":"Soukouroula",
    "gn:population":0,
    "gn:timezone":"Africa/Abidjan",
    "iso:country":"CI",
    "wof:name":"Soukouroula",
    "wof:placetype":"locality"
},
  "geometry": {"coordinates":[-4.76675,9.14805],"type":"Point"}
}