{
  "type": "Feature",
  "properties": {
    "gn:admin1_code":"82.0",
    "gn:asciiname":"Die",
    "gn:country_code":"CI",
    "gn:dem":49,
    "gn:feature_class":"P",
    "gn:feature_code":"PPL",
    "gn:name":"Di\u00e9",
    "gn:population":0,
    "gn:timezone":"Africa/Abidjan",
    "iso:country":"CI",
    "name:cat_x_preferred":[
        "Die"
    ],
    "name:ceb_x_preferred":[
        "Die"
    ],
    "name:ces_x_preferred":[
        "Die"
    ],
    "name:deu_x_preferred":[
        "Die"
    ],
    "name:fra_x_preferred":[
        "Die"
    ],
    "name:hun_x_preferred":[
        "Die"
    ],
    "name:nep_x_preferred":[
        "\u092e\u0930\u094d\u0928\u0941"
    ],
    "name:nor_x_preferred":[
        "Die"
    ],
    "name:slk_x_preferred":[
        "Die"
    ],
    "name:swe_x_preferred":[
        "Die"
    ],
    "name:tgl_x_preferred":[
        "Die"
    ],
    "wof:name":"Die",
    "wof:placetype":"locality"
},
  "geometry": {"coordinates":[-4.22749,5.90018],"type":"Point"}
}