{
  "type": "Feature",
  "properties": {
    "gn:admin1_code":"78.0",
    "gn:asciiname":"Guezon",
    "gn:country_code":"CI",
    "gn:dem":242,
    "gn:feature_class":"P",
    "gn:feature_code":"PPL",
    "gn:name":"Gu\u00e9zon",
    "gn:population":0,
    "gn:timezone":"Africa/Abidjan",
    "iso:country":"CI",
    "name:und_x_variant":[
        "Gu\u00e9zon",
        "Bodi-goazon"
    ],
    "wof:name":"Guezon",
    "wof:placetype":"locality"
},
  "geometry": {"coordinates":[-7.70203,6.56696],"type":"Point"}
}