{
  "type": "Feature",
  "properties": {
    "gn:admin1_code":"94.0",
    "gn:asciiname":"Bintrebo",
    "gn:country_code":"CI",
    "gn:dem":6,
    "gn:feature_class":"P",
    "gn:feature_code":"PPL",
    "gn:name":"Bintr\u00e9bo",
    "gn:population":0,
    "gn:timezone":"Africa/Abidjan",
    "iso:country":"CI",
    "wof:name":"Bintrebo",
    "wof:placetype":"locality"
},
  "geometry": {"coordinates":[-2.9693,5.11673],"type":"Point"}
}