{
  "type": "Feature",
  "properties": {
    "gn:admin1_code":"87",
    "gn:asciiname":"Talyan",
    "gn:country_code":"CI",
    "gn:dem":342,
    "gn:feature_class":"P",
    "gn:feature_code":"PPL",
    "gn:name":"Talyan",
    "gn:population":0,
    "gn:timezone":"Africa/Abidjan",
    "iso:country":"CI",
    "name:und_x_variant":[
        "Talian",
        "Talyan"
    ],
    "wof:name":"Talyan",
    "wof:placetype":"locality"
},
  "geometry": {"coordinates":[-5.83333,9.58333],"type":"Point"}
}