{
  "type": "Feature",
  "properties": {
    "gn:admin1_code":"87.0",
    "gn:asciiname":"Kakoloko",
    "gn:country_code":"CI",
    "gn:dem":350,
    "gn:feature_class":"P",
    "gn:feature_code":"PPL",
    "gn:name":"Kakoloko",
    "gn:population":0,
    "gn:timezone":"Africa/Abidjan",
    "iso:country":"CI",
    "name:und_x_variant":[
        "Kakologo",
        "Kakoloko"
    ],
    "wof:name":"Kakoloko",
    "wof:placetype":"locality"
},
  "geometry": {"coordinates":[-5.59151,9.24319],"type":"Point"}
}