{
  "type": "Feature",
  "properties": {
    "gn:admin1_code":"92",
    "gn:asciiname":"Sepele",
    "gn:country_code":"CI",
    "gn:dem":328,
    "gn:feature_class":"P",
    "gn:feature_code":"PPL",
    "gn:name":"S\u00e9p\u00e8l\u00e8",
    "gn:population":0,
    "gn:timezone":"Africa/Abidjan",
    "iso:country":"CI",
    "wof:name":"Sepele",
    "wof:placetype":"locality"
},
  "geometry": {"coordinates":[-3.26667,9.78333],"type":"Point"}
}