{
  "type": "Feature",
  "properties": {
    "gn:admin1_code":"90.0",
    "gn:asciiname":"Bouarebo",
    "gn:country_code":"CI",
    "gn:dem":212,
    "gn:feature_class":"P",
    "gn:feature_code":"PPL",
    "gn:name":"Bouar\u00e9bo",
    "gn:population":0,
    "gn:timezone":"Africa/Abidjan",
    "iso:country":"CI",
    "wof:name":"Bouarebo",
    "wof:placetype":"locality"
},
  "geometry": {"coordinates":[-5.5925,7.56167],"type":"Point"}
}