{
  "type": "Feature",
  "properties": {
    "gn:admin1_code":"87",
    "gn:asciiname":"Welleo",
    "gn:country_code":"CI",
    "gn:dem":364,
    "gn:feature_class":"P",
    "gn:feature_code":"PPL",
    "gn:name":"Well\u00e9o",
    "gn:population":0,
    "gn:timezone":"Africa/Abidjan",
    "iso:country":"CI",
    "name:und_x_variant":[
        "Ouole",
        "Well\u00e9o"
    ],
    "wof:name":"Welleo",
    "wof:placetype":"locality"
},
  "geometry": {"coordinates":[-5.75639,9.66252],"type":"Point"}
}