{
  "type": "Feature",
  "properties": {
    "gn:admin1_code":"82.0",
    "gn:asciiname":"Maleu",
    "gn:country_code":"CI",
    "gn:dem":88,
    "gn:feature_class":"P",
    "gn:feature_code":"PPL",
    "gn:name":"Maleu",
    "gn:population":0,
    "gn:timezone":"Africa/Abidjan",
    "iso:country":"CI",
    "wof:name":"Maleu",
    "wof:placetype":"locality"
},
  "geometry": {"coordinates":[-3.74408,5.71364],"type":"Point"}
}