{
  "type": "Feature",
  "properties": {
    "gn:admin1_code":"82.0",
    "gn:asciiname":"Sahuye",
    "gn:country_code":"CI",
    "gn:dem":99,
    "gn:feature_class":"P",
    "gn:feature_code":"PPL",
    "gn:name":"Sahuy\u00e9",
    "gn:population":0,
    "gn:timezone":"Africa/Abidjan",
    "iso:country":"CI",
    "name:und_x_variant":[
        "Sahuy\u00e9"
    ],
    "wof:name":"Sahuye",
    "wof:placetype":"locality"
},
  "geometry": {"coordinates":[-4.52683,5.73253],"type":"Point"}
}