{
  "type": "Feature",
  "properties": {
    "gn:admin1_code":"94.0",
    "gn:asciiname":"Maffible Aladjan",
    "gn:country_code":"CI",
    "gn:dem":16,
    "gn:feature_class":"P",
    "gn:feature_code":"PPL",
    "gn:name":"Maffibl\u00e9 Aladjan",
    "gn:population":0,
    "gn:timezone":"Africa/Abidjan",
    "iso:country":"CI",
    "wof:name":"Maffible Aladjan",
    "wof:placetype":"locality"
},
  "geometry": {"coordinates":[-3.84803,5.22537],"type":"Point"}
}