{
  "type": "Feature",
  "properties": {
    "gn:admin1_code":"96",
    "gn:asciiname":"Ligueguhe",
    "gn:country_code":"CI",
    "gn:dem":233,
    "gn:feature_class":"P",
    "gn:feature_code":"PPL",
    "gn:name":"Ligu\u00e9guh\u00e9",
    "gn:population":0,
    "gn:timezone":"Africa/Abidjan",
    "iso:country":"CI",
    "wof:name":"Ligueguhe",
    "wof:placetype":"locality"
},
  "geometry": {"coordinates":[-6.60012,6.6886],"type":"Point"}
}