{
  "type": "Feature",
  "properties": {
    "gn:admin1_code":"82.0",
    "gn:asciiname":"Salsa Samaouga",
    "gn:country_code":"CI",
    "gn:dem":65,
    "gn:feature_class":"P",
    "gn:feature_code":"PPL",
    "gn:name":"Salsa Samaouga",
    "gn:population":0,
    "gn:timezone":"Africa/Abidjan",
    "iso:country":"CI",
    "wof:name":"Salsa Samaouga",
    "wof:placetype":"locality"
},
  "geometry": {"coordinates":[-4.2722,5.94863],"type":"Point"}
}