{
  "type": "Feature",
  "properties": {
    "gn:admin1_code":"87",
    "gn:asciiname":"Nionkoukaha",
    "gn:country_code":"CI",
    "gn:dem":343,
    "gn:feature_class":"P",
    "gn:feature_code":"PPL",
    "gn:name":"Nionkoukaha",
    "gn:population":0,
    "gn:timezone":"Africa/Abidjan",
    "iso:country":"CI",
    "wof:name":"Nionkoukaha",
    "wof:placetype":"locality"
},
  "geometry": {"coordinates":[-5.56667,9.25],"type":"Point"}
}