{
  "type": "Feature",
  "properties": {
    "gn:admin1_code":"96.0",
    "gn:asciiname":"Bassaraguhe",
    "gn:country_code":"CI",
    "gn:dem":247,
    "gn:feature_class":"P",
    "gn:feature_code":"PPL",
    "gn:name":"Bassaraguh\u00e9",
    "gn:population":0,
    "gn:timezone":"Africa/Abidjan",
    "iso:country":"CI",
    "name:und_x_variant":[
        "Basaraguh\u00e9",
        "Bassaraguh\u00e9"
    ],
    "wof:name":"Bassaraguhe",
    "wof:placetype":"locality"
},
  "geometry": {"coordinates":[-6.84779,6.67274],"type":"Point"}
}