{
  "type": "Feature",
  "properties": {
    "gn:admin1_code":"81",
    "gn:asciiname":"Sakassou",
    "gn:country_code":"CI",
    "gn:dem":172,
    "gn:feature_class":"P",
    "gn:feature_code":"PPL",
    "gn:name":"Sakassou",
    "gn:population":0,
    "gn:timezone":"Africa/Abidjan",
    "iso:country":"CI",
    "wof:name":"Sakassou",
    "wof:placetype":"locality"
},
  "geometry": {"coordinates":[-4.8869,6.92752],"type":"Point"}
}