{
  "type": "Feature",
  "properties": {
    "gn:admin1_code":"78",
    "gn:asciiname":"Tyebli",
    "gn:country_code":"CI",
    "gn:dem":258,
    "gn:feature_class":"P",
    "gn:feature_code":"PPL",
    "gn:name":"Ty\u00e9bli",
    "gn:population":0,
    "gn:timezone":"Africa/Abidjan",
    "iso:country":"CI",
    "wof:name":"Tyebli",
    "wof:placetype":"locality"
},
  "geometry": {"coordinates":[-7.20885,7.49513],"type":"Point"}
}