{
  "type": "Feature",
  "properties": {
    "gn:admin1_code":"81.0",
    "gn:asciiname":"Drenamouinou",
    "gn:country_code":"CI",
    "gn:dem":147,
    "gn:feature_class":"P",
    "gn:feature_code":"PPL",
    "gn:name":"Dr\u00e9namouinou",
    "gn:population":0,
    "gn:timezone":"Africa/Abidjan",
    "iso:country":"CI",
    "wof:name":"Drenamouinou",
    "wof:placetype":"locality"
},
  "geometry": {"coordinates":[-4.23333,7.46667],"type":"Point"}
}