{
  "type": "Feature",
  "properties": {
    "gn:admin1_code":"95.0",
    "gn:asciiname":"Bigbie I",
    "gn:country_code":"CI",
    "gn:dem":240,
    "gn:feature_class":"P",
    "gn:feature_code":"PPL",
    "gn:name":"Bigbi\u00e9 I",
    "gn:population":0,
    "gn:timezone":"Africa/Abidjan",
    "iso:country":"CI",
    "wof:name":"Bigbie I",
    "wof:placetype":"locality"
},
  "geometry": {"coordinates":[-5.95772,6.40234],"type":"Point"}
}