{
  "type": "Feature",
  "properties": {
    "gn:admin1_code":"81",
    "gn:asciiname":"Takikro",
    "gn:country_code":"CI",
    "gn:dem":165,
    "gn:feature_class":"P",
    "gn:feature_code":"PPL",
    "gn:name":"Takikro",
    "gn:population":0,
    "gn:timezone":"Africa/Abidjan",
    "iso:country":"CI",
    "name:fra_x_preferred":[
        "Takikro"
    ],
    "name:msa_x_preferred":[
        "Takikro"
    ],
    "name:und_x_variant":[
        "Taki"
    ],
    "wof:name":"Takikro",
    "wof:placetype":"locality"
},
  "geometry": {"coordinates":[-4.81614,7.28664],"type":"Point"}
}