{
  "type": "Feature",
  "properties": {
    "gn:admin1_code":"81.0",
    "gn:asciiname":"Kangrassou-Yebouebo",
    "gn:country_code":"CI",
    "gn:dem":102,
    "gn:feature_class":"P",
    "gn:feature_code":"PPL",
    "gn:name":"Kangrassou-Y\u00e9bou\u00e9bo",
    "gn:population":0,
    "gn:timezone":"Africa/Abidjan",
    "iso:country":"CI",
    "wof:name":"Kangrassou-Yebouebo",
    "wof:placetype":"locality"
},
  "geometry": {"coordinates":[-4.76925,6.7395],"type":"Point"}
}