{
  "type": "Feature",
  "properties": {
    "gn:admin1_code":"92.0",
    "gn:asciiname":"Goumere",
    "gn:country_code":"CI",
    "gn:dem":264,
    "gn:feature_class":"P",
    "gn:feature_code":"PPL",
    "gn:name":"Goum\u00e9r\u00e9",
    "gn:population":0,
    "gn:timezone":"Africa/Abidjan",
    "iso:country":"CI",
    "name:fra_x_preferred":[
        "Goum\u00e9r\u00e9"
    ],
    "name:ita_x_preferred":[
        "Goum\u00e9r\u00e9"
    ],
    "name:msa_x_preferred":[
        "Goum\u00e9r\u00e9"
    ],
    "name:und_x_variant":[
        "Gomb\u00e9l\u00e9",
        "Goum\u00e9r\u00e9"
    ],
    "wof:name":"Goumere",
    "wof:placetype":"locality"
},
  "geometry": {"coordinates":[-2.98013,7.8963],"type":"Point"}
}