{
  "type": "Feature",
  "properties": {
    "gn:admin1_code":"82.0",
    "gn:asciiname":"Ehouo Ncho",
    "gn:country_code":"CI",
    "gn:dem":102,
    "gn:feature_class":"P",
    "gn:feature_code":"PPL",
    "gn:name":"Ehouo Ncho",
    "gn:population":0,
    "gn:timezone":"Africa/Abidjan",
    "iso:country":"CI",
    "wof:name":"Ehouo Ncho",
    "wof:placetype":"locality"
},
  "geometry": {"coordinates":[-3.58507,5.81604],"type":"Point"}
}