{
  "type": "Feature",
  "properties": {
    "gn:admin1_code":"93.0",
    "gn:asciiname":"Oie Kouako",
    "gn:country_code":"CI",
    "gn:dem":72,
    "gn:feature_class":"P",
    "gn:feature_code":"PPL",
    "gn:name":"Oie Kouako",
    "gn:population":0,
    "gn:timezone":"Africa/Abidjan",
    "iso:country":"CI",
    "wof:name":"Oie Kouako",
    "wof:placetype":"locality"
},
  "geometry": {"coordinates":[-4.04798,5.56879],"type":"Point"}
}