{
  "type": "Feature",
  "properties": {
    "gn:admin1_code":"82.0",
    "gn:asciiname":"Legue Bitie",
    "gn:country_code":"CI",
    "gn:dem":41,
    "gn:feature_class":"P",
    "gn:feature_code":"PPL",
    "gn:name":"Legue Biti\u00e9",
    "gn:population":0,
    "gn:timezone":"Africa/Abidjan",
    "iso:country":"CI",
    "wof:name":"Legue Bitie",
    "wof:placetype":"locality"
},
  "geometry": {"coordinates":[-4.26448,5.92125],"type":"Point"}
}