{
  "type": "Feature",
  "properties": {
    "gn:admin1_code":"90",
    "gn:asciiname":"Sahue",
    "gn:country_code":"CI",
    "gn:dem":300,
    "gn:feature_class":"P",
    "gn:feature_code":"PPL",
    "gn:name":"Sahu\u00e9",
    "gn:population":0,
    "gn:timezone":"Africa/Abidjan",
    "iso:country":"CI",
    "name:und_x_variant":[
        "Sahu\u00e9",
        "Sau\u00e9"
    ],
    "wof:name":"Sahue",
    "wof:placetype":"locality"
},
  "geometry": {"coordinates":[-5.38712,7.73805],"type":"Point"}
}