{
  "type": "Feature",
  "properties": {
    "gn:admin1_code":"78.0",
    "gn:asciiname":"Dinomobli",
    "gn:country_code":"CI",
    "gn:dem":246,
    "gn:feature_class":"P",
    "gn:feature_code":"PPL",
    "gn:name":"Dinomobli",
    "gn:population":0,
    "gn:timezone":"Africa/Abidjan",
    "iso:country":"CI",
    "wof:name":"Dinomobli",
    "wof:placetype":"locality"
},
  "geometry": {"coordinates":[-8.41984,6.62731],"type":"Point"}
}