{
  "type": "Feature",
  "properties": {
    "gn:admin1_code":"95.0",
    "gn:asciiname":"Dadjayo",
    "gn:country_code":"CI",
    "gn:dem":230,
    "gn:feature_class":"P",
    "gn:feature_code":"PPL",
    "gn:name":"Dadjayo",
    "gn:population":0,
    "gn:timezone":"Africa/Abidjan",
    "iso:country":"CI",
    "name:und_x_variant":[
        "Dadjahio"
    ],
    "wof:name":"Dadjayo",
    "wof:placetype":"locality"
},
  "geometry": {"coordinates":[-6.1797,6.31941],"type":"Point"}
}