{
  "type": "Feature",
  "properties": {
    "gn:admin1_code":"78.0",
    "gn:asciiname":"Goulegui Guezon",
    "gn:country_code":"CI",
    "gn:dem":215,
    "gn:feature_class":"P",
    "gn:feature_code":"PPL",
    "gn:name":"Goul\u00e9gui Gu\u00e9zon",
    "gn:population":0,
    "gn:timezone":"Africa/Abidjan",
    "iso:country":"CI",
    "wof:name":"Goulegui Guezon",
    "wof:placetype":"locality"
},
  "geometry": {"coordinates":[-7.56,6.54333],"type":"Point"}
}