{
  "type": "Feature",
  "properties": {
    "gn:admin1_code":"81",
    "gn:asciiname":"Tokro",
    "gn:country_code":"CI",
    "gn:dem":133,
    "gn:feature_class":"P",
    "gn:feature_code":"PPL",
    "gn:name":"Tokro",
    "gn:population":0,
    "gn:timezone":"Africa/Abidjan",
    "iso:country":"CI",
    "wof:name":"Tokro",
    "wof:placetype":"locality"
},
  "geometry": {"coordinates":[-4.49265,6.8826],"type":"Point"}
}