{
  "type": "Feature",
  "properties": {
    "gn:admin1_code":"94.0",
    "gn:asciiname":"Kongodjan",
    "gn:country_code":"CI",
    "gn:dem":108,
    "gn:feature_class":"P",
    "gn:feature_code":"PPL",
    "gn:name":"Kongodjan",
    "gn:population":0,
    "gn:timezone":"Africa/Abidjan",
    "iso:country":"CI",
    "wof:name":"Kongodjan",
    "wof:placetype":"locality"
},
  "geometry": {"coordinates":[-3.435,5.29849],"type":"Point"}
}