{
  "type": "Feature",
  "properties": {
    "gn:admin1_code":"97",
    "gn:asciiname":"Senko",
    "gn:country_code":"CI",
    "gn:dem":582,
    "gn:feature_class":"P",
    "gn:feature_code":"PPL",
    "gn:name":"Senko",
    "gn:population":0,
    "gn:timezone":"Africa/Abidjan",
    "iso:country":"CI",
    "name:und_x_variant":[
        "Sinko",
        "Senko"
    ],
    "wof:name":"Senko",
    "wof:placetype":"locality"
},
  "geometry": {"coordinates":[-7.89151,8.27523],"type":"Point"}
}