{
  "type": "Feature",
  "properties": {
    "gn:admin1_code":"95",
    "gn:asciiname":"Seliboua",
    "gn:country_code":"CI",
    "gn:dem":196,
    "gn:feature_class":"P",
    "gn:feature_code":"PPL",
    "gn:name":"S\u00e9liboua",
    "gn:population":0,
    "gn:timezone":"Africa/Abidjan",
    "iso:country":"CI",
    "wof:name":"Seliboua",
    "wof:placetype":"locality"
},
  "geometry": {"coordinates":[-5.57805,5.92002],"type":"Point"}
}