{
  "type": "Feature",
  "properties": {
    "gn:admin1_code":"82.0",
    "gn:asciiname":"Etechi Koua",
    "gn:country_code":"CI",
    "gn:dem":120,
    "gn:feature_class":"P",
    "gn:feature_code":"PPL",
    "gn:name":"Etechi Koua",
    "gn:population":0,
    "gn:timezone":"Africa/Abidjan",
    "iso:country":"CI",
    "wof:name":"Etechi Koua",
    "wof:placetype":"locality"
},
  "geometry": {"coordinates":[-3.78229,5.96699],"type":"Point"}
}