{
  "type": "Feature",
  "properties": {
    "gn:admin1_code":"97.0",
    "gn:asciiname":"Gbanvyelou",
    "gn:country_code":"CI",
    "gn:dem":328,
    "gn:feature_class":"P",
    "gn:feature_code":"PPL",
    "gn:name":"Gbanvy\u00e9lou",
    "gn:population":0,
    "gn:timezone":"Africa/Abidjan",
    "iso:country":"CI",
    "wof:name":"Gbanvyelou",
    "wof:placetype":"locality"
},
  "geometry": {"coordinates":[-6.15735,8.00623],"type":"Point"}
}