{
  "type": "Feature",
  "properties": {
    "gn:admin1_code":"97",
    "gn:asciiname":"Sanandougou",
    "gn:country_code":"CI",
    "gn:dem":546,
    "gn:feature_class":"P",
    "gn:feature_code":"PPL",
    "gn:name":"Sanandougou",
    "gn:population":0,
    "gn:timezone":"Africa/Abidjan",
    "iso:country":"CI",
    "wof:name":"Sanandougou",
    "wof:placetype":"locality"
},
  "geometry": {"coordinates":[-7.92536,8.30291],"type":"Point"}
}