{
  "type": "Feature",
  "properties": {
    "gn:admin1_code":"78",
    "gn:asciiname":"Sebli",
    "gn:country_code":"CI",
    "gn:dem":277,
    "gn:feature_class":"P",
    "gn:feature_code":"PPL",
    "gn:name":"Sebli",
    "gn:population":0,
    "gn:timezone":"Africa/Abidjan",
    "iso:country":"CI",
    "wof:name":"Sebli",
    "wof:placetype":"locality"
},
  "geometry": {"coordinates":[-8.42914,6.59251],"type":"Point"}
}