{
  "type": "Feature",
  "properties": {
    "gn:admin1_code":"95",
    "gn:asciiname":"Zaboua",
    "gn:country_code":"CI",
    "gn:dem":223,
    "gn:feature_class":"P",
    "gn:feature_code":"PPL",
    "gn:name":"Zaboua",
    "gn:population":0,
    "gn:timezone":"Africa/Abidjan",
    "iso:country":"CI",
    "wof:name":"Zaboua",
    "wof:placetype":"locality"
},
  "geometry": {"coordinates":[-5.58372,6.01847],"type":"Point"}
}