{
  "type": "Feature",
  "properties": {
    "gn:admin1_code":"78.0",
    "gn:asciiname":"Gbagompleu",
    "gn:country_code":"CI",
    "gn:dem":504,
    "gn:feature_class":"P",
    "gn:feature_code":"PPL",
    "gn:name":"Gbagompleu",
    "gn:population":0,
    "gn:timezone":"Africa/Abidjan",
    "iso:country":"CI",
    "wof:name":"Gbagompleu",
    "wof:placetype":"locality"
},
  "geometry": {"coordinates":[-7.94635,7.74388],"type":"Point"}
}