{
  "type": "Feature",
  "properties": {
    "gn:admin1_code":"78.0",
    "gn:asciiname":"Gbangatouo",
    "gn:country_code":"CI",
    "gn:dem":320,
    "gn:feature_class":"P",
    "gn:feature_code":"PPL",
    "gn:name":"Gbangatouo",
    "gn:population":0,
    "gn:timezone":"Africa/Abidjan",
    "iso:country":"CI",
    "name:und_x_variant":[
        "Gbangatauo"
    ],
    "wof:name":"Gbangatouo",
    "wof:placetype":"locality"
},
  "geometry": {"coordinates":[-8.28543,7.23565],"type":"Point"}
}