{
  "type": "Feature",
  "properties": {
    "gn:admin1_code":"87",
    "gn:asciiname":"Mapina",
    "gn:country_code":"CI",
    "gn:dem":280,
    "gn:feature_class":"P",
    "gn:feature_code":"PPL",
    "gn:name":"Mapina",
    "gn:population":0,
    "gn:timezone":"Africa/Abidjan",
    "iso:country":"CI",
    "wof:name":"Mapina",
    "wof:placetype":"locality"
},
  "geometry": {"coordinates":[-4.38757,9.42748],"type":"Point"}
}