{
  "type": "Feature",
  "properties": {
    "gn:admin1_code":"94.0",
    "gn:asciiname":"Aniaman",
    "gn:country_code":"CI",
    "gn:dem":43,
    "gn:feature_class":"P",
    "gn:feature_code":"PPL",
    "gn:name":"Aniaman",
    "gn:population":0,
    "gn:timezone":"Africa/Abidjan",
    "iso:country":"CI",
    "wof:name":"Aniaman",
    "wof:placetype":"locality"
},
  "geometry": {"coordinates":[-3.52198,5.2658],"type":"Point"}
}