{
  "type": "Feature",
  "properties": {
    "gn:admin1_code":"82.0",
    "gn:asciiname":"Attore",
    "gn:country_code":"CI",
    "gn:dem":84,
    "gn:feature_class":"P",
    "gn:feature_code":"PPL",
    "gn:name":"Attore",
    "gn:population":0,
    "gn:timezone":"Africa/Abidjan",
    "iso:country":"CI",
    "wof:name":"Attore",
    "wof:placetype":"locality"
},
  "geometry": {"coordinates":[-4.4646,5.66799],"type":"Point"}
}