{
  "type": "Feature",
  "properties": {
    "gn:admin1_code":"93.0",
    "gn:asciiname":"Guimi Nde",
    "gn:country_code":"CI",
    "gn:dem":16,
    "gn:feature_class":"P",
    "gn:feature_code":"PPL",
    "gn:name":"Guimi Nd\u00e9",
    "gn:population":0,
    "gn:timezone":"Africa/Abidjan",
    "iso:country":"CI",
    "wof:name":"Guimi Nde",
    "wof:placetype":"locality"
},
  "geometry": {"coordinates":[-3.93953,5.44618],"type":"Point"}
}