{
  "type": "Feature",
  "properties": {
    "gn:admin1_code":"82.0",
    "gn:asciiname":"Manin Kukubu",
    "gn:country_code":"CI",
    "gn:dem":61,
    "gn:feature_class":"P",
    "gn:feature_code":"PPL",
    "gn:name":"Manin Kukubu",
    "gn:population":0,
    "gn:timezone":"Africa/Abidjan",
    "iso:country":"CI",
    "wof:name":"Manin Kukubu",
    "wof:placetype":"locality"
},
  "geometry": {"coordinates":[-3.65808,5.78843],"type":"Point"}
}