{
  "type": "Feature",
  "properties": {
    "gn:admin1_code":"81",
    "gn:asciiname":"Tioumoukro",
    "gn:country_code":"CI",
    "gn:dem":97,
    "gn:feature_class":"P",
    "gn:feature_code":"PPL",
    "gn:name":"Tioumoukro",
    "gn:population":0,
    "gn:timezone":"Africa/Abidjan",
    "iso:country":"CI",
    "wof:name":"Tioumoukro",
    "wof:placetype":"locality"
},
  "geometry": {"coordinates":[-4.42811,6.89701],"type":"Point"}
}