{
  "type": "Feature",
  "properties": {
    "gn:admin1_code":"78",
    "gn:asciiname":"Sokourala",
    "gn:country_code":"CI",
    "gn:dem":582,
    "gn:feature_class":"P",
    "gn:feature_code":"PPL",
    "gn:name":"Sokourala",
    "gn:population":0,
    "gn:timezone":"Africa/Abidjan",
    "iso:country":"CI",
    "name:bul_x_preferred":[
        "\u0421\u043e\u043a\u0443\u0440\u0430\u043b\u0430"
    ],
    "name:ita_x_preferred":[
        "Sokourala"
    ],
    "name:msa_x_preferred":[
        "Sokourala"
    ],
    "name:spa_x_preferred":[
        "Sokourala"
    ],
    "name:und_x_variant":[
        "Soukourala",
        "Sokorala"
    ],
    "wof:name":"Sokourala",
    "wof:placetype":"locality"
},
  "geometry": {"coordinates":[-7.5475,7.60456],"type":"Point"}
}