{
  "type": "Feature",
  "properties": {
    "gn:admin1_code":"97.0",
    "gn:asciiname":"Fena",
    "gn:country_code":"CI",
    "gn:dem":501,
    "gn:feature_class":"P",
    "gn:feature_code":"PPL",
    "gn:name":"F\u00e9na",
    "gn:population":0,
    "gn:timezone":"Africa/Abidjan",
    "iso:country":"CI",
    "wof:name":"Fena",
    "wof:placetype":"locality"
},
  "geometry": {"coordinates":[-7.84832,8.80402],"type":"Point"}
}