{
  "type": "Feature",
  "properties": {
    "gn:admin1_code":"77",
    "gn:asciiname":"Siansoba",
    "gn:country_code":"CI",
    "gn:dem":593,
    "gn:feature_class":"P",
    "gn:feature_code":"PPL",
    "gn:name":"Siansoba",
    "gn:population":0,
    "gn:timezone":"Africa/Abidjan",
    "iso:country":"CI",
    "name:fra_x_preferred":[
        "Siansoba"
    ],
    "name:msa_x_preferred":[
        "Siansoba"
    ],
    "name:und_x_variant":[
        "Siensoba"
    ],
    "wof:name":"Siansoba",
    "wof:placetype":"locality"
},
  "geometry": {"coordinates":[-7.07601,9.63631],"type":"Point"}
}