{
  "type": "Feature",
  "properties": {
    "gn:admin1_code":"78.0",
    "gn:asciiname":"Kessesso",
    "gn:country_code":"CI",
    "gn:dem":436,
    "gn:feature_class":"P",
    "gn:feature_code":"PPL",
    "gn:name":"K\u00e9ss\u00e9sso",
    "gn:population":0,
    "gn:timezone":"Africa/Abidjan",
    "iso:country":"CI",
    "wof:name":"Kessesso",
    "wof:placetype":"locality"
},
  "geometry": {"coordinates":[-7.60653,7.83234],"type":"Point"}
}