{
  "type": "Feature",
  "properties": {
    "gn:admin1_code":"82.0",
    "gn:asciiname":"Ato Achou",
    "gn:country_code":"CI",
    "gn:dem":124,
    "gn:feature_class":"P",
    "gn:feature_code":"PPL",
    "gn:name":"Ato Achou",
    "gn:population":0,
    "gn:timezone":"Africa/Abidjan",
    "iso:country":"CI",
    "wof:name":"Ato Achou",
    "wof:placetype":"locality"
},
  "geometry": {"coordinates":[-3.52617,5.79022],"type":"Point"}
}