{
  "type": "Feature",
  "properties": {
    "gn:admin1_code":"82.0",
    "gn:asciiname":"Akahin",
    "gn:country_code":"CI",
    "gn:dem":100,
    "gn:feature_class":"P",
    "gn:feature_code":"PPL",
    "gn:name":"Akahin",
    "gn:population":0,
    "gn:timezone":"Africa/Abidjan",
    "iso:country":"CI",
    "wof:name":"Akahin",
    "wof:placetype":"locality"
},
  "geometry": {"coordinates":[-3.74328,5.71755],"type":"Point"}
}