{
  "type": "Feature",
  "properties": {
    "gn:admin1_code":"90",
    "gn:asciiname":"Panangana",
    "gn:country_code":"CI",
    "gn:dem":281,
    "gn:feature_class":"P",
    "gn:feature_code":"PPL",
    "gn:name":"Panangana",
    "gn:population":0,
    "gn:timezone":"Africa/Abidjan",
    "iso:country":"CI",
    "wof:name":"Panangana",
    "wof:placetype":"locality"
},
  "geometry": {"coordinates":[-4.40128,8.51067],"type":"Point"}
}