{
  "type": "Feature",
  "properties": {
    "gn:admin1_code":"78.0",
    "gn:asciiname":"Kaibli",
    "gn:country_code":"CI",
    "gn:dem":241,
    "gn:feature_class":"P",
    "gn:feature_code":"PPL",
    "gn:name":"Kaibli",
    "gn:population":0,
    "gn:timezone":"Africa/Abidjan",
    "iso:country":"CI",
    "wof:name":"Kaibli",
    "wof:placetype":"locality"
},
  "geometry": {"coordinates":[-8.47184,6.60016],"type":"Point"}
}