{
  "type": "Feature",
  "properties": {
    "gn:admin1_code":"97",
    "gn:asciiname":"Manyerekoro",
    "gn:country_code":"CI",
    "gn:dem":297,
    "gn:feature_class":"P",
    "gn:feature_code":"PPL",
    "gn:name":"Many\u00e9r\u00e9koro",
    "gn:population":0,
    "gn:timezone":"Africa/Abidjan",
    "iso:country":"CI",
    "wof:name":"Manyerekoro",
    "wof:placetype":"locality"
},
  "geometry": {"coordinates":[-6.08606,8.0688],"type":"Point"}
}