{
  "type": "Feature",
  "properties": {
    "gn:admin1_code":"90",
    "gn:asciiname":"Safolo",
    "gn:country_code":"CI",
    "gn:dem":266,
    "gn:feature_class":"P",
    "gn:feature_code":"PPL",
    "gn:name":"Safolo",
    "gn:population":0,
    "gn:timezone":"Africa/Abidjan",
    "iso:country":"CI",
    "wof:name":"Safolo",
    "wof:placetype":"locality"
},
  "geometry": {"coordinates":[-4.38329,8.29801],"type":"Point"}
}