{
  "type": "Feature",
  "properties": {
    "gn:admin1_code":"97.0",
    "gn:asciiname":"Gongoyo",
    "gn:country_code":"CI",
    "gn:dem":524,
    "gn:feature_class":"P",
    "gn:feature_code":"PPL",
    "gn:name":"Gongoyo",
    "gn:population":0,
    "gn:timezone":"Africa/Abidjan",
    "iso:country":"CI",
    "wof:name":"Gongoyo",
    "wof:placetype":"locality"
},
  "geometry": {"coordinates":[-8.11034,8.24572],"type":"Point"}
}