{
  "type": "Feature",
  "properties": {
    "gn:admin1_code":"81",
    "gn:asciiname":"Kouadio-Etienkro",
    "gn:country_code":"CI",
    "gn:dem":96,
    "gn:feature_class":"P",
    "gn:feature_code":"PPL",
    "gn:name":"Kouadio-Etienkro",
    "gn:population":0,
    "gn:timezone":"Africa/Abidjan",
    "iso:country":"CI",
    "name:und_x_variant":[
        "Kouadioettankro",
        "Kouadio-Ettienkro"
    ],
    "wof:name":"Kouadio-Etienkro",
    "wof:placetype":"locality"
},
  "geometry": {"coordinates":[-4.74949,6.79472],"type":"Point"}
}