{
  "type": "Feature",
  "properties": {
    "gn:admin1_code":"78.0",
    "gn:asciiname":"Biadapleu",
    "gn:country_code":"CI",
    "gn:dem":356,
    "gn:feature_class":"P",
    "gn:feature_code":"PPL",
    "gn:name":"Biadapleu",
    "gn:population":0,
    "gn:timezone":"Africa/Abidjan",
    "iso:country":"CI",
    "wof:name":"Biadapleu",
    "wof:placetype":"locality"
},
  "geometry": {"coordinates":[-8.35739,7.30904],"type":"Point"}
}