{
  "type": "Feature",
  "properties": {
    "gn:admin1_code":"93.0",
    "gn:asciiname":"Bogui",
    "gn:country_code":"CI",
    "gn:dem":15,
    "gn:feature_class":"P",
    "gn:feature_code":"PPL",
    "gn:name":"Bogui",
    "gn:population":0,
    "gn:timezone":"Africa/Abidjan",
    "iso:country":"CI",
    "wof:name":"Bogui",
    "wof:placetype":"locality"
},
  "geometry": {"coordinates":[-4.11527,5.23508],"type":"Point"}
}