{
  "type": "Feature",
  "properties": {
    "gn:admin1_code":"82.0",
    "gn:asciiname":"Adama",
    "gn:country_code":"CI",
    "gn:dem":12,
    "gn:feature_class":"P",
    "gn:feature_code":"PPL",
    "gn:name":"Adama",
    "gn:population":0,
    "gn:timezone":"Africa/Abidjan",
    "iso:country":"CI",
    "wof:name":"Adama",
    "wof:placetype":"locality"
},
  "geometry": {"coordinates":[-3.7799,5.24743],"type":"Point"}
}