{
  "type": "Feature",
  "properties": {
    "gn:admin1_code":"82.0",
    "gn:asciiname":"Adama",
    "gn:country_code":"CI",
    "gn:dem":12,
    "gn:feature_class":"P",
    "gn:feature_code":"PPL",
    "gn:name":"Adama",
    "gn:population":0,
    "gn:timezone":"Africa/Abidjan",
    "iso:country":"CI",
    "name:amh_x_preferred":[
        "\u12a0\u12f3\u121b"
    ],
    "name:ara_x_preferred":[
        "\u0623\u062f\u0627\u0645\u0627"
    ],
    "name:bel_x_preferred":[
        "\u0410\u0434\u0430\u043c\u0430"
    ],
    "name:bre_x_preferred":[
        "Adama"
    ],
    "name:ceb_x_preferred":[
        "Nazr\u0113t"
    ],
    "name:ces_x_preferred":[
        "Adama"
    ],
    "name:dan_x_preferred":[
        "Nazret"
    ],
    "name:deu_x_preferred":[
        "Adama"
    ],
    "name:ell_x_preferred":[
        "\u0391\u03b4\u03ac\u03bc\u03b1"
    ],
    "name:epo_x_preferred":[
        "Adamo"
    ],
    "name:eus_x_preferred":[
        "Adama"
    ],
    "name:fra_x_preferred":[
        "Adama"
    ],
    "name:heb_x_preferred":[
        "\u05d0\u05d3\u05d0\u05de\u05d4"
    ],
    "name:hrv_x_preferred":[
        "Adama"
    ],
    "name:hun_x_preferred":[
        "Adama"
    ],
    "name:ita_x_preferred":[
        "Adama"
    ],
    "name:jav_x_preferred":[
        "Adama"
    ],
    "name:jpn_x_preferred":[
        "\u30a2\u30c0\u30de"
    ],
    "name:kat_x_preferred":[
        "\u10d0\u10d3\u10d0\u10db\u10d0"
    ],
    "name:kor_x_preferred":[
        "\uc544\ub2e4\ub9c8"
    ],
    "name:lit_x_preferred":[
        "Nazretas"
    ],
    "name:mon_x_preferred":[
        "\u041d\u0430\u0437\u0440\u0435\u0442"
    ],
    "name:nld_x_preferred":[
        "Adama"
    ],
    "name:nor_x_preferred":[
        "Nazret"
    ],
    "name:orm_x_preferred":[
        "Adaamaa"
    ],
    "name:pol_x_preferred":[
        "Adama"
    ],
    "name:ron_x_preferred":[
        "Adama"
    ],
    "name:rus_x_preferred":[
        "\u041d\u0430\u0437\u0440\u0435\u0442"
    ],
    "name:sna_x_preferred":[
        "Adama"
    ],
    "name:spa_x_preferred":[
        "Adama"
    ],
    "name:swa_x_preferred":[
        "Adama"
    ],
    "name:swe_x_preferred":[
        "Nazret"
    ],
    "name:ukr_x_preferred":[
        "\u0410\u0434\u0430\u043c\u0430"
    ],
    "name:vie_x_preferred":[
        "Adama"
    ],
    "name:war_x_preferred":[
        "Adama"
    ],
    "name:zho_x_preferred":[
        "\u963f\u9054\u746a"
    ],
    "wof:name":"Adama",
    "wof:placetype":"locality"
},
  "geometry": {"coordinates":[-3.7799,5.24743],"type":"Point"}
}