{
  "type": "Feature",
  "properties": {
    "gn:admin1_code":"97",
    "gn:asciiname":"Sagweso",
    "gn:country_code":"CI",
    "gn:dem":298,
    "gn:feature_class":"P",
    "gn:feature_code":"PPL",
    "gn:name":"Sagw\u00e9so",
    "gn:population":0,
    "gn:timezone":"Africa/Abidjan",
    "iso:country":"CI",
    "wof:name":"Sagweso",
    "wof:placetype":"locality"
},
  "geometry": {"coordinates":[-7.17808,8.3374],"type":"Point"}
}