{
  "type": "Feature",
  "properties": {
    "gn:admin1_code":"96.0",
    "gn:asciiname":"Bougouloboua",
    "gn:country_code":"CI",
    "gn:dem":239,
    "gn:feature_class":"P",
    "gn:feature_code":"PPL",
    "gn:name":"Bougouloboua",
    "gn:population":0,
    "gn:timezone":"Africa/Abidjan",
    "iso:country":"CI",
    "name:und_x_variant":[
        "Boboloboua",
        "Bogouloboua"
    ],
    "wof:name":"Bougouloboua",
    "wof:placetype":"locality"
},
  "geometry": {"coordinates":[-6.33324,6.54731],"type":"Point"}
}