{
  "type": "Feature",
  "properties": {
    "gn:admin1_code":"82",
    "gn:asciiname":"Vieux Ousrou",
    "gn:country_code":"CI",
    "gn:dem":69,
    "gn:feature_class":"P",
    "gn:feature_code":"PPL",
    "gn:name":"Vieux Ousrou",
    "gn:population":0,
    "gn:timezone":"Africa/Abidjan",
    "iso:country":"CI",
    "name:und_x_variant":[
        "Ousrou",
        "Vieux Ousrou"
    ],
    "wof:name":"Vieux Ousrou",
    "wof:placetype":"locality"
},
  "geometry": {"coordinates":[-4.53606,5.41584],"type":"Point"}
}