{
  "type": "Feature",
  "properties": {
    "gn:admin1_code":"97",
    "gn:asciiname":"Sandala",
    "gn:country_code":"CI",
    "gn:dem":352,
    "gn:feature_class":"P",
    "gn:feature_code":"PPL",
    "gn:name":"Sandala",
    "gn:population":0,
    "gn:timezone":"Africa/Abidjan",
    "iso:country":"CI",
    "name:fra_x_preferred":[
        "Sandala"
    ],
    "name:msa_x_preferred":[
        "Sandala,Ivory Coast"
    ],
    "wof:name":"Sandala",
    "wof:placetype":"locality"
},
  "geometry": {"coordinates":[-6.46828,8.11215],"type":"Point"}
}