{
  "type": "Feature",
  "properties": {
    "gn:admin1_code":"82.0",
    "gn:asciiname":"Brou Ndrin",
    "gn:country_code":"CI",
    "gn:dem":76,
    "gn:feature_class":"P",
    "gn:feature_code":"PPL",
    "gn:name":"Brou Ndrin",
    "gn:population":0,
    "gn:timezone":"Africa/Abidjan",
    "iso:country":"CI",
    "wof:name":"Brou Ndrin",
    "wof:placetype":"locality"
},
  "geometry": {"coordinates":[-4.44255,5.625],"type":"Point"}
}