{
  "type": "Feature",
  "properties": {
    "gn:admin1_code":"90",
    "gn:asciiname":"Sarala",
    "gn:country_code":"CI",
    "gn:dem":391,
    "gn:feature_class":"P",
    "gn:feature_code":"PPL",
    "gn:name":"Sarala",
    "gn:population":0,
    "gn:timezone":"Africa/Abidjan",
    "iso:country":"CI",
    "name:deu_x_preferred":[
        "Sarala"
    ],
    "wof:name":"Sarala",
    "wof:placetype":"locality"
},
  "geometry": {"coordinates":[-4.63938,8.61371],"type":"Point"}
}