{
  "type": "Feature",
  "properties": {
    "gn:admin1_code":"97",
    "gn:asciiname":"Nangapla",
    "gn:country_code":"CI",
    "gn:dem":289,
    "gn:feature_class":"P",
    "gn:feature_code":"PPL",
    "gn:name":"Nangapla",
    "gn:population":0,
    "gn:timezone":"Africa/Abidjan",
    "iso:country":"CI",
    "wof:name":"Nangapla",
    "wof:placetype":"locality"
},
  "geometry": {"coordinates":[-5.79194,7.84944],"type":"Point"}
}