{
  "type": "Feature",
  "properties": {
    "gn:admin1_code":"87",
    "gn:asciiname":"Warga",
    "gn:country_code":"CI",
    "gn:dem":334,
    "gn:feature_class":"P",
    "gn:feature_code":"PPL",
    "gn:name":"Warga",
    "gn:population":0,
    "gn:timezone":"Africa/Abidjan",
    "iso:country":"CI",
    "wof:name":"Warga",
    "wof:placetype":"locality"
},
  "geometry": {"coordinates":[-5.57824,10.40164],"type":"Point"}
}