{
  "type": "Feature",
  "properties": {
    "gn:admin1_code":"92.0",
    "gn:asciiname":"Govitan",
    "gn:country_code":"CI",
    "gn:dem":335,
    "gn:feature_class":"P",
    "gn:feature_code":"PPL",
    "gn:name":"Govitan",
    "gn:population":0,
    "gn:timezone":"Africa/Abidjan",
    "iso:country":"CI",
    "name:und_x_variant":[
        "Gobaitan",
        "Gobeitane",
        "Govitan"
    ],
    "wof:name":"Govitan",
    "wof:placetype":"locality"
},
  "geometry": {"coordinates":[-3.72553,9.86654],"type":"Point"}
}