{
  "type": "Feature",
  "properties": {
    "gn:admin1_code":"77",
    "gn:asciiname":"Tienni",
    "gn:country_code":"CI",
    "gn:dem":415,
    "gn:feature_class":"P",
    "gn:feature_code":"PPL",
    "gn:name":"Tienni",
    "gn:population":0,
    "gn:timezone":"Africa/Abidjan",
    "iso:country":"CI",
    "name:und_x_variant":[
        "Tienny",
        "Tienni"
    ],
    "wof:name":"Tienni",
    "wof:placetype":"locality"
},
  "geometry": {"coordinates":[-7.92113,10.065],"type":"Point"}
}