{
  "type": "Feature",
  "properties": {
    "gn:admin1_code":"87.0",
    "gn:asciiname":"Dogidyokaha",
    "gn:country_code":"CI",
    "gn:dem":339,
    "gn:feature_class":"P",
    "gn:feature_code":"PPL",
    "gn:name":"Dogidyokaha",
    "gn:population":0,
    "gn:timezone":"Africa/Abidjan",
    "iso:country":"CI",
    "name:und_x_variant":[
        "Doguitinkaha",
        "Dogidyokaha"
    ],
    "wof:name":"Dogidyokaha",
    "wof:placetype":"locality"
},
  "geometry": {"coordinates":[-5.42475,9.35805],"type":"Point"}
}