{
  "type": "Feature",
  "properties": {
    "gn:admin1_code":"77",
    "gn:asciiname":"Tiekorodougou",
    "gn:country_code":"CI",
    "gn:dem":343,
    "gn:feature_class":"P",
    "gn:feature_code":"PPL",
    "gn:name":"Ti\u00e9korodougou",
    "gn:population":0,
    "gn:timezone":"Africa/Abidjan",
    "iso:country":"CI",
    "wof:name":"Tiekorodougou",
    "wof:placetype":"locality"
},
  "geometry": {"coordinates":[-7.2662,9.02966],"type":"Point"}
}