{
  "type": "Feature",
  "properties": {
    "gn:admin1_code":"81",
    "gn:asciiname":"Laourebo",
    "gn:country_code":"CI",
    "gn:dem":88,
    "gn:feature_class":"P",
    "gn:feature_code":"PPL",
    "gn:name":"Laour\u00e9bo",
    "gn:population":0,
    "gn:timezone":"Africa/Abidjan",
    "iso:country":"CI",
    "wof:name":"Laourebo",
    "wof:placetype":"locality"
},
  "geometry": {"coordinates":[-4.79615,6.51081],"type":"Point"}
}