{
  "type": "Feature",
  "properties": {
    "gn:admin1_code":"87",
    "gn:asciiname":"Wolovogo",
    "gn:country_code":"CI",
    "gn:dem":335,
    "gn:feature_class":"P",
    "gn:feature_code":"PPL",
    "gn:name":"Wolovogo",
    "gn:population":0,
    "gn:timezone":"Africa/Abidjan",
    "iso:country":"CI",
    "wof:name":"Wolovogo",
    "wof:placetype":"locality"
},
  "geometry": {"coordinates":[-5.30147,9.64109],"type":"Point"}
}