{
  "type": "Feature",
  "properties": {
    "gn:admin1_code":"87.0",
    "gn:asciiname":"Dyendoro",
    "gn:country_code":"CI",
    "gn:dem":402,
    "gn:feature_class":"P",
    "gn:feature_code":"PPL",
    "gn:name":"Dy\u00e8ndoro",
    "gn:population":0,
    "gn:timezone":"Africa/Abidjan",
    "iso:country":"CI",
    "name:und_x_variant":[
        "Diendoro",
        "Diendorno",
        "Dy\u00e8ndoro"
    ],
    "wof:name":"Dyendoro",
    "wof:placetype":"locality"
},
  "geometry": {"coordinates":[-5.85236,9.00297],"type":"Point"}
}