{
  "type": "Feature",
  "properties": {
    "gn:admin1_code":"93",
    "gn:asciiname":"Niangon-Lokoa",
    "gn:country_code":"CI",
    "gn:dem":7,
    "gn:feature_class":"P",
    "gn:feature_code":"PPL",
    "gn:name":"Niangon-Lokoa",
    "gn:population":0,
    "gn:timezone":"Africa/Abidjan",
    "iso:country":"CI",
    "name:und_x_variant":[
        "Niango Lokoa",
        "Niangon-Lokoua",
        "Niangon-Lokoa"
    ],
    "wof:name":"Niangon-Lokoa",
    "wof:placetype":"locality"
},
  "geometry": {"coordinates":[-4.10437,5.31009],"type":"Point"}
}