{
  "type": "Feature",
  "properties": {
    "gn:admin1_code":"87",
    "gn:asciiname":"Lavagakaha",
    "gn:country_code":"CI",
    "gn:dem":346,
    "gn:feature_class":"P",
    "gn:feature_code":"PPL",
    "gn:name":"Lavagakaha",
    "gn:population":0,
    "gn:timezone":"Africa/Abidjan",
    "iso:country":"CI",
    "wof:name":"Lavagakaha",
    "wof:placetype":"locality"
},
  "geometry": {"coordinates":[-5.40765,9.60492],"type":"Point"}
}