{
  "type": "Feature",
  "properties": {
    "gn:admin1_code":"92",
    "gn:asciiname":"Yaotroukro",
    "gn:country_code":"CI",
    "gn:dem":162,
    "gn:feature_class":"P",
    "gn:feature_code":"PPL",
    "gn:name":"Yaotroukro",
    "gn:population":0,
    "gn:timezone":"Africa/Abidjan",
    "iso:country":"CI",
    "wof:name":"Yaotroukro",
    "wof:placetype":"locality"
},
  "geometry": {"coordinates":[-3.6975,7.65806],"type":"Point"}
}