{
  "type": "Feature",
  "properties": {
    "gn:admin1_code":"92.0",
    "gn:asciiname":"Ahi Bango",
    "gn:country_code":"CI",
    "gn:dem":237,
    "gn:feature_class":"P",
    "gn:feature_code":"PPL",
    "gn:name":"Ahi Bango",
    "gn:population":0,
    "gn:timezone":"Africa/Abidjan",
    "iso:country":"CI",
    "wof:name":"Ahi Bango",
    "wof:placetype":"locality"
},
  "geometry": {"coordinates":[-3.25394,7.83372],"type":"Point"}
}