{
  "type": "Feature",
  "properties": {
    "gn:admin1_code":"87",
    "gn:asciiname":"Loulo",
    "gn:country_code":"CI",
    "gn:dem":355,
    "gn:feature_class":"P",
    "gn:feature_code":"PPL",
    "gn:name":"Loulo",
    "gn:population":0,
    "gn:timezone":"Africa/Abidjan",
    "iso:country":"CI",
    "wof:name":"Loulo",
    "wof:placetype":"locality"
},
  "geometry": {"coordinates":[-5.8131,10.37206],"type":"Point"}
}