{
  "type": "Feature",
  "properties": {
    "gn:admin1_code":"97.0",
    "gn:asciiname":"Blamadougou",
    "gn:country_code":"CI",
    "gn:dem":421,
    "gn:feature_class":"P",
    "gn:feature_code":"PPL",
    "gn:name":"Blamadougou",
    "gn:population":0,
    "gn:timezone":"Africa/Abidjan",
    "iso:country":"CI",
    "wof:name":"Blamadougou",
    "wof:placetype":"locality"
},
  "geometry": {"coordinates":[-7.70899,8.76635],"type":"Point"}
}