{
  "type": "Feature",
  "properties": {
    "gn:admin1_code":"92.0",
    "gn:asciiname":"Alikrou",
    "gn:country_code":"CI",
    "gn:dem":220,
    "gn:feature_class":"P",
    "gn:feature_code":"PPL",
    "gn:name":"Alikrou",
    "gn:population":0,
    "gn:timezone":"Africa/Abidjan",
    "iso:country":"CI",
    "wof:name":"Alikrou",
    "wof:placetype":"locality"
},
  "geometry": {"coordinates":[-3.61439,7.79463],"type":"Point"}
}