{
  "type": "Feature",
  "properties": {
    "gn:admin1_code":"82.0",
    "gn:asciiname":"Bero Atte",
    "gn:country_code":"CI",
    "gn:dem":54,
    "gn:feature_class":"P",
    "gn:feature_code":"PPL",
    "gn:name":"Bero Att\u00e9",
    "gn:population":0,
    "gn:timezone":"Africa/Abidjan",
    "iso:country":"CI",
    "wof:name":"Bero Atte",
    "wof:placetype":"locality"
},
  "geometry": {"coordinates":[-4.37514,5.86232],"type":"Point"}
}