{
  "type": "Feature",
  "properties": {
    "gn:admin1_code":"93.0",
    "gn:asciiname":"Tiemoko Kone",
    "gn:country_code":"CI",
    "gn:dem":68,
    "gn:feature_class":"P",
    "gn:feature_code":"PPL",
    "gn:name":"Ti\u00e9moko Kone",
    "gn:population":0,
    "gn:timezone":"Africa/Abidjan",
    "iso:country":"CI",
    "wof:name":"Tiemoko Kone",
    "wof:placetype":"locality"
},
  "geometry": {"coordinates":[-4.06385,5.54244],"type":"Point"}
}