{
  "type": "Feature",
  "properties": {
    "gn:admin1_code":"81.0",
    "gn:asciiname":"Dalossou",
    "gn:country_code":"CI",
    "gn:dem":181,
    "gn:feature_class":"P",
    "gn:feature_code":"PPL",
    "gn:name":"Dalossou",
    "gn:population":0,
    "gn:timezone":"Africa/Abidjan",
    "iso:country":"CI",
    "name:und_x_variant":[
        "Dalosso",
        "Dalousso",
        "Dalossou"
    ],
    "wof:name":"Dalossou",
    "wof:placetype":"locality"
},
  "geometry": {"coordinates":[-3.93663,6.8217],"type":"Point"}
}