{
  "type": "Feature",
  "properties": {
    "gn:admin1_code":"87",
    "gn:asciiname":"Kouwovogo",
    "gn:country_code":"CI",
    "gn:dem":371,
    "gn:feature_class":"P",
    "gn:feature_code":"PPL",
    "gn:name":"Kouwovogo",
    "gn:population":0,
    "gn:timezone":"Africa/Abidjan",
    "iso:country":"CI",
    "name:und_x_variant":[
        "Kouwavogo",
        "Kouwovogo"
    ],
    "wof:name":"Kouwovogo",
    "wof:placetype":"locality"
},
  "geometry": {"coordinates":[-5.55137,9.62879],"type":"Point"}
}