{
  "type": "Feature",
  "properties": {
    "gn:admin1_code":"89.0",
    "gn:asciiname":"Egbeni",
    "gn:country_code":"CI",
    "gn:dem":0,
    "gn:feature_class":"P",
    "gn:feature_code":"PPL",
    "gn:name":"\u00c9gb\u00e9ni",
    "gn:population":0,
    "gn:timezone":"Africa/Abidjan",
    "iso:country":"CI",
    "wof:name":"Egbeni",
    "wof:placetype":"locality"
},
  "geometry": {"coordinates":[-3.27762,5.1751],"type":"Point"}
}