{
  "type": "Feature",
  "properties": {
    "gn:admin1_code":"87.0",
    "gn:asciiname":"Gbaparikaha",
    "gn:country_code":"CI",
    "gn:dem":333,
    "gn:feature_class":"P",
    "gn:feature_code":"PPL",
    "gn:name":"Gbaparikaha",
    "gn:population":0,
    "gn:timezone":"Africa/Abidjan",
    "iso:country":"CI",
    "name:und_x_variant":[
        "Paparikaha",
        "Gbaparikaha"
    ],
    "wof:name":"Gbaparikaha",
    "wof:placetype":"locality"
},
  "geometry": {"coordinates":[-5.43333,9.35],"type":"Point"}
}