{
  "type": "Feature",
  "properties": {
    "gn:admin1_code":"97.0",
    "gn:asciiname":"Borotou-Koro",
    "gn:country_code":"CI",
    "gn:dem":291,
    "gn:feature_class":"P",
    "gn:feature_code":"PPL",
    "gn:name":"Borotou-Koro",
    "gn:population":0,
    "gn:timezone":"Africa/Abidjan",
    "iso:country":"CI",
    "wof:name":"Borotou-Koro",
    "wof:placetype":"locality"
},
  "geometry": {"coordinates":[-7.17861,8.49111],"type":"Point"}
}