{
  "type": "Feature",
  "properties": {
    "gn:admin1_code":"90",
    "gn:asciiname":"Lassinkro",
    "gn:country_code":"CI",
    "gn:dem":303,
    "gn:feature_class":"P",
    "gn:feature_code":"PPL",
    "gn:name":"Lassinkro",
    "gn:population":0,
    "gn:timezone":"Africa/Abidjan",
    "iso:country":"CI",
    "name:und_x_variant":[
        "Lassikro",
        "Losikro"
    ],
    "wof:name":"Lassinkro",
    "wof:placetype":"locality"
},
  "geometry": {"coordinates":[-5.30331,7.70144],"type":"Point"}
}