{
  "type": "Feature",
  "properties": {
    "gn:admin1_code":"82.0",
    "gn:asciiname":"Diateke",
    "gn:country_code":"CI",
    "gn:dem":11,
    "gn:feature_class":"P",
    "gn:feature_code":"PPL",
    "gn:name":"Diat\u00e9k\u00e9",
    "gn:population":0,
    "gn:timezone":"Africa/Abidjan",
    "iso:country":"CI",
    "wof:name":"Diateke",
    "wof:placetype":"locality"
},
  "geometry": {"coordinates":[-4.88115,5.14877],"type":"Point"}
}