{
  "type": "Feature",
  "properties": {
    "gn:admin1_code":"82.0",
    "gn:asciiname":"Atikon",
    "gn:country_code":"CI",
    "gn:dem":47,
    "gn:feature_class":"P",
    "gn:feature_code":"PPL",
    "gn:name":"Atikon",
    "gn:population":0,
    "gn:timezone":"Africa/Abidjan",
    "iso:country":"CI",
    "wof:name":"Atikon",
    "wof:placetype":"locality"
},
  "geometry": {"coordinates":[-4.40266,5.45713],"type":"Point"}
}