{
  "type": "Feature",
  "properties": {
    "gn:admin1_code":"90",
    "gn:asciiname":"Namayondougou",
    "gn:country_code":"CI",
    "gn:dem":257,
    "gn:feature_class":"P",
    "gn:feature_code":"PPL",
    "gn:name":"Namayondougou",
    "gn:population":0,
    "gn:timezone":"Africa/Abidjan",
    "iso:country":"CI",
    "wof:name":"Namayondougou",
    "wof:placetype":"locality"
},
  "geometry": {"coordinates":[-4.11695,8.10264],"type":"Point"}
}