{
  "type": "Feature",
  "properties": {
    "gn:admin1_code":"78.0",
    "gn:asciiname":"Bahe-Blaon",
    "gn:country_code":"CI",
    "gn:dem":245,
    "gn:feature_class":"P",
    "gn:feature_code":"PPL",
    "gn:name":"Bah\u00e9-Blaon",
    "gn:population":0,
    "gn:timezone":"Africa/Abidjan",
    "iso:country":"CI",
    "name:und_x_variant":[
        "Bah\u00e9-Blaon",
        "Bah\u00e9"
    ],
    "wof:name":"Bahe-Blaon",
    "wof:placetype":"locality"
},
  "geometry": {"coordinates":[-7.34265,6.67073],"type":"Point"}
}