{
  "type": "Feature",
  "properties": {
    "gn:admin1_code":"87",
    "gn:asciiname":"Meraga",
    "gn:country_code":"CI",
    "gn:dem":314,
    "gn:feature_class":"P",
    "gn:feature_code":"PPL",
    "gn:name":"M\u00e9raga",
    "gn:population":0,
    "gn:timezone":"Africa/Abidjan",
    "iso:country":"CI",
    "wof:name":"Meraga",
    "wof:placetype":"locality"
},
  "geometry": {"coordinates":[-5.4916,10.2815],"type":"Point"}
}