{
  "type": "Feature",
  "properties": {
    "gn:admin1_code":"92.0",
    "gn:asciiname":"Aourossua",
    "gn:country_code":"CI",
    "gn:dem":243,
    "gn:feature_class":"P",
    "gn:feature_code":"PPL",
    "gn:name":"Aourossua",
    "gn:population":0,
    "gn:timezone":"Africa/Abidjan",
    "iso:country":"CI",
    "wof:name":"Aourossua",
    "wof:placetype":"locality"
},
  "geometry": {"coordinates":[-3.05859,7.40796],"type":"Point"}
}