{
  "type": "Feature",
  "properties": {
    "gn:admin1_code":"81.0",
    "gn:asciiname":"Ande",
    "gn:country_code":"CI",
    "gn:dem":181,
    "gn:feature_class":"P",
    "gn:feature_code":"PPL",
    "gn:name":"And\u00e9",
    "gn:population":0,
    "gn:timezone":"Africa/Abidjan",
    "iso:country":"CI",
    "wof:name":"Ande",
    "wof:placetype":"locality"
},
  "geometry": {"coordinates":[-4.08517,6.78176],"type":"Point"}
}