{
  "type": "Feature",
  "properties": {
    "gn:admin1_code":"81.0",
    "gn:asciiname":"Diankro",
    "gn:country_code":"CI",
    "gn:dem":275,
    "gn:feature_class":"P",
    "gn:feature_code":"PPL",
    "gn:name":"Diankro",
    "gn:population":0,
    "gn:timezone":"Africa/Abidjan",
    "iso:country":"CI",
    "wof:name":"Diankro",
    "wof:placetype":"locality"
},
  "geometry": {"coordinates":[-5.02486,7.4139],"type":"Point"}
}