{
  "type": "Feature",
  "properties": {
    "gn:admin1_code":"82.0",
    "gn:asciiname":"Asseka",
    "gn:country_code":"CI",
    "gn:dem":74,
    "gn:feature_class":"P",
    "gn:feature_code":"PPL",
    "gn:name":"Ass\u00e8ka",
    "gn:population":0,
    "gn:timezone":"Africa/Abidjan",
    "iso:country":"CI",
    "wof:name":"Asseka",
    "wof:placetype":"locality"
},
  "geometry": {"coordinates":[-3.63538,5.82365],"type":"Point"}
}