{
  "type": "Feature",
  "properties": {
    "gn:admin1_code":"76",
    "gn:asciiname":"Yeouli",
    "gn:country_code":"CI",
    "gn:dem":10,
    "gn:feature_class":"P",
    "gn:feature_code":"PPL",
    "gn:name":"Y\u00e9ouli",
    "gn:population":0,
    "gn:timezone":"Africa/Abidjan",
    "iso:country":"CI",
    "name:und_x_variant":[
        "Y\u00e9ouli",
        "Yeouli"
    ],
    "wof:name":"Yeouli",
    "wof:placetype":"locality"
},
  "geometry": {"coordinates":[-7.5577,4.52293],"type":"Point"}
}