{
  "type": "Feature",
  "properties": {
    "gn:admin1_code":"92",
    "gn:asciiname":"Timorossie",
    "gn:country_code":"CI",
    "gn:dem":310,
    "gn:feature_class":"P",
    "gn:feature_code":"PPL",
    "gn:name":"Timorossi\u00e9",
    "gn:population":0,
    "gn:timezone":"Africa/Abidjan",
    "iso:country":"CI",
    "wof:name":"Timorossie",
    "wof:placetype":"locality"
},
  "geometry": {"coordinates":[-2.69703,8.03046],"type":"Point"}
}