{
  "type": "Feature",
  "properties": {
    "gn:admin1_code":"95",
    "gn:asciiname":"Yokoboue",
    "gn:country_code":"CI",
    "gn:dem":64,
    "gn:feature_class":"P",
    "gn:feature_code":"PPL",
    "gn:name":"Yokobou\u00e9",
    "gn:population":0,
    "gn:timezone":"Africa/Abidjan",
    "iso:country":"CI",
    "name:und_x_variant":[
        "Yocobou\u00e9",
        "Yokobou\u00e9"
    ],
    "wof:name":"Yokoboue",
    "wof:placetype":"locality"
},
  "geometry": {"coordinates":[-5.10658,5.26933],"type":"Point"}
}