{
  "type": "Feature",
  "properties": {
    "gn:admin1_code":"90",
    "gn:asciiname":"Tindikan-Dioulasso",
    "gn:country_code":"CI",
    "gn:dem":240,
    "gn:feature_class":"P",
    "gn:feature_code":"PPL",
    "gn:name":"Tindikan-Dioulasso",
    "gn:population":0,
    "gn:timezone":"Africa/Abidjan",
    "iso:country":"CI",
    "wof:name":"Tindikan-Dioulasso",
    "wof:placetype":"locality"
},
  "geometry": {"coordinates":[-4.38405,8.338],"type":"Point"}
}