{
  "type": "Feature",
  "properties": {
    "gn:admin1_code":"81",
    "gn:asciiname":"Lalasso",
    "gn:country_code":"CI",
    "gn:dem":176,
    "gn:feature_class":"P",
    "gn:feature_code":"PPL",
    "gn:name":"Lalasso",
    "gn:population":0,
    "gn:timezone":"Africa/Abidjan",
    "iso:country":"CI",
    "wof:name":"Lalasso",
    "wof:placetype":"locality"
},
  "geometry": {"coordinates":[-3.72724,7.30421],"type":"Point"}
}