{
  "type": "Feature",
  "properties": {
    "gn:admin1_code":"82.0",
    "gn:asciiname":"Solam",
    "gn:country_code":"CI",
    "gn:dem":48,
    "gn:feature_class":"P",
    "gn:feature_code":"PPL",
    "gn:name":"Solam",
    "gn:population":0,
    "gn:timezone":"Africa/Abidjan",
    "iso:country":"CI",
    "wof:name":"Solam",
    "wof:placetype":"locality"
},
  "geometry": {"coordinates":[-4.27903,5.84891],"type":"Point"}
}