{
  "type": "Feature",
  "properties": {
    "gn:admin1_code":"97",
    "gn:asciiname":"Konekedou",
    "gn:country_code":"CI",
    "gn:dem":327,
    "gn:feature_class":"P",
    "gn:feature_code":"PPL",
    "gn:name":"Kon\u00e9k\u00e9dou",
    "gn:population":0,
    "gn:timezone":"Africa/Abidjan",
    "iso:country":"CI",
    "wof:name":"Konekedou",
    "wof:placetype":"locality"
},
  "geometry": {"coordinates":[-7.22611,8.4275],"type":"Point"}
}