{
  "type": "Feature",
  "properties": {
    "gn:admin1_code":"82.0",
    "gn:asciiname":"Essab Dempa",
    "gn:country_code":"CI",
    "gn:dem":80,
    "gn:feature_class":"P",
    "gn:feature_code":"PPL",
    "gn:name":"Essab Dempa",
    "gn:population":0,
    "gn:timezone":"Africa/Abidjan",
    "iso:country":"CI",
    "wof:name":"Essab Dempa",
    "wof:placetype":"locality"
},
  "geometry": {"coordinates":[-4.49447,5.61559],"type":"Point"}
}