{
  "type": "Feature",
  "properties": {
    "gn:admin1_code":"82.0",
    "gn:asciiname":"Amoichi",
    "gn:country_code":"CI",
    "gn:dem":62,
    "gn:feature_class":"P",
    "gn:feature_code":"PPL",
    "gn:name":"Amoichi",
    "gn:population":0,
    "gn:timezone":"Africa/Abidjan",
    "iso:country":"CI",
    "wof:name":"Amoichi",
    "wof:placetype":"locality"
},
  "geometry": {"coordinates":[-4.37691,5.86213],"type":"Point"}
}