{
  "type": "Feature",
  "properties": {
    "gn:admin1_code":"94",
    "gn:asciiname":"Monga",
    "gn:country_code":"CI",
    "gn:dem":15,
    "gn:feature_class":"P",
    "gn:feature_code":"PPL",
    "gn:name":"Monga",
    "gn:population":0,
    "gn:timezone":"Africa/Abidjan",
    "iso:country":"CI",
    "name:fra_x_preferred":[
        "Monga"
    ],
    "name:msa_x_preferred":[
        "Monga"
    ],
    "wof:name":"Monga",
    "wof:placetype":"locality"
},
  "geometry": {"coordinates":[-3.6607,5.47623],"type":"Point"}
}