{
  "type": "Feature",
  "properties": {
    "gn:admin1_code":"87",
    "gn:asciiname":"Nianelekaha",
    "gn:country_code":"CI",
    "gn:dem":355,
    "gn:feature_class":"P",
    "gn:feature_code":"PPL",
    "gn:name":"Nian\u00e9l\u00e9kaha",
    "gn:population":0,
    "gn:timezone":"Africa/Abidjan",
    "iso:country":"CI",
    "wof:name":"Nianelekaha",
    "wof:placetype":"locality"
},
  "geometry": {"coordinates":[-5.60854,9.41663],"type":"Point"}
}