{
  "type": "Feature",
  "properties": {
    "gn:admin1_code":"77",
    "gn:asciiname":"Ngoloblasso",
    "gn:country_code":"CI",
    "gn:dem":525,
    "gn:feature_class":"P",
    "gn:feature_code":"PPL",
    "gn:name":"Ngoloblasso",
    "gn:population":0,
    "gn:timezone":"Africa/Abidjan",
    "iso:country":"CI",
    "name:fra_x_preferred":[
        "Ngoloblasso"
    ],
    "name:ita_x_preferred":[
        "N'Goloblasso"
    ],
    "name:msa_x_preferred":[
        "N\u2019Goloblasso"
    ],
    "name:und_x_variant":[
        "Ngoloblaso"
    ],
    "wof:name":"Ngoloblasso",
    "wof:placetype":"locality"
},
  "geometry": {"coordinates":[-7.22373,9.68488],"type":"Point"}
}