{
  "type": "Feature",
  "properties": {
    "gn:admin1_code":"94.0",
    "gn:asciiname":"Flomoudje",
    "gn:country_code":"CI",
    "gn:dem":69,
    "gn:feature_class":"P",
    "gn:feature_code":"PPL",
    "gn:name":"Flomoudj\u00e9",
    "gn:population":0,
    "gn:timezone":"Africa/Abidjan",
    "iso:country":"CI",
    "wof:name":"Flomoudje",
    "wof:placetype":"locality"
},
  "geometry": {"coordinates":[-3.55828,5.5191],"type":"Point"}
}