{
  "type": "Feature",
  "properties": {
    "gn:admin1_code":"87.0",
    "gn:asciiname":"Dyendana",
    "gn:country_code":"CI",
    "gn:dem":370,
    "gn:feature_class":"P",
    "gn:feature_code":"PPL",
    "gn:name":"Dy\u00e9ndana",
    "gn:population":0,
    "gn:timezone":"Africa/Abidjan",
    "iso:country":"CI",
    "name:und_x_variant":[
        "Di\u00e9nana",
        "Dy\u00e9ndana"
    ],
    "wof:name":"Dyendana",
    "wof:placetype":"locality"
},
  "geometry": {"coordinates":[-5.59629,9.51528],"type":"Point"}
}