{
  "type": "Feature",
  "properties": {
    "gn:admin1_code":"77",
    "gn:asciiname":"Ouassangalasso",
    "gn:country_code":"CI",
    "gn:dem":355,
    "gn:feature_class":"P",
    "gn:feature_code":"PPL",
    "gn:name":"Ouassangalasso",
    "gn:population":0,
    "gn:timezone":"Africa/Abidjan",
    "iso:country":"CI",
    "name:und_x_variant":[
        "Ouassoungolasso",
        "Oussoungolasso",
        "Ouassangalasso"
    ],
    "wof:name":"Ouassangalasso",
    "wof:placetype":"locality"
},
  "geometry": {"coordinates":[-6.62785,10.17377],"type":"Point"}
}