{
  "type": "Feature",
  "properties": {
    "gn:admin1_code":"96",
    "gn:asciiname":"Manematiefla",
    "gn:country_code":"CI",
    "gn:dem":283,
    "gn:feature_class":"P",
    "gn:feature_code":"PPL",
    "gn:name":"Man\u00e9mati\u00e9fla",
    "gn:population":0,
    "gn:timezone":"Africa/Abidjan",
    "iso:country":"CI",
    "name:und_x_variant":[
        "Man\u00e9matifla",
        "Man\u00e9mati\u00e9fla"
    ],
    "wof:name":"Manematiefla",
    "wof:placetype":"locality"
},
  "geometry": {"coordinates":[-5.87778,7.64722],"type":"Point"}
}