{
  "type": "Feature",
  "properties": {
    "gn:admin1_code":"87",
    "gn:asciiname":"Nogotyok",
    "gn:country_code":"CI",
    "gn:dem":337,
    "gn:feature_class":"P",
    "gn:feature_code":"PPL",
    "gn:name":"Nogotyok",
    "gn:population":0,
    "gn:timezone":"Africa/Abidjan",
    "iso:country":"CI",
    "name:und_x_variant":[
        "Nogotiok",
        "Nogotyok"
    ],
    "wof:name":"Nogotyok",
    "wof:placetype":"locality"
},
  "geometry": {"coordinates":[-5.62064,9.2543],"type":"Point"}
}