{
  "type": "Feature",
  "properties": {
    "gn:admin1_code":"77.0",
    "gn:asciiname":"Bara",
    "gn:country_code":"CI",
    "gn:dem":399,
    "gn:feature_class":"P",
    "gn:feature_code":"PPL",
    "gn:name":"Bara",
    "gn:population":0,
    "gn:timezone":"Africa/Abidjan",
    "iso:country":"CI",
    "name:und_x_variant":[
        "Baga",
        "Bara"
    ],
    "wof:name":"Bara",
    "wof:placetype":"locality"
},
  "geometry": {"coordinates":[-7.55226,9.71752],"type":"Point"}
}