{
  "type": "Feature",
  "properties": {
    "gn:admin1_code":"87",
    "gn:asciiname":"Mameadougou",
    "gn:country_code":"CI",
    "gn:dem":311,
    "gn:feature_class":"P",
    "gn:feature_code":"PPL",
    "gn:name":"Mam\u00e9adougou",
    "gn:population":0,
    "gn:timezone":"Africa/Abidjan",
    "iso:country":"CI",
    "wof:name":"Mameadougou",
    "wof:placetype":"locality"
},
  "geometry": {"coordinates":[-5.12359,10.11799],"type":"Point"}
}