{
  "type": "Feature",
  "properties": {
    "gn:admin1_code":"97.0",
    "gn:asciiname":"Ouehisso",
    "gn:country_code":"CI",
    "gn:dem":484,
    "gn:feature_class":"P",
    "gn:feature_code":"PPL",
    "gn:name":"Ou\u00e9hisso",
    "gn:population":0,
    "gn:timezone":"Africa/Abidjan",
    "iso:country":"CI",
    "wof:name":"Ouehisso",
    "wof:placetype":"locality"
},
  "geometry": {"coordinates":[-7.70481,7.9248],"type":"Point"}
}