{
  "type": "Feature",
  "properties": {
    "gn:admin1_code":"78",
    "gn:asciiname":"Ouetomba",
    "gn:country_code":"CI",
    "gn:dem":430,
    "gn:feature_class":"P",
    "gn:feature_code":"PPL",
    "gn:name":"Ou\u00e9tomba",
    "gn:population":0,
    "gn:timezone":"Africa/Abidjan",
    "iso:country":"CI",
    "wof:name":"Ouetomba",
    "wof:placetype":"locality"
},
  "geometry": {"coordinates":[-7.45462,7.52211],"type":"Point"}
}