{
  "type": "Feature",
  "properties": {
    "gn:admin1_code":"90.0",
    "gn:asciiname":"Akandi",
    "gn:country_code":"CI",
    "gn:dem":224,
    "gn:feature_class":"P",
    "gn:feature_code":"PPL",
    "gn:name":"Akandi",
    "gn:population":0,
    "gn:timezone":"Africa/Abidjan",
    "iso:country":"CI",
    "wof:name":"Akandi",
    "wof:placetype":"locality"
},
  "geometry": {"coordinates":[-5.13987,7.35353],"type":"Point"}
}