{
  "type": "Feature",
  "properties": {
    "gn:admin1_code":"82.0",
    "gn:asciiname":"Fetchi Kama",
    "gn:country_code":"CI",
    "gn:dem":42,
    "gn:feature_class":"P",
    "gn:feature_code":"PPL",
    "gn:name":"F\u00e9tchi Kama",
    "gn:population":0,
    "gn:timezone":"Africa/Abidjan",
    "iso:country":"CI",
    "wof:name":"Fetchi Kama",
    "wof:placetype":"locality"
},
  "geometry": {"coordinates":[-4.24512,5.85761],"type":"Point"}
}