{
  "type": "Feature",
  "properties": {
    "gn:admin1_code":"78",
    "gn:asciiname":"Yapleu",
    "gn:country_code":"CI",
    "gn:dem":293,
    "gn:feature_class":"P",
    "gn:feature_code":"PPL",
    "gn:name":"Yapleu",
    "gn:population":0,
    "gn:timezone":"Africa/Abidjan",
    "iso:country":"CI",
    "name:fra_x_preferred":[
        "Yapleu"
    ],
    "name:ita_x_preferred":[
        "Yapleu"
    ],
    "name:msa_x_preferred":[
        "Yapleu"
    ],
    "name:ron_x_preferred":[
        "Yapleu"
    ],
    "name:und_x_variant":[
        "Iapleu",
        "Yapleu"
    ],
    "wof:name":"Yapleu",
    "wof:placetype":"locality"
},
  "geometry": {"coordinates":[-7.71028,7.09056],"type":"Point"}
}