{
  "type": "Feature",
  "properties": {
    "gn:admin1_code":"78",
    "gn:asciiname":"Soba",
    "gn:country_code":"CI",
    "gn:dem":525,
    "gn:feature_class":"P",
    "gn:feature_code":"PPL",
    "gn:name":"Soba",
    "gn:population":0,
    "gn:timezone":"Africa/Abidjan",
    "iso:country":"CI",
    "wof:name":"Soba",
    "wof:placetype":"locality"
},
  "geometry": {"coordinates":[-7.31731,7.80556],"type":"Point"}
}