{
  "type": "Feature",
  "properties": {
    "gn:admin1_code":"78",
    "gn:asciiname":"Soba",
    "gn:country_code":"CI",
    "gn:dem":525,
    "gn:feature_class":"P",
    "gn:feature_code":"PPL",
    "gn:name":"Soba",
    "gn:population":0,
    "gn:timezone":"Africa/Abidjan",
    "iso:country":"CI",
    "name:ara_x_preferred":[
        "\u0633\u0648\u0628\u0627"
    ],
    "name:cat_x_preferred":[
        "Fideus soba"
    ],
    "name:ces_x_preferred":[
        "Soba"
    ],
    "name:dan_x_preferred":[
        "Soba"
    ],
    "name:deu_x_preferred":[
        "Soba"
    ],
    "name:epo_x_preferred":[
        "Soba"
    ],
    "name:eus_x_preferred":[
        "Soba"
    ],
    "name:fas_x_preferred":[
        "\u0633\u0648\u0628\u0627"
    ],
    "name:fin_x_preferred":[
        "Soba"
    ],
    "name:fra_x_preferred":[
        "Soba"
    ],
    "name:heb_x_preferred":[
        "\u05e1\u05d5\u05d1\u05d4"
    ],
    "name:hun_x_preferred":[
        "Szoba"
    ],
    "name:hye_x_preferred":[
        "\u054d\u0578\u0562\u0561"
    ],
    "name:ind_x_preferred":[
        "Soba"
    ],
    "name:ita_x_preferred":[
        "Soba"
    ],
    "name:jav_x_preferred":[
        "Soba"
    ],
    "name:lit_x_preferred":[
        "Soba"
    ],
    "name:msa_x_preferred":[
        "Soba"
    ],
    "name:pol_x_preferred":[
        "Soba"
    ],
    "name:por_x_preferred":[
        "Sob\u00e1"
    ],
    "name:rus_x_preferred":[
        "\u0421\u043e\u0431\u0430"
    ],
    "name:spa_x_preferred":[
        "Soba"
    ],
    "name:sun_x_preferred":[
        "Soba"
    ],
    "name:swe_x_preferred":[
        "Soba"
    ],
    "name:tha_x_preferred":[
        "\u0e42\u0e0b\u0e1a\u0e30"
    ],
    "name:tur_x_preferred":[
        "Soba"
    ],
    "name:ukr_x_preferred":[
        "\u0421\u043e\u0431\u0430"
    ],
    "name:vie_x_preferred":[
        "Soba"
    ],
    "name:wuu_x_preferred":[
        "\u854e\u9ea5\u9eb5"
    ],
    "name:zho_x_preferred":[
        "\u835e\u9ea6\u9762"
    ],
    "wof:name":"Soba",
    "wof:placetype":"locality"
},
  "geometry": {"coordinates":[-7.31731,7.80556],"type":"Point"}
}