{
  "type": "Feature",
  "properties": {
    "gn:admin1_code":"95.0",
    "gn:asciiname":"Guiguia",
    "gn:country_code":"CI",
    "gn:dem":238,
    "gn:feature_class":"P",
    "gn:feature_code":"PPL",
    "gn:name":"Guiguia",
    "gn:population":0,
    "gn:timezone":"Africa/Abidjan",
    "iso:country":"CI",
    "wof:name":"Guiguia",
    "wof:placetype":"locality"
},
  "geometry": {"coordinates":[-5.92709,5.97732],"type":"Point"}
}