{
  "type": "Feature",
  "properties": {
    "gn:admin1_code":"82",
    "gn:asciiname":"Moofoue",
    "gn:country_code":"CI",
    "gn:dem":53,
    "gn:feature_class":"P",
    "gn:feature_code":"PPL",
    "gn:name":"Moofou\u00e9",
    "gn:population":0,
    "gn:timezone":"Africa/Abidjan",
    "iso:country":"CI",
    "wof:name":"Moofoue",
    "wof:placetype":"locality"
},
  "geometry": {"coordinates":[-4.73868,6.11627],"type":"Point"}
}