{
  "type": "Feature",
  "properties": {
    "gn:admin1_code":"92",
    "gn:asciiname":"Nemouko",
    "gn:country_code":"CI",
    "gn:dem":324,
    "gn:feature_class":"P",
    "gn:feature_code":"PPL",
    "gn:name":"N\u00e9mouko",
    "gn:population":0,
    "gn:timezone":"Africa/Abidjan",
    "iso:country":"CI",
    "wof:name":"Nemouko",
    "wof:placetype":"locality"
},
  "geometry": {"coordinates":[-3.77745,9.78594],"type":"Point"}
}