{
  "type": "Feature",
  "properties": {
    "gn:admin1_code":"81.0",
    "gn:asciiname":"Ahua",
    "gn:country_code":"CI",
    "gn:dem":107,
    "gn:feature_class":"P",
    "gn:feature_code":"PPL",
    "gn:name":"Ahua",
    "gn:population":0,
    "gn:timezone":"Africa/Abidjan",
    "iso:country":"CI",
    "wof:name":"Ahua",
    "wof:placetype":"locality"
},
  "geometry": {"coordinates":[-4.67239,6.66535],"type":"Point"}
}