{
  "type": "Feature",
  "properties": {
    "gn:admin1_code":"81",
    "gn:asciiname":"Srakakro",
    "gn:country_code":"CI",
    "gn:dem":181,
    "gn:feature_class":"P",
    "gn:feature_code":"PPL",
    "gn:name":"Srakakro",
    "gn:population":0,
    "gn:timezone":"Africa/Abidjan",
    "iso:country":"CI",
    "wof:name":"Srakakro",
    "wof:placetype":"locality"
},
  "geometry": {"coordinates":[-4.18333,7.06667],"type":"Point"}
}