{
  "type": "Feature",
  "properties": {
    "gn:admin1_code":"82.0",
    "gn:asciiname":"Achokoa",
    "gn:country_code":"CI",
    "gn:dem":56,
    "gn:feature_class":"P",
    "gn:feature_code":"PPL",
    "gn:name":"Achokoa",
    "gn:population":0,
    "gn:timezone":"Africa/Abidjan",
    "iso:country":"CI",
    "name:und_x_variant":[
        "Achokoua"
    ],
    "wof:name":"Achokoa",
    "wof:placetype":"locality"
},
  "geometry": {"coordinates":[-3.83772,5.37429],"type":"Point"}
}