{
  "type": "Feature",
  "properties": {
    "gn:admin1_code":"94.0",
    "gn:asciiname":"Nzabenou",
    "gn:country_code":"CI",
    "gn:dem":7,
    "gn:feature_class":"P",
    "gn:feature_code":"PPL",
    "gn:name":"Nzab\u00e9nou",
    "gn:population":0,
    "gn:timezone":"Africa/Abidjan",
    "iso:country":"CI",
    "wof:name":"Nzabenou",
    "wof:placetype":"locality"
},
  "geometry": {"coordinates":[-2.97866,5.12427],"type":"Point"}
}