{
  "type": "Feature",
  "properties": {
    "gn:admin1_code":"92.0",
    "gn:asciiname":"Dioum",
    "gn:country_code":"CI",
    "gn:dem":293,
    "gn:feature_class":"P",
    "gn:feature_code":"PPL",
    "gn:name":"Dioum",
    "gn:population":0,
    "gn:timezone":"Africa/Abidjan",
    "iso:country":"CI",
    "wof:name":"Dioum",
    "wof:placetype":"locality"
},
  "geometry": {"coordinates":[-3.05598,7.95981],"type":"Point"}
}