{
  "type": "Feature",
  "properties": {
    "gn:admin1_code":"90.0",
    "gn:asciiname":"Bouakro",
    "gn:country_code":"CI",
    "gn:dem":242,
    "gn:feature_class":"P",
    "gn:feature_code":"PPL",
    "gn:name":"Bouakro",
    "gn:population":0,
    "gn:timezone":"Africa/Abidjan",
    "iso:country":"CI",
    "wof:name":"Bouakro",
    "wof:placetype":"locality"
},
  "geometry": {"coordinates":[-5.45545,7.79825],"type":"Point"}
}