{
  "type": "Feature",
  "properties": {
    "gn:admin1_code":"97",
    "gn:asciiname":"Soukoro-Komatou",
    "gn:country_code":"CI",
    "gn:dem":350,
    "gn:feature_class":"P",
    "gn:feature_code":"PPL",
    "gn:name":"Soukoro-Komatou",
    "gn:population":0,
    "gn:timezone":"Africa/Abidjan",
    "iso:country":"CI",
    "name:und_x_variant":[
        "Komantou",
        "Komatou",
        "Soukoro-Komatou"
    ],
    "wof:name":"Soukoro-Komatou",
    "wof:placetype":"locality"
},
  "geometry": {"coordinates":[-6.69327,8.54095],"type":"Point"}
}