{
  "type": "Feature",
  "properties": {
    "gn:admin1_code":"78.0",
    "gn:asciiname":"Drohouleu",
    "gn:country_code":"CI",
    "gn:dem":678,
    "gn:feature_class":"P",
    "gn:feature_code":"PPL",
    "gn:name":"Drohouleu",
    "gn:population":0,
    "gn:timezone":"Africa/Abidjan",
    "iso:country":"CI",
    "name:und_x_variant":[
        "Gbal\u00e9 1"
    ],
    "wof:name":"Drohouleu",
    "wof:placetype":"locality"
},
  "geometry": {"coordinates":[-7.93736,7.54735],"type":"Point"}
}