{
  "type": "Feature",
  "properties": {
    "gn:admin1_code":"82.0",
    "gn:asciiname":"Ndja Kouame",
    "gn:country_code":"CI",
    "gn:dem":61,
    "gn:feature_class":"P",
    "gn:feature_code":"PPL",
    "gn:name":"Ndja Kouam\u00e9",
    "gn:population":0,
    "gn:timezone":"Africa/Abidjan",
    "iso:country":"CI",
    "wof:name":"Ndja Kouame",
    "wof:placetype":"locality"
},
  "geometry": {"coordinates":[-4.27485,5.90803],"type":"Point"}
}