{
  "type": "Feature",
  "properties": {
    "gn:admin1_code":"93.0",
    "gn:asciiname":"Brou Asse",
    "gn:country_code":"CI",
    "gn:dem":41,
    "gn:feature_class":"P",
    "gn:feature_code":"PPL",
    "gn:name":"Brou Ass\u00e9",
    "gn:population":0,
    "gn:timezone":"Africa/Abidjan",
    "iso:country":"CI",
    "wof:name":"Brou Asse",
    "wof:placetype":"locality"
},
  "geometry": {"coordinates":[-4.05,5.53333],"type":"Point"}
}