{
  "type": "Feature",
  "properties": {
    "gn:admin1_code":"97",
    "gn:asciiname":"Worofla",
    "gn:country_code":"CI",
    "gn:dem":388,
    "gn:feature_class":"P",
    "gn:feature_code":"PPL",
    "gn:name":"Worofla",
    "gn:population":0,
    "gn:timezone":"Africa/Abidjan",
    "iso:country":"CI",
    "name:fra_x_preferred":[
        "Worofla"
    ],
    "name:ita_x_preferred":[
        "Worofla"
    ],
    "name:msa_x_preferred":[
        "Worofla"
    ],
    "name:und_x_variant":[
        "Ouorofia",
        "Ouorofla",
        "Ouorofoula",
        "Ourenfla",
        "Ouroufla"
    ],
    "wof:name":"Worofla",
    "wof:placetype":"locality"
},
  "geometry": {"coordinates":[-6.90555,8.27335],"type":"Point"}
}