{
  "type": "Feature",
  "properties": {
    "gn:admin1_code":"81",
    "gn:asciiname":"Ouaouakro",
    "gn:country_code":"CI",
    "gn:dem":162,
    "gn:feature_class":"P",
    "gn:feature_code":"PPL",
    "gn:name":"Ouaouakro",
    "gn:population":0,
    "gn:timezone":"Africa/Abidjan",
    "iso:country":"CI",
    "name:und_x_variant":[
        "Wawakro"
    ],
    "wof:name":"Ouaouakro",
    "wof:placetype":"locality"
},
  "geometry": {"coordinates":[-4.95707,6.99312],"type":"Point"}
}