{
  "type": "Feature",
  "properties": {
    "gn:admin1_code":"90.0",
    "gn:asciiname":"Fangoli-Sokoura",
    "gn:country_code":"CI",
    "gn:dem":245,
    "gn:feature_class":"P",
    "gn:feature_code":"PPL",
    "gn:name":"Fangoli-Sokoura",
    "gn:population":0,
    "gn:timezone":"Africa/Abidjan",
    "iso:country":"CI",
    "wof:name":"Fangoli-Sokoura",
    "wof:placetype":"locality"
},
  "geometry": {"coordinates":[-4.38746,8.19935],"type":"Point"}
}