{
  "type": "Feature",
  "properties": {
    "gn:admin1_code":"77.0",
    "gn:asciiname":"Bouake",
    "gn:country_code":"CI",
    "gn:dem":423,
    "gn:feature_class":"P",
    "gn:feature_code":"PPL",
    "gn:name":"Bouak\u00e9",
    "gn:population":0,
    "gn:timezone":"Africa/Abidjan",
    "iso:country":"CI",
    "wof:name":"Bouake",
    "wof:placetype":"locality"
},
  "geometry": {"coordinates":[-7.41667,9.61667],"type":"Point"}
}