{
  "type": "Feature",
  "properties": {
    "gn:admin1_code":"81",
    "gn:asciiname":"Kokinsikro",
    "gn:country_code":"CI",
    "gn:dem":168,
    "gn:feature_class":"P",
    "gn:feature_code":"PPL",
    "gn:name":"Kokinsikro",
    "gn:population":0,
    "gn:timezone":"Africa/Abidjan",
    "iso:country":"CI",
    "wof:name":"Kokinsikro",
    "wof:placetype":"locality"
},
  "geometry": {"coordinates":[-3.83333,7.03333],"type":"Point"}
}