{
  "type": "Feature",
  "properties": {
    "gn:admin1_code":"92.0",
    "gn:asciiname":"Kanton",
    "gn:country_code":"CI",
    "gn:dem":216,
    "gn:feature_class":"P",
    "gn:feature_code":"PPL",
    "gn:name":"Kanton",
    "gn:population":0,
    "gn:timezone":"Africa/Abidjan",
    "iso:country":"CI",
    "wof:name":"Kanton",
    "wof:placetype":"locality"
},
  "geometry": {"coordinates":[-3.30093,7.82028],"type":"Point"}
}