{
  "type": "Feature",
  "properties": {
    "gn:admin1_code":"82.0",
    "gn:asciiname":"Djibi",
    "gn:country_code":"CI",
    "gn:dem":50,
    "gn:feature_class":"P",
    "gn:feature_code":"PPL",
    "gn:name":"Djibi",
    "gn:population":0,
    "gn:timezone":"Africa/Abidjan",
    "iso:country":"CI",
    "wof:name":"Djibi",
    "wof:placetype":"locality"
},
  "geometry": {"coordinates":[-3.73218,5.54396],"type":"Point"}
}