{
  "type": "Feature",
  "properties": {
    "gn:admin1_code":"92.0",
    "gn:asciiname":"Kantara",
    "gn:country_code":"CI",
    "gn:dem":298,
    "gn:feature_class":"P",
    "gn:feature_code":"PPL",
    "gn:name":"Kantara",
    "gn:population":0,
    "gn:timezone":"Africa/Abidjan",
    "iso:country":"CI",
    "name:ceb_x_preferred":[
        "Kantara"
    ],
    "name:deu_x_preferred":[
        "Kantara"
    ],
    "name:swe_x_preferred":[
        "Kantara"
    ],
    "wof:name":"Kantara",
    "wof:placetype":"locality"
},
  "geometry": {"coordinates":[-3.08987,9.80243],"type":"Point"}
}