{
  "type": "Feature",
  "properties": {
    "gn:admin1_code":"97",
    "gn:asciiname":"Zodofouma",
    "gn:country_code":"CI",
    "gn:dem":552,
    "gn:feature_class":"P",
    "gn:feature_code":"PPL",
    "gn:name":"Zodofouma",
    "gn:population":0,
    "gn:timezone":"Africa/Abidjan",
    "iso:country":"CI",
    "wof:name":"Zodofouma",
    "wof:placetype":"locality"
},
  "geometry": {"coordinates":[-8.0603,8.42862],"type":"Point"}
}