{
  "type": "Feature",
  "properties": {
    "gn:admin1_code":"90.0",
    "gn:asciiname":"Babroukro",
    "gn:country_code":"CI",
    "gn:dem":273,
    "gn:feature_class":"P",
    "gn:feature_code":"PPL",
    "gn:name":"Babroukro",
    "gn:population":0,
    "gn:timezone":"Africa/Abidjan",
    "iso:country":"CI",
    "name:und_x_variant":[
        "Gbakroukro"
    ],
    "wof:name":"Babroukro",
    "wof:placetype":"locality"
},
  "geometry": {"coordinates":[-5.45856,7.9177],"type":"Point"}
}