{
  "type": "Feature",
  "properties": {
    "gn:admin1_code":"78.0",
    "gn:asciiname":"Gouefinso",
    "gn:country_code":"CI",
    "gn:dem":498,
    "gn:feature_class":"P",
    "gn:feature_code":"PPL",
    "gn:name":"Gou\u00e9finso",
    "gn:population":0,
    "gn:timezone":"Africa/Abidjan",
    "iso:country":"CI",
    "name:und_x_variant":[
        "Gu\u00e9finso",
        "G\u00e9f\u00e8nso",
        "Gou\u00e9finso"
    ],
    "wof:name":"Gouefinso",
    "wof:placetype":"locality"
},
  "geometry": {"coordinates":[-7.63959,7.78478],"type":"Point"}
}