{
  "type": "Feature",
  "properties": {
    "gn:admin1_code":"92.0",
    "gn:asciiname":"Andan",
    "gn:country_code":"CI",
    "gn:dem":320,
    "gn:feature_class":"P",
    "gn:feature_code":"PPL",
    "gn:name":"Andan",
    "gn:population":0,
    "gn:timezone":"Africa/Abidjan",
    "iso:country":"CI",
    "name:und_x_variant":[
        "Endan",
        "Andan"
    ],
    "wof:name":"Andan",
    "wof:placetype":"locality"
},
  "geometry": {"coordinates":[-3.72103,9.90678],"type":"Point"}
}