{
  "type": "Feature",
  "properties": {
    "gn:admin1_code":"94.0",
    "gn:asciiname":"Mauricekro",
    "gn:country_code":"CI",
    "gn:dem":5,
    "gn:feature_class":"P",
    "gn:feature_code":"PPL",
    "gn:name":"Mauricekro",
    "gn:population":0,
    "gn:timezone":"Africa/Abidjan",
    "iso:country":"CI",
    "wof:name":"Mauricekro",
    "wof:placetype":"locality"
},
  "geometry": {"coordinates":[-3.2697,5.29302],"type":"Point"}
}