{
  "type": "Feature",
  "properties": {
    "gn:admin1_code":"90",
    "gn:asciiname":"Ndokro",
    "gn:country_code":"CI",
    "gn:dem":326,
    "gn:feature_class":"P",
    "gn:feature_code":"PPL",
    "gn:name":"Ndokro",
    "gn:population":0,
    "gn:timezone":"Africa/Abidjan",
    "iso:country":"CI",
    "name:und_x_variant":[
        "Andokro"
    ],
    "wof:name":"Ndokro",
    "wof:placetype":"locality"
},
  "geometry": {"coordinates":[-5.03847,7.76098],"type":"Point"}
}