{
  "type": "Feature",
  "properties": {
    "gn:admin1_code":"81",
    "gn:asciiname":"Kouadianikro",
    "gn:country_code":"CI",
    "gn:dem":96,
    "gn:feature_class":"P",
    "gn:feature_code":"PPL",
    "gn:name":"Kouadianikro",
    "gn:population":0,
    "gn:timezone":"Africa/Abidjan",
    "iso:country":"CI",
    "name:und_x_variant":[
        "Kouadian\u00e9kro"
    ],
    "wof:name":"Kouadianikro",
    "wof:placetype":"locality"
},
  "geometry": {"coordinates":[-4.53979,6.77309],"type":"Point"}
}