{
  "type": "Feature",
  "properties": {
    "gn:admin1_code":"87",
    "gn:asciiname":"Korologo",
    "gn:country_code":"CI",
    "gn:dem":360,
    "gn:feature_class":"P",
    "gn:feature_code":"PPL",
    "gn:name":"Korologo",
    "gn:population":0,
    "gn:timezone":"Africa/Abidjan",
    "iso:country":"CI",
    "wof:name":"Korologo",
    "wof:placetype":"locality"
},
  "geometry": {"coordinates":[-5.79626,10.02659],"type":"Point"}
}