{
  "type": "Feature",
  "properties": {
    "gn:admin1_code":"94.0",
    "gn:asciiname":"Kokotile-Anvo",
    "gn:country_code":"CI",
    "gn:dem":62,
    "gn:feature_class":"P",
    "gn:feature_code":"PPL",
    "gn:name":"Kokotile-Anvo",
    "gn:population":0,
    "gn:timezone":"Africa/Abidjan",
    "iso:country":"CI",
    "wof:name":"Kokotile-Anvo",
    "wof:placetype":"locality"
},
  "geometry": {"coordinates":[-3.1154,5.38005],"type":"Point"}
}