{
  "type": "Feature",
  "properties": {
    "gn:admin1_code":"78",
    "gn:asciiname":"Zohoueleu",
    "gn:country_code":"CI",
    "gn:dem":281,
    "gn:feature_class":"P",
    "gn:feature_code":"PPL",
    "gn:name":"Zohou\u00e9leu",
    "gn:population":0,
    "gn:timezone":"Africa/Abidjan",
    "iso:country":"CI",
    "name:und_x_variant":[
        "Zohouoileu",
        "Zohou\u00e9l\u00e9",
        "Zohou\u00e9leu"
    ],
    "wof:name":"Zohoueleu",
    "wof:placetype":"locality"
},
  "geometry": {"coordinates":[-8.16835,7.05912],"type":"Point"}
}