{
  "type": "Feature",
  "properties": {
    "gn:admin1_code":"82.0",
    "gn:asciiname":"Souleymane",
    "gn:country_code":"CI",
    "gn:dem":74,
    "gn:feature_class":"P",
    "gn:feature_code":"PPL",
    "gn:name":"Souleymane",
    "gn:population":0,
    "gn:timezone":"Africa/Abidjan",
    "iso:country":"CI",
    "wof:name":"Souleymane",
    "wof:placetype":"locality"
},
  "geometry": {"coordinates":[-4.39635,5.90761],"type":"Point"}
}