{
  "type": "Feature",
  "properties": {
    "gn:admin1_code":"87",
    "gn:asciiname":"Kourou",
    "gn:country_code":"CI",
    "gn:dem":275,
    "gn:feature_class":"P",
    "gn:feature_code":"PPL",
    "gn:name":"Kourou",
    "gn:population":0,
    "gn:timezone":"Africa/Abidjan",
    "iso:country":"CI",
    "wof:name":"Kourou",
    "wof:placetype":"locality"
},
  "geometry": {"coordinates":[-4.33333,8.83333],"type":"Point"}
}