{
  "type": "Feature",
  "properties": {
    "gn:admin1_code":"82.0",
    "gn:asciiname":"Ahieremou",
    "gn:country_code":"CI",
    "gn:dem":93,
    "gn:feature_class":"P",
    "gn:feature_code":"PPL",
    "gn:name":"Ahi\u00e9r\u00e9mou",
    "gn:population":0,
    "gn:timezone":"Africa/Abidjan",
    "iso:country":"CI",
    "wof:name":"Ahieremou",
    "wof:placetype":"locality"
},
  "geometry": {"coordinates":[-4.93012,6.21777],"type":"Point"}
}