{
  "type": "Feature",
  "properties": {
    "gn:admin1_code":"93.0",
    "gn:asciiname":"Komoe Konan",
    "gn:country_code":"CI",
    "gn:dem":11,
    "gn:feature_class":"P",
    "gn:feature_code":"PPL",
    "gn:name":"Komo\u00e9 Konan",
    "gn:population":0,
    "gn:timezone":"Africa/Abidjan",
    "iso:country":"CI",
    "wof:name":"Komoe Konan",
    "wof:placetype":"locality"
},
  "geometry": {"coordinates":[-3.94324,5.44619],"type":"Point"}
}