{
  "type": "Feature",
  "properties": {
    "gn:admin1_code":"81.0",
    "gn:asciiname":"Findimanou",
    "gn:country_code":"CI",
    "gn:dem":191,
    "gn:feature_class":"P",
    "gn:feature_code":"PPL",
    "gn:name":"Findimanou",
    "gn:population":0,
    "gn:timezone":"Africa/Abidjan",
    "iso:country":"CI",
    "wof:name":"Findimanou",
    "wof:placetype":"locality"
},
  "geometry": {"coordinates":[-4.08298,6.83153],"type":"Point"}
}