{
  "type": "Feature",
  "properties": {
    "gn:admin1_code":"93.0",
    "gn:asciiname":"Ossohou",
    "gn:country_code":"CI",
    "gn:dem":55,
    "gn:feature_class":"P",
    "gn:feature_code":"PPL",
    "gn:name":"Ossohou",
    "gn:population":0,
    "gn:timezone":"Africa/Abidjan",
    "iso:country":"CI",
    "wof:name":"Ossohou",
    "wof:placetype":"locality"
},
  "geometry": {"coordinates":[-4.36174,5.57582],"type":"Point"}
}