{
  "type": "Feature",
  "properties": {
    "gn:admin1_code":"92",
    "gn:asciiname":"Tongobo",
    "gn:country_code":"CI",
    "gn:dem":185,
    "gn:feature_class":"P",
    "gn:feature_code":"PPL",
    "gn:name":"Tongobo",
    "gn:population":0,
    "gn:timezone":"Africa/Abidjan",
    "iso:country":"CI",
    "wof:name":"Tongobo",
    "wof:placetype":"locality"
},
  "geometry": {"coordinates":[-3.55,7.76667],"type":"Point"}
}