{
  "type": "Feature",
  "properties": {
    "gn:admin1_code":"97.0",
    "gn:asciiname":"Digoue",
    "gn:country_code":"CI",
    "gn:dem":258,
    "gn:feature_class":"P",
    "gn:feature_code":"PPL",
    "gn:name":"Digou\u00e9",
    "gn:population":0,
    "gn:timezone":"Africa/Abidjan",
    "iso:country":"CI",
    "wof:name":"Digoue",
    "wof:placetype":"locality"
},
  "geometry": {"coordinates":[-5.56128,8.13616],"type":"Point"}
}