{
  "type": "Feature",
  "properties": {
    "gn:admin1_code":"78.0",
    "gn:asciiname":"Beapleu",
    "gn:country_code":"CI",
    "gn:dem":296,
    "gn:feature_class":"P",
    "gn:feature_code":"PPL",
    "gn:name":"B\u00e9apleu",
    "gn:population":0,
    "gn:timezone":"Africa/Abidjan",
    "iso:country":"CI",
    "wof:name":"Beapleu",
    "wof:placetype":"locality"
},
  "geometry": {"coordinates":[-8.11886,7.04019],"type":"Point"}
}