{
  "type": "Feature",
  "properties": {
    "gn:admin1_code":"95.0",
    "gn:asciiname":"Bomenanda",
    "gn:country_code":"CI",
    "gn:dem":247,
    "gn:feature_class":"P",
    "gn:feature_code":"PPL",
    "gn:name":"Bom\u00e9nanda",
    "gn:population":0,
    "gn:timezone":"Africa/Abidjan",
    "iso:country":"CI",
    "wof:name":"Bomenanda",
    "wof:placetype":"locality"
},
  "geometry": {"coordinates":[-5.58329,6.23087],"type":"Point"}
}