{
  "type": "Feature",
  "properties": {
    "gn:admin1_code":"93.0",
    "gn:asciiname":"Koroukro",
    "gn:country_code":"CI",
    "gn:dem":57,
    "gn:feature_class":"P",
    "gn:feature_code":"PPL",
    "gn:name":"Koroukro",
    "gn:population":0,
    "gn:timezone":"Africa/Abidjan",
    "iso:country":"CI",
    "wof:name":"Koroukro",
    "wof:placetype":"locality"
},
  "geometry": {"coordinates":[-4.22669,5.39974],"type":"Point"}
}