{
  "type": "Feature",
  "properties": {
    "gn:admin1_code":"96",
    "gn:asciiname":"Sayeta",
    "gn:country_code":"CI",
    "gn:dem":282,
    "gn:feature_class":"P",
    "gn:feature_code":"PPL",
    "gn:name":"Say\u00e9ta",
    "gn:population":0,
    "gn:timezone":"Africa/Abidjan",
    "iso:country":"CI",
    "wof:name":"Sayeta",
    "wof:placetype":"locality"
},
  "geometry": {"coordinates":[-6.07189,6.77722],"type":"Point"}
}