{
  "type": "Feature",
  "properties": {
    "gn:admin1_code":"97",
    "gn:asciiname":"Yafe",
    "gn:country_code":"CI",
    "gn:dem":475,
    "gn:feature_class":"P",
    "gn:feature_code":"PPL",
    "gn:name":"Yaf\u00e9",
    "gn:population":0,
    "gn:timezone":"Africa/Abidjan",
    "iso:country":"CI",
    "wof:name":"Yafe",
    "wof:placetype":"locality"
},
  "geometry": {"coordinates":[-7.92217,8.05146],"type":"Point"}
}