{
  "type": "Feature",
  "properties": {
    "gn:admin1_code":"76.0",
    "gn:asciiname":"Bereto",
    "gn:country_code":"CI",
    "gn:dem":103,
    "gn:feature_class":"P",
    "gn:feature_code":"PPL",
    "gn:name":"B\u00e9r\u00e9to",
    "gn:population":0,
    "gn:timezone":"Africa/Abidjan",
    "iso:country":"CI",
    "wof:name":"Bereto",
    "wof:placetype":"locality"
},
  "geometry": {"coordinates":[-7.36508,5.33302],"type":"Point"}
}