{
  "type": "Feature",
  "properties": {
    "gn:admin1_code":"97",
    "gn:asciiname":"Mofredougou",
    "gn:country_code":"CI",
    "gn:dem":308,
    "gn:feature_class":"P",
    "gn:feature_code":"PPL",
    "gn:name":"Mofr\u00e9dougou",
    "gn:population":0,
    "gn:timezone":"Africa/Abidjan",
    "iso:country":"CI",
    "wof:name":"Mofredougou",
    "wof:placetype":"locality"
},
  "geometry": {"coordinates":[-5.88333,8.08333],"type":"Point"}
}