{
  "type": "Feature",
  "properties": {
    "gn:admin1_code":"95.0",
    "gn:asciiname":"Dueoa",
    "gn:country_code":"CI",
    "gn:dem":258,
    "gn:feature_class":"P",
    "gn:feature_code":"PPL",
    "gn:name":"Du\u00e9oa",
    "gn:population":0,
    "gn:timezone":"Africa/Abidjan",
    "iso:country":"CI",
    "name:und_x_variant":[
        "Du\u00e9oa",
        "Du\u00e9hoa"
    ],
    "wof:name":"Dueoa",
    "wof:placetype":"locality"
},
  "geometry": {"coordinates":[-6.33978,6.25753],"type":"Point"}
}