{
  "type": "Feature",
  "properties": {
    "gn:admin1_code":"94.0",
    "gn:asciiname":"Mia",
    "gn:country_code":"CI",
    "gn:dem":5,
    "gn:feature_class":"P",
    "gn:feature_code":"PPL",
    "gn:name":"Mia",
    "gn:population":0,
    "gn:timezone":"Africa/Abidjan",
    "iso:country":"CI",
    "name:ceb_x_preferred":[
        "Mia"
    ],
    "name:deu_x_preferred":[
        "Mia"
    ],
    "name:nld_x_preferred":[
        "Mia"
    ],
    "name:nor_x_preferred":[
        "Mia"
    ],
    "name:por_x_preferred":[
        "Mia"
    ],
    "name:tur_x_preferred":[
        "MIA"
    ],
    "wof:name":"Mia",
    "wof:placetype":"locality"
},
  "geometry": {"coordinates":[-3.75363,5.20961],"type":"Point"}
}