{
  "type": "Feature",
  "properties": {
    "gn:admin1_code":"96",
    "gn:asciiname":"Zagbezon",
    "gn:country_code":"CI",
    "gn:dem":205,
    "gn:feature_class":"P",
    "gn:feature_code":"PPL",
    "gn:name":"Zagb\u00e9zon",
    "gn:population":0,
    "gn:timezone":"Africa/Abidjan",
    "iso:country":"CI",
    "wof:name":"Zagbezon",
    "wof:placetype":"locality"
},
  "geometry": {"coordinates":[-6.97136,6.68525],"type":"Point"}
}