{
  "type": "Feature",
  "properties": {
    "gn:admin1_code":"90",
    "gn:asciiname":"Tikouakro",
    "gn:country_code":"CI",
    "gn:dem":234,
    "gn:feature_class":"P",
    "gn:feature_code":"PPL",
    "gn:name":"Tikouakro",
    "gn:population":0,
    "gn:timezone":"Africa/Abidjan",
    "iso:country":"CI",
    "name:und_x_variant":[
        "Tikourikro"
    ],
    "wof:name":"Tikouakro",
    "wof:placetype":"locality"
},
  "geometry": {"coordinates":[-4.51382,7.8294],"type":"Point"}
}