{
  "type": "Feature",
  "properties": {
    "gn:admin1_code":"78.0",
    "gn:asciiname":"Kpobli",
    "gn:country_code":"CI",
    "gn:dem":297,
    "gn:feature_class":"P",
    "gn:feature_code":"PPL",
    "gn:name":"Kpobli",
    "gn:population":0,
    "gn:timezone":"Africa/Abidjan",
    "iso:country":"CI",
    "wof:name":"Kpobli",
    "wof:placetype":"locality"
},
  "geometry": {"coordinates":[-8.28109,6.54735],"type":"Point"}
}