{
  "type": "Feature",
  "properties": {
    "gn:admin1_code":"81.0",
    "gn:asciiname":"Fitalssou",
    "gn:country_code":"CI",
    "gn:dem":210,
    "gn:feature_class":"P",
    "gn:feature_code":"PPL",
    "gn:name":"Fitalssou",
    "gn:population":0,
    "gn:timezone":"Africa/Abidjan",
    "iso:country":"CI",
    "name:und_x_variant":[
        "Fitessou"
    ],
    "wof:name":"Fitalssou",
    "wof:placetype":"locality"
},
  "geometry": {"coordinates":[-4.88975,7.47834],"type":"Point"}
}