{
  "type": "Feature",
  "properties": {
    "gn:admin1_code":"96.0",
    "gn:admin2_code":"11153166.0",
    "gn:admin3_code":"2280044.0",
    "gn:admin4_code":"2280042.0",
    "gn:asciiname":"Akanzakro",
    "gn:country_code":"CI",
    "gn:dem":261,
    "gn:feature_class":"P",
    "gn:feature_code":"PPL",
    "gn:name":"Akanzakro",
    "gn:population":0,
    "gn:timezone":"Africa/Abidjan",
    "iso:country":"CI",
    "wof:name":"Akanzakro",
    "wof:placetype":"locality"
},
  "geometry": {"coordinates":[-6.48,7.33],"type":"Point"}
}