{
  "type": "Feature",
  "properties": {
    "gn:admin1_code":"78.0",
    "gn:asciiname":"Beablo",
    "gn:country_code":"CI",
    "gn:dem":213,
    "gn:feature_class":"P",
    "gn:feature_code":"PPL",
    "gn:name":"B\u00e9ablo",
    "gn:population":0,
    "gn:timezone":"Africa/Abidjan",
    "iso:country":"CI",
    "wof:name":"Beablo",
    "wof:placetype":"locality"
},
  "geometry": {"coordinates":[-7.33397,6.37887],"type":"Point"}
}