{
  "type": "Feature",
  "properties": {
    "gn:admin1_code":"78.0",
    "gn:asciiname":"Digouale",
    "gn:country_code":"CI",
    "gn:dem":371,
    "gn:feature_class":"P",
    "gn:feature_code":"PPL",
    "gn:name":"Digoual\u00e9",
    "gn:population":0,
    "gn:timezone":"Africa/Abidjan",
    "iso:country":"CI",
    "name:und_x_variant":[
        "Lougbale",
        "Digoual\u00e9"
    ],
    "wof:name":"Digouale",
    "wof:placetype":"locality"
},
  "geometry": {"coordinates":[-7.80712,7.52493],"type":"Point"}
}