{
  "type": "Feature",
  "properties": {
    "gn:admin1_code":"93.0",
    "gn:asciiname":"Kouadjo",
    "gn:country_code":"CI",
    "gn:dem":19,
    "gn:feature_class":"P",
    "gn:feature_code":"PPL",
    "gn:name":"Kouadjo",
    "gn:population":0,
    "gn:timezone":"Africa/Abidjan",
    "iso:country":"CI",
    "wof:name":"Kouadjo",
    "wof:placetype":"locality"
},
  "geometry": {"coordinates":[-3.89849,5.41625],"type":"Point"}
}