{
  "type": "Feature",
  "properties": {
    "gn:admin1_code":"94.0",
    "gn:asciiname":"Bleouhokro",
    "gn:country_code":"CI",
    "gn:dem":77,
    "gn:feature_class":"P",
    "gn:feature_code":"PPL",
    "gn:name":"Bl\u00e9ouhokro",
    "gn:population":0,
    "gn:timezone":"Africa/Abidjan",
    "iso:country":"CI",
    "wof:name":"Bleouhokro",
    "wof:placetype":"locality"
},
  "geometry": {"coordinates":[-3.08944,5.36889],"type":"Point"}
}