{
  "type": "Feature",
  "properties": {
    "gn:admin1_code":"78.0",
    "gn:asciiname":"Allangba Kouadiokro",
    "gn:country_code":"CI",
    "gn:dem":177,
    "gn:feature_class":"P",
    "gn:feature_code":"PPL",
    "gn:name":"Allangba Kouadiokro",
    "gn:population":0,
    "gn:timezone":"Africa/Abidjan",
    "iso:country":"CI",
    "wof:name":"Allangba Kouadiokro",
    "wof:placetype":"locality"
},
  "geometry": {"coordinates":[-7.55006,5.97885],"type":"Point"}
}