{
  "type": "Feature",
  "properties": {
    "gn:admin1_code":"87",
    "gn:asciiname":"Samorokaha",
    "gn:country_code":"CI",
    "gn:dem":316,
    "gn:feature_class":"P",
    "gn:feature_code":"PPL",
    "gn:name":"Samorokaha",
    "gn:population":0,
    "gn:timezone":"Africa/Abidjan",
    "iso:country":"CI",
    "wof:name":"Samorokaha",
    "wof:placetype":"locality"
},
  "geometry": {"coordinates":[-5.5666,9.18967],"type":"Point"}
}