{
  "type": "Feature",
  "properties": {
    "gn:admin1_code":"97",
    "gn:asciiname":"Tyemasoba",
    "gn:country_code":"CI",
    "gn:dem":326,
    "gn:feature_class":"P",
    "gn:feature_code":"PPL",
    "gn:name":"Ty\u00e9masoba",
    "gn:population":0,
    "gn:timezone":"Africa/Abidjan",
    "iso:country":"CI",
    "name:und_x_variant":[
        "Ti\u00e9masoba",
        "Ti\u00e9massoba",
        "Ty\u00e9masoba"
    ],
    "wof:name":"Tyemasoba",
    "wof:placetype":"locality"
},
  "geometry": {"coordinates":[-6.45253,7.81532],"type":"Point"}
}