{
  "type": "Feature",
  "properties": {
    "gn:admin1_code":"94",
    "gn:asciiname":"Tankouakouro",
    "gn:country_code":"CI",
    "gn:dem":208,
    "gn:feature_class":"P",
    "gn:feature_code":"PPL",
    "gn:name":"Tankouakouro",
    "gn:population":0,
    "gn:timezone":"Africa/Abidjan",
    "iso:country":"CI",
    "wof:name":"Tankouakouro",
    "wof:placetype":"locality"
},
  "geometry": {"coordinates":[-3.33083,7.24111],"type":"Point"}
}