{
  "type": "Feature",
  "properties": {
    "gn:admin1_code":"78.0",
    "gn:asciiname":"Gloleu",
    "gn:country_code":"CI",
    "gn:dem":318,
    "gn:feature_class":"P",
    "gn:feature_code":"PPL",
    "gn:name":"Gloleu",
    "gn:population":0,
    "gn:timezone":"Africa/Abidjan",
    "iso:country":"CI",
    "wof:name":"Gloleu",
    "wof:placetype":"locality"
},
  "geometry": {"coordinates":[-7.76901,7.12901],"type":"Point"}
}