{
  "type": "Feature",
  "properties": {
    "gn:admin1_code":"92",
    "gn:asciiname":"Tangamourou",
    "gn:country_code":"CI",
    "gn:dem":248,
    "gn:feature_class":"P",
    "gn:feature_code":"PPL",
    "gn:name":"Tangamourou",
    "gn:population":0,
    "gn:timezone":"Africa/Abidjan",
    "iso:country":"CI",
    "wof:name":"Tangamourou",
    "wof:placetype":"locality"
},
  "geometry": {"coordinates":[-3.21656,7.83337],"type":"Point"}
}