{
  "type": "Feature",
  "properties": {
    "gn:admin1_code":"78",
    "gn:asciiname":"Tiekpoloupleu",
    "gn:country_code":"CI",
    "gn:dem":345,
    "gn:feature_class":"P",
    "gn:feature_code":"PPL",
    "gn:name":"Ti\u00e8kpoloupleu",
    "gn:population":0,
    "gn:timezone":"Africa/Abidjan",
    "iso:country":"CI",
    "name:und_x_variant":[
        "Ti\u00e8kpoloupleu",
        "Teapoulopleu"
    ],
    "wof:name":"Tiekpoloupleu",
    "wof:placetype":"locality"
},
  "geometry": {"coordinates":[-8.16404,7.23555],"type":"Point"}
}