{
  "type": "Feature",
  "properties": {
    "gn:admin1_code":"90",
    "gn:asciiname":"Kouebo",
    "gn:country_code":"CI",
    "gn:dem":272,
    "gn:feature_class":"P",
    "gn:feature_code":"PPL",
    "gn:name":"Kou\u00e9bo",
    "gn:population":0,
    "gn:timezone":"Africa/Abidjan",
    "iso:country":"CI",
    "wof:name":"Kouebo",
    "wof:placetype":"locality"
},
  "geometry": {"coordinates":[-5.38449,7.66912],"type":"Point"}
}