{
  "type": "Feature",
  "properties": {
    "gn:admin1_code":"90",
    "gn:asciiname":"Mbabo Farifoue",
    "gn:country_code":"CI",
    "gn:dem":256,
    "gn:feature_class":"P",
    "gn:feature_code":"PPL",
    "gn:name":"Mbabo Farifou\u00e9",
    "gn:population":0,
    "gn:timezone":"Africa/Abidjan",
    "iso:country":"CI",
    "name:und_x_variant":[
        "Mbabo Farifou\u00e9",
        "Mbabo"
    ],
    "wof:name":"Mbabo Farifoue",
    "wof:placetype":"locality"
},
  "geometry": {"coordinates":[-5.52017,7.59839],"type":"Point"}
}