{
  "type": "Feature",
  "properties": {
    "gn:admin1_code":"76",
    "gn:asciiname":"Seribouo",
    "gn:country_code":"CI",
    "gn:dem":226,
    "gn:feature_class":"P",
    "gn:feature_code":"PPL",
    "gn:name":"S\u00e9ribouo",
    "gn:population":0,
    "gn:timezone":"Africa/Abidjan",
    "iso:country":"CI",
    "wof:name":"Seribouo",
    "wof:placetype":"locality"
},
  "geometry": {"coordinates":[-6.4506,6.13679],"type":"Point"}
}