{
  "type": "Feature",
  "properties": {
    "gn:admin1_code":"92.0",
    "gn:asciiname":"Dihinebo",
    "gn:country_code":"CI",
    "gn:dem":150,
    "gn:feature_class":"P",
    "gn:feature_code":"PPL",
    "gn:name":"Dihin\u00e9bo",
    "gn:population":0,
    "gn:timezone":"Africa/Abidjan",
    "iso:country":"CI",
    "name:und_x_variant":[
        "Diin\u00e9bo",
        "Dihin\u00e9bo"
    ],
    "wof:name":"Dihinebo",
    "wof:placetype":"locality"
},
  "geometry": {"coordinates":[-3.3642,7.35476],"type":"Point"}
}