{
  "type": "Feature",
  "properties": {
    "gn:admin1_code":"97.0",
    "gn:asciiname":"Bengbwaso",
    "gn:country_code":"CI",
    "gn:dem":481,
    "gn:feature_class":"P",
    "gn:feature_code":"PPL",
    "gn:name":"Bengbwaso",
    "gn:population":0,
    "gn:timezone":"Africa/Abidjan",
    "iso:country":"CI",
    "wof:name":"Bengbwaso",
    "wof:placetype":"locality"
},
  "geometry": {"coordinates":[-7.78403,8.0455],"type":"Point"}
}