{
  "type": "Feature",
  "properties": {
    "gn:admin1_code":"87.0",
    "gn:asciiname":"Badon",
    "gn:country_code":"CI",
    "gn:dem":373,
    "gn:feature_class":"P",
    "gn:feature_code":"PPL",
    "gn:name":"Badon",
    "gn:population":0,
    "gn:timezone":"Africa/Abidjan",
    "iso:country":"CI",
    "wof:name":"Badon",
    "wof:placetype":"locality"
},
  "geometry": {"coordinates":[-6.07958,9.3642],"type":"Point"}
}