{
  "type": "Feature",
  "properties": {
    "gn:admin1_code":"95.0",
    "gn:asciiname":"Gozobia Bahiri",
    "gn:country_code":"CI",
    "gn:dem":220,
    "gn:feature_class":"P",
    "gn:feature_code":"PPL",
    "gn:name":"Gozobia Bahiri",
    "gn:population":0,
    "gn:timezone":"Africa/Abidjan",
    "iso:country":"CI",
    "name:und_x_variant":[
        "Gozabia-Bahiri"
    ],
    "wof:name":"Gozobia Bahiri",
    "wof:placetype":"locality"
},
  "geometry": {"coordinates":[-5.88587,6.0969],"type":"Point"}
}