{
  "type": "Feature",
  "properties": {
    "gn:admin1_code":"95",
    "gn:asciiname":"Tieko",
    "gn:country_code":"CI",
    "gn:dem":166,
    "gn:feature_class":"P",
    "gn:feature_code":"PPL",
    "gn:name":"Ti\u00e9ko",
    "gn:population":0,
    "gn:timezone":"Africa/Abidjan",
    "iso:country":"CI",
    "wof:name":"Tieko",
    "wof:placetype":"locality"
},
  "geometry": {"coordinates":[-5.41988,5.96004],"type":"Point"}
}