{
  "type": "Feature",
  "properties": {
    "gn:admin1_code":"95.0",
    "gn:asciiname":"Beheri",
    "gn:country_code":"CI",
    "gn:dem":115,
    "gn:feature_class":"P",
    "gn:feature_code":"PPL",
    "gn:name":"Beh\u00e9ri",
    "gn:population":0,
    "gn:timezone":"Africa/Abidjan",
    "iso:country":"CI",
    "name:und_x_variant":[
        "B\u00e9n\u00e9ri",
        "Beh\u00e9ri"
    ],
    "wof:name":"Beheri",
    "wof:placetype":"locality"
},
  "geometry": {"coordinates":[-5.18985,5.87986],"type":"Point"}
}