{
  "type": "Feature",
  "properties": {
    "gn:admin1_code":"78.0",
    "gn:asciiname":"Gouetimba",
    "gn:country_code":"CI",
    "gn:dem":383,
    "gn:feature_class":"P",
    "gn:feature_code":"PPL",
    "gn:name":"Gou\u00e9timba",
    "gn:population":0,
    "gn:timezone":"Africa/Abidjan",
    "iso:country":"CI",
    "name:und_x_variant":[
        "Gouatimba",
        "Gou\u00e9timba"
    ],
    "wof:name":"Gouetimba",
    "wof:placetype":"locality"
},
  "geometry": {"coordinates":[-7.46052,7.4999],"type":"Point"}
}