{
  "type": "Feature",
  "properties": {
    "gn:admin1_code":"92",
    "gn:asciiname":"Siraodi",
    "gn:country_code":"CI",
    "gn:dem":330,
    "gn:feature_class":"P",
    "gn:feature_code":"PPL",
    "gn:name":"Siraodi",
    "gn:population":0,
    "gn:timezone":"Africa/Abidjan",
    "iso:country":"CI",
    "wof:name":"Siraodi",
    "wof:placetype":"locality"
},
  "geometry": {"coordinates":[-3.06471,8.88491],"type":"Point"}
}