{
  "type": "Feature",
  "properties": {
    "gn:admin1_code":"81",
    "gn:asciiname":"Komona",
    "gn:country_code":"CI",
    "gn:dem":254,
    "gn:feature_class":"P",
    "gn:feature_code":"PPL",
    "gn:name":"Komona",
    "gn:population":0,
    "gn:timezone":"Africa/Abidjan",
    "iso:country":"CI",
    "name:ceb_x_preferred":[
        "Komona"
    ],
    "name:fra_x_preferred":[
        "Komona"
    ],
    "name:swe_x_preferred":[
        "Komona"
    ],
    "wof:name":"Komona",
    "wof:placetype":"locality"
},
  "geometry": {"coordinates":[-3.91667,7.65],"type":"Point"}
}