{
  "type": "Feature",
  "properties": {
    "gn:admin1_code":"90.0",
    "gn:asciiname":"Dindiodougou",
    "gn:country_code":"CI",
    "gn:dem":313,
    "gn:feature_class":"P",
    "gn:feature_code":"PPL",
    "gn:name":"Dindiodougou",
    "gn:population":0,
    "gn:timezone":"Africa/Abidjan",
    "iso:country":"CI",
    "wof:name":"Dindiodougou",
    "wof:placetype":"locality"
},
  "geometry": {"coordinates":[-4.48333,8.46667],"type":"Point"}
}