{
  "type": "Feature",
  "properties": {
    "gn:admin1_code":"0.0",
    "gn:asciiname":"Kekrenou",
    "gn:country_code":"CI",
    "gn:dem":201,
    "gn:feature_class":"P",
    "gn:feature_code":"PPL",
    "gn:name":"K\u00e9kr\u00e9nou",
    "gn:population":0,
    "gn:timezone":"Africa/Abidjan",
    "iso:country":"CI",
    "wof:name":"Kekrenou",
    "wof:placetype":"locality"
},
  "geometry": {"coordinates":[-5.70806,7.44361],"type":"Point"}
}