{
  "type": "Feature",
  "properties": {
    "gn:admin1_code":"92",
    "gn:asciiname":"Nonpele",
    "gn:country_code":"CI",
    "gn:dem":360,
    "gn:feature_class":"P",
    "gn:feature_code":"PPL",
    "gn:name":"Nonp\u00e9l\u00e9",
    "gn:population":0,
    "gn:timezone":"Africa/Abidjan",
    "iso:country":"CI",
    "wof:name":"Nonpele",
    "wof:placetype":"locality"
},
  "geometry": {"coordinates":[-3.41667,9.66667],"type":"Point"}
}