{
  "type": "Feature",
  "properties": {
    "gn:admin1_code":"94",
    "gn:asciiname":"Kouakro",
    "gn:country_code":"CI",
    "gn:dem":50,
    "gn:feature_class":"P",
    "gn:feature_code":"PPL",
    "gn:name":"Kouakro",
    "gn:population":0,
    "gn:timezone":"Africa/Abidjan",
    "iso:country":"CI",
    "name:fra_x_preferred":[
        "Kouakro"
    ],
    "name:ita_x_preferred":[
        "Kouakro"
    ],
    "name:msa_x_preferred":[
        "Kouakro"
    ],
    "wof:name":"Kouakro",
    "wof:placetype":"locality"
},
  "geometry": {"coordinates":[-2.90642,5.444],"type":"Point"}
}