{
  "type": "Feature",
  "properties": {
    "gn:admin1_code":"87",
    "gn:asciiname":"Niangbala",
    "gn:country_code":"CI",
    "gn:dem":326,
    "gn:feature_class":"P",
    "gn:feature_code":"PPL",
    "gn:name":"Niangbala",
    "gn:population":0,
    "gn:timezone":"Africa/Abidjan",
    "iso:country":"CI",
    "wof:name":"Niangbala",
    "wof:placetype":"locality"
},
  "geometry": {"coordinates":[-4.67918,9.31479],"type":"Point"}
}