{
  "type": "Feature",
  "properties": {
    "gn:admin1_code":"76.0",
    "gn:asciiname":"Bairo",
    "gn:country_code":"CI",
    "gn:dem":34,
    "gn:feature_class":"P",
    "gn:feature_code":"PPL",
    "gn:name":"Bairo",
    "gn:population":0,
    "gn:timezone":"Africa/Abidjan",
    "iso:country":"CI",
    "wof:name":"Bairo",
    "wof:placetype":"locality"
},
  "geometry": {"coordinates":[-7.38248,4.58671],"type":"Point"}
}