{
  "type": "Feature",
  "properties": {
    "gn:admin1_code":"76.0",
    "gn:asciiname":"Bairo",
    "gn:country_code":"CI",
    "gn:dem":34,
    "gn:feature_class":"P",
    "gn:feature_code":"PPL",
    "gn:name":"Bairo",
    "gn:population":0,
    "gn:timezone":"Africa/Abidjan",
    "iso:country":"CI",
    "name:azb_x_preferred":[
        "\u0628\u0627\u06cc\u0631\u0648"
    ],
    "name:bar_x_preferred":[
        "Bairo"
    ],
    "name:bel_x_preferred":[
        "\u0411\u0430\u0439\u0440\u0430"
    ],
    "name:bul_x_preferred":[
        "\u0411\u0430\u0439\u0440\u043e"
    ],
    "name:ceb_x_preferred":[
        "Bairo"
    ],
    "name:deu_x_preferred":[
        "Bairo"
    ],
    "name:epo_x_preferred":[
        "Bairo"
    ],
    "name:eus_x_preferred":[
        "Bairo"
    ],
    "name:fas_x_preferred":[
        "\u0628\u0627\u06cc\u0631\u0648"
    ],
    "name:fra_x_preferred":[
        "Bairo"
    ],
    "name:hun_x_preferred":[
        "Bairo"
    ],
    "name:hye_x_preferred":[
        "\u0532\u0561\u0575\u0580\u0578"
    ],
    "name:ind_x_preferred":[
        "Bairo"
    ],
    "name:ita_x_preferred":[
        "Bairo"
    ],
    "name:jpn_x_preferred":[
        "\u30d0\u30fc\u30a4\u30ed"
    ],
    "name:kaz_x_preferred":[
        "\u0411\u0430\u0439\u0440\u043e"
    ],
    "name:lat_x_preferred":[
        "Barium"
    ],
    "name:lmo_x_preferred":[
        "Bairo"
    ],
    "name:msa_x_preferred":[
        "Bairo"
    ],
    "name:nap_x_preferred":[
        "Bairo"
    ],
    "name:nld_x_preferred":[
        "Bairo"
    ],
    "name:pms_x_preferred":[
        "Ber"
    ],
    "name:pol_x_preferred":[
        "Bairo"
    ],
    "name:por_x_preferred":[
        "Bairo"
    ],
    "name:ron_x_preferred":[
        "Bairo"
    ],
    "name:rus_x_preferred":[
        "\u0411\u0430\u0439\u0440\u043e"
    ],
    "name:scn_x_preferred":[
        "Bairo"
    ],
    "name:sco_x_preferred":[
        "Bairo"
    ],
    "name:spa_x_preferred":[
        "Bairo"
    ],
    "name:srp_x_preferred":[
        "\u0411\u0430\u0458\u0440\u043e"
    ],
    "name:swe_x_preferred":[
        "Bairo"
    ],
    "name:tgl_x_preferred":[
        "Bairo"
    ],
    "name:ukr_x_preferred":[
        "\u0411\u0430\u0457\u0440\u043e"
    ],
    "name:uzb_x_preferred":[
        "Bairo"
    ],
    "name:vie_x_preferred":[
        "Bairo"
    ],
    "name:vol_x_preferred":[
        "Bairo"
    ],
    "name:war_x_preferred":[
        "Bairo"
    ],
    "name:zho_x_preferred":[
        "\u5df4\u4f0a\u7f57"
    ],
    "wof:name":"Bairo",
    "wof:placetype":"locality"
},
  "geometry": {"coordinates":[-7.38248,4.58671],"type":"Point"}
}