{
  "type": "Feature",
  "properties": {
    "gn:admin1_code":"87.0",
    "gn:asciiname":"Fandiovogo",
    "gn:country_code":"CI",
    "gn:dem":307,
    "gn:feature_class":"P",
    "gn:feature_code":"PPL",
    "gn:name":"Fandiovogo",
    "gn:population":0,
    "gn:timezone":"Africa/Abidjan",
    "iso:country":"CI",
    "wof:name":"Fandiovogo",
    "wof:placetype":"locality"
},
  "geometry": {"coordinates":[-5.36667,9.63333],"type":"Point"}
}