{
  "type": "Feature",
  "properties": {
    "gn:admin1_code":"78.0",
    "gn:asciiname":"Gopoupleu",
    "gn:country_code":"CI",
    "gn:dem":376,
    "gn:feature_class":"P",
    "gn:feature_code":"PPL",
    "gn:name":"Gopoupleu",
    "gn:population":0,
    "gn:timezone":"Africa/Abidjan",
    "iso:country":"CI",
    "name:fra_x_preferred":[
        "Gopoupleu"
    ],
    "name:msa_x_preferred":[
        "Gopoupleu"
    ],
    "wof:name":"Gopoupleu",
    "wof:placetype":"locality"
},
  "geometry": {"coordinates":[-8.28532,7.43483],"type":"Point"}
}