{
  "type": "Feature",
  "properties": {
    "gn:admin1_code":"92",
    "gn:asciiname":"Vigoli",
    "gn:country_code":"CI",
    "gn:dem":338,
    "gn:feature_class":"P",
    "gn:feature_code":"PPL",
    "gn:name":"Vigoli",
    "gn:population":0,
    "gn:timezone":"Africa/Abidjan",
    "iso:country":"CI",
    "wof:name":"Vigoli",
    "wof:placetype":"locality"
},
  "geometry": {"coordinates":[-3.1495,9.35452],"type":"Point"}
}