{
  "type": "Feature",
  "properties": {
    "gn:admin1_code":"87.0",
    "gn:asciiname":"Gbolokaha",
    "gn:country_code":"CI",
    "gn:dem":365,
    "gn:feature_class":"P",
    "gn:feature_code":"PPL",
    "gn:name":"Gbolokaha",
    "gn:population":0,
    "gn:timezone":"Africa/Abidjan",
    "iso:country":"CI",
    "wof:name":"Gbolokaha",
    "wof:placetype":"locality"
},
  "geometry": {"coordinates":[-5.68412,9.37831],"type":"Point"}
}