{
  "type": "Feature",
  "properties": {
    "gn:admin1_code":"82.0",
    "gn:asciiname":"Diby Kottou",
    "gn:country_code":"CI",
    "gn:dem":115,
    "gn:feature_class":"P",
    "gn:feature_code":"PPL",
    "gn:name":"Diby Kottou",
    "gn:population":0,
    "gn:timezone":"Africa/Abidjan",
    "iso:country":"CI",
    "wof:name":"Diby Kottou",
    "wof:placetype":"locality"
},
  "geometry": {"coordinates":[-4.47463,5.70074],"type":"Point"}
}