{
  "type": "Feature",
  "properties": {
    "gn:admin1_code":"92.0",
    "gn:asciiname":"Afouanvam",
    "gn:country_code":"CI",
    "gn:dem":287,
    "gn:feature_class":"P",
    "gn:feature_code":"PPL",
    "gn:name":"Afouanvam",
    "gn:population":0,
    "gn:timezone":"Africa/Abidjan",
    "iso:country":"CI",
    "wof:name":"Afouanvam",
    "wof:placetype":"locality"
},
  "geometry": {"coordinates":[-2.89805,7.99571],"type":"Point"}
}