{
  "type": "Feature",
  "properties": {
    "gn:admin1_code":"82.0",
    "gn:asciiname":"Koli Yapo",
    "gn:country_code":"CI",
    "gn:dem":93,
    "gn:feature_class":"P",
    "gn:feature_code":"PPL",
    "gn:name":"Koli Yapo",
    "gn:population":0,
    "gn:timezone":"Africa/Abidjan",
    "iso:country":"CI",
    "wof:name":"Koli Yapo",
    "wof:placetype":"locality"
},
  "geometry": {"coordinates":[-3.73154,5.98405],"type":"Point"}
}