{
  "type": "Feature",
  "properties": {
    "gn:admin1_code":"95",
    "gn:asciiname":"Niali Gribouo",
    "gn:country_code":"CI",
    "gn:dem":247,
    "gn:feature_class":"P",
    "gn:feature_code":"PPL",
    "gn:name":"Niali Gribouo",
    "gn:population":0,
    "gn:timezone":"Africa/Abidjan",
    "iso:country":"CI",
    "wof:name":"Niali Gribouo",
    "wof:placetype":"locality"
},
  "geometry": {"coordinates":[-5.91417,5.88806],"type":"Point"}
}