{
  "type": "Feature",
  "properties": {
    "gn:admin1_code":"78",
    "gn:asciiname":"Oulaikpabli",
    "gn:country_code":"CI",
    "gn:dem":286,
    "gn:feature_class":"P",
    "gn:feature_code":"PPL",
    "gn:name":"Oulaikpabli",
    "gn:population":0,
    "gn:timezone":"Africa/Abidjan",
    "iso:country":"CI",
    "name:und_x_variant":[
        "Oulahipably",
        "Oulaikpabli"
    ],
    "wof:name":"Oulaikpabli",
    "wof:placetype":"locality"
},
  "geometry": {"coordinates":[-8.10527,6.58499],"type":"Point"}
}