{
  "type": "Feature",
  "properties": {
    "gn:admin1_code":"82.0",
    "gn:asciiname":"N'Doumikro",
    "gn:country_code":"CI",
    "gn:dem":79,
    "gn:feature_class":"P",
    "gn:feature_code":"PPL",
    "gn:name":"N\u2019Doumikro",
    "gn:population":0,
    "gn:timezone":"Africa/Abidjan",
    "iso:country":"CI",
    "name:und_x_variant":[
        "N\u2019Doumikro",
        "Anomikro"
    ],
    "wof:name":"N'Doumikro",
    "wof:placetype":"locality"
},
  "geometry": {"coordinates":[-4.50195,5.46814],"type":"Point"}
}