{
  "type": "Feature",
  "properties": {
    "gn:admin1_code":"92",
    "gn:asciiname":"Yaga",
    "gn:country_code":"CI",
    "gn:dem":253,
    "gn:feature_class":"P",
    "gn:feature_code":"PPL",
    "gn:name":"Yaga",
    "gn:population":0,
    "gn:timezone":"Africa/Abidjan",
    "iso:country":"CI",
    "name:ceb_x_preferred":[
        "Yaga"
    ],
    "name:fra_x_preferred":[
        "Yaga"
    ],
    "name:swe_x_preferred":[
        "Yaga"
    ],
    "wof:name":"Yaga",
    "wof:placetype":"locality"
},
  "geometry": {"coordinates":[-3.44514,8.54499],"type":"Point"}
}