{
  "type": "Feature",
  "properties": {
    "gn:admin1_code":"97",
    "gn:asciiname":"Kofina-Sokourala",
    "gn:country_code":"CI",
    "gn:dem":516,
    "gn:feature_class":"P",
    "gn:feature_code":"PPL",
    "gn:name":"Kofina-Sokourala",
    "gn:population":0,
    "gn:timezone":"Africa/Abidjan",
    "iso:country":"CI",
    "wof:name":"Kofina-Sokourala",
    "wof:placetype":"locality"
},
  "geometry": {"coordinates":[-7.87762,8.84636],"type":"Point"}
}