{
  "type": "Feature",
  "properties": {
    "gn:admin1_code":"95",
    "gn:asciiname":"Ourepa",
    "gn:country_code":"CI",
    "gn:dem":228,
    "gn:feature_class":"P",
    "gn:feature_code":"PPL",
    "gn:name":"Our\u00e9pa",
    "gn:population":0,
    "gn:timezone":"Africa/Abidjan",
    "iso:country":"CI",
    "wof:name":"Ourepa",
    "wof:placetype":"locality"
},
  "geometry": {"coordinates":[-5.83769,6.15793],"type":"Point"}
}