{
  "type": "Feature",
  "properties": {
    "gn:admin1_code":"81",
    "gn:asciiname":"Koffi Amoukro",
    "gn:country_code":"CI",
    "gn:dem":230,
    "gn:feature_class":"P",
    "gn:feature_code":"PPL",
    "gn:name":"Koffi Amoukro",
    "gn:population":0,
    "gn:timezone":"Africa/Abidjan",
    "iso:country":"CI",
    "name:und_x_variant":[
        "Kofi-Amoukro",
        "Koffi Amoukro"
    ],
    "wof:name":"Koffi Amoukro",
    "wof:placetype":"locality"
},
  "geometry": {"coordinates":[-3.96111,7.46751],"type":"Point"}
}