{
  "type": "Feature",
  "properties": {
    "gn:admin1_code":"81.0",
    "gn:asciiname":"Ediakro",
    "gn:country_code":"CI",
    "gn:dem":88,
    "gn:feature_class":"P",
    "gn:feature_code":"PPL",
    "gn:name":"Ediakro",
    "gn:population":0,
    "gn:timezone":"Africa/Abidjan",
    "iso:country":"CI",
    "wof:name":"Ediakro",
    "wof:placetype":"locality"
},
  "geometry": {"coordinates":[-4.80802,6.65163],"type":"Point"}
}