{
  "type": "Feature",
  "properties": {
    "gn:admin1_code":"96.0",
    "gn:asciiname":"Badiefla",
    "gn:country_code":"CI",
    "gn:dem":261,
    "gn:feature_class":"P",
    "gn:feature_code":"PPL",
    "gn:name":"Badi\u00e9fla",
    "gn:population":0,
    "gn:timezone":"Africa/Abidjan",
    "iso:country":"CI",
    "wof:name":"Badiefla",
    "wof:placetype":"locality"
},
  "geometry": {"coordinates":[-5.96015,7.59432],"type":"Point"}
}