{
  "type": "Feature",
  "properties": {
    "gn:admin1_code":"90.0",
    "gn:asciiname":"Bouloukro",
    "gn:country_code":"CI",
    "gn:dem":296,
    "gn:feature_class":"P",
    "gn:feature_code":"PPL",
    "gn:name":"Bouloukro",
    "gn:population":0,
    "gn:timezone":"Africa/Abidjan",
    "iso:country":"CI",
    "wof:name":"Bouloukro",
    "wof:placetype":"locality"
},
  "geometry": {"coordinates":[-5.34638,7.65678],"type":"Point"}
}