{
  "type": "Feature",
  "properties": {
    "gn:admin1_code":"82.0",
    "gn:asciiname":"Kapa Ale",
    "gn:country_code":"CI",
    "gn:dem":93,
    "gn:feature_class":"P",
    "gn:feature_code":"PPL",
    "gn:name":"Kapa Al\u00e9",
    "gn:population":0,
    "gn:timezone":"Africa/Abidjan",
    "iso:country":"CI",
    "wof:name":"Kapa Ale",
    "wof:placetype":"locality"
},
  "geometry": {"coordinates":[-4.45802,5.64517],"type":"Point"}
}