{
  "type": "Feature",
  "properties": {
    "gn:admin1_code":"78",
    "gn:asciiname":"Dempleu",
    "gn:country_code":"CI",
    "gn:dem":333,
    "gn:feature_class":"P",
    "gn:feature_code":"PPL",
    "gn:name":"Dempleu",
    "gn:population":0,
    "gn:timezone":"Africa/Abidjan",
    "iso:country":"CI",
    "name:und_x_variant":[
        "Youdepleu"
    ],
    "wof:name":"Dempleu",
    "wof:placetype":"locality"
},
  "geometry": {"coordinates":[-8.19497,7.22665],"type":"Point"}
}