{
  "type": "Feature",
  "properties": {
    "gn:admin1_code":"81",
    "gn:asciiname":"Zaboukro",
    "gn:country_code":"CI",
    "gn:dem":127,
    "gn:feature_class":"P",
    "gn:feature_code":"PPL",
    "gn:name":"Zaboukro",
    "gn:population":0,
    "gn:timezone":"Africa/Abidjan",
    "iso:country":"CI",
    "wof:name":"Zaboukro",
    "wof:placetype":"locality"
},
  "geometry": {"coordinates":[-4.04561,6.64659],"type":"Point"}
}