{
  "type": "Feature",
  "properties": {
    "gn:admin1_code":"95.0",
    "gn:asciiname":"Gbagrelilie",
    "gn:country_code":"CI",
    "gn:dem":254,
    "gn:feature_class":"P",
    "gn:feature_code":"PPL",
    "gn:name":"Gbagr\u00e9lili\u00e9",
    "gn:population":0,
    "gn:timezone":"Africa/Abidjan",
    "iso:country":"CI",
    "wof:name":"Gbagrelilie",
    "wof:placetype":"locality"
},
  "geometry": {"coordinates":[-5.79215,5.87771],"type":"Point"}
}