{
  "type": "Feature",
  "properties": {
    "gn:admin1_code":"92",
    "gn:asciiname":"Sekre-Bango",
    "gn:country_code":"CI",
    "gn:dem":232,
    "gn:feature_class":"P",
    "gn:feature_code":"PPL",
    "gn:name":"S\u00e9kr\u00e9-Bango",
    "gn:population":0,
    "gn:timezone":"Africa/Abidjan",
    "iso:country":"CI",
    "name:und_x_variant":[
        "S\u00e9kir\u00e9kouro",
        "S\u00e9kr\u00e9-Bango"
    ],
    "wof:name":"Sekre-Bango",
    "wof:placetype":"locality"
},
  "geometry": {"coordinates":[-3.28032,7.92764],"type":"Point"}
}