{
  "type": "Feature",
  "properties": {
    "gn:admin1_code":"87",
    "gn:asciiname":"Kpongokaha",
    "gn:country_code":"CI",
    "gn:dem":359,
    "gn:feature_class":"P",
    "gn:feature_code":"PPL",
    "gn:name":"Kpongokaha",
    "gn:population":0,
    "gn:timezone":"Africa/Abidjan",
    "iso:country":"CI",
    "name:und_x_variant":[
        "Pongokaha",
        "Kpongokaha"
    ],
    "wof:name":"Kpongokaha",
    "wof:placetype":"locality"
},
  "geometry": {"coordinates":[-5.40496,9.56911],"type":"Point"}
}