{
  "type": "Feature",
  "properties": {
    "gn:admin1_code":"82.0",
    "gn:asciiname":"Bakari",
    "gn:country_code":"CI",
    "gn:dem":57,
    "gn:feature_class":"P",
    "gn:feature_code":"PPL",
    "gn:name":"Bakari",
    "gn:population":0,
    "gn:timezone":"Africa/Abidjan",
    "iso:country":"CI",
    "wof:name":"Bakari",
    "wof:placetype":"locality"
},
  "geometry": {"coordinates":[-4.35358,5.93111],"type":"Point"}
}