{
  "type": "Feature",
  "properties": {
    "gn:admin1_code":"92",
    "gn:asciiname":"Sogui",
    "gn:country_code":"CI",
    "gn:dem":290,
    "gn:feature_class":"P",
    "gn:feature_code":"PPL",
    "gn:name":"Sogui",
    "gn:population":0,
    "gn:timezone":"Africa/Abidjan",
    "iso:country":"CI",
    "wof:name":"Sogui",
    "wof:placetype":"locality"
},
  "geometry": {"coordinates":[-3.11504,8.02123],"type":"Point"}
}