{
  "type": "Feature",
  "properties": {
    "gn:admin1_code":"78.0",
    "gn:asciiname":"Brizreu",
    "gn:country_code":"CI",
    "gn:dem":357,
    "gn:feature_class":"P",
    "gn:feature_code":"PPL",
    "gn:name":"Brizreu",
    "gn:population":0,
    "gn:timezone":"Africa/Abidjan",
    "iso:country":"CI",
    "name:und_x_variant":[
        "Brizereu"
    ],
    "wof:name":"Brizreu",
    "wof:placetype":"locality"
},
  "geometry": {"coordinates":[-8.20134,7.27656],"type":"Point"}
}