{
  "type": "Feature",
  "properties": {
    "gn:admin1_code":"95.0",
    "gn:asciiname":"Dagodio",
    "gn:country_code":"CI",
    "gn:dem":218,
    "gn:feature_class":"P",
    "gn:feature_code":"PPL",
    "gn:name":"Dagodio",
    "gn:population":0,
    "gn:timezone":"Africa/Abidjan",
    "iso:country":"CI",
    "wof:name":"Dagodio",
    "wof:placetype":"locality"
},
  "geometry": {"coordinates":[-6.09069,6.15534],"type":"Point"}
}