{
  "type": "Feature",
  "properties": {
    "gn:admin1_code":"96",
    "gn:asciiname":"Proziblanfla",
    "gn:country_code":"CI",
    "gn:dem":253,
    "gn:feature_class":"P",
    "gn:feature_code":"PPL",
    "gn:name":"Proziblanfla",
    "gn:population":0,
    "gn:timezone":"Africa/Abidjan",
    "iso:country":"CI",
    "name:und_x_variant":[
        "Proziblan",
        "Proziblanfla"
    ],
    "wof:name":"Proziblanfla",
    "wof:placetype":"locality"
},
  "geometry": {"coordinates":[-5.87626,6.6865],"type":"Point"}
}