{
  "type": "Feature",
  "properties": {
    "gn:admin1_code":"90.0",
    "gn:asciiname":"Demakro",
    "gn:country_code":"CI",
    "gn:dem":234,
    "gn:feature_class":"P",
    "gn:feature_code":"PPL",
    "gn:name":"D\u00e9makro",
    "gn:population":0,
    "gn:timezone":"Africa/Abidjan",
    "iso:country":"CI",
    "wof:name":"Demakro",
    "wof:placetype":"locality"
},
  "geometry": {"coordinates":[-5.54982,7.72171],"type":"Point"}
}