{
  "type": "Feature",
  "properties": {
    "gn:admin1_code":"82.0",
    "gn:asciiname":"Diangobo",
    "gn:country_code":"CI",
    "gn:dem":117,
    "gn:feature_class":"P",
    "gn:feature_code":"PPL",
    "gn:name":"Diangobo",
    "gn:population":0,
    "gn:timezone":"Africa/Abidjan",
    "iso:country":"CI",
    "name:fra_x_preferred":[
        "Diangobo"
    ],
    "name:msa_x_preferred":[
        "Diangobo"
    ],
    "name:ron_x_preferred":[
        "Diangobo"
    ],
    "wof:name":"Diangobo",
    "wof:placetype":"locality"
},
  "geometry": {"coordinates":[-3.64219,6.14632],"type":"Point"}
}