{
  "type": "Feature",
  "properties": {
    "gn:admin1_code":"81",
    "gn:asciiname":"Ngata Nguessamblekro",
    "gn:country_code":"CI",
    "gn:dem":199,
    "gn:feature_class":"P",
    "gn:feature_code":"PPL",
    "gn:name":"Ngata Nguessambl\u00e9kro",
    "gn:population":0,
    "gn:timezone":"Africa/Abidjan",
    "iso:country":"CI",
    "name:und_x_variant":[
        "Ngata Nguessambl\u00e9kro",
        "Ngataguessanbl\u00e9kro"
    ],
    "wof:name":"Ngata Nguessamblekro",
    "wof:placetype":"locality"
},
  "geometry": {"coordinates":[-5.02269,7.04816],"type":"Point"}
}