{
  "type": "Feature",
  "properties": {
    "gn:admin1_code":"87",
    "gn:asciiname":"Pelagono",
    "gn:country_code":"CI",
    "gn:dem":392,
    "gn:feature_class":"P",
    "gn:feature_code":"PPL",
    "gn:name":"P\u00e9lagono",
    "gn:population":0,
    "gn:timezone":"Africa/Abidjan",
    "iso:country":"CI",
    "name:und_x_variant":[
        "Plagouno",
        "P\u00e9lagono"
    ],
    "wof:name":"Pelagono",
    "wof:placetype":"locality"
},
  "geometry": {"coordinates":[-6.20437,9.86175],"type":"Point"}
}