{
  "type": "Feature",
  "properties": {
    "gn:admin1_code":"87.0",
    "gn:asciiname":"Bodou",
    "gn:country_code":"CI",
    "gn:dem":354,
    "gn:feature_class":"P",
    "gn:feature_code":"PPL",
    "gn:name":"Bodou",
    "gn:population":0,
    "gn:timezone":"Africa/Abidjan",
    "iso:country":"CI",
    "wof:name":"Bodou",
    "wof:placetype":"locality"
},
  "geometry": {"coordinates":[-6.04261,9.03521],"type":"Point"}
}