{
  "type": "Feature",
  "properties": {
    "gn:admin1_code":"82.0",
    "gn:asciiname":"Amon",
    "gn:country_code":"CI",
    "gn:dem":29,
    "gn:feature_class":"P",
    "gn:feature_code":"PPL",
    "gn:name":"Amon",
    "gn:population":0,
    "gn:timezone":"Africa/Abidjan",
    "iso:country":"CI",
    "name:als_x_preferred":[
        "Amon"
    ],
    "name:ceb_x_preferred":[
        "Amon"
    ],
    "name:chv_x_preferred":[
        "\u0410\u043c\u043e\u043d"
    ],
    "name:deu_x_preferred":[
        "Amon"
    ],
    "name:epo_x_preferred":[
        "Amon"
    ],
    "name:fas_x_preferred":[
        "\u0622\u0645\u0648\u0646"
    ],
    "name:fra_x_preferred":[
        "Amon"
    ],
    "name:hrv_x_preferred":[
        "Amon"
    ],
    "name:hun_x_preferred":[
        "\u00c1mon"
    ],
    "name:ind_x_preferred":[
        "Amon"
    ],
    "name:ita_x_preferred":[
        "Amon"
    ],
    "name:jpn_x_preferred":[
        "\u30a2\u30e2\u30f3"
    ],
    "name:lit_x_preferred":[
        "Amonas"
    ],
    "name:nld_x_preferred":[
        "Amon"
    ],
    "name:pol_x_preferred":[
        "Amon"
    ],
    "name:rus_x_preferred":[
        "\u0410\u043c\u043e\u043d"
    ],
    "name:slv_x_preferred":[
        "Amon"
    ],
    "name:spa_x_preferred":[
        "Am\u00f3n"
    ],
    "name:srp_x_preferred":[
        "\u0410\u043c\u043e\u043d"
    ],
    "name:tgl_x_preferred":[
        "Amon"
    ],
    "name:ukr_x_preferred":[
        "\u0410\u043c\u043e\u043d"
    ],
    "wof:name":"Amon",
    "wof:placetype":"locality"
},
  "geometry": {"coordinates":[-3.85243,5.56019],"type":"Point"}
}