{
  "type": "Feature",
  "properties": {
    "gn:admin1_code":"82.0",
    "gn:asciiname":"Amon",
    "gn:country_code":"CI",
    "gn:dem":29,
    "gn:feature_class":"P",
    "gn:feature_code":"PPL",
    "gn:name":"Amon",
    "gn:population":0,
    "gn:timezone":"Africa/Abidjan",
    "iso:country":"CI",
    "wof:name":"Amon",
    "wof:placetype":"locality"
},
  "geometry": {"coordinates":[-3.85243,5.56019],"type":"Point"}
}