{
  "type": "Feature",
  "properties": {
    "gn:admin1_code":"90.0",
    "gn:asciiname":"Finesseguedougou",
    "gn:country_code":"CI",
    "gn:dem":286,
    "gn:feature_class":"P",
    "gn:feature_code":"PPL",
    "gn:name":"Fin\u00e9ss\u00e9gu\u00e9dougou",
    "gn:population":0,
    "gn:timezone":"Africa/Abidjan",
    "iso:country":"CI",
    "name:und_x_variant":[
        "Fininsiguidougou",
        "Finessigu\u00e9",
        "Fin\u00e9ss\u00e9gu\u00e9dougou"
    ],
    "wof:name":"Finesseguedougou",
    "wof:placetype":"locality"
},
  "geometry": {"coordinates":[-4.56674,8.30879],"type":"Point"}
}