{
  "type": "Feature",
  "properties": {
    "gn:admin1_code":"90.0",
    "gn:asciiname":"Dila",
    "gn:country_code":"CI",
    "gn:dem":279,
    "gn:feature_class":"P",
    "gn:feature_code":"PPL",
    "gn:name":"Dila",
    "gn:population":0,
    "gn:timezone":"Africa/Abidjan",
    "iso:country":"CI",
    "name:ceb_x_preferred":[
        "Dila"
    ],
    "name:fra_x_preferred":[
        "Dila"
    ],
    "name:pol_x_preferred":[
        "Dila"
    ],
    "name:swe_x_preferred":[
        "Dila"
    ],
    "name:tgl_x_preferred":[
        "Dila"
    ],
    "wof:name":"Dila",
    "wof:placetype":"locality"
},
  "geometry": {"coordinates":[-5.20664,7.61614],"type":"Point"}
}