{
  "type": "Feature",
  "properties": {
    "gn:admin1_code":"77.0",
    "gn:asciiname":"Badouhala",
    "gn:country_code":"CI",
    "gn:dem":436,
    "gn:feature_class":"P",
    "gn:feature_code":"PPL",
    "gn:name":"Badouhala",
    "gn:population":0,
    "gn:timezone":"Africa/Abidjan",
    "iso:country":"CI",
    "wof:name":"Badouhala",
    "wof:placetype":"locality"
},
  "geometry": {"coordinates":[-7.52663,8.92976],"type":"Point"}
}