{
  "type": "Feature",
  "properties": {
    "gn:admin1_code":"82.0",
    "gn:asciiname":"Banguie",
    "gn:country_code":"CI",
    "gn:dem":123,
    "gn:feature_class":"P",
    "gn:feature_code":"PPL",
    "gn:name":"Bangui\u00e9",
    "gn:population":0,
    "gn:timezone":"Africa/Abidjan",
    "iso:country":"CI",
    "wof:name":"Banguie",
    "wof:placetype":"locality"
},
  "geometry": {"coordinates":[-4.35,6.11667],"type":"Point"}
}