{
  "type": "Feature",
  "properties": {
    "gn:admin1_code":"78",
    "gn:asciiname":"Pehoue",
    "gn:country_code":"CI",
    "gn:dem":330,
    "gn:feature_class":"P",
    "gn:feature_code":"PPL",
    "gn:name":"P\u00e9hou\u00e9",
    "gn:population":0,
    "gn:timezone":"Africa/Abidjan",
    "iso:country":"CI",
    "wof:name":"Pehoue",
    "wof:placetype":"locality"
},
  "geometry": {"coordinates":[-7.41667,7.35],"type":"Point"}
}