{
  "type": "Feature",
  "properties": {
    "gn:admin1_code":"92",
    "gn:asciiname":"Maguidan",
    "gn:country_code":"CI",
    "gn:dem":332,
    "gn:feature_class":"P",
    "gn:feature_code":"PPL",
    "gn:name":"Maguidan",
    "gn:population":0,
    "gn:timezone":"Africa/Abidjan",
    "iso:country":"CI",
    "wof:name":"Maguidan",
    "wof:placetype":"locality"
},
  "geometry": {"coordinates":[-3.56667,9.61667],"type":"Point"}
}