{
  "type": "Feature",
  "properties": {
    "gn:admin1_code":"87.0",
    "gn:asciiname":"Katyorple",
    "gn:country_code":"CI",
    "gn:dem":363,
    "gn:feature_class":"P",
    "gn:feature_code":"PPL",
    "gn:name":"Katyorpl\u00e9",
    "gn:population":0,
    "gn:timezone":"Africa/Abidjan",
    "iso:country":"CI",
    "name:und_x_variant":[
        "Katioripl\u00e9",
        "Katyorpl\u00e9"
    ],
    "wof:name":"Katyorple",
    "wof:placetype":"locality"
},
  "geometry": {"coordinates":[-5.71321,9.21991],"type":"Point"}
}