{
  "type": "Feature",
  "properties": {
    "gn:admin1_code":"90",
    "gn:asciiname":"Niediekaha",
    "gn:country_code":"CI",
    "gn:dem":397,
    "gn:feature_class":"P",
    "gn:feature_code":"PPL",
    "gn:name":"Ni\u00e9di\u00e9kaha",
    "gn:population":0,
    "gn:timezone":"Africa/Abidjan",
    "iso:country":"CI",
    "name:fra_x_preferred":[
        "Ni\u00e9di\u00e9kaha"
    ],
    "name:ita_x_preferred":[
        "Ni\u00e9di\u00e9kaha"
    ],
    "name:msa_x_preferred":[
        "Ni\u00e9di\u00e9kaha"
    ],
    "name:und_x_variant":[
        "Ni\u00e9di\u00e9",
        "Niem-Kaha",
        "Ny\u00e9dy\u00e9kaha"
    ],
    "wof:name":"Niediekaha",
    "wof:placetype":"locality"
},
  "geometry": {"coordinates":[-5.17636,8.9337],"type":"Point"}
}