{
  "type": "Feature",
  "properties": {
    "gn:admin1_code":"76.0",
    "gn:asciiname":"Bredie",
    "gn:country_code":"CI",
    "gn:dem":12,
    "gn:feature_class":"P",
    "gn:feature_code":"PPL",
    "gn:name":"Br\u00e9di\u00e9",
    "gn:population":0,
    "gn:timezone":"Africa/Abidjan",
    "iso:country":"CI",
    "wof:name":"Bredie",
    "wof:placetype":"locality"
},
  "geometry": {"coordinates":[-7.29799,4.45463],"type":"Point"}
}