{
  "type": "Feature",
  "properties": {
    "gn:admin1_code":"98",
    "gn:asciiname":"Zambakro",
    "gn:country_code":"CI",
    "gn:dem":166,
    "gn:feature_class":"P",
    "gn:feature_code":"PPL",
    "gn:name":"Zambakro",
    "gn:population":0,
    "gn:timezone":"Africa/Abidjan",
    "iso:country":"CI",
    "name:fra_x_preferred":[
        "Zambakro"
    ],
    "name:msa_x_preferred":[
        "Zambakro"
    ],
    "wof:name":"Zambakro",
    "wof:placetype":"locality"
},
  "geometry": {"coordinates":[-5.41117,6.73322],"type":"Point"}
}