{
  "type": "Feature",
  "properties": {
    "gn:admin1_code":"90.0",
    "gn:asciiname":"Aoussankro",
    "gn:country_code":"CI",
    "gn:dem":249,
    "gn:feature_class":"P",
    "gn:feature_code":"PPL",
    "gn:name":"Aoussankro",
    "gn:population":0,
    "gn:timezone":"Africa/Abidjan",
    "iso:country":"CI",
    "wof:name":"Aoussankro",
    "wof:placetype":"locality"
},
  "geometry": {"coordinates":[-5.12253,7.50598],"type":"Point"}
}