{
  "type": "Feature",
  "properties": {
    "gn:admin1_code":"78.0",
    "gn:asciiname":"Kamalo",
    "gn:country_code":"CI",
    "gn:dem":271,
    "gn:feature_class":"P",
    "gn:feature_code":"PPL",
    "gn:name":"Kamalo",
    "gn:population":0,
    "gn:timezone":"Africa/Abidjan",
    "iso:country":"CI",
    "wof:name":"Kamalo",
    "wof:placetype":"locality"
},
  "geometry": {"coordinates":[-7.10872,7.76853],"type":"Point"}
}