{
  "type": "Feature",
  "properties": {
    "gn:admin1_code":"81.0",
    "gn:asciiname":"Barikokro",
    "gn:country_code":"CI",
    "gn:dem":216,
    "gn:feature_class":"P",
    "gn:feature_code":"PPL",
    "gn:name":"Barikokro",
    "gn:population":0,
    "gn:timezone":"Africa/Abidjan",
    "iso:country":"CI",
    "wof:name":"Barikokro",
    "wof:placetype":"locality"
},
  "geometry": {"coordinates":[-4.03464,7.24989],"type":"Point"}
}