{
  "type": "Feature",
  "properties": {
    "gn:admin1_code":"78",
    "gn:asciiname":"Tadoua",
    "gn:country_code":"CI",
    "gn:dem":224,
    "gn:feature_class":"P",
    "gn:feature_code":"PPL",
    "gn:name":"Tadoua",
    "gn:population":0,
    "gn:timezone":"Africa/Abidjan",
    "iso:country":"CI",
    "wof:name":"Tadoua",
    "wof:placetype":"locality"
},
  "geometry": {"coordinates":[-7.44055,6.55758],"type":"Point"}
}