{
  "type": "Feature",
  "properties": {
    "gn:admin1_code":"93.0",
    "gn:asciiname":"Bakari Korri",
    "gn:country_code":"CI",
    "gn:dem":124,
    "gn:feature_class":"P",
    "gn:feature_code":"PPL",
    "gn:name":"Bakari Korri",
    "gn:population":0,
    "gn:timezone":"Africa/Abidjan",
    "iso:country":"CI",
    "wof:name":"Bakari Korri",
    "wof:placetype":"locality"
},
  "geometry": {"coordinates":[-4.08322,5.45765],"type":"Point"}
}