{
  "type": "Feature",
  "properties": {
    "gn:admin1_code":"87",
    "gn:asciiname":"Ledorokaha",
    "gn:country_code":"CI",
    "gn:dem":342,
    "gn:feature_class":"P",
    "gn:feature_code":"PPL",
    "gn:name":"L\u00e9dorokaha",
    "gn:population":0,
    "gn:timezone":"Africa/Abidjan",
    "iso:country":"CI",
    "name:und_x_variant":[
        "Ladorikaha",
        "L\u00e9dorokaha"
    ],
    "wof:name":"Ledorokaha",
    "wof:placetype":"locality"
},
  "geometry": {"coordinates":[-5.55,9.36667],"type":"Point"}
}