{
  "type": "Feature",
  "properties": {
    "gn:admin1_code":"94.0",
    "gn:asciiname":"Asse",
    "gn:country_code":"CI",
    "gn:dem":115,
    "gn:feature_class":"P",
    "gn:feature_code":"PPL",
    "gn:name":"Ass\u00e9",
    "gn:population":0,
    "gn:timezone":"Africa/Abidjan",
    "iso:country":"CI",
    "wof:name":"Asse",
    "wof:placetype":"locality"
},
  "geometry": {"coordinates":[-3.47028,5.32771],"type":"Point"}
}