{
  "type": "Feature",
  "properties": {
    "gn:admin1_code":"94.0",
    "gn:asciiname":"Asse",
    "gn:country_code":"CI",
    "gn:dem":115,
    "gn:feature_class":"P",
    "gn:feature_code":"PPL",
    "gn:name":"Ass\u00e9",
    "gn:population":0,
    "gn:timezone":"Africa/Abidjan",
    "iso:country":"CI",
    "name:bre_x_preferred":[
        "Asse"
    ],
    "name:bul_x_preferred":[
        "\u0410\u0441\u0435"
    ],
    "name:cat_x_preferred":[
        "Asse"
    ],
    "name:ceb_x_preferred":[
        "Asse"
    ],
    "name:deu_x_preferred":[
        "Asse"
    ],
    "name:epo_x_preferred":[
        "Asse"
    ],
    "name:eus_x_preferred":[
        "Asse"
    ],
    "name:fas_x_preferred":[
        "\u0627\u0633"
    ],
    "name:fra_x_preferred":[
        "Asse"
    ],
    "name:gle_x_preferred":[
        "Asse"
    ],
    "name:ita_x_preferred":[
        "Asse"
    ],
    "name:kor_x_preferred":[
        "\uc544\uc11c"
    ],
    "name:nld_x_preferred":[
        "Asse"
    ],
    "name:nor_x_preferred":[
        "Asse"
    ],
    "name:oci_x_preferred":[
        "Asse"
    ],
    "name:pol_x_preferred":[
        "Asse"
    ],
    "name:por_x_preferred":[
        "Asse"
    ],
    "name:ron_x_preferred":[
        "Asse"
    ],
    "name:rus_x_preferred":[
        "\u0410\u0441\u0441\u0435"
    ],
    "name:slk_x_preferred":[
        "Asse"
    ],
    "name:spa_x_preferred":[
        "Asse"
    ],
    "name:swe_x_preferred":[
        "Asse"
    ],
    "name:tur_x_preferred":[
        "Asse"
    ],
    "name:vie_x_preferred":[
        "Asse"
    ],
    "name:vol_x_preferred":[
        "Asse"
    ],
    "name:war_x_preferred":[
        "Asse"
    ],
    "wof:name":"Asse",
    "wof:placetype":"locality"
},
  "geometry": {"coordinates":[-3.47028,5.32771],"type":"Point"}
}