{
  "type": "Feature",
  "properties": {
    "gn:admin1_code":"82.0",
    "gn:asciiname":"Assouma Beugie",
    "gn:country_code":"CI",
    "gn:dem":86,
    "gn:feature_class":"P",
    "gn:feature_code":"PPL",
    "gn:name":"Assouma Beugi\u00e9",
    "gn:population":0,
    "gn:timezone":"Africa/Abidjan",
    "iso:country":"CI",
    "wof:name":"Assouma Beugie",
    "wof:placetype":"locality"
},
  "geometry": {"coordinates":[-4.46734,5.75494],"type":"Point"}
}