{
  "type": "Feature",
  "properties": {
    "gn:admin1_code":"81.0",
    "gn:asciiname":"Anouanze Bokaha",
    "gn:country_code":"CI",
    "gn:dem":221,
    "gn:feature_class":"P",
    "gn:feature_code":"PPL",
    "gn:name":"Anouanze Bokaha",
    "gn:population":0,
    "gn:timezone":"Africa/Abidjan",
    "iso:country":"CI",
    "wof:name":"Anouanze Bokaha",
    "wof:placetype":"locality"
},
  "geometry": {"coordinates":[-4.84151,7.00797],"type":"Point"}
}