{
  "type": "Feature",
  "properties": {
    "gn:admin1_code":"78.0",
    "gn:asciiname":"Gouantouo",
    "gn:country_code":"CI",
    "gn:dem":263,
    "gn:feature_class":"P",
    "gn:feature_code":"PPL",
    "gn:name":"Gouantouo",
    "gn:population":0,
    "gn:timezone":"Africa/Abidjan",
    "iso:country":"CI",
    "wof:name":"Gouantouo",
    "wof:placetype":"locality"
},
  "geometry": {"coordinates":[-8.32041,6.70911],"type":"Point"}
}