{
  "type": "Feature",
  "properties": {
    "gn:admin1_code":"97.0",
    "gn:asciiname":"Kaako",
    "gn:country_code":"CI",
    "gn:dem":460,
    "gn:feature_class":"P",
    "gn:feature_code":"PPL",
    "gn:name":"Kaako",
    "gn:population":0,
    "gn:timezone":"Africa/Abidjan",
    "iso:country":"CI",
    "wof:name":"Kaako",
    "wof:placetype":"locality"
},
  "geometry": {"coordinates":[-7.26433,8.20606],"type":"Point"}
}