{
  "type": "Feature",
  "properties": {
    "gn:admin1_code":"87.0",
    "gn:asciiname":"Kasseligue",
    "gn:country_code":"CI",
    "gn:dem":346,
    "gn:feature_class":"P",
    "gn:feature_code":"PPL",
    "gn:name":"Kass\u00e9ligu\u00e9",
    "gn:population":0,
    "gn:timezone":"Africa/Abidjan",
    "iso:country":"CI",
    "name:und_x_variant":[
        "Kass\u00e9l\u00e9k\u00e9",
        "Kass\u00e9ligu\u00e9"
    ],
    "wof:name":"Kasseligue",
    "wof:placetype":"locality"
},
  "geometry": {"coordinates":[-6.0204,9.93636],"type":"Point"}
}