{
  "type": "Feature",
  "properties": {
    "gn:admin1_code":"92",
    "gn:asciiname":"Maninbouri",
    "gn:country_code":"CI",
    "gn:dem":292,
    "gn:feature_class":"P",
    "gn:feature_code":"PPL",
    "gn:name":"Maninbouri",
    "gn:population":0,
    "gn:timezone":"Africa/Abidjan",
    "iso:country":"CI",
    "wof:name":"Maninbouri",
    "wof:placetype":"locality"
},
  "geometry": {"coordinates":[-2.99193,9.62572],"type":"Point"}
}