{
  "type": "Feature",
  "properties": {
    "gn:admin1_code":"82.0",
    "gn:asciiname":"Ake-Befiat",
    "gn:country_code":"CI",
    "gn:dem":42,
    "gn:feature_class":"P",
    "gn:feature_code":"PPL",
    "gn:name":"Ak\u00e9-B\u00e9fiat",
    "gn:population":0,
    "gn:timezone":"Africa/Abidjan",
    "iso:country":"CI",
    "name:und_x_variant":[
        "Ak\u00e9b\u00e9fia",
        "Ak\u00e9-B\u00e9fiat"
    ],
    "wof:name":"Ake-Befiat",
    "wof:placetype":"locality"
},
  "geometry": {"coordinates":[-4.17544,5.66523],"type":"Point"}
}