{
  "type": "Feature",
  "properties": {
    "gn:admin1_code":"78",
    "gn:asciiname":"Kouayaguiepleu",
    "gn:country_code":"CI",
    "gn:dem":256,
    "gn:feature_class":"P",
    "gn:feature_code":"PPL",
    "gn:name":"Kouayagui\u00e9pleu",
    "gn:population":0,
    "gn:timezone":"Africa/Abidjan",
    "iso:country":"CI",
    "name:und_x_variant":[
        "Kouayagui\u00e9pleu",
        "Kouyagui\u00e9pleu"
    ],
    "wof:name":"Kouayaguiepleu",
    "wof:placetype":"locality"
},
  "geometry": {"coordinates":[-8.2982,6.94601],"type":"Point"}
}