{
  "type": "Feature",
  "properties": {
    "gn:admin1_code":"78",
    "gn:asciiname":"Souapleu",
    "gn:country_code":"CI",
    "gn:dem":236,
    "gn:feature_class":"P",
    "gn:feature_code":"PPL",
    "gn:name":"Souapleu",
    "gn:population":0,
    "gn:timezone":"Africa/Abidjan",
    "iso:country":"CI",
    "name:und_x_variant":[
        "Gouapleu",
        "Souapleu"
    ],
    "wof:name":"Souapleu",
    "wof:placetype":"locality"
},
  "geometry": {"coordinates":[-8.36272,6.74433],"type":"Point"}
}