{
  "type": "Feature",
  "properties": {
    "gn:admin1_code":"89.0",
    "gn:asciiname":"Bediegouasso",
    "gn:country_code":"CI",
    "gn:dem":9,
    "gn:feature_class":"P",
    "gn:feature_code":"PPL",
    "gn:name":"B\u00e9di\u00e9gouasso",
    "gn:population":0,
    "gn:timezone":"Africa/Abidjan",
    "iso:country":"CI",
    "wof:name":"Bediegouasso",
    "wof:placetype":"locality"
},
  "geometry": {"coordinates":[-3.19896,5.35095],"type":"Point"}
}