{
  "type": "Feature",
  "properties": {
    "gn:admin1_code":"77",
    "gn:asciiname":"Tienko",
    "gn:country_code":"CI",
    "gn:dem":407,
    "gn:feature_class":"P",
    "gn:feature_code":"PPL",
    "gn:name":"Tienko",
    "gn:population":0,
    "gn:timezone":"Africa/Abidjan",
    "iso:country":"CI",
    "name:fra_x_preferred":[
        "Tienko"
    ],
    "name:ita_x_preferred":[
        "Tienko"
    ],
    "name:msa_x_preferred":[
        "Tienko"
    ],
    "name:ron_x_preferred":[
        "Tienko"
    ],
    "wof:name":"Tienko",
    "wof:placetype":"locality"
},
  "geometry": {"coordinates":[-7.4825,10.22472],"type":"Point"}
}