{
  "type": "Feature",
  "properties": {
    "gn:admin1_code":"96.0",
    "gn:asciiname":"Alaou",
    "gn:country_code":"CI",
    "gn:dem":236,
    "gn:feature_class":"P",
    "gn:feature_code":"PPL",
    "gn:name":"Alaou",
    "gn:population":0,
    "gn:timezone":"Africa/Abidjan",
    "iso:country":"CI",
    "name:und_x_variant":[
        "Alaou Bassi"
    ],
    "wof:name":"Alaou",
    "wof:placetype":"locality"
},
  "geometry": {"coordinates":[-5.51722,7.03728],"type":"Point"}
}