{
  "type": "Feature",
  "properties": {
    "gn:admin1_code":"76",
    "gn:asciiname":"Malan",
    "gn:country_code":"CI",
    "gn:dem":56,
    "gn:feature_class":"P",
    "gn:feature_code":"PPL",
    "gn:name":"Malan",
    "gn:population":0,
    "gn:timezone":"Africa/Abidjan",
    "iso:country":"CI",
    "wof:name":"Malan",
    "wof:placetype":"locality"
},
  "geometry": {"coordinates":[-7.04311,4.81947],"type":"Point"}
}