{
  "type": "Feature",
  "properties": {
    "gn:admin1_code":"92.0",
    "gn:asciiname":"Akrassikro",
    "gn:country_code":"CI",
    "gn:dem":192,
    "gn:feature_class":"P",
    "gn:feature_code":"PPL",
    "gn:name":"Akrassikro",
    "gn:population":0,
    "gn:timezone":"Africa/Abidjan",
    "iso:country":"CI",
    "name:und_x_variant":[
        "Daoukro",
        "Akrassikro"
    ],
    "wof:name":"Akrassikro",
    "wof:placetype":"locality"
},
  "geometry": {"coordinates":[-3.29055,7.65947],"type":"Point"}
}