{
  "type": "Feature",
  "properties": {
    "gn:admin1_code":"78.0",
    "gn:asciiname":"Gueoule",
    "gn:country_code":"CI",
    "gn:dem":638,
    "gn:feature_class":"P",
    "gn:feature_code":"PPL",
    "gn:name":"Gu\u00e9oul\u00e9",
    "gn:population":0,
    "gn:timezone":"Africa/Abidjan",
    "iso:country":"CI",
    "name:und_x_variant":[
        "G\u00e9l\u00e9mou",
        "G\u00e9oul\u00e9",
        "Gu\u00e9oul\u00e9"
    ],
    "wof:name":"Gueoule",
    "wof:placetype":"locality"
},
  "geometry": {"coordinates":[-7.90071,7.59893],"type":"Point"}
}