{
  "type": "Feature",
  "properties": {
    "gn:admin1_code":"87",
    "gn:asciiname":"Tigisikaha",
    "gn:country_code":"CI",
    "gn:dem":342,
    "gn:feature_class":"P",
    "gn:feature_code":"PPL",
    "gn:name":"Tigisikaha",
    "gn:population":0,
    "gn:timezone":"Africa/Abidjan",
    "iso:country":"CI",
    "name:und_x_variant":[
        "Tiguissikaha",
        "Tigisikaha"
    ],
    "wof:name":"Tigisikaha",
    "wof:placetype":"locality"
},
  "geometry": {"coordinates":[-5.19384,9.43636],"type":"Point"}
}