{
  "type": "Feature",
  "properties": {
    "gn:admin1_code":"97",
    "gn:asciiname":"Touoko",
    "gn:country_code":"CI",
    "gn:dem":484,
    "gn:feature_class":"P",
    "gn:feature_code":"PPL",
    "gn:name":"Touoko",
    "gn:population":0,
    "gn:timezone":"Africa/Abidjan",
    "iso:country":"CI",
    "wof:name":"Touoko",
    "wof:placetype":"locality"
},
  "geometry": {"coordinates":[-7.57707,8.09619],"type":"Point"}
}