{
  "type": "Feature",
  "properties": {
    "gn:admin1_code":"93.0",
    "gn:asciiname":"Djaya",
    "gn:country_code":"CI",
    "gn:dem":61,
    "gn:feature_class":"P",
    "gn:feature_code":"PPL",
    "gn:name":"Djaya",
    "gn:population":0,
    "gn:timezone":"Africa/Abidjan",
    "iso:country":"CI",
    "wof:name":"Djaya",
    "wof:placetype":"locality"
},
  "geometry": {"coordinates":[-4.03017,5.52544],"type":"Point"}
}