{
  "type": "Feature",
  "properties": {
    "gn:admin1_code":"82.0",
    "gn:asciiname":"Ehai Achi",
    "gn:country_code":"CI",
    "gn:dem":93,
    "gn:feature_class":"P",
    "gn:feature_code":"PPL",
    "gn:name":"Ehai Achi",
    "gn:population":0,
    "gn:timezone":"Africa/Abidjan",
    "iso:country":"CI",
    "wof:name":"Ehai Achi",
    "wof:placetype":"locality"
},
  "geometry": {"coordinates":[-3.89988,5.9872],"type":"Point"}
}