{
  "type": "Feature",
  "properties": {
    "gn:admin1_code":"76",
    "gn:asciiname":"Lipoyo",
    "gn:country_code":"CI",
    "gn:dem":25,
    "gn:feature_class":"P",
    "gn:feature_code":"PPL",
    "gn:name":"Lipoyo",
    "gn:population":0,
    "gn:timezone":"Africa/Abidjan",
    "iso:country":"CI",
    "wof:name":"Lipoyo",
    "wof:placetype":"locality"
},
  "geometry": {"coordinates":[-6.02107,4.99534],"type":"Point"}
}