{
  "type": "Feature",
  "properties": {
    "gn:admin1_code":"97",
    "gn:asciiname":"Mehidougou",
    "gn:country_code":"CI",
    "gn:dem":474,
    "gn:feature_class":"P",
    "gn:feature_code":"PPL",
    "gn:name":"M\u00e9hidougou",
    "gn:population":0,
    "gn:timezone":"Africa/Abidjan",
    "iso:country":"CI",
    "wof:name":"Mehidougou",
    "wof:placetype":"locality"
},
  "geometry": {"coordinates":[-7.79347,8.45248],"type":"Point"}
}