{
  "type": "Feature",
  "properties": {
    "gn:admin1_code":"96.0",
    "gn:asciiname":"Gabia",
    "gn:country_code":"CI",
    "gn:dem":252,
    "gn:feature_class":"P",
    "gn:feature_code":"PPL",
    "gn:name":"Gabia",
    "gn:population":0,
    "gn:timezone":"Africa/Abidjan",
    "iso:country":"CI",
    "name:glg_x_preferred":[
        "Gabia"
    ],
    "name:spa_x_preferred":[
        "Gabia"
    ],
    "wof:name":"Gabia",
    "wof:placetype":"locality"
},
  "geometry": {"coordinates":[-6.3791,6.40891],"type":"Point"}
}