{
  "type": "Feature",
  "properties": {
    "gn:admin1_code":"82.0",
    "gn:asciiname":"Attoutou",
    "gn:country_code":"CI",
    "gn:dem":9,
    "gn:feature_class":"P",
    "gn:feature_code":"PPL",
    "gn:name":"Attoutou",
    "gn:population":0,
    "gn:timezone":"Africa/Abidjan",
    "iso:country":"CI",
    "name:fra_x_preferred":[
        "Attoutou"
    ],
    "name:ita_x_preferred":[
        "Attoutou"
    ],
    "name:msa_x_preferred":[
        "Attoutou"
    ],
    "name:und_x_variant":[
        "Attoutou-Amarou",
        "Attoutou"
    ],
    "wof:name":"Attoutou",
    "wof:placetype":"locality"
},
  "geometry": {"coordinates":[-4.57236,5.22099],"type":"Point"}
}