{
  "type": "Feature",
  "properties": {
    "gn:admin1_code":"82",
    "gn:asciiname":"Nigui Nanon",
    "gn:country_code":"CI",
    "gn:dem":49,
    "gn:feature_class":"P",
    "gn:feature_code":"PPL",
    "gn:name":"Nigui Nanon",
    "gn:population":0,
    "gn:timezone":"Africa/Abidjan",
    "iso:country":"CI",
    "wof:name":"Nigui Nanon",
    "wof:placetype":"locality"
},
  "geometry": {"coordinates":[-4.61276,5.28087],"type":"Point"}
}