{
  "type": "Feature",
  "properties": {
    "gn:admin1_code":"81.0",
    "gn:asciiname":"Katchre Essekro",
    "gn:country_code":"CI",
    "gn:dem":156,
    "gn:feature_class":"P",
    "gn:feature_code":"PPL",
    "gn:name":"Katchr\u00e9 Essekro",
    "gn:population":0,
    "gn:timezone":"Africa/Abidjan",
    "iso:country":"CI",
    "name:und_x_variant":[
        "Katchr\u00e9 Essekro",
        "Ass\u00e9kro"
    ],
    "wof:name":"Katchre Essekro",
    "wof:placetype":"locality"
},
  "geometry": {"coordinates":[-4.6128,7.02407],"type":"Point"}
}