{
  "type": "Feature",
  "properties": {
    "gn:admin1_code":"97",
    "gn:asciiname":"Ouahiere",
    "gn:country_code":"CI",
    "gn:dem":357,
    "gn:feature_class":"P",
    "gn:feature_code":"PPL",
    "gn:name":"Ouahier\u00e9",
    "gn:population":0,
    "gn:timezone":"Africa/Abidjan",
    "iso:country":"CI",
    "name:und_x_variant":[
        "Wahir",
        "Oua\u00efr\u00e9",
        "Wahiri",
        "Ouahiri",
        "Wayiri",
        "Ouahini",
        "Ouahier\u00e9"
    ],
    "wof:name":"Ouahiere",
    "wof:placetype":"locality"
},
  "geometry": {"coordinates":[-6.45556,8.97139],"type":"Point"}
}