{
  "type": "Feature",
  "properties": {
    "gn:admin1_code":"82",
    "gn:asciiname":"Nsakoua",
    "gn:country_code":"CI",
    "gn:dem":22,
    "gn:feature_class":"P",
    "gn:feature_code":"PPL",
    "gn:name":"Nsakoua",
    "gn:population":0,
    "gn:timezone":"Africa/Abidjan",
    "iso:country":"CI",
    "name:und_x_variant":[
        "Sokoi",
        "Nsakoi",
        "Nsakoua"
    ],
    "wof:name":"Nsakoua",
    "wof:placetype":"locality"
},
  "geometry": {"coordinates":[-3.93225,5.64104],"type":"Point"}
}