{
  "type": "Feature",
  "properties": {
    "gn:admin1_code":"90",
    "gn:asciiname":"Sokala-Sobara",
    "gn:country_code":"CI",
    "gn:dem":347,
    "gn:feature_class":"P",
    "gn:feature_code":"PPL",
    "gn:name":"Sokala-Sobara",
    "gn:population":0,
    "gn:timezone":"Africa/Abidjan",
    "iso:country":"CI",
    "name:fra_x_preferred":[
        "Sokala-Sobara"
    ],
    "name:ita_x_preferred":[
        "Sokala-Sobara"
    ],
    "name:msa_x_preferred":[
        "Sokala-Sobara"
    ],
    "name:und_x_variant":[
        "Sokala",
        "Sobara"
    ],
    "wof:name":"Sokala-Sobara",
    "wof:placetype":"locality"
},
  "geometry": {"coordinates":[-4.5141,8.44227],"type":"Point"}
}