{
  "type": "Feature",
  "properties": {
    "gn:admin1_code":"78.0",
    "gn:asciiname":"Bietouo",
    "gn:country_code":"CI",
    "gn:dem":272,
    "gn:feature_class":"P",
    "gn:feature_code":"PPL",
    "gn:name":"Bi\u00e9touo",
    "gn:population":0,
    "gn:timezone":"Africa/Abidjan",
    "iso:country":"CI",
    "wof:name":"Bietouo",
    "wof:placetype":"locality"
},
  "geometry": {"coordinates":[-8.12164,6.90557],"type":"Point"}
}