{
  "type": "Feature",
  "properties": {
    "gn:admin1_code":"90",
    "gn:asciiname":"Konionan",
    "gn:country_code":"CI",
    "gn:dem":365,
    "gn:feature_class":"P",
    "gn:feature_code":"PPL",
    "gn:name":"Konionan",
    "gn:population":0,
    "gn:timezone":"Africa/Abidjan",
    "iso:country":"CI",
    "wof:name":"Konionan",
    "wof:placetype":"locality"
},
  "geometry": {"coordinates":[-4.73592,8.4756],"type":"Point"}
}