{
  "type": "Feature",
  "properties": {
    "gn:admin1_code":"94.0",
    "gn:asciiname":"Brahimakro",
    "gn:country_code":"CI",
    "gn:dem":116,
    "gn:feature_class":"P",
    "gn:feature_code":"PPL",
    "gn:name":"Brahimakro",
    "gn:population":0,
    "gn:timezone":"Africa/Abidjan",
    "iso:country":"CI",
    "wof:name":"Brahimakro",
    "wof:placetype":"locality"
},
  "geometry": {"coordinates":[-3.44895,5.40345],"type":"Point"}
}