{
  "type": "Feature",
  "properties": {
    "gn:admin1_code":"96.0",
    "gn:asciiname":"Kami",
    "gn:country_code":"CI",
    "gn:dem":323,
    "gn:feature_class":"P",
    "gn:feature_code":"PPL",
    "gn:name":"Kami",
    "gn:population":0,
    "gn:timezone":"Africa/Abidjan",
    "iso:country":"CI",
    "wof:name":"Kami",
    "wof:placetype":"locality"
},
  "geometry": {"coordinates":[-5.60293,7.01577],"type":"Point"}
}