{
  "type": "Feature",
  "properties": {
    "gn:admin1_code":"93.0",
    "gn:asciiname":"Tiemoko",
    "gn:country_code":"CI",
    "gn:dem":20,
    "gn:feature_class":"P",
    "gn:feature_code":"PPL",
    "gn:name":"Ti\u00e9moko",
    "gn:population":0,
    "gn:timezone":"Africa/Abidjan",
    "iso:country":"CI",
    "wof:name":"Tiemoko",
    "wof:placetype":"locality"
},
  "geometry": {"coordinates":[-3.93718,5.45583],"type":"Point"}
}