{
  "type": "Feature",
  "properties": {
    "gn:admin1_code":"96.0",
    "gn:asciiname":"Detroya",
    "gn:country_code":"CI",
    "gn:dem":243,
    "gn:feature_class":"P",
    "gn:feature_code":"PPL",
    "gn:name":"D\u00e9troya",
    "gn:population":0,
    "gn:timezone":"Africa/Abidjan",
    "iso:country":"CI",
    "name:und_x_variant":[
        "D\u00e9troya"
    ],
    "wof:name":"Detroya",
    "wof:placetype":"locality"
},
  "geometry": {"coordinates":[-6.82599,6.68297],"type":"Point"}
}