{
  "type": "Feature",
  "properties": {
    "gn:admin1_code":"81.0",
    "gn:asciiname":"Bananguezansou",
    "gn:country_code":"CI",
    "gn:dem":161,
    "gn:feature_class":"P",
    "gn:feature_code":"PPL",
    "gn:name":"Banangu\u00e9zansou",
    "gn:population":0,
    "gn:timezone":"Africa/Abidjan",
    "iso:country":"CI",
    "wof:name":"Bananguezansou",
    "wof:placetype":"locality"
},
  "geometry": {"coordinates":[-4.32028,7.03528],"type":"Point"}
}