{
  "type": "Feature",
  "properties": {
    "gn:admin1_code":"90.0",
    "gn:asciiname":"Pohoukro",
    "gn:country_code":"CI",
    "gn:dem":259,
    "gn:feature_class":"P",
    "gn:feature_code":"PPL",
    "gn:name":"Pohoukro",
    "gn:population":0,
    "gn:timezone":"Africa/Abidjan",
    "iso:country":"CI",
    "name:und_x_variant":[
        "Goli-Poukro"
    ],
    "wof:name":"Pohoukro",
    "wof:placetype":"locality"
},
  "geometry": {"coordinates":[-5.32019,7.51868],"type":"Point"}
}