{
  "type": "Feature",
  "properties": {
    "gn:admin1_code":"97.0",
    "gn:asciiname":"Gbenimanso",
    "gn:country_code":"CI",
    "gn:dem":736,
    "gn:feature_class":"P",
    "gn:feature_code":"PPL",
    "gn:name":"Gb\u00e9nimanso",
    "gn:population":0,
    "gn:timezone":"Africa/Abidjan",
    "iso:country":"CI",
    "name:fra_x_preferred":[
        "Gu\u00e9nimanzo"
    ],
    "name:msa_x_preferred":[
        "Gu\u00e9nimanzo"
    ],
    "name:und_x_variant":[
        "Gu\u00e9n\u00e9manzo",
        "Gb\u00e9nimanso"
    ],
    "wof:name":"Gbenimanso",
    "wof:placetype":"locality"
},
  "geometry": {"coordinates":[-7.60721,8.20483],"type":"Point"}
}