{
  "type": "Feature",
  "properties": {
    "gn:admin1_code":"87",
    "gn:asciiname":"Kogotoukaha",
    "gn:country_code":"CI",
    "gn:dem":322,
    "gn:feature_class":"P",
    "gn:feature_code":"PPL",
    "gn:name":"Kogotoukaha",
    "gn:population":0,
    "gn:timezone":"Africa/Abidjan",
    "iso:country":"CI",
    "name:und_x_variant":[
        "Kogotonkaha",
        "Kogotoukaha"
    ],
    "wof:name":"Kogotoukaha",
    "wof:placetype":"locality"
},
  "geometry": {"coordinates":[-5.4664,9.39492],"type":"Point"}
}