{
  "type": "Feature",
  "properties": {
    "gn:admin1_code":"95",
    "gn:asciiname":"Sokrobonyoa",
    "gn:country_code":"CI",
    "gn:dem":192,
    "gn:feature_class":"P",
    "gn:feature_code":"PPL",
    "gn:name":"Sokrobonyoa",
    "gn:population":0,
    "gn:timezone":"Africa/Abidjan",
    "iso:country":"CI",
    "name:und_x_variant":[
        "Sokrobognoa",
        "Sokrobonyoa"
    ],
    "wof:name":"Sokrobonyoa",
    "wof:placetype":"locality"
},
  "geometry": {"coordinates":[-6.13237,6.07239],"type":"Point"}
}