{
  "type": "Feature",
  "properties": {
    "gn:admin1_code":"87.0",
    "gn:asciiname":"Kanofonkaha",
    "gn:country_code":"CI",
    "gn:dem":394,
    "gn:feature_class":"P",
    "gn:feature_code":"PPL",
    "gn:name":"Kanofonkaha",
    "gn:population":0,
    "gn:timezone":"Africa/Abidjan",
    "iso:country":"CI",
    "wof:name":"Kanofonkaha",
    "wof:placetype":"locality"
},
  "geometry": {"coordinates":[-5.7013,9.39414],"type":"Point"}
}