{
  "type": "Feature",
  "properties": {
    "gn:admin1_code":"87",
    "gn:asciiname":"Nyenefor",
    "gn:country_code":"CI",
    "gn:dem":335,
    "gn:feature_class":"P",
    "gn:feature_code":"PPL",
    "gn:name":"Ny\u00e9n\u00e9for",
    "gn:population":0,
    "gn:timezone":"Africa/Abidjan",
    "iso:country":"CI",
    "name:und_x_variant":[
        "Ni\u00e9n\u00e9for",
        "Ny\u00e9n\u00e9for"
    ],
    "wof:name":"Nyenefor",
    "wof:placetype":"locality"
},
  "geometry": {"coordinates":[-5.96393,9.9541],"type":"Point"}
}