{
  "type": "Feature",
  "properties": {
    "gn:admin1_code":"92",
    "gn:asciiname":"Pambasso",
    "gn:country_code":"CI",
    "gn:dem":249,
    "gn:feature_class":"P",
    "gn:feature_code":"PPL",
    "gn:name":"Pambasso",
    "gn:population":0,
    "gn:timezone":"Africa/Abidjan",
    "iso:country":"CI",
    "name:und_x_variant":[
        "Panbasso",
        "Pambasso"
    ],
    "wof:name":"Pambasso",
    "wof:placetype":"locality"
},
  "geometry": {"coordinates":[-3.13723,7.61249],"type":"Point"}
}