{
  "type": "Feature",
  "properties": {
    "gn:admin1_code":"87.0",
    "gn:asciiname":"Kassiongo-Koura",
    "gn:country_code":"CI",
    "gn:dem":355,
    "gn:feature_class":"P",
    "gn:feature_code":"PPL",
    "gn:name":"Kassiongo-Koura",
    "gn:population":0,
    "gn:timezone":"Africa/Abidjan",
    "iso:country":"CI",
    "name:und_x_variant":[
        "Kassiongho",
        "Kassiongo",
        "Kassiongo-Koura"
    ],
    "wof:name":"Kassiongo-Koura",
    "wof:placetype":"locality"
},
  "geometry": {"coordinates":[-5.57195,10.01975],"type":"Point"}
}