{
  "type": "Feature",
  "properties": {
    "gn:admin1_code":"81.0",
    "gn:asciiname":"Assahara",
    "gn:country_code":"CI",
    "gn:dem":106,
    "gn:feature_class":"P",
    "gn:feature_code":"PPL",
    "gn:name":"Assahara",
    "gn:population":0,
    "gn:timezone":"Africa/Abidjan",
    "iso:country":"CI",
    "name:und_x_variant":[
        "Assara",
        "Assahara"
    ],
    "wof:name":"Assahara",
    "wof:placetype":"locality"
},
  "geometry": {"coordinates":[-4.49775,6.66643],"type":"Point"}
}