{
  "type": "Feature",
  "properties": {
    "gn:admin1_code":"82.0",
    "gn:asciiname":"Adjicoa",
    "gn:country_code":"CI",
    "gn:dem":84,
    "gn:feature_class":"P",
    "gn:feature_code":"PPL",
    "gn:name":"Adjicoa",
    "gn:population":0,
    "gn:timezone":"Africa/Abidjan",
    "iso:country":"CI",
    "wof:name":"Adjicoa",
    "wof:placetype":"locality"
},
  "geometry": {"coordinates":[-3.64342,5.84556],"type":"Point"}
}