{
  "type": "Feature",
  "properties": {
    "gn:admin1_code":"87",
    "gn:asciiname":"Sekourone",
    "gn:country_code":"CI",
    "gn:dem":320,
    "gn:feature_class":"P",
    "gn:feature_code":"PPL",
    "gn:name":"S\u00e9kouron\u00e9",
    "gn:population":0,
    "gn:timezone":"Africa/Abidjan",
    "iso:country":"CI",
    "wof:name":"Sekourone",
    "wof:placetype":"locality"
},
  "geometry": {"coordinates":[-5.16685,9.9975],"type":"Point"}
}