{
  "type": "Feature",
  "properties": {
    "gn:admin1_code":"0.0",
    "gn:asciiname":"Satoue",
    "gn:country_code":"CI",
    "gn:dem":13,
    "gn:feature_class":"P",
    "gn:feature_code":"PPL",
    "gn:name":"Satou\u00e9",
    "gn:population":0,
    "gn:timezone":"Africa/Abidjan",
    "iso:country":"CI",
    "wof:name":"Satoue",
    "wof:placetype":"locality"
},
  "geometry": {"coordinates":[-7.56139,4.53861],"type":"Point"}
}