{
  "type": "Feature",
  "properties": {
    "gn:admin1_code":"95",
    "gn:asciiname":"Mokta",
    "gn:country_code":"CI",
    "gn:dem":71,
    "gn:feature_class":"P",
    "gn:feature_code":"PPL",
    "gn:name":"Mokta",
    "gn:population":0,
    "gn:timezone":"Africa/Abidjan",
    "iso:country":"CI",
    "name:und_x_variant":[
        "Mokta el Hadid",
        "Mokta"
    ],
    "wof:name":"Mokta",
    "wof:placetype":"locality"
},
  "geometry": {"coordinates":[-5.38903,5.32366],"type":"Point"}
}