{
  "type": "Feature",
  "properties": {
    "gn:admin1_code":"97",
    "gn:asciiname":"Marhana",
    "gn:country_code":"CI",
    "gn:dem":275,
    "gn:feature_class":"P",
    "gn:feature_code":"PPL",
    "gn:name":"Marhana",
    "gn:population":0,
    "gn:timezone":"Africa/Abidjan",
    "iso:country":"CI",
    "wof:name":"Marhana",
    "wof:placetype":"locality"
},
  "geometry": {"coordinates":[-6.33825,7.87229],"type":"Point"}
}