{
  "type": "Feature",
  "properties": {
    "gn:admin1_code":"78.0",
    "gn:asciiname":"Ponan Ouinlo",
    "gn:country_code":"CI",
    "gn:dem":218,
    "gn:feature_class":"P",
    "gn:feature_code":"PPL",
    "gn:name":"Ponan Ouinlo",
    "gn:population":0,
    "gn:timezone":"Africa/Abidjan",
    "iso:country":"CI",
    "wof:name":"Ponan Ouinlo",
    "wof:placetype":"locality"
},
  "geometry": {"coordinates":[-7.09635,6.73516],"type":"Point"}
}