{
  "type": "Feature",
  "properties": {
    "gn:admin1_code":"81",
    "gn:asciiname":"Tromabo",
    "gn:country_code":"CI",
    "gn:dem":109,
    "gn:feature_class":"P",
    "gn:feature_code":"PPL",
    "gn:name":"Tromabo",
    "gn:population":0,
    "gn:timezone":"Africa/Abidjan",
    "iso:country":"CI",
    "wof:name":"Tromabo",
    "wof:placetype":"locality"
},
  "geometry": {"coordinates":[-4.7079,6.72055],"type":"Point"}
}