{
  "type": "Feature",
  "properties": {
    "gn:admin1_code":"95",
    "gn:asciiname":"Noppa",
    "gn:country_code":"CI",
    "gn:dem":238,
    "gn:feature_class":"P",
    "gn:feature_code":"PPL",
    "gn:name":"Noppa",
    "gn:population":0,
    "gn:timezone":"Africa/Abidjan",
    "iso:country":"CI",
    "name:und_x_variant":[
        "Nappa"
    ],
    "wof:name":"Noppa",
    "wof:placetype":"locality"
},
  "geometry": {"coordinates":[-5.83946,6.21642],"type":"Point"}
}