{
  "type": "Feature",
  "properties": {
    "gn:admin1_code":"90.0",
    "gn:asciiname":"Alebla",
    "gn:country_code":"CI",
    "gn:dem":261,
    "gn:feature_class":"P",
    "gn:feature_code":"PPL",
    "gn:name":"Al\u00e9bla",
    "gn:population":0,
    "gn:timezone":"Africa/Abidjan",
    "iso:country":"CI",
    "wof:name":"Alebla",
    "wof:placetype":"locality"
},
  "geometry": {"coordinates":[-5.39363,7.65861],"type":"Point"}
}