{
  "type": "Feature",
  "properties": {
    "gn:admin1_code":"76",
    "gn:asciiname":"Poutou",
    "gn:country_code":"CI",
    "gn:dem":127,
    "gn:feature_class":"P",
    "gn:feature_code":"PPL",
    "gn:name":"Poutou",
    "gn:population":0,
    "gn:timezone":"Africa/Abidjan",
    "iso:country":"CI",
    "wof:name":"Poutou",
    "wof:placetype":"locality"
},
  "geometry": {"coordinates":[-7.29463,5.29839],"type":"Point"}
}