{
  "type": "Feature",
  "properties": {
    "gn:admin1_code":"96.0",
    "gn:asciiname":"Irogogoua",
    "gn:country_code":"CI",
    "gn:dem":188,
    "gn:feature_class":"P",
    "gn:feature_code":"PPL",
    "gn:name":"Irogogoua",
    "gn:population":0,
    "gn:timezone":"Africa/Abidjan",
    "iso:country":"CI",
    "wof:name":"Irogogoua",
    "wof:placetype":"locality"
},
  "geometry": {"coordinates":[-6.5761,6.41233],"type":"Point"}
}