{
  "type": "Feature",
  "properties": {
    "gn:admin1_code":"96",
    "gn:asciiname":"Zala",
    "gn:country_code":"CI",
    "gn:dem":253,
    "gn:feature_class":"P",
    "gn:feature_code":"PPL",
    "gn:name":"Zala",
    "gn:population":0,
    "gn:timezone":"Africa/Abidjan",
    "iso:country":"CI",
    "name:als_x_preferred":[
        "Zala"
    ],
    "name:bos_x_preferred":[
        "Zala"
    ],
    "name:bul_x_preferred":[
        "\u0417\u0430\u043b\u0430"
    ],
    "name:ceb_x_preferred":[
        "Zala"
    ],
    "name:deu_x_preferred":[
        "Zala"
    ],
    "name:fra_x_preferred":[
        "Zala"
    ],
    "name:hrv_x_preferred":[
        "Zala"
    ],
    "name:hun_x_preferred":[
        "Zala"
    ],
    "name:lit_x_preferred":[
        "Zala"
    ],
    "name:nld_x_preferred":[
        "Zala"
    ],
    "name:pol_x_preferred":[
        "Zala"
    ],
    "name:por_x_preferred":[
        "Zala"
    ],
    "name:rus_x_preferred":[
        "\u0417\u0430\u043b\u0430"
    ],
    "name:slk_x_preferred":[
        "Zala"
    ],
    "name:slv_x_preferred":[
        "Zala"
    ],
    "name:spa_x_preferred":[
        "Zala"
    ],
    "name:srp_x_preferred":[
        "\u0417\u0430\u043b\u0430"
    ],
    "name:swe_x_preferred":[
        "Zala"
    ],
    "name:und_x_variant":[
        "Zaala"
    ],
    "wof:name":"Zala",
    "wof:placetype":"locality"
},
  "geometry": {"coordinates":[-6.69131,7.33296],"type":"Point"}
}