{
  "type": "Feature",
  "properties": {
    "gn:admin1_code":"92",
    "gn:asciiname":"Sekouaye",
    "gn:country_code":"CI",
    "gn:dem":336,
    "gn:feature_class":"P",
    "gn:feature_code":"PPL",
    "gn:name":"S\u00e9kouaye",
    "gn:population":0,
    "gn:timezone":"Africa/Abidjan",
    "iso:country":"CI",
    "wof:name":"Sekouaye",
    "wof:placetype":"locality"
},
  "geometry": {"coordinates":[-2.80879,8.27005],"type":"Point"}
}