{
  "type": "Feature",
  "properties": {
    "gn:admin1_code":"87",
    "gn:asciiname":"Nondara",
    "gn:country_code":"CI",
    "gn:dem":381,
    "gn:feature_class":"P",
    "gn:feature_code":"PPL",
    "gn:name":"Nondara",
    "gn:population":0,
    "gn:timezone":"Africa/Abidjan",
    "iso:country":"CI",
    "name:und_x_variant":[
        "Nandala",
        "Noonlara",
        "Nondara"
    ],
    "wof:name":"Nondara",
    "wof:placetype":"locality"
},
  "geometry": {"coordinates":[-6.52806,9.53333],"type":"Point"}
}