{
  "type": "Feature",
  "properties": {
    "gn:admin1_code":"97.0",
    "gn:asciiname":"Brounon",
    "gn:country_code":"CI",
    "gn:dem":271,
    "gn:feature_class":"P",
    "gn:feature_code":"PPL",
    "gn:name":"Brounon",
    "gn:population":0,
    "gn:timezone":"Africa/Abidjan",
    "iso:country":"CI",
    "wof:name":"Brounon",
    "wof:placetype":"locality"
},
  "geometry": {"coordinates":[-6.13333,7.71667],"type":"Point"}
}