{
  "type": "Feature",
  "properties": {
    "gn:admin1_code":"93.0",
    "gn:asciiname":"Adjin",
    "gn:country_code":"CI",
    "gn:dem":15,
    "gn:feature_class":"P",
    "gn:feature_code":"PPL",
    "gn:name":"Adjin",
    "gn:population":0,
    "gn:timezone":"Africa/Abidjan",
    "iso:country":"CI",
    "name:und_x_variant":[
        "Aghi\u00e9n",
        "Aguien",
        "Adjin"
    ],
    "wof:name":"Adjin",
    "wof:placetype":"locality"
},
  "geometry": {"coordinates":[-3.8539,5.3959],"type":"Point"}
}