{
  "type": "Feature",
  "properties": {
    "gn:admin1_code":"82.0",
    "gn:asciiname":"Sombo Makou",
    "gn:country_code":"CI",
    "gn:dem":67,
    "gn:feature_class":"P",
    "gn:feature_code":"PPL",
    "gn:name":"Sombo Makou",
    "gn:population":0,
    "gn:timezone":"Africa/Abidjan",
    "iso:country":"CI",
    "wof:name":"Sombo Makou",
    "wof:placetype":"locality"
},
  "geometry": {"coordinates":[-4.04523,5.87759],"type":"Point"}
}