{
  "type": "Feature",
  "properties": {
    "gn:admin1_code":"92",
    "gn:asciiname":"Tonkiro",
    "gn:country_code":"CI",
    "gn:dem":329,
    "gn:feature_class":"P",
    "gn:feature_code":"PPL",
    "gn:name":"Tonkiro",
    "gn:population":0,
    "gn:timezone":"Africa/Abidjan",
    "iso:country":"CI",
    "wof:name":"Tonkiro",
    "wof:placetype":"locality"
},
  "geometry": {"coordinates":[-3.18153,9.74378],"type":"Point"}
}