{
  "type": "Feature",
  "properties": {
    "gn:admin1_code":"92.0",
    "gn:asciiname":"Bielini",
    "gn:country_code":"CI",
    "gn:dem":331,
    "gn:feature_class":"P",
    "gn:feature_code":"PPL",
    "gn:name":"Bi\u00e9lini",
    "gn:population":0,
    "gn:timezone":"Africa/Abidjan",
    "iso:country":"CI",
    "wof:name":"Bielini",
    "wof:placetype":"locality"
},
  "geometry": {"coordinates":[-3.42552,9.79679],"type":"Point"}
}