{
  "type": "Feature",
  "properties": {
    "gn:admin1_code":"96",
    "gn:asciiname":"Kouritadou",
    "gn:country_code":"CI",
    "gn:dem":424,
    "gn:feature_class":"P",
    "gn:feature_code":"PPL",
    "gn:name":"Kouritadou",
    "gn:population":0,
    "gn:timezone":"Africa/Abidjan",
    "iso:country":"CI",
    "wof:name":"Kouritadou",
    "wof:placetype":"locality"
},
  "geometry": {"coordinates":[-5.56608,6.96775],"type":"Point"}
}