{
  "type": "Feature",
  "properties": {
    "gn:admin1_code":"81.0",
    "gn:asciiname":"Kouamenakro",
    "gn:country_code":"CI",
    "gn:dem":126,
    "gn:feature_class":"P",
    "gn:feature_code":"PPL",
    "gn:name":"Kouam\u00e9nakro",
    "gn:population":0,
    "gn:timezone":"Africa/Abidjan",
    "iso:country":"CI",
    "wof:name":"Kouamenakro",
    "wof:placetype":"locality"
},
  "geometry": {"coordinates":[-3.77101,6.72025],"type":"Point"}
}