{
  "type": "Feature",
  "properties": {
    "gn:admin1_code":"76",
    "gn:asciiname":"Pounie",
    "gn:country_code":"CI",
    "gn:dem":25,
    "gn:feature_class":"P",
    "gn:feature_code":"PPL",
    "gn:name":"Pouni\u00e9",
    "gn:population":0,
    "gn:timezone":"Africa/Abidjan",
    "iso:country":"CI",
    "wof:name":"Pounie",
    "wof:placetype":"locality"
},
  "geometry": {"coordinates":[-7.38019,4.53824],"type":"Point"}
}