{
  "type": "Feature",
  "properties": {
    "gn:admin1_code":"87",
    "gn:asciiname":"Sorodi",
    "gn:country_code":"CI",
    "gn:dem":356,
    "gn:feature_class":"P",
    "gn:feature_code":"PPL",
    "gn:name":"Sorodi",
    "gn:population":0,
    "gn:timezone":"Africa/Abidjan",
    "iso:country":"CI",
    "wof:name":"Sorodi",
    "wof:placetype":"locality"
},
  "geometry": {"coordinates":[-5.43422,10.06924],"type":"Point"}
}