{
  "type": "Feature",
  "properties": {
    "gn:admin1_code":"92",
    "gn:asciiname":"Wangare",
    "gn:country_code":"CI",
    "gn:dem":387,
    "gn:feature_class":"P",
    "gn:feature_code":"PPL",
    "gn:name":"Wangar\u00e9",
    "gn:population":0,
    "gn:timezone":"Africa/Abidjan",
    "iso:country":"CI",
    "wof:name":"Wangare",
    "wof:placetype":"locality"
},
  "geometry": {"coordinates":[-3.05054,8.2219],"type":"Point"}
}