{
  "type": "Feature",
  "properties": {
    "gn:admin1_code":"78",
    "gn:asciiname":"Tahapleu",
    "gn:country_code":"CI",
    "gn:dem":337,
    "gn:feature_class":"P",
    "gn:feature_code":"PPL",
    "gn:name":"Tahapleu",
    "gn:population":0,
    "gn:timezone":"Africa/Abidjan",
    "iso:country":"CI",
    "wof:name":"Tahapleu",
    "wof:placetype":"locality"
},
  "geometry": {"coordinates":[-8.05493,7.17989],"type":"Point"}
}