{
  "type": "Feature",
  "properties": {
    "gn:admin1_code":"76",
    "gn:asciiname":"Zuezueko",
    "gn:country_code":"CI",
    "gn:dem":27,
    "gn:feature_class":"P",
    "gn:feature_code":"PPL",
    "gn:name":"Zu\u00e9zu\u00e9ko",
    "gn:population":0,
    "gn:timezone":"Africa/Abidjan",
    "iso:country":"CI",
    "name:und_x_variant":[
        "Zuzu\u00e9co",
        "Zuzu\u00e9ko",
        "Zu\u00e9zu\u00e9ko"
    ],
    "wof:name":"Zuezueko",
    "wof:placetype":"locality"
},
  "geometry": {"coordinates":[-5.7696,5.05093],"type":"Point"}
}