{
  "type": "Feature",
  "properties": {
    "gn:admin1_code":"78.0",
    "gn:asciiname":"Koulinle",
    "gn:country_code":"CI",
    "gn:dem":276,
    "gn:feature_class":"P",
    "gn:feature_code":"PPL",
    "gn:name":"Koulinl\u00e9",
    "gn:population":0,
    "gn:timezone":"Africa/Abidjan",
    "iso:country":"CI",
    "name:und_x_variant":[
        "Keinl\u00e9",
        "Klind\u00e9",
        "Klinl\u00e9",
        "Klenl\u00e9",
        "Koulinl\u00e9"
    ],
    "wof:name":"Koulinle",
    "wof:placetype":"locality"
},
  "geometry": {"coordinates":[-7.52069,7.15007],"type":"Point"}
}