{
  "type": "Feature",
  "properties": {
    "gn:admin1_code":"82.0",
    "gn:asciiname":"Tebi Douhoua",
    "gn:country_code":"CI",
    "gn:dem":63,
    "gn:feature_class":"P",
    "gn:feature_code":"PPL",
    "gn:name":"Tebi Douhoua",
    "gn:population":0,
    "gn:timezone":"Africa/Abidjan",
    "iso:country":"CI",
    "wof:name":"Tebi Douhoua",
    "wof:placetype":"locality"
},
  "geometry": {"coordinates":[-4.28508,5.96134],"type":"Point"}
}