{
  "type": "Feature",
  "properties": {
    "gn:admin1_code":"87.0",
    "gn:asciiname":"Blediemene",
    "gn:country_code":"CI",
    "gn:dem":459,
    "gn:feature_class":"P",
    "gn:feature_code":"PPL",
    "gn:name":"Bl\u00e9di\u00e9m\u00e9n\u00e9",
    "gn:population":0,
    "gn:timezone":"Africa/Abidjan",
    "iso:country":"CI",
    "name:und_x_variant":[
        "Pleutyim\u00e9n\u00e9",
        "Bl\u00e9di\u00e9m\u00e9h\u00e9",
        "Bl\u00e9di\u00e9m\u00e9n\u00e9"
    ],
    "wof:name":"Blediemene",
    "wof:placetype":"locality"
},
  "geometry": {"coordinates":[-6.58417,9.76917],"type":"Point"}
}