{
  "type": "Feature",
  "properties": {
    "gn:admin1_code":"94.0",
    "gn:asciiname":"Kodiokro",
    "gn:country_code":"CI",
    "gn:dem":16,
    "gn:feature_class":"P",
    "gn:feature_code":"PPL",
    "gn:name":"Kodiokro",
    "gn:population":0,
    "gn:timezone":"Africa/Abidjan",
    "iso:country":"CI",
    "name:und_x_variant":[
        "Kadiakro"
    ],
    "wof:name":"Kodiokro",
    "wof:placetype":"locality"
},
  "geometry": {"coordinates":[-3.19648,5.39275],"type":"Point"}
}