{
  "type": "Feature",
  "properties": {
    "gn:admin1_code":"90",
    "gn:asciiname":"Nangre",
    "gn:country_code":"CI",
    "gn:dem":269,
    "gn:feature_class":"P",
    "gn:feature_code":"PPL",
    "gn:name":"Nangr\u00e9",
    "gn:population":0,
    "gn:timezone":"Africa/Abidjan",
    "iso:country":"CI",
    "wof:name":"Nangre",
    "wof:placetype":"locality"
},
  "geometry": {"coordinates":[-5.36798,7.71117],"type":"Point"}
}