{
  "type": "Feature",
  "properties": {
    "gn:admin1_code":"96.0",
    "gn:asciiname":"Hueflambota",
    "gn:country_code":"CI",
    "gn:dem":262,
    "gn:feature_class":"P",
    "gn:feature_code":"PPL",
    "gn:name":"Hu\u00e9flambota",
    "gn:population":0,
    "gn:timezone":"Africa/Abidjan",
    "iso:country":"CI",
    "wof:name":"Hueflambota",
    "wof:placetype":"locality"
},
  "geometry": {"coordinates":[-5.919,6.62599],"type":"Point"}
}