{
  "type": "Feature",
  "properties": {
    "gn:admin1_code":"82.0",
    "gn:asciiname":"Eboue Mossan",
    "gn:country_code":"CI",
    "gn:dem":86,
    "gn:feature_class":"P",
    "gn:feature_code":"PPL",
    "gn:name":"Ebou\u00e9 Mossan",
    "gn:population":0,
    "gn:timezone":"Africa/Abidjan",
    "iso:country":"CI",
    "wof:name":"Eboue Mossan",
    "wof:placetype":"locality"
},
  "geometry": {"coordinates":[-4.01081,5.88725],"type":"Point"}
}