{
  "type": "Feature",
  "properties": {
    "gn:admin1_code":"82.0",
    "gn:asciiname":"Abaoua",
    "gn:country_code":"CI",
    "gn:dem":118,
    "gn:feature_class":"P",
    "gn:feature_code":"PPL",
    "gn:name":"Abaoua",
    "gn:population":0,
    "gn:timezone":"Africa/Abidjan",
    "iso:country":"CI",
    "wof:name":"Abaoua",
    "wof:placetype":"locality"
},
  "geometry": {"coordinates":[-3.85903,6.35947],"type":"Point"}
}