{
  "type": "Feature",
  "properties": {
    "gn:admin1_code":"78.0",
    "gn:asciiname":"Guingleu",
    "gn:country_code":"CI",
    "gn:dem":251,
    "gn:feature_class":"P",
    "gn:feature_code":"PPL",
    "gn:name":"Guingleu",
    "gn:population":0,
    "gn:timezone":"Africa/Abidjan",
    "iso:country":"CI",
    "wof:name":"Guingleu",
    "wof:placetype":"locality"
},
  "geometry": {"coordinates":[-8.26408,7.03658],"type":"Point"}
}