{
  "type": "Feature",
  "properties": {
    "gn:admin1_code":"96",
    "gn:asciiname":"Zelia Kora",
    "gn:country_code":"CI",
    "gn:dem":263,
    "gn:feature_class":"P",
    "gn:feature_code":"PPL",
    "gn:name":"Z\u00e9lia Kora",
    "gn:population":0,
    "gn:timezone":"Africa/Abidjan",
    "iso:country":"CI",
    "wof:name":"Zelia Kora",
    "wof:placetype":"locality"
},
  "geometry": {"coordinates":[-6.49597,6.70453],"type":"Point"}
}