{
  "type": "Feature",
  "properties": {
    "gn:admin1_code":"95",
    "gn:asciiname":"Krisserahio",
    "gn:country_code":"CI",
    "gn:dem":225,
    "gn:feature_class":"P",
    "gn:feature_code":"PPL",
    "gn:name":"Kriss\u00e9rahio",
    "gn:population":0,
    "gn:timezone":"Africa/Abidjan",
    "iso:country":"CI",
    "name:und_x_variant":[
        "Kriss\u00e9rahio",
        "Kris\u00e9rayo"
    ],
    "wof:name":"Krisserahio",
    "wof:placetype":"locality"
},
  "geometry": {"coordinates":[-6.15447,6.22714],"type":"Point"}
}