{
  "type": "Feature",
  "properties": {
    "gn:admin1_code":"92",
    "gn:asciiname":"Titirikiou",
    "gn:country_code":"CI",
    "gn:dem":317,
    "gn:feature_class":"P",
    "gn:feature_code":"PPL",
    "gn:name":"Titirikiou",
    "gn:population":0,
    "gn:timezone":"Africa/Abidjan",
    "iso:country":"CI",
    "wof:name":"Titirikiou",
    "wof:placetype":"locality"
},
  "geometry": {"coordinates":[-3.44675,9.83951],"type":"Point"}
}