{
  "type": "Feature",
  "properties": {
    "gn:admin1_code":"97.0",
    "gn:asciiname":"Bomankoro",
    "gn:country_code":"CI",
    "gn:dem":507,
    "gn:feature_class":"P",
    "gn:feature_code":"PPL",
    "gn:name":"Bomankoro",
    "gn:population":0,
    "gn:timezone":"Africa/Abidjan",
    "iso:country":"CI",
    "name:und_x_variant":[
        "Banankoro",
        "Banankora",
        "Bomankoro"
    ],
    "wof:name":"Bomankoro",
    "wof:placetype":"locality"
},
  "geometry": {"coordinates":[-7.82643,9.02055],"type":"Point"}
}