{
  "type": "Feature",
  "properties": {
    "gn:admin1_code":"95",
    "gn:asciiname":"Onayo",
    "gn:country_code":"CI",
    "gn:dem":239,
    "gn:feature_class":"P",
    "gn:feature_code":"PPL",
    "gn:name":"Onayo",
    "gn:population":0,
    "gn:timezone":"Africa/Abidjan",
    "iso:country":"CI",
    "name:und_x_variant":[
        "Onahio"
    ],
    "wof:name":"Onayo",
    "wof:placetype":"locality"
},
  "geometry": {"coordinates":[-6.30197,6.26815],"type":"Point"}
}