{
  "type": "Feature",
  "properties": {
    "gn:admin1_code":"90",
    "gn:asciiname":"Sileoule",
    "gn:country_code":"CI",
    "gn:dem":269,
    "gn:feature_class":"P",
    "gn:feature_code":"PPL",
    "gn:name":"Sil\u00e9oul\u00e9",
    "gn:population":0,
    "gn:timezone":"Africa/Abidjan",
    "iso:country":"CI",
    "wof:name":"Sileoule",
    "wof:placetype":"locality"
},
  "geometry": {"coordinates":[-4.45242,8.32988],"type":"Point"}
}