{
  "type": "Feature",
  "properties": {
    "gn:admin1_code":"78",
    "gn:asciiname":"Tieouleoula",
    "gn:country_code":"CI",
    "gn:dem":149,
    "gn:feature_class":"P",
    "gn:feature_code":"PPL",
    "gn:name":"Ti\u00e9oul\u00e9oula",
    "gn:population":0,
    "gn:timezone":"Africa/Abidjan",
    "iso:country":"CI",
    "wof:name":"Tieouleoula",
    "wof:placetype":"locality"
},
  "geometry": {"coordinates":[-7.4018,5.73615],"type":"Point"}
}