{
  "type": "Feature",
  "properties": {
    "gn:admin1_code":"76",
    "gn:asciiname":"Negreadji",
    "gn:country_code":"CI",
    "gn:dem":103,
    "gn:feature_class":"P",
    "gn:feature_code":"PPL",
    "gn:name":"N\u00e9gr\u00e9adji",
    "gn:population":0,
    "gn:timezone":"Africa/Abidjan",
    "iso:country":"CI",
    "name:und_x_variant":[
        "N\u00e9gr\u00e9agui",
        "N\u00e9gr\u00e9adji"
    ],
    "wof:name":"Negreadji",
    "wof:placetype":"locality"
},
  "geometry": {"coordinates":[-6.50894,5.44666],"type":"Point"}
}