{
  "type": "Feature",
  "properties": {
    "gn:admin1_code":"78",
    "gn:asciiname":"Yanguileu",
    "gn:country_code":"CI",
    "gn:dem":596,
    "gn:feature_class":"P",
    "gn:feature_code":"PPL",
    "gn:name":"Yanguileu",
    "gn:population":0,
    "gn:timezone":"Africa/Abidjan",
    "iso:country":"CI",
    "wof:name":"Yanguileu",
    "wof:placetype":"locality"
},
  "geometry": {"coordinates":[-8.10992,7.6785],"type":"Point"}
}