{
  "type": "Feature",
  "properties": {
    "gn:admin1_code":"92.0",
    "gn:asciiname":"Deko",
    "gn:country_code":"CI",
    "gn:dem":358,
    "gn:feature_class":"P",
    "gn:feature_code":"PPL",
    "gn:name":"D\u00e9ko",
    "gn:population":0,
    "gn:timezone":"Africa/Abidjan",
    "iso:country":"CI",
    "wof:name":"Deko",
    "wof:placetype":"locality"
},
  "geometry": {"coordinates":[-3.24927,9.64748],"type":"Point"}
}