{
  "type": "Feature",
  "properties": {
    "gn:admin1_code":"94.0",
    "gn:asciiname":"Koffikro",
    "gn:country_code":"CI",
    "gn:dem":93,
    "gn:feature_class":"P",
    "gn:feature_code":"PPL",
    "gn:name":"Koffikro",
    "gn:population":0,
    "gn:timezone":"Africa/Abidjan",
    "iso:country":"CI",
    "name:fas_x_preferred":[
        "\u0627\u0647\u06cc\u06af\u0628\u06cc-\u06a9\u0627\u0641\u06cc\u06a9\u0631\u0648"
    ],
    "name:fra_x_preferred":[
        "Ahigb\u00e9-Koffikro"
    ],
    "name:msa_x_preferred":[
        "Ahigb\u00e9-Koffikro"
    ],
    "name:urd_x_preferred":[
        "\u0627\u06c1\u06cc\u06af\u0628\u06d2-\u06a9\u0648\u0641\u06cc\u06a9\u0631\u0648"
    ],
    "wof:name":"Koffikro",
    "wof:placetype":"locality"
},
  "geometry": {"coordinates":[-2.97775,5.59072],"type":"Point"}
}