{
  "type": "Feature",
  "properties": {
    "gn:admin1_code":"90.0",
    "gn:asciiname":"Fitabro",
    "gn:country_code":"CI",
    "gn:dem":220,
    "gn:feature_class":"P",
    "gn:feature_code":"PPL",
    "gn:name":"Fitabro",
    "gn:population":0,
    "gn:timezone":"Africa/Abidjan",
    "iso:country":"CI",
    "wof:name":"Fitabro",
    "wof:placetype":"locality"
},
  "geometry": {"coordinates":[-5.62269,7.79455],"type":"Point"}
}