{
  "type": "Feature",
  "properties": {
    "gn:admin1_code":"87.0",
    "gn:asciiname":"Gelenda",
    "gn:country_code":"CI",
    "gn:dem":370,
    "gn:feature_class":"P",
    "gn:feature_code":"PPL",
    "gn:name":"G\u00e9lenda",
    "gn:population":0,
    "gn:timezone":"Africa/Abidjan",
    "iso:country":"CI",
    "wof:name":"Gelenda",
    "wof:placetype":"locality"
},
  "geometry": {"coordinates":[-5.10885,9.50225],"type":"Point"}
}