{
  "type": "Feature",
  "properties": {
    "gn:admin1_code":"78",
    "gn:asciiname":"Nounoubaye",
    "gn:country_code":"CI",
    "gn:dem":251,
    "gn:feature_class":"P",
    "gn:feature_code":"PPL",
    "gn:name":"Nounoubay\u00e9",
    "gn:population":0,
    "gn:timezone":"Africa/Abidjan",
    "iso:country":"CI",
    "name:und_x_variant":[
        "Nounoubay\u00e9",
        "Nounoubaye"
    ],
    "wof:name":"Nounoubaye",
    "wof:placetype":"locality"
},
  "geometry": {"coordinates":[-7.56028,6.46008],"type":"Point"}
}