{
  "type": "Feature",
  "properties": {
    "gn:admin1_code":"87",
    "gn:asciiname":"Niellefogo",
    "gn:country_code":"CI",
    "gn:dem":322,
    "gn:feature_class":"P",
    "gn:feature_code":"PPL",
    "gn:name":"Niell\u00e9fogo",
    "gn:population":0,
    "gn:timezone":"Africa/Abidjan",
    "iso:country":"CI",
    "wof:name":"Niellefogo",
    "wof:placetype":"locality"
},
  "geometry": {"coordinates":[-5.34244,10.05376],"type":"Point"}
}