{
  "type": "Feature",
  "properties": {
    "gn:admin1_code":"76",
    "gn:asciiname":"Neplou",
    "gn:country_code":"CI",
    "gn:dem":107,
    "gn:feature_class":"P",
    "gn:feature_code":"PPL",
    "gn:name":"N\u00e9plou",
    "gn:population":0,
    "gn:timezone":"Africa/Abidjan",
    "iso:country":"CI",
    "name:und_x_variant":[
        "Niprou",
        "Noplou",
        "N\u00e9plou"
    ],
    "wof:name":"Neplou",
    "wof:placetype":"locality"
},
  "geometry": {"coordinates":[-7.3985,4.82602],"type":"Point"}
}