{
  "type": "Feature",
  "properties": {
    "gn:admin1_code":"87",
    "gn:asciiname":"Nandivogo",
    "gn:country_code":"CI",
    "gn:dem":340,
    "gn:feature_class":"P",
    "gn:feature_code":"PPL",
    "gn:name":"Nandivogo",
    "gn:population":0,
    "gn:timezone":"Africa/Abidjan",
    "iso:country":"CI",
    "wof:name":"Nandivogo",
    "wof:placetype":"locality"
},
  "geometry": {"coordinates":[-5.47858,9.66779],"type":"Point"}
}