{
  "type": "Feature",
  "properties": {
    "gn:admin1_code":"96",
    "gn:asciiname":"Kraka",
    "gn:country_code":"CI",
    "gn:dem":229,
    "gn:feature_class":"P",
    "gn:feature_code":"PPL",
    "gn:name":"Kraka",
    "gn:population":0,
    "gn:timezone":"Africa/Abidjan",
    "iso:country":"CI",
    "wof:name":"Kraka",
    "wof:placetype":"locality"
},
  "geometry": {"coordinates":[-6.58081,6.67822],"type":"Point"}
}