{
  "type": "Feature",
  "properties": {
    "gn:admin1_code":"81.0",
    "gn:asciiname":"Guimbo Ndolikro",
    "gn:country_code":"CI",
    "gn:dem":145,
    "gn:feature_class":"P",
    "gn:feature_code":"PPL",
    "gn:name":"Guimbo Ndolikro",
    "gn:population":0,
    "gn:timezone":"Africa/Abidjan",
    "iso:country":"CI",
    "name:und_x_variant":[
        "Guimbo",
        "Dimbo-Ndolikro",
        "Guimbo Ndolikro"
    ],
    "wof:name":"Guimbo Ndolikro",
    "wof:placetype":"locality"
},
  "geometry": {"coordinates":[-4.55944,7.22389],"type":"Point"}
}