{
  "type": "Feature",
  "properties": {
    "gn:admin1_code":"92.0",
    "gn:asciiname":"Aibekro",
    "gn:country_code":"CI",
    "gn:dem":144,
    "gn:feature_class":"P",
    "gn:feature_code":"PPL",
    "gn:name":"Aib\u00e9kro",
    "gn:population":0,
    "gn:timezone":"Africa/Abidjan",
    "iso:country":"CI",
    "wof:name":"Aibekro",
    "wof:placetype":"locality"
},
  "geometry": {"coordinates":[-3.50662,7.44862],"type":"Point"}
}