{
  "type": "Feature",
  "properties": {
    "gn:admin1_code":"82.0",
    "gn:asciiname":"Angra",
    "gn:country_code":"CI",
    "gn:dem":37,
    "gn:feature_class":"P",
    "gn:feature_code":"PPL",
    "gn:name":"Angra",
    "gn:population":0,
    "gn:timezone":"Africa/Abidjan",
    "iso:country":"CI",
    "wof:name":"Angra",
    "wof:placetype":"locality"
},
  "geometry": {"coordinates":[-4.02338,5.64649],"type":"Point"}
}