{
  "type": "Feature",
  "properties": {
    "gn:admin1_code":"92",
    "gn:asciiname":"Parbouli",
    "gn:country_code":"CI",
    "gn:dem":359,
    "gn:feature_class":"P",
    "gn:feature_code":"PPL",
    "gn:name":"Parbouli",
    "gn:population":0,
    "gn:timezone":"Africa/Abidjan",
    "iso:country":"CI",
    "wof:name":"Parbouli",
    "wof:placetype":"locality"
},
  "geometry": {"coordinates":[-3.68333,9.85],"type":"Point"}
}