{
  "type": "Feature",
  "properties": {
    "gn:admin1_code":"90.0",
    "gn:asciiname":"Gisankro",
    "gn:country_code":"CI",
    "gn:dem":276,
    "gn:feature_class":"P",
    "gn:feature_code":"PPL",
    "gn:name":"Gisankro",
    "gn:population":0,
    "gn:timezone":"Africa/Abidjan",
    "iso:country":"CI",
    "name:und_x_variant":[
        "Nguessankro",
        "Guessankro",
        "Gisankro"
    ],
    "wof:name":"Gisankro",
    "wof:placetype":"locality"
},
  "geometry": {"coordinates":[-5.44478,8.02879],"type":"Point"}
}