{
  "type": "Feature",
  "properties": {
    "gn:admin1_code":"87",
    "gn:asciiname":"Niafounagbo",
    "gn:country_code":"CI",
    "gn:dem":318,
    "gn:feature_class":"P",
    "gn:feature_code":"PPL",
    "gn:name":"Niafounagbo",
    "gn:population":0,
    "gn:timezone":"Africa/Abidjan",
    "iso:country":"CI",
    "wof:name":"Niafounagbo",
    "wof:placetype":"locality"
},
  "geometry": {"coordinates":[-4.60548,9.50469],"type":"Point"}
}