{
  "type": "Feature",
  "properties": {
    "gn:admin1_code":"90",
    "gn:asciiname":"Pindikro",
    "gn:country_code":"CI",
    "gn:dem":257,
    "gn:feature_class":"P",
    "gn:feature_code":"PPL",
    "gn:name":"Pindikro",
    "gn:population":0,
    "gn:timezone":"Africa/Abidjan",
    "iso:country":"CI",
    "name:und_x_variant":[
        "Pinikro"
    ],
    "wof:name":"Pindikro",
    "wof:placetype":"locality"
},
  "geometry": {"coordinates":[-5.31029,7.85817],"type":"Point"}
}