{
  "type": "Feature",
  "properties": {
    "gn:admin1_code":"93.0",
    "gn:asciiname":"Akakro",
    "gn:country_code":"CI",
    "gn:dem":8,
    "gn:feature_class":"P",
    "gn:feature_code":"PPL",
    "gn:name":"Akakro",
    "gn:population":0,
    "gn:timezone":"Africa/Abidjan",
    "iso:country":"CI",
    "wof:name":"Akakro",
    "wof:placetype":"locality"
},
  "geometry": {"coordinates":[-3.92079,5.43305],"type":"Point"}
}