{
  "type": "Feature",
  "properties": {
    "gn:admin1_code":"96.0",
    "gn:asciiname":"Kissahio",
    "gn:country_code":"CI",
    "gn:dem":220,
    "gn:feature_class":"P",
    "gn:feature_code":"PPL",
    "gn:name":"Kissahio",
    "gn:population":0,
    "gn:timezone":"Africa/Abidjan",
    "iso:country":"CI",
    "wof:name":"Kissahio",
    "wof:placetype":"locality"
},
  "geometry": {"coordinates":[-6.34306,6.37333],"type":"Point"}
}