{
  "type": "Feature",
  "properties": {
    "gn:admin1_code":"87",
    "gn:asciiname":"Wodoro",
    "gn:country_code":"CI",
    "gn:dem":366,
    "gn:feature_class":"P",
    "gn:feature_code":"PPL",
    "gn:name":"Wodoro",
    "gn:population":0,
    "gn:timezone":"Africa/Abidjan",
    "iso:country":"CI",
    "name:und_x_variant":[
        "Odoro",
        "Wodoro"
    ],
    "wof:name":"Wodoro",
    "wof:placetype":"locality"
},
  "geometry": {"coordinates":[-5.75742,9.63079],"type":"Point"}
}