{
  "type": "Feature",
  "properties": {
    "gn:admin1_code":"92",
    "gn:asciiname":"Nota",
    "gn:country_code":"CI",
    "gn:dem":329,
    "gn:feature_class":"P",
    "gn:feature_code":"PPL",
    "gn:name":"Nota",
    "gn:population":0,
    "gn:timezone":"Africa/Abidjan",
    "iso:country":"CI",
    "name:nld_x_preferred":[
        "Nota"
    ],
    "wof:name":"Nota",
    "wof:placetype":"locality"
},
  "geometry": {"coordinates":[-3.05953,9.4721],"type":"Point"}
}