{
  "type": "Feature",
  "properties": {
    "gn:admin1_code":"92.0",
    "gn:asciiname":"Digba",
    "gn:country_code":"CI",
    "gn:dem":351,
    "gn:feature_class":"P",
    "gn:feature_code":"PPL",
    "gn:name":"Digba",
    "gn:population":0,
    "gn:timezone":"Africa/Abidjan",
    "iso:country":"CI",
    "wof:name":"Digba",
    "wof:placetype":"locality"
},
  "geometry": {"coordinates":[-3.15945,9.43186],"type":"Point"}
}