{
  "type": "Feature",
  "properties": {
    "gn:admin1_code":"95.0",
    "gn:asciiname":"Eremankono",
    "gn:country_code":"CI",
    "gn:dem":56,
    "gn:feature_class":"P",
    "gn:feature_code":"PPL",
    "gn:name":"Er\u00e9mankono",
    "gn:population":0,
    "gn:timezone":"Africa/Abidjan",
    "iso:country":"CI",
    "name:und_x_variant":[
        "Emankono",
        "Er\u00e9mankono"
    ],
    "wof:name":"Eremankono",
    "wof:placetype":"locality"
},
  "geometry": {"coordinates":[-5.36667,5.55],"type":"Point"}
}