{
  "type": "Feature",
  "properties": {
    "gn:admin1_code":"87",
    "gn:asciiname":"Tianhana",
    "gn:country_code":"CI",
    "gn:dem":346,
    "gn:feature_class":"P",
    "gn:feature_code":"PPL",
    "gn:name":"Tianhana",
    "gn:population":0,
    "gn:timezone":"Africa/Abidjan",
    "iso:country":"CI",
    "wof:name":"Tianhana",
    "wof:placetype":"locality"
},
  "geometry": {"coordinates":[-6.29469,10.23295],"type":"Point"}
}