{
  "type": "Feature",
  "properties": {
    "gn:admin1_code":"87.0",
    "gn:asciiname":"Vanaloro",
    "gn:country_code":"CI",
    "gn:dem":353,
    "gn:feature_class":"P",
    "gn:feature_code":"PPL",
    "gn:name":"Vanaloro",
    "gn:population":0,
    "gn:timezone":"Africa/Abidjan",
    "iso:country":"CI",
    "wof:name":"Vanaloro",
    "wof:placetype":"locality"
},
  "geometry": {"coordinates":[-6.0019,10.12533],"type":"Point"}
}