{
  "type": "Feature",
  "properties": {
    "gn:admin1_code":"78.0",
    "gn:asciiname":"Gbeadapleu",
    "gn:country_code":"CI",
    "gn:dem":344,
    "gn:feature_class":"P",
    "gn:feature_code":"PPL",
    "gn:name":"Gb\u00e9adapleu",
    "gn:population":0,
    "gn:timezone":"Africa/Abidjan",
    "iso:country":"CI",
    "name:und_x_variant":[
        "Gb\u00e9adapleu",
        "Gbedapleu"
    ],
    "wof:name":"Gbeadapleu",
    "wof:placetype":"locality"
},
  "geometry": {"coordinates":[-8.35207,7.28989],"type":"Point"}
}