{
  "type": "Feature",
  "properties": {
    "gn:admin1_code":"94.0",
    "gn:admin2_code":"2293506.0",
    "gn:asciiname":"Bakakro",
    "gn:country_code":"CI",
    "gn:dem":61,
    "gn:feature_class":"P",
    "gn:feature_code":"PPL",
    "gn:name":"Bakakro",
    "gn:population":0,
    "gn:timezone":"Africa/Abidjan",
    "iso:country":"CI",
    "wof:name":"Bakakro",
    "wof:placetype":"locality"
},
  "geometry": {"coordinates":[-3.3345,5.40445],"type":"Point"}
}