{
  "type": "Feature",
  "properties": {
    "gn:admin1_code":"81",
    "gn:asciiname":"Sakassou",
    "gn:country_code":"CI",
    "gn:dem":124,
    "gn:feature_class":"P",
    "gn:feature_code":"PPL",
    "gn:name":"Sakassou",
    "gn:population":0,
    "gn:timezone":"Africa/Abidjan",
    "iso:country":"CI",
    "wof:name":"Sakassou",
    "wof:placetype":"locality"
},
  "geometry": {"coordinates":[-4.82498,6.54885],"type":"Point"}
}