{
  "type": "Feature",
  "properties": {
    "gn:admin1_code":"76",
    "gn:asciiname":"Outouke",
    "gn:country_code":"CI",
    "gn:dem":22,
    "gn:feature_class":"P",
    "gn:feature_code":"PPL",
    "gn:name":"Outouk\u00e9",
    "gn:population":0,
    "gn:timezone":"Africa/Abidjan",
    "iso:country":"CI",
    "wof:name":"Outouke",
    "wof:placetype":"locality"
},
  "geometry": {"coordinates":[-7.55977,4.72454],"type":"Point"}
}