{
  "type": "Feature",
  "properties": {
    "gn:admin1_code":"96.0",
    "gn:asciiname":"Blablata",
    "gn:country_code":"CI",
    "gn:dem":253,
    "gn:feature_class":"P",
    "gn:feature_code":"PPL",
    "gn:name":"Blablata",
    "gn:population":0,
    "gn:timezone":"Africa/Abidjan",
    "iso:country":"CI",
    "wof:name":"Blablata",
    "wof:placetype":"locality"
},
  "geometry": {"coordinates":[-6.01195,6.92798],"type":"Point"}
}