{
  "type": "Feature",
  "properties": {
    "gn:admin1_code":"78.0",
    "gn:asciiname":"Soloky",
    "gn:country_code":"CI",
    "gn:dem":209,
    "gn:feature_class":"P",
    "gn:feature_code":"PPL",
    "gn:name":"Soloky",
    "gn:population":0,
    "gn:timezone":"Africa/Abidjan",
    "iso:country":"CI",
    "wof:name":"Soloky",
    "wof:placetype":"locality"
},
  "geometry": {"coordinates":[-7.48972,6.11139],"type":"Point"}
}