{
  "type": "Feature",
  "properties": {
    "gn:admin1_code":"97",
    "gn:asciiname":"Tieningboue",
    "gn:country_code":"CI",
    "gn:dem":310,
    "gn:feature_class":"P",
    "gn:feature_code":"PPL",
    "gn:name":"Ti\u00e9ningbou\u00e9",
    "gn:population":0,
    "gn:timezone":"Africa/Abidjan",
    "iso:country":"CI",
    "name:fra_x_preferred":[
        "Ti\u00e9ningbou\u00e9"
    ],
    "name:ita_x_preferred":[
        "Ti\u00e9ningbou\u00e9"
    ],
    "name:msa_x_preferred":[
        "Ti\u00e9ningbou\u00e9"
    ],
    "name:und_x_variant":[
        "Ti\u00e9nigb\u00e9",
        "Ti\u00e9ningbu\u00e9"
    ],
    "wof:name":"Tieningboue",
    "wof:placetype":"locality"
},
  "geometry": {"coordinates":[-5.72147,8.17838],"type":"Point"}
}