{
  "type": "Feature",
  "properties": {
    "gn:admin1_code":"78.0",
    "gn:asciiname":"Gbeapieu",
    "gn:country_code":"CI",
    "gn:dem":284,
    "gn:feature_class":"P",
    "gn:feature_code":"PPL",
    "gn:name":"Gb\u00e9apieu",
    "gn:population":0,
    "gn:timezone":"Africa/Abidjan",
    "iso:country":"CI",
    "name:und_x_variant":[
        "Gb\u00e9apieu",
        "Gb\u00e9apleu"
    ],
    "wof:name":"Gbeapieu",
    "wof:placetype":"locality"
},
  "geometry": {"coordinates":[-8.10993,7.01148],"type":"Point"}
}