{
  "type": "Feature",
  "properties": {
    "gn:admin1_code":"81.0",
    "gn:asciiname":"Aman Salekro",
    "gn:country_code":"CI",
    "gn:dem":226,
    "gn:feature_class":"P",
    "gn:feature_code":"PPL",
    "gn:name":"Aman Sal\u00e9kro",
    "gn:population":0,
    "gn:timezone":"Africa/Abidjan",
    "iso:country":"CI",
    "name:und_x_variant":[
        "Sal\u00e9kro",
        "Aman Sal\u00e9kro"
    ],
    "wof:name":"Aman Salekro",
    "wof:placetype":"locality"
},
  "geometry": {"coordinates":[-5.57404,7.22577],"type":"Point"}
}