{
  "type": "Feature",
  "properties": {
    "gn:admin1_code":"97.0",
    "gn:asciiname":"Gbemazo",
    "gn:country_code":"CI",
    "gn:dem":405,
    "gn:feature_class":"P",
    "gn:feature_code":"PPL",
    "gn:name":"Gb\u00e9mazo",
    "gn:population":0,
    "gn:timezone":"Africa/Abidjan",
    "iso:country":"CI",
    "name:und_x_variant":[
        "Gb\u00e9manzo",
        "Gb\u00e9mazo"
    ],
    "wof:name":"Gbemazo",
    "wof:placetype":"locality"
},
  "geometry": {"coordinates":[-6.94,8.51306],"type":"Point"}
}