{
  "type": "Feature",
  "properties": {
    "gn:admin1_code":"93.0",
    "gn:asciiname":"Abiate II",
    "gn:country_code":"CI",
    "gn:dem":7,
    "gn:feature_class":"P",
    "gn:feature_code":"PPL",
    "gn:name":"Abiat\u00e9 II",
    "gn:population":0,
    "gn:timezone":"Africa/Abidjan",
    "iso:country":"CI",
    "wof:name":"Abiate II",
    "wof:placetype":"locality"
},
  "geometry": {"coordinates":[-4.29323,5.40773],"type":"Point"}
}