{
  "type": "Feature",
  "properties": {
    "gn:admin1_code":"92.0",
    "gn:asciiname":"Danbe",
    "gn:country_code":"CI",
    "gn:dem":359,
    "gn:feature_class":"P",
    "gn:feature_code":"PPL",
    "gn:name":"Danb\u00e9",
    "gn:population":0,
    "gn:timezone":"Africa/Abidjan",
    "iso:country":"CI",
    "name:und_x_variant":[
        "Dame",
        "Danb\u00e9"
    ],
    "wof:name":"Danbe",
    "wof:placetype":"locality"
},
  "geometry": {"coordinates":[-3.01446,8.06734],"type":"Point"}
}