{
  "type": "Feature",
  "properties": {
    "gn:admin1_code":"87",
    "gn:asciiname":"Negelavogo",
    "gn:country_code":"CI",
    "gn:dem":340,
    "gn:feature_class":"P",
    "gn:feature_code":"PPL",
    "gn:name":"N\u00e9g\u00e9lavogo",
    "gn:population":0,
    "gn:timezone":"Africa/Abidjan",
    "iso:country":"CI",
    "name:und_x_variant":[
        "N\u00e9gu\u00e9yavogo",
        "N\u00e9g\u00e9lavogo"
    ],
    "wof:name":"Negelavogo",
    "wof:placetype":"locality"
},
  "geometry": {"coordinates":[-5.20636,9.4925],"type":"Point"}
}