{
  "type": "Feature",
  "properties": {
    "gn:admin1_code":"82.0",
    "gn:asciiname":"Zobougo Laie",
    "gn:country_code":"CI",
    "gn:dem":58,
    "gn:feature_class":"P",
    "gn:feature_code":"PPL",
    "gn:name":"Zobougo Lai\u00e9",
    "gn:population":0,
    "gn:timezone":"Africa/Abidjan",
    "iso:country":"CI",
    "wof:name":"Zobougo Laie",
    "wof:placetype":"locality"
},
  "geometry": {"coordinates":[-4.32891,5.93327],"type":"Point"}
}