{
  "type": "Feature",
  "properties": {
    "gn:admin1_code":"77",
    "gn:asciiname":"Sienso-Koroni",
    "gn:country_code":"CI",
    "gn:dem":366,
    "gn:feature_class":"P",
    "gn:feature_code":"PPL",
    "gn:name":"Sienso-Koroni",
    "gn:population":0,
    "gn:timezone":"Africa/Abidjan",
    "iso:country":"CI",
    "wof:name":"Sienso-Koroni",
    "wof:placetype":"locality"
},
  "geometry": {"coordinates":[-7.1025,9.30564],"type":"Point"}
}