{
  "type": "Feature",
  "properties": {
    "gn:admin1_code":"94.0",
    "gn:asciiname":"Bondoukou",
    "gn:country_code":"CI",
    "gn:dem":13,
    "gn:feature_class":"P",
    "gn:feature_code":"PPL",
    "gn:name":"Bondoukou",
    "gn:population":0,
    "gn:timezone":"Africa/Abidjan",
    "iso:country":"CI",
    "name:ceb_x_preferred":[
        "Bondoukou"
    ],
    "name:dan_x_preferred":[
        "Bondoukou"
    ],
    "name:deu_x_preferred":[
        "Bondoukou"
    ],
    "name:fra_x_preferred":[
        "Bondoukou"
    ],
    "name:frr_x_preferred":[
        "Bondoukou"
    ],
    "name:heb_x_preferred":[
        "\u05d1\u05d5\u05e0\u05d3\u05d5\u05e7\u05d5"
    ],
    "name:hrv_x_preferred":[
        "Bondoukou"
    ],
    "name:ita_x_preferred":[
        "Bondoukou"
    ],
    "name:jpn_x_preferred":[
        "\u30dc\u30f3\u30c9\u30fc\u30af\u30fc"
    ],
    "name:lit_x_preferred":[
        "Bonduku"
    ],
    "name:msa_x_preferred":[
        "Bondoukou"
    ],
    "name:nld_x_preferred":[
        "Bondoukou"
    ],
    "name:pol_x_preferred":[
        "Bondoukou"
    ],
    "name:ron_x_preferred":[
        "Bondoukou"
    ],
    "name:rus_x_preferred":[
        "\u0411\u043e\u043d\u0434\u0443\u043a\u0443"
    ],
    "name:spa_x_preferred":[
        "Bondoukou"
    ],
    "name:swe_x_preferred":[
        "Bondoukou"
    ],
    "name:urd_x_preferred":[
        "\u0628\u0648\u0646\u062f\u0624\u06a9\u0624"
    ],
    "name:zho_x_preferred":[
        "\u90a6\u675c\u5eab"
    ],
    "wof:name":"Bondoukou",
    "wof:placetype":"locality"
},
  "geometry": {"coordinates":[-3.41754,5.21324],"type":"Point"}
}