{
  "type": "Feature",
  "properties": {
    "gn:admin1_code":"82.0",
    "gn:asciiname":"Kete",
    "gn:country_code":"CI",
    "gn:dem":77,
    "gn:feature_class":"P",
    "gn:feature_code":"PPL",
    "gn:name":"K\u00e9t\u00e9",
    "gn:population":0,
    "gn:timezone":"Africa/Abidjan",
    "iso:country":"CI",
    "name:ceb_x_preferred":[
        "Kete"
    ],
    "name:fra_x_preferred":[
        "Kete"
    ],
    "name:nno_x_preferred":[
        "Kete"
    ],
    "name:swe_x_preferred":[
        "Kete"
    ],
    "wof:name":"Kete",
    "wof:placetype":"locality"
},
  "geometry": {"coordinates":[-3.72061,5.67365],"type":"Point"}
}