{
  "type": "Feature",
  "properties": {
    "gn:admin1_code":"96.0",
    "gn:asciiname":"Gouedefla",
    "gn:country_code":"CI",
    "gn:dem":261,
    "gn:feature_class":"P",
    "gn:feature_code":"PPL",
    "gn:name":"Gou\u00e9d\u00e9fla",
    "gn:population":0,
    "gn:timezone":"Africa/Abidjan",
    "iso:country":"CI",
    "wof:name":"Gouedefla",
    "wof:placetype":"locality"
},
  "geometry": {"coordinates":[-6.00093,7.70982],"type":"Point"}
}