{
  "type": "Feature",
  "properties": {
    "gn:admin1_code":"97",
    "gn:asciiname":"Nigbila",
    "gn:country_code":"CI",
    "gn:dem":399,
    "gn:feature_class":"P",
    "gn:feature_code":"PPL",
    "gn:name":"Nigbila",
    "gn:population":0,
    "gn:timezone":"Africa/Abidjan",
    "iso:country":"CI",
    "name:und_x_variant":[
        "Nibila",
        "Nigbila"
    ],
    "wof:name":"Nigbila",
    "wof:placetype":"locality"
},
  "geometry": {"coordinates":[-7.46124,8.65938],"type":"Point"}
}