{
  "type": "Feature",
  "properties": {
    "gn:admin1_code":"92.0",
    "gn:asciiname":"Farankoye",
    "gn:country_code":"CI",
    "gn:dem":390,
    "gn:feature_class":"P",
    "gn:feature_code":"PPL",
    "gn:name":"Farankoye",
    "gn:population":0,
    "gn:timezone":"Africa/Abidjan",
    "iso:country":"CI",
    "wof:name":"Farankoye",
    "wof:placetype":"locality"
},
  "geometry": {"coordinates":[-3.3454,9.57266],"type":"Point"}
}