{
  "type": "Feature",
  "properties": {
    "gn:admin1_code":"76.0",
    "gn:asciiname":"Djiroutou",
    "gn:country_code":"CI",
    "gn:dem":108,
    "gn:feature_class":"P",
    "gn:feature_code":"PPL",
    "gn:name":"Djiroutou",
    "gn:population":0,
    "gn:timezone":"Africa/Abidjan",
    "iso:country":"CI",
    "name:und_x_variant":[
        "Patokla",
        "Fort Binger",
        "Guiroutou",
        "Djiroutou"
    ],
    "wof:name":"Djiroutou",
    "wof:placetype":"locality"
},
  "geometry": {"coordinates":[-7.28412,5.36758],"type":"Point"}
}