{
  "type": "Feature",
  "properties": {
    "gn:admin1_code":"77",
    "gn:asciiname":"Tomozomo",
    "gn:country_code":"CI",
    "gn:dem":453,
    "gn:feature_class":"P",
    "gn:feature_code":"PPL",
    "gn:name":"Tomozomo",
    "gn:population":0,
    "gn:timezone":"Africa/Abidjan",
    "iso:country":"CI",
    "name:und_x_variant":[
        "Tamozomo",
        "Tiomozomo",
        "Tomozomo"
    ],
    "wof:name":"Tomozomo",
    "wof:placetype":"locality"
},
  "geometry": {"coordinates":[-6.78786,9.87467],"type":"Point"}
}