{
  "type": "Feature",
  "properties": {
    "gn:admin1_code":"76",
    "gn:asciiname":"Petit-Pedro",
    "gn:country_code":"CI",
    "gn:dem":14,
    "gn:feature_class":"P",
    "gn:feature_code":"PPL",
    "gn:name":"Petit-P\u00e9dro",
    "gn:population":0,
    "gn:timezone":"Africa/Abidjan",
    "iso:country":"CI",
    "wof:name":"Petit-Pedro",
    "wof:placetype":"locality"
},
  "geometry": {"coordinates":[-6.55203,4.77349],"type":"Point"}
}