{
  "type": "Feature",
  "properties": {
    "gn:admin1_code":"97.0",
    "gn:asciiname":"Gbirikoro",
    "gn:country_code":"CI",
    "gn:dem":283,
    "gn:feature_class":"P",
    "gn:feature_code":"PPL",
    "gn:name":"Gbirikoro",
    "gn:population":0,
    "gn:timezone":"Africa/Abidjan",
    "iso:country":"CI",
    "wof:name":"Gbirikoro",
    "wof:placetype":"locality"
},
  "geometry": {"coordinates":[-6.2175,8.10806],"type":"Point"}
}