{
  "type": "Feature",
  "properties": {
    "gn:admin1_code":"97",
    "gn:asciiname":"Mwisola",
    "gn:country_code":"CI",
    "gn:dem":331,
    "gn:feature_class":"P",
    "gn:feature_code":"PPL",
    "gn:name":"Mwisola",
    "gn:population":0,
    "gn:timezone":"Africa/Abidjan",
    "iso:country":"CI",
    "wof:name":"Mwisola",
    "wof:placetype":"locality"
},
  "geometry": {"coordinates":[-6.16333,8.075],"type":"Point"}
}