{
  "type": "Feature",
  "properties": {
    "gn:admin1_code":"94.0",
    "gn:asciiname":"Akiekrou",
    "gn:country_code":"CI",
    "gn:dem":121,
    "gn:feature_class":"P",
    "gn:feature_code":"PPL",
    "gn:name":"Aki\u00e9krou",
    "gn:population":0,
    "gn:timezone":"Africa/Abidjan",
    "iso:country":"CI",
    "wof:name":"Akiekrou",
    "wof:placetype":"locality"
},
  "geometry": {"coordinates":[-3.67932,6.64448],"type":"Point"}
}