{
  "type": "Feature",
  "properties": {
    "gn:admin1_code":"87.0",
    "gn:asciiname":"Kafalafon",
    "gn:country_code":"CI",
    "gn:dem":358,
    "gn:feature_class":"P",
    "gn:feature_code":"PPL",
    "gn:name":"Kafalafon",
    "gn:population":0,
    "gn:timezone":"Africa/Abidjan",
    "iso:country":"CI",
    "wof:name":"Kafalafon",
    "wof:placetype":"locality"
},
  "geometry": {"coordinates":[-5.83615,10.08],"type":"Point"}
}