{
  "type": "Feature",
  "properties": {
    "gn:admin1_code":"92",
    "gn:asciiname":"Saboukba",
    "gn:country_code":"CI",
    "gn:dem":333,
    "gn:feature_class":"P",
    "gn:feature_code":"PPL",
    "gn:name":"Saboukba",
    "gn:population":0,
    "gn:timezone":"Africa/Abidjan",
    "iso:country":"CI",
    "wof:name":"Saboukba",
    "wof:placetype":"locality"
},
  "geometry": {"coordinates":[-3.25,8.58333],"type":"Point"}
}