{
  "type": "Feature",
  "properties": {
    "gn:admin1_code":"82.0",
    "gn:asciiname":"Djechou",
    "gn:country_code":"CI",
    "gn:dem":66,
    "gn:feature_class":"P",
    "gn:feature_code":"PPL",
    "gn:name":"Djechou",
    "gn:population":0,
    "gn:timezone":"Africa/Abidjan",
    "iso:country":"CI",
    "wof:name":"Djechou",
    "wof:placetype":"locality"
},
  "geometry": {"coordinates":[-4.20047,5.7363],"type":"Point"}
}