{
  "type": "Feature",
  "properties": {
    "gn:admin1_code":"82.0",
    "gn:asciiname":"Ndrimin",
    "gn:country_code":"CI",
    "gn:dem":79,
    "gn:feature_class":"P",
    "gn:feature_code":"PPL",
    "gn:name":"Ndrimin",
    "gn:population":0,
    "gn:timezone":"Africa/Abidjan",
    "iso:country":"CI",
    "wof:name":"Ndrimin",
    "wof:placetype":"locality"
},
  "geometry": {"coordinates":[-4.36997,5.9034],"type":"Point"}
}