{
  "type": "Feature",
  "properties": {
    "gn:admin1_code":"81",
    "gn:asciiname":"Kokoun-Koimikro",
    "gn:country_code":"CI",
    "gn:dem":192,
    "gn:feature_class":"P",
    "gn:feature_code":"PPL",
    "gn:name":"Kokoun-Koimikro",
    "gn:population":0,
    "gn:timezone":"Africa/Abidjan",
    "iso:country":"CI",
    "wof:name":"Kokoun-Koimikro",
    "wof:placetype":"locality"
},
  "geometry": {"coordinates":[-4.78389,7.28278],"type":"Point"}
}