{
  "type": "Feature",
  "properties": {
    "gn:admin1_code":"93.0",
    "gn:asciiname":"Songon",
    "gn:country_code":"CI",
    "gn:dem":19,
    "gn:feature_class":"P",
    "gn:feature_code":"PPLA4",
    "gn:name":"Songon",
    "gn:population":0,
    "gn:timezone":"Africa/Abidjan",
    "iso:country":"CI",
    "name:fra_x_preferred":[
        "Songon"
    ],
    "name:msa_x_preferred":[
        "Songon"
    ],
    "wof:name":"Songon",
    "wof:placetype":"locality"
},
  "geometry": {"coordinates":[-4.25415,5.3196],"type":"Point"}
}