{
  "type": "Feature",
  "properties": {
    "gn:admin1_code":"81.0",
    "gn:asciiname":"Akrarinkro",
    "gn:country_code":"CI",
    "gn:dem":256,
    "gn:feature_class":"P",
    "gn:feature_code":"PPL",
    "gn:name":"Akrarinkro",
    "gn:population":0,
    "gn:timezone":"Africa/Abidjan",
    "iso:country":"CI",
    "wof:name":"Akrarinkro",
    "wof:placetype":"locality"
},
  "geometry": {"coordinates":[-3.85112,7.39884],"type":"Point"}
}