{
  "type": "Feature",
  "properties": {
    "gn:admin1_code":"97.0",
    "gn:asciiname":"Dourougbe",
    "gn:country_code":"CI",
    "gn:dem":416,
    "gn:feature_class":"P",
    "gn:feature_code":"PPL",
    "gn:name":"Dourougb\u00e9",
    "gn:population":0,
    "gn:timezone":"Africa/Abidjan",
    "iso:country":"CI",
    "name:und_x_variant":[
        "Dougougou\u00e9",
        "Dougougb\u00e9",
        "Dourougb\u00e9"
    ],
    "wof:name":"Dourougbe",
    "wof:placetype":"locality"
},
  "geometry": {"coordinates":[-6.96766,8.43871],"type":"Point"}
}