{
  "type": "Feature",
  "properties": {
    "gn:admin1_code":"78.0",
    "gn:asciiname":"Greta",
    "gn:country_code":"CI",
    "gn:dem":473,
    "gn:feature_class":"P",
    "gn:feature_code":"PPL",
    "gn:name":"Greta",
    "gn:population":0,
    "gn:timezone":"Africa/Abidjan",
    "iso:country":"CI",
    "wof:name":"Greta",
    "wof:placetype":"locality"
},
  "geometry": {"coordinates":[-7.82475,7.80905],"type":"Point"}
}