{
  "type": "Feature",
  "properties": {
    "gn:admin1_code":"78.0",
    "gn:asciiname":"Greta",
    "gn:country_code":"CI",
    "gn:dem":473,
    "gn:feature_class":"P",
    "gn:feature_code":"PPL",
    "gn:name":"Greta",
    "gn:population":0,
    "gn:timezone":"Africa/Abidjan",
    "iso:country":"CI",
    "name:deu_x_preferred":[
        "Greta"
    ],
    "name:fra_x_preferred":[
        "Greta"
    ],
    "name:ita_x_preferred":[
        "Greta"
    ],
    "name:jpn_x_preferred":[
        "\u30b0\u30ec\u30bf"
    ],
    "name:nld_x_preferred":[
        "Greta"
    ],
    "name:por_x_preferred":[
        "Greta"
    ],
    "name:rus_x_preferred":[
        "\u0413\u0440\u0435\u0442\u0430"
    ],
    "name:spa_x_preferred":[
        "Greta"
    ],
    "wof:name":"Greta",
    "wof:placetype":"locality"
},
  "geometry": {"coordinates":[-7.82475,7.80905],"type":"Point"}
}