{
  "type": "Feature",
  "properties": {
    "gn:admin1_code":"94.0",
    "gn:asciiname":"Wehou",
    "gn:country_code":"CI",
    "gn:dem":113,
    "gn:feature_class":"P",
    "gn:feature_code":"PPL",
    "gn:name":"Wehou",
    "gn:population":0,
    "gn:timezone":"Africa/Abidjan",
    "iso:country":"CI",
    "wof:name":"Wehou",
    "wof:placetype":"locality"
},
  "geometry": {"coordinates":[-3.45092,5.52399],"type":"Point"}
}