{
  "type": "Feature",
  "properties": {
    "gn:admin1_code":"95",
    "gn:asciiname":"Tiegbayo",
    "gn:country_code":"CI",
    "gn:dem":235,
    "gn:feature_class":"P",
    "gn:feature_code":"PPL",
    "gn:name":"Ti\u00e9gbayo",
    "gn:population":0,
    "gn:timezone":"Africa/Abidjan",
    "iso:country":"CI",
    "name:und_x_variant":[
        "Ti\u00e9gbayo",
        "Tiegbahio"
    ],
    "wof:name":"Tiegbayo",
    "wof:placetype":"locality"
},
  "geometry": {"coordinates":[-5.97681,6.46946],"type":"Point"}
}