{
  "type": "Feature",
  "properties": {
    "gn:admin1_code":"82.0",
    "gn:asciiname":"Bekouin Aman",
    "gn:country_code":"CI",
    "gn:dem":112,
    "gn:feature_class":"P",
    "gn:feature_code":"PPL",
    "gn:name":"B\u00e9kouin Aman",
    "gn:population":0,
    "gn:timezone":"Africa/Abidjan",
    "iso:country":"CI",
    "wof:name":"Bekouin Aman",
    "wof:placetype":"locality"
},
  "geometry": {"coordinates":[-3.56794,5.81769],"type":"Point"}
}