{
  "type": "Feature",
  "properties": {
    "gn:admin1_code":"82.0",
    "gn:asciiname":"Yapi Okun",
    "gn:country_code":"CI",
    "gn:dem":52,
    "gn:feature_class":"P",
    "gn:feature_code":"PPL",
    "gn:name":"Yapi Okun",
    "gn:population":0,
    "gn:timezone":"Africa/Abidjan",
    "iso:country":"CI",
    "wof:name":"Yapi Okun",
    "wof:placetype":"locality"
},
  "geometry": {"coordinates":[-3.92041,5.77281],"type":"Point"}
}