{
  "type": "Feature",
  "properties": {
    "gn:admin1_code":"96",
    "gn:asciiname":"Oueproye",
    "gn:country_code":"CI",
    "gn:dem":280,
    "gn:feature_class":"P",
    "gn:feature_code":"PPL",
    "gn:name":"Oueproye",
    "gn:population":0,
    "gn:timezone":"Africa/Abidjan",
    "iso:country":"CI",
    "wof:name":"Oueproye",
    "wof:placetype":"locality"
},
  "geometry": {"coordinates":[-5.84694,7.5025],"type":"Point"}
}