{
  "type": "Feature",
  "properties": {
    "gn:admin1_code":"81",
    "gn:asciiname":"Nziblekro",
    "gn:country_code":"CI",
    "gn:dem":96,
    "gn:feature_class":"P",
    "gn:feature_code":"PPL",
    "gn:name":"Nzibl\u00e9kro",
    "gn:population":0,
    "gn:timezone":"Africa/Abidjan",
    "iso:country":"CI",
    "wof:name":"Nziblekro",
    "wof:placetype":"locality"
},
  "geometry": {"coordinates":[-4.34034,6.8684],"type":"Point"}
}