{
  "type": "Feature",
  "properties": {
    "gn:admin1_code":"94.0",
    "gn:asciiname":"Ayebo",
    "gn:country_code":"CI",
    "gn:dem":85,
    "gn:feature_class":"P",
    "gn:feature_code":"PPL",
    "gn:name":"Ay\u00e9bo",
    "gn:population":0,
    "gn:timezone":"Africa/Abidjan",
    "iso:country":"CI",
    "wof:name":"Ayebo",
    "wof:placetype":"locality"
},
  "geometry": {"coordinates":[-3.26408,5.44242],"type":"Point"}
}