{
  "type": "Feature",
  "properties": {
    "gn:admin1_code":"78.0",
    "gn:asciiname":"Bloma",
    "gn:country_code":"CI",
    "gn:dem":564,
    "gn:feature_class":"P",
    "gn:feature_code":"PPL",
    "gn:name":"Bloma",
    "gn:population":0,
    "gn:timezone":"Africa/Abidjan",
    "iso:country":"CI",
    "name:und_x_variant":[
        "Blomba",
        "Biomba",
        "Bloma"
    ],
    "wof:name":"Bloma",
    "wof:placetype":"locality"
},
  "geometry": {"coordinates":[-8.05912,7.80638],"type":"Point"}
}