{
  "type": "Feature",
  "properties": {
    "gn:admin1_code":"81",
    "gn:asciiname":"Nguissankro",
    "gn:country_code":"CI",
    "gn:dem":151,
    "gn:feature_class":"P",
    "gn:feature_code":"PPL",
    "gn:name":"Nguissankro",
    "gn:population":0,
    "gn:timezone":"Africa/Abidjan",
    "iso:country":"CI",
    "wof:name":"Nguissankro",
    "wof:placetype":"locality"
},
  "geometry": {"coordinates":[-4.23333,7.01667],"type":"Point"}
}