{
  "type": "Feature",
  "properties": {
    "gn:admin1_code":"90",
    "gn:asciiname":"Kouame Assekro",
    "gn:country_code":"CI",
    "gn:dem":297,
    "gn:feature_class":"P",
    "gn:feature_code":"PPL",
    "gn:name":"Kouam\u00e9 Assekro",
    "gn:population":0,
    "gn:timezone":"Africa/Abidjan",
    "iso:country":"CI",
    "wof:name":"Kouame Assekro",
    "wof:placetype":"locality"
},
  "geometry": {"coordinates":[-5.02298,7.85321],"type":"Point"}
}