{
  "type": "Feature",
  "properties": {
    "gn:admin1_code":"87",
    "gn:asciiname":"Sisyan",
    "gn:country_code":"CI",
    "gn:dem":372,
    "gn:feature_class":"P",
    "gn:feature_code":"PPL",
    "gn:name":"Sisyan",
    "gn:population":0,
    "gn:timezone":"Africa/Abidjan",
    "iso:country":"CI",
    "name:und_x_variant":[
        "Sissian",
        "Sisyan"
    ],
    "wof:name":"Sisyan",
    "wof:placetype":"locality"
},
  "geometry": {"coordinates":[-5.71478,9.3815],"type":"Point"}
}