{
  "type": "Feature",
  "properties": {
    "gn:admin1_code":"82",
    "gn:asciiname":"Laoguie",
    "gn:country_code":"CI",
    "gn:dem":64,
    "gn:feature_class":"P",
    "gn:feature_code":"PPL",
    "gn:name":"Laogui\u00e9",
    "gn:population":0,
    "gn:timezone":"Africa/Abidjan",
    "iso:country":"CI",
    "name:und_x_variant":[
        "Laogul\u00e9",
        "Lahogui\u00e9",
        "Laogui\u00e9"
    ],
    "wof:name":"Laoguie",
    "wof:placetype":"locality"
},
  "geometry": {"coordinates":[-4.1677,5.97693],"type":"Point"}
}