{
  "type": "Feature",
  "properties": {
    "gn:admin1_code":"97",
    "gn:asciiname":"Meneni",
    "gn:country_code":"CI",
    "gn:dem":378,
    "gn:feature_class":"P",
    "gn:feature_code":"PPL",
    "gn:name":"M\u00e9n\u00e9ni",
    "gn:population":0,
    "gn:timezone":"Africa/Abidjan",
    "iso:country":"CI",
    "name:und_x_variant":[
        "M\u00e9r\u00e9ni",
        "M\u00e9n\u00e9ni"
    ],
    "wof:name":"Meneni",
    "wof:placetype":"locality"
},
  "geometry": {"coordinates":[-6.18136,8.36245],"type":"Point"}
}