{
  "type": "Feature",
  "properties": {
    "gn:admin1_code":"97.0",
    "gn:asciiname":"Blikro",
    "gn:country_code":"CI",
    "gn:dem":212,
    "gn:feature_class":"P",
    "gn:feature_code":"PPL",
    "gn:name":"Blikro",
    "gn:population":0,
    "gn:timezone":"Africa/Abidjan",
    "iso:country":"CI",
    "name:und_x_variant":[
        "Brikro"
    ],
    "wof:name":"Blikro",
    "wof:placetype":"locality"
},
  "geometry": {"coordinates":[-5.70555,7.65528],"type":"Point"}
}