{
  "type": "Feature",
  "properties": {
    "gn:admin1_code":"82",
    "gn:asciiname":"Kodiebouman",
    "gn:country_code":"CI",
    "gn:dem":111,
    "gn:feature_class":"P",
    "gn:feature_code":"PPL",
    "gn:name":"Kodi\u00e9bouman",
    "gn:population":0,
    "gn:timezone":"Africa/Abidjan",
    "iso:country":"CI",
    "name:und_x_variant":[
        "Kondi\u00e9bouma",
        "Kondi\u00e9bouman",
        "Kodi\u00e9bouman"
    ],
    "wof:name":"Kodiebouman",
    "wof:placetype":"locality"
},
  "geometry": {"coordinates":[-4.54056,6.22107],"type":"Point"}
}