{
  "type": "Feature",
  "properties": {
    "gn:admin1_code":"82.0",
    "gn:asciiname":"Manin Dai",
    "gn:country_code":"CI",
    "gn:dem":87,
    "gn:feature_class":"P",
    "gn:feature_code":"PPL",
    "gn:name":"Manin Dai",
    "gn:population":0,
    "gn:timezone":"Africa/Abidjan",
    "iso:country":"CI",
    "wof:name":"Manin Dai",
    "wof:placetype":"locality"
},
  "geometry": {"coordinates":[-3.88412,5.97501],"type":"Point"}
}