{
  "type": "Feature",
  "properties": {
    "gn:admin1_code":"76.0",
    "gn:admin2_code":"11153077.0",
    "gn:admin3_code":"2281118.0",
    "gn:asciiname":"Gnakapero",
    "gn:country_code":"CI",
    "gn:dem":85,
    "gn:feature_class":"P",
    "gn:feature_code":"PPL",
    "gn:name":"Gnakap\u00e9ro",
    "gn:population":0,
    "gn:timezone":"Africa/Abidjan",
    "iso:country":"CI",
    "wof:name":"Gnakapero",
    "wof:placetype":"locality"
},
  "geometry": {"coordinates":[-7.44298,4.37479],"type":"Point"}
}