{
  "type": "Feature",
  "properties": {
    "gn:admin1_code":"78.0",
    "gn:asciiname":"Glakon",
    "gn:country_code":"CI",
    "gn:dem":264,
    "gn:feature_class":"P",
    "gn:feature_code":"PPL",
    "gn:name":"Glakon",
    "gn:population":0,
    "gn:timezone":"Africa/Abidjan",
    "iso:country":"CI",
    "wof:name":"Glakon",
    "wof:placetype":"locality"
},
  "geometry": {"coordinates":[-8.27897,6.58489],"type":"Point"}
}