{
  "type": "Feature",
  "properties": {
    "gn:admin1_code":"87",
    "gn:asciiname":"Tindara",
    "gn:country_code":"CI",
    "gn:dem":386,
    "gn:feature_class":"P",
    "gn:feature_code":"PPL",
    "gn:name":"Tindara",
    "gn:population":0,
    "gn:timezone":"Africa/Abidjan",
    "iso:country":"CI",
    "name:und_x_variant":[
        "Tindarala",
        "Tind\u00e9r\u00e9la",
        "Zanasso",
        "Tindara"
    ],
    "wof:name":"Tindara",
    "wof:placetype":"locality"
},
  "geometry": {"coordinates":[-6.47599,10.00959],"type":"Point"}
}