{
  "type": "Feature",
  "properties": {
    "gn:admin1_code":"95.0",
    "gn:asciiname":"Behiri",
    "gn:country_code":"CI",
    "gn:dem":182,
    "gn:feature_class":"P",
    "gn:feature_code":"PPL",
    "gn:name":"B\u00e9hiri",
    "gn:population":0,
    "gn:timezone":"Africa/Abidjan",
    "iso:country":"CI",
    "wof:name":"Behiri",
    "wof:placetype":"locality"
},
  "geometry": {"coordinates":[-5.44031,5.63464],"type":"Point"}
}