{
  "type": "Feature",
  "properties": {
    "gn:admin1_code":"82.0",
    "gn:asciiname":"Achi",
    "gn:country_code":"CI",
    "gn:dem":91,
    "gn:feature_class":"P",
    "gn:feature_code":"PPL",
    "gn:name":"Achi",
    "gn:population":0,
    "gn:timezone":"Africa/Abidjan",
    "iso:country":"CI",
    "wof:name":"Achi",
    "wof:placetype":"locality"
},
  "geometry": {"coordinates":[-3.71509,5.66435],"type":"Point"}
}