{
  "type": "Feature",
  "properties": {
    "gn:admin1_code":"82.0",
    "gn:asciiname":"Abe",
    "gn:country_code":"CI",
    "gn:dem":73,
    "gn:feature_class":"P",
    "gn:feature_code":"PPL",
    "gn:name":"Ab\u00e9",
    "gn:population":0,
    "gn:timezone":"Africa/Abidjan",
    "iso:country":"CI",
    "wof:name":"Abe",
    "wof:placetype":"locality"
},
  "geometry": {"coordinates":[-4.42904,5.92845],"type":"Point"}
}