{
  "type": "Feature",
  "properties": {
    "gn:admin1_code":"82.0",
    "gn:asciiname":"Taria",
    "gn:country_code":"CI",
    "gn:dem":103,
    "gn:feature_class":"P",
    "gn:feature_code":"PPL",
    "gn:name":"Taria",
    "gn:population":0,
    "gn:timezone":"Africa/Abidjan",
    "iso:country":"CI",
    "wof:name":"Taria",
    "wof:placetype":"locality"
},
  "geometry": {"coordinates":[-3.44141,5.96582],"type":"Point"}
}