{
  "type": "Feature",
  "properties": {
    "gn:admin1_code":"90",
    "gn:asciiname":"Natere-Dioulasso",
    "gn:country_code":"CI",
    "gn:dem":259,
    "gn:feature_class":"P",
    "gn:feature_code":"PPL",
    "gn:name":"Nat\u00e9r\u00e9-Dioulasso",
    "gn:population":0,
    "gn:timezone":"Africa/Abidjan",
    "iso:country":"CI",
    "wof:name":"Natere-Dioulasso",
    "wof:placetype":"locality"
},
  "geometry": {"coordinates":[-4.32434,8.29665],"type":"Point"}
}