{
  "type": "Feature",
  "properties": {
    "gn:admin1_code":"92",
    "gn:asciiname":"Nassian",
    "gn:country_code":"CI",
    "gn:dem":353,
    "gn:feature_class":"P",
    "gn:feature_code":"PPLA3",
    "gn:name":"Nassian",
    "gn:population":0,
    "gn:timezone":"Africa/Abidjan",
    "iso:country":"CI",
    "name:fra_x_preferred":[
        "Nassian"
    ],
    "name:ita_x_preferred":[
        "Nassian"
    ],
    "name:msa_x_preferred":[
        "Nassian"
    ],
    "name:spa_x_preferred":[
        "Nassian"
    ],
    "name:und_x_variant":[
        "Nasian",
        "Nasiam"
    ],
    "wof:name":"Nassian",
    "wof:placetype":"locality"
},
  "geometry": {"coordinates":[-3.47152,8.45275],"type":"Point"}
}