{
  "type": "Feature",
  "properties": {
    "gn:admin1_code":"96.0",
    "gn:asciiname":"Balogi",
    "gn:country_code":"CI",
    "gn:dem":260,
    "gn:feature_class":"P",
    "gn:feature_code":"PPL",
    "gn:name":"Balogi",
    "gn:population":0,
    "gn:timezone":"Africa/Abidjan",
    "iso:country":"CI",
    "name:und_x_variant":[
        "Balogui",
        "Balogi"
    ],
    "wof:name":"Balogi",
    "wof:placetype":"locality"
},
  "geometry": {"coordinates":[-6.19964,7.50761],"type":"Point"}
}