{
  "type": "Feature",
  "properties": {
    "gn:admin1_code":"92.0",
    "gn:asciiname":"Bondo-Koulanko",
    "gn:country_code":"CI",
    "gn:dem":334,
    "gn:feature_class":"P",
    "gn:feature_code":"PPL",
    "gn:name":"Bondo-Koulanko",
    "gn:population":0,
    "gn:timezone":"Africa/Abidjan",
    "iso:country":"CI",
    "name:und_x_variant":[
        "Boundo-Koulanko",
        "Bondo-Koulanko"
    ],
    "wof:name":"Bondo-Koulanko",
    "wof:placetype":"locality"
},
  "geometry": {"coordinates":[-3.18949,8.2188],"type":"Point"}
}