{
  "type": "Feature",
  "properties": {
    "gn:admin1_code":"81",
    "gn:asciiname":"Yaokro",
    "gn:country_code":"CI",
    "gn:dem":212,
    "gn:feature_class":"P",
    "gn:feature_code":"PPL",
    "gn:name":"Yaokro",
    "gn:population":0,
    "gn:timezone":"Africa/Abidjan",
    "iso:country":"CI",
    "wof:name":"Yaokro",
    "wof:placetype":"locality"
},
  "geometry": {"coordinates":[-3.9857,7.74595],"type":"Point"}
}