{
  "type": "Feature",
  "properties": {
    "gn:admin1_code":"92.0",
    "gn:asciiname":"Bake",
    "gn:country_code":"CI",
    "gn:dem":515,
    "gn:feature_class":"P",
    "gn:feature_code":"PPL",
    "gn:name":"Bak\u00e9",
    "gn:population":0,
    "gn:timezone":"Africa/Abidjan",
    "iso:country":"CI",
    "wof:name":"Bake",
    "wof:placetype":"locality"
},
  "geometry": {"coordinates":[-2.90694,8.19346],"type":"Point"}
}