{
  "type": "Feature",
  "properties": {
    "gn:admin1_code":"78",
    "gn:asciiname":"Kodoupleu",
    "gn:country_code":"CI",
    "gn:dem":324,
    "gn:feature_class":"P",
    "gn:feature_code":"PPL",
    "gn:name":"Kodoupleu",
    "gn:population":0,
    "gn:timezone":"Africa/Abidjan",
    "iso:country":"CI",
    "wof:name":"Kodoupleu",
    "wof:placetype":"locality"
},
  "geometry": {"coordinates":[-7.5811,7.20334],"type":"Point"}
}