{
  "type": "Feature",
  "properties": {
    "gn:admin1_code":"87",
    "gn:asciiname":"Zouani",
    "gn:country_code":"CI",
    "gn:dem":343,
    "gn:feature_class":"P",
    "gn:feature_code":"PPL",
    "gn:name":"Zouani",
    "gn:population":0,
    "gn:timezone":"Africa/Abidjan",
    "iso:country":"CI",
    "wof:name":"Zouani",
    "wof:placetype":"locality"
},
  "geometry": {"coordinates":[-6.1194,9.85502],"type":"Point"}
}