{
  "type": "Feature",
  "properties": {
    "gn:admin1_code":"87",
    "gn:asciiname":"Teneguera",
    "gn:country_code":"CI",
    "gn:dem":321,
    "gn:feature_class":"P",
    "gn:feature_code":"PPL",
    "gn:name":"T\u00e9n\u00e9gu\u00e9ra",
    "gn:population":0,
    "gn:timezone":"Africa/Abidjan",
    "iso:country":"CI",
    "name:und_x_variant":[
        "Teningara",
        "Teninguera",
        "T\u00e9n\u00e9gu\u00e9ra"
    ],
    "wof:name":"Teneguera",
    "wof:placetype":"locality"
},
  "geometry": {"coordinates":[-4.58599,9.09681],"type":"Point"}
}