{
  "type": "Feature",
  "properties": {
    "gn:admin1_code":"78.0",
    "gn:asciiname":"Doueleu",
    "gn:country_code":"CI",
    "gn:dem":255,
    "gn:feature_class":"P",
    "gn:feature_code":"PPL",
    "gn:name":"Dou\u00e9leu",
    "gn:population":0,
    "gn:timezone":"Africa/Abidjan",
    "iso:country":"CI",
    "wof:name":"Doueleu",
    "wof:placetype":"locality"
},
  "geometry": {"coordinates":[-8.3062,6.96005],"type":"Point"}
}