{
  "type": "Feature",
  "properties": {
    "gn:admin1_code":"87",
    "gn:asciiname":"Lamekaha",
    "gn:country_code":"CI",
    "gn:dem":368,
    "gn:feature_class":"P",
    "gn:feature_code":"PPL",
    "gn:name":"Lam\u00e9kaha",
    "gn:population":0,
    "gn:timezone":"Africa/Abidjan",
    "iso:country":"CI",
    "name:und_x_variant":[
        "Daziovogo",
        "Lam\u00e9kaha"
    ],
    "wof:name":"Lamekaha",
    "wof:placetype":"locality"
},
  "geometry": {"coordinates":[-5.03701,9.35217],"type":"Point"}
}