{
  "type": "Feature",
  "properties": {
    "gn:admin1_code":"96",
    "gn:asciiname":"Porabenefla",
    "gn:country_code":"CI",
    "gn:dem":245,
    "gn:feature_class":"P",
    "gn:feature_code":"PPL",
    "gn:name":"Porab\u00e9n\u00e9fla",
    "gn:population":0,
    "gn:timezone":"Africa/Abidjan",
    "iso:country":"CI",
    "name:und_x_variant":[
        "Porab\u00e9n\u00e9fla",
        "Poab\u00e9n\u00e9fla"
    ],
    "wof:name":"Porabenefla",
    "wof:placetype":"locality"
},
  "geometry": {"coordinates":[-5.79144,6.55904],"type":"Point"}
}