{
  "type": "Feature",
  "properties": {
    "gn:admin1_code":"82.0",
    "gn:asciiname":"Ahoutoue",
    "gn:country_code":"CI",
    "gn:dem":42,
    "gn:feature_class":"P",
    "gn:feature_code":"PPL",
    "gn:name":"Ahoutou\u00e9",
    "gn:population":0,
    "gn:timezone":"Africa/Abidjan",
    "iso:country":"CI",
    "name:und_x_variant":[
        "Autou\u00e9",
        "Aoutou\u00e9",
        "Ahoutou\u00e9"
    ],
    "wof:name":"Ahoutoue",
    "wof:placetype":"locality"
},
  "geometry": {"coordinates":[-3.80419,5.47429],"type":"Point"}
}