{
  "type": "Feature",
  "properties": {
    "gn:admin1_code":"93.0",
    "gn:asciiname":"Kouadio Ncho",
    "gn:country_code":"CI",
    "gn:dem":29,
    "gn:feature_class":"P",
    "gn:feature_code":"PPL",
    "gn:name":"Kouadio Ncho",
    "gn:population":0,
    "gn:timezone":"Africa/Abidjan",
    "iso:country":"CI",
    "wof:name":"Kouadio Ncho",
    "wof:placetype":"locality"
},
  "geometry": {"coordinates":[-4.22263,5.4081],"type":"Point"}
}