{
  "type": "Feature",
  "properties": {
    "gn:admin1_code":"93.0",
    "gn:asciiname":"Brahima Toure",
    "gn:country_code":"CI",
    "gn:dem":92,
    "gn:feature_class":"P",
    "gn:feature_code":"PPL",
    "gn:name":"Brahima Tour\u00e9",
    "gn:population":0,
    "gn:timezone":"Africa/Abidjan",
    "iso:country":"CI",
    "wof:name":"Brahima Toure",
    "wof:placetype":"locality"
},
  "geometry": {"coordinates":[-3.97603,5.38511],"type":"Point"}
}