{
  "type": "Feature",
  "properties": {
    "gn:admin1_code":"78.0",
    "gn:asciiname":"Glaou",
    "gn:country_code":"CI",
    "gn:dem":242,
    "gn:feature_class":"P",
    "gn:feature_code":"PPL",
    "gn:name":"Glaou",
    "gn:population":0,
    "gn:timezone":"Africa/Abidjan",
    "iso:country":"CI",
    "wof:name":"Glaou",
    "wof:placetype":"locality"
},
  "geometry": {"coordinates":[-7.37005,6.62573],"type":"Point"}
}