{
  "type": "Feature",
  "properties": {
    "gn:admin1_code":"94.0",
    "gn:asciiname":"Kacoukro",
    "gn:country_code":"CI",
    "gn:dem":63,
    "gn:feature_class":"P",
    "gn:feature_code":"PPL",
    "gn:name":"Kacoukro",
    "gn:population":0,
    "gn:timezone":"Africa/Abidjan",
    "iso:country":"CI",
    "wof:name":"Kacoukro",
    "wof:placetype":"locality"
},
  "geometry": {"coordinates":[-3.37752,5.29605],"type":"Point"}
}