{
  "type": "Feature",
  "properties": {
    "gn:admin1_code":"96",
    "gn:asciiname":"Zougounefla",
    "gn:country_code":"CI",
    "gn:dem":268,
    "gn:feature_class":"P",
    "gn:feature_code":"PPL",
    "gn:name":"Zougoun\u00e9fla",
    "gn:population":0,
    "gn:timezone":"Africa/Abidjan",
    "iso:country":"CI",
    "name:fra_x_preferred":[
        "Zougoun\u00e9fla"
    ],
    "name:msa_x_preferred":[
        "Zougoun\u00e9fla"
    ],
    "wof:name":"Zougounefla",
    "wof:placetype":"locality"
},
  "geometry": {"coordinates":[-5.92868,7.71034],"type":"Point"}
}