{
  "type": "Feature",
  "properties": {
    "gn:admin1_code":"77.0",
    "gn:asciiname":"Bogodougou",
    "gn:country_code":"CI",
    "gn:dem":442,
    "gn:feature_class":"P",
    "gn:feature_code":"PPL",
    "gn:name":"Bogodougou",
    "gn:population":0,
    "gn:timezone":"Africa/Abidjan",
    "iso:country":"CI",
    "wof:name":"Bogodougou",
    "wof:placetype":"locality"
},
  "geometry": {"coordinates":[-7.89739,9.68277],"type":"Point"}
}