{
  "type": "Feature",
  "properties": {
    "gn:admin1_code":"82.0",
    "gn:asciiname":"Abou Abe",
    "gn:country_code":"CI",
    "gn:dem":57,
    "gn:feature_class":"P",
    "gn:feature_code":"PPL",
    "gn:name":"Abou Ab\u00e9",
    "gn:population":0,
    "gn:timezone":"Africa/Abidjan",
    "iso:country":"CI",
    "wof:name":"Abou Abe",
    "wof:placetype":"locality"
},
  "geometry": {"coordinates":[-4.07518,5.80238],"type":"Point"}
}