{
  "type": "Feature",
  "properties": {
    "gn:admin1_code":"78.0",
    "gn:asciiname":"Zouzousso II",
    "gn:country_code":"CI",
    "gn:dem":450,
    "gn:feature_class":"P",
    "gn:feature_code":"PPL",
    "gn:name":"Zouzousso II",
    "gn:population":0,
    "gn:timezone":"Africa/Abidjan",
    "iso:country":"CI",
    "wof:name":"Zouzousso II",
    "wof:placetype":"locality"
},
  "geometry": {"coordinates":[-7.65165,7.82027],"type":"Point"}
}