{
  "type": "Feature",
  "properties": {
    "gn:admin1_code":"92.0",
    "gn:asciiname":"Bagelebe",
    "gn:country_code":"CI",
    "gn:dem":516,
    "gn:feature_class":"P",
    "gn:feature_code":"PPL",
    "gn:name":"Bag\u00e9l\u00e9b\u00e9",
    "gn:population":0,
    "gn:timezone":"Africa/Abidjan",
    "iso:country":"CI",
    "wof:name":"Bagelebe",
    "wof:placetype":"locality"
},
  "geometry": {"coordinates":[-2.95221,8.11894],"type":"Point"}
}