{
  "type": "Feature",
  "properties": {
    "gn:admin1_code":"92.0",
    "gn:asciiname":"Braye",
    "gn:country_code":"CI",
    "gn:dem":181,
    "gn:feature_class":"P",
    "gn:feature_code":"PPL",
    "gn:name":"Bray\u00e9",
    "gn:population":0,
    "gn:timezone":"Africa/Abidjan",
    "iso:country":"CI",
    "name:bul_x_preferred":[
        "\u0411\u0440\u0435\u0439"
    ],
    "name:deu_x_preferred":[
        "Braye"
    ],
    "name:fra_x_preferred":[
        "Braye"
    ],
    "name:hye_x_preferred":[
        "\u0532\u0580\u0565\u0575"
    ],
    "name:nld_x_preferred":[
        "Braye"
    ],
    "name:por_x_preferred":[
        "Braye"
    ],
    "name:rus_x_preferred":[
        "\u0411\u0440\u0435\u0439"
    ],
    "name:swe_x_preferred":[
        "Braye"
    ],
    "name:ukr_x_preferred":[
        "\u0411\u0440\u0435\u0439"
    ],
    "wof:name":"Braye",
    "wof:placetype":"locality"
},
  "geometry": {"coordinates":[-3.36143,7.62994],"type":"Point"}
}