{
  "type": "Feature",
  "properties": {
    "gn:admin1_code":"92.0",
    "gn:asciiname":"Braye",
    "gn:country_code":"CI",
    "gn:dem":181,
    "gn:feature_class":"P",
    "gn:feature_code":"PPL",
    "gn:name":"Bray\u00e9",
    "gn:population":0,
    "gn:timezone":"Africa/Abidjan",
    "iso:country":"CI",
    "wof:name":"Braye",
    "wof:placetype":"locality"
},
  "geometry": {"coordinates":[-3.36143,7.62994],"type":"Point"}
}