{
  "type": "Feature",
  "properties": {
    "gn:admin1_code":"90.0",
    "gn:asciiname":"Agouede",
    "gn:country_code":"CI",
    "gn:dem":251,
    "gn:feature_class":"P",
    "gn:feature_code":"PPL",
    "gn:name":"Agou\u00e9d\u00e9",
    "gn:population":0,
    "gn:timezone":"Africa/Abidjan",
    "iso:country":"CI",
    "wof:name":"Agouede",
    "wof:placetype":"locality"
},
  "geometry": {"coordinates":[-5.20607,7.53024],"type":"Point"}
}