{
  "type": "Feature",
  "properties": {
    "gn:admin1_code":"87.0",
    "gn:asciiname":"Gorohui",
    "gn:country_code":"CI",
    "gn:dem":256,
    "gn:feature_class":"P",
    "gn:feature_code":"PPL",
    "gn:name":"Gorohui",
    "gn:population":0,
    "gn:timezone":"Africa/Abidjan",
    "iso:country":"CI",
    "name:und_x_variant":[
        "Gorowi",
        "Gorowy",
        "Goroouy",
        "Gorovouy",
        "Gorohui"
    ],
    "wof:name":"Gorohui",
    "wof:placetype":"locality"
},
  "geometry": {"coordinates":[-3.98396,8.81399],"type":"Point"}
}