{
  "type": "Feature",
  "properties": {
    "gn:admin1_code":"76",
    "gn:asciiname":"Zagueoua",
    "gn:country_code":"CI",
    "gn:dem":187,
    "gn:feature_class":"P",
    "gn:feature_code":"PPL",
    "gn:name":"Zagu\u00e9oua",
    "gn:population":0,
    "gn:timezone":"Africa/Abidjan",
    "iso:country":"CI",
    "wof:name":"Zagueoua",
    "wof:placetype":"locality"
},
  "geometry": {"coordinates":[-6.95092,6.22223],"type":"Point"}
}