{
  "type": "Feature",
  "properties": {
    "gn:admin1_code":"77",
    "gn:asciiname":"Ndeou",
    "gn:country_code":"CI",
    "gn:dem":392,
    "gn:feature_class":"P",
    "gn:feature_code":"PPL",
    "gn:name":"Nd\u00e9ou",
    "gn:population":0,
    "gn:timezone":"Africa/Abidjan",
    "iso:country":"CI",
    "wof:name":"Ndeou",
    "wof:placetype":"locality"
},
  "geometry": {"coordinates":[-7.13286,9.35921],"type":"Point"}
}