{
  "type": "Feature",
  "properties": {
    "gn:admin1_code":"95",
    "gn:asciiname":"Tiegba",
    "gn:country_code":"CI",
    "gn:dem":263,
    "gn:feature_class":"P",
    "gn:feature_code":"PPL",
    "gn:name":"Ti\u00e9gba",
    "gn:population":0,
    "gn:timezone":"Africa/Abidjan",
    "iso:country":"CI",
    "wof:name":"Tiegba",
    "wof:placetype":"locality"
},
  "geometry": {"coordinates":[-5.65306,6.2328],"type":"Point"}
}