{
  "type": "Feature",
  "properties": {
    "gn:admin1_code":"78.0",
    "gn:asciiname":"Dehe",
    "gn:country_code":"CI",
    "gn:dem":377,
    "gn:feature_class":"P",
    "gn:feature_code":"PPL",
    "gn:name":"D\u00e9h\u00e9",
    "gn:population":0,
    "gn:timezone":"Africa/Abidjan",
    "iso:country":"CI",
    "wof:name":"Dehe",
    "wof:placetype":"locality"
},
  "geometry": {"coordinates":[-8.35464,7.32307],"type":"Point"}
}