{
  "type": "Feature",
  "properties": {
    "gn:admin1_code":"92",
    "gn:asciiname":"Koulda",
    "gn:country_code":"CI",
    "gn:dem":303,
    "gn:feature_class":"P",
    "gn:feature_code":"PPL",
    "gn:name":"Koulda",
    "gn:population":0,
    "gn:timezone":"Africa/Abidjan",
    "iso:country":"CI",
    "wof:name":"Koulda",
    "wof:placetype":"locality"
},
  "geometry": {"coordinates":[-2.77307,9.39225],"type":"Point"}
}