{
  "type": "Feature",
  "properties": {
    "gn:admin1_code":"93.0",
    "gn:asciiname":"Djorogo Bite Deux",
    "gn:country_code":"CI",
    "gn:dem":104,
    "gn:feature_class":"P",
    "gn:feature_code":"PPL",
    "gn:name":"Djorogo Bit\u00e9 Deux",
    "gn:population":0,
    "gn:timezone":"Africa/Abidjan",
    "iso:country":"CI",
    "wof:name":"Djorogo Bite Deux",
    "wof:placetype":"locality"
},
  "geometry": {"coordinates":[-3.95452,5.40958],"type":"Point"}
}