{
  "type": "Feature",
  "properties": {
    "gn:admin1_code":"81.0",
    "gn:asciiname":"Afotobo",
    "gn:country_code":"CI",
    "gn:dem":233,
    "gn:feature_class":"P",
    "gn:feature_code":"PPL",
    "gn:name":"Afotobo",
    "gn:population":0,
    "gn:timezone":"Africa/Abidjan",
    "iso:country":"CI",
    "name:fra_x_preferred":[
        "Affotobo"
    ],
    "name:msa_x_preferred":[
        "Afotobo"
    ],
    "name:und_x_variant":[
        "Afatobo",
        "Afotobo"
    ],
    "wof:name":"Afotobo",
    "wof:placetype":"locality"
},
  "geometry": {"coordinates":[-5.01624,6.66432],"type":"Point"}
}