{
  "type": "Feature",
  "properties": {
    "gn:admin1_code":"82.0",
    "gn:asciiname":"Boumama Kone",
    "gn:country_code":"CI",
    "gn:dem":56,
    "gn:feature_class":"P",
    "gn:feature_code":"PPL",
    "gn:name":"Boumama Kone",
    "gn:population":0,
    "gn:timezone":"Africa/Abidjan",
    "iso:country":"CI",
    "wof:name":"Boumama Kone",
    "wof:placetype":"locality"
},
  "geometry": {"coordinates":[-4.22237,5.69094],"type":"Point"}
}