{
  "type": "Feature",
  "properties": {
    "gn:admin1_code":"76.0",
    "gn:asciiname":"Dibayo",
    "gn:country_code":"CI",
    "gn:dem":126,
    "gn:feature_class":"P",
    "gn:feature_code":"PPL",
    "gn:name":"Dibayo",
    "gn:population":0,
    "gn:timezone":"Africa/Abidjan",
    "iso:country":"CI",
    "name:und_x_variant":[
        "Dobayou",
        "Dibayo"
    ],
    "wof:name":"Dibayo",
    "wof:placetype":"locality"
},
  "geometry": {"coordinates":[-6.59461,5.77294],"type":"Point"}
}