{
  "type": "Feature",
  "properties": {
    "gn:admin1_code":"82.0",
    "gn:asciiname":"Agbaille",
    "gn:country_code":"CI",
    "gn:dem":25,
    "gn:feature_class":"P",
    "gn:feature_code":"PPL",
    "gn:name":"Agbaill\u00e9",
    "gn:population":0,
    "gn:timezone":"Africa/Abidjan",
    "iso:country":"CI",
    "name:und_x_variant":[
        "Agbay\u00e9",
        "Agbaill\u00e9"
    ],
    "wof:name":"Agbaille",
    "wof:placetype":"locality"
},
  "geometry": {"coordinates":[-4.51631,5.30068],"type":"Point"}
}