{
  "type": "Feature",
  "properties": {
    "gn:admin1_code":"95.0",
    "gn:asciiname":"Bayepa Broudoua",
    "gn:country_code":"CI",
    "gn:dem":260,
    "gn:feature_class":"P",
    "gn:feature_code":"PPL",
    "gn:name":"Bay\u00e9pa Broudoua",
    "gn:population":0,
    "gn:timezone":"Africa/Abidjan",
    "iso:country":"CI",
    "wof:name":"Bayepa Broudoua",
    "wof:placetype":"locality"
},
  "geometry": {"coordinates":[-5.87327,6.36372],"type":"Point"}
}