{
  "type": "Feature",
  "properties": {
    "gn:admin1_code":"82.0",
    "gn:asciiname":"Nabdou",
    "gn:country_code":"CI",
    "gn:dem":93,
    "gn:feature_class":"P",
    "gn:feature_code":"PPL",
    "gn:name":"Nabdou",
    "gn:population":0,
    "gn:timezone":"Africa/Abidjan",
    "iso:country":"CI",
    "wof:name":"Nabdou",
    "wof:placetype":"locality"
},
  "geometry": {"coordinates":[-4.4581,5.99336],"type":"Point"}
}