{
  "type": "Feature",
  "properties": {
    "gn:admin1_code":"97.0",
    "gn:asciiname":"Gouemana",
    "gn:country_code":"CI",
    "gn:dem":325,
    "gn:feature_class":"P",
    "gn:feature_code":"PPL",
    "gn:name":"Gou\u00e9mana",
    "gn:population":0,
    "gn:timezone":"Africa/Abidjan",
    "iso:country":"CI",
    "name:und_x_variant":[
        "Gouamana",
        "Gou\u00e9mana"
    ],
    "wof:name":"Gouemana",
    "wof:placetype":"locality"
},
  "geometry": {"coordinates":[-6.4678,7.81528],"type":"Point"}
}