{
  "type": "Feature",
  "properties": {
    "gn:admin1_code":"76",
    "gn:asciiname":"Kratwe",
    "gn:country_code":"CI",
    "gn:dem":51,
    "gn:feature_class":"P",
    "gn:feature_code":"PPL",
    "gn:name":"Kratw\u00e9",
    "gn:population":0,
    "gn:timezone":"Africa/Abidjan",
    "iso:country":"CI",
    "name:und_x_variant":[
        "Kratou\u00e9",
        "Kratw\u00e9"
    ],
    "wof:name":"Kratwe",
    "wof:placetype":"locality"
},
  "geometry": {"coordinates":[-7.35724,4.65446],"type":"Point"}
}