{
  "type": "Feature",
  "properties": {
    "gn:admin1_code":"97",
    "gn:asciiname":"Teguela",
    "gn:country_code":"CI",
    "gn:dem":334,
    "gn:feature_class":"P",
    "gn:feature_code":"PPL",
    "gn:name":"T\u00e9gu\u00e9la",
    "gn:population":0,
    "gn:timezone":"Africa/Abidjan",
    "iso:country":"CI",
    "name:fas_x_preferred":[
        "\u062a\u06af\u0648\u0626\u0644\u0627"
    ],
    "name:fra_x_preferred":[
        "T\u00e9gu\u00e9la"
    ],
    "name:msa_x_preferred":[
        "T\u00e9gu\u00e9la"
    ],
    "name:und_x_variant":[
        "T\u00e9g\u00e9la"
    ],
    "wof:name":"Teguela",
    "wof:placetype":"locality"
},
  "geometry": {"coordinates":[-6.62558,7.8465],"type":"Point"}
}