{
  "type": "Feature",
  "properties": {
    "gn:admin1_code":"90",
    "gn:asciiname":"Yakofikro",
    "gn:country_code":"CI",
    "gn:dem":202,
    "gn:feature_class":"P",
    "gn:feature_code":"PPL",
    "gn:name":"Yakofikro",
    "gn:population":0,
    "gn:timezone":"Africa/Abidjan",
    "iso:country":"CI",
    "wof:name":"Yakofikro",
    "wof:placetype":"locality"
},
  "geometry": {"coordinates":[-5.62457,7.92037],"type":"Point"}
}