{
  "type": "Feature",
  "properties": {
    "gn:admin1_code":"81.0",
    "gn:asciiname":"Fronobo",
    "gn:country_code":"CI",
    "gn:dem":126,
    "gn:feature_class":"P",
    "gn:feature_code":"PPL",
    "gn:name":"Fronobo",
    "gn:population":0,
    "gn:timezone":"Africa/Abidjan",
    "iso:country":"CI",
    "name:und_x_variant":[
        "Frondobo",
        "Frondoho",
        "Fronobo"
    ],
    "wof:name":"Fronobo",
    "wof:placetype":"locality"
},
  "geometry": {"coordinates":[-4.37941,6.70865],"type":"Point"}
}