{
  "type": "Feature",
  "properties": {
    "gn:admin1_code":"90",
    "gn:asciiname":"Kouamekro",
    "gn:country_code":"CI",
    "gn:dem":286,
    "gn:feature_class":"P",
    "gn:feature_code":"PPL",
    "gn:name":"Kouam\u00e9kro",
    "gn:population":0,
    "gn:timezone":"Africa/Abidjan",
    "iso:country":"CI",
    "name:und_x_variant":[
        "Kouam\u00e9kro",
        "Kouamikro"
    ],
    "wof:name":"Kouamekro",
    "wof:placetype":"locality"
},
  "geometry": {"coordinates":[-5.18685,7.56776],"type":"Point"}
}