{
  "type": "Feature",
  "properties": {
    "gn:admin1_code":"81.0",
    "gn:asciiname":"Asse Bledoukro",
    "gn:country_code":"CI",
    "gn:dem":262,
    "gn:feature_class":"P",
    "gn:feature_code":"PPL",
    "gn:name":"Ass\u00e9 Bl\u00e9doukro",
    "gn:population":0,
    "gn:timezone":"Africa/Abidjan",
    "iso:country":"CI",
    "name:und_x_variant":[
        "Ass\u00e9 Bl\u00e9doukro",
        "Ass\u00e9-Bl\u00e9-Ndoukro"
    ],
    "wof:name":"Asse Bledoukro",
    "wof:placetype":"locality"
},
  "geometry": {"coordinates":[-4.98482,7.38893],"type":"Point"}
}