{
  "type": "Feature",
  "properties": {
    "gn:admin1_code":"78.0",
    "gn:asciiname":"Douelli",
    "gn:country_code":"CI",
    "gn:dem":240,
    "gn:feature_class":"P",
    "gn:feature_code":"PPL",
    "gn:name":"Douelli",
    "gn:population":0,
    "gn:timezone":"Africa/Abidjan",
    "iso:country":"CI",
    "wof:name":"Douelli",
    "wof:placetype":"locality"
},
  "geometry": {"coordinates":[-8.47561,6.60254],"type":"Point"}
}