{
  "type": "Feature",
  "properties": {
    "gn:admin1_code":"92.0",
    "gn:asciiname":"Akayao",
    "gn:country_code":"CI",
    "gn:dem":189,
    "gn:feature_class":"P",
    "gn:feature_code":"PPL",
    "gn:name":"Akayao",
    "gn:population":0,
    "gn:timezone":"Africa/Abidjan",
    "iso:country":"CI",
    "wof:name":"Akayao",
    "wof:placetype":"locality"
},
  "geometry": {"coordinates":[-3.37541,7.69946],"type":"Point"}
}