{
  "type": "Feature",
  "properties": {
    "gn:admin1_code":"87",
    "gn:asciiname":"Topigakaha",
    "gn:country_code":"CI",
    "gn:dem":319,
    "gn:feature_class":"P",
    "gn:feature_code":"PPL",
    "gn:name":"Topigakaha",
    "gn:population":0,
    "gn:timezone":"Africa/Abidjan",
    "iso:country":"CI",
    "name:und_x_variant":[
        "Topinakaha",
        "Topigakaha"
    ],
    "wof:name":"Topigakaha",
    "wof:placetype":"locality"
},
  "geometry": {"coordinates":[-5.4836,9.39528],"type":"Point"}
}