{
  "type": "Feature",
  "properties": {
    "gn:admin1_code":"81.0",
    "gn:asciiname":"Sialoukro",
    "gn:country_code":"CI",
    "gn:dem":123,
    "gn:feature_class":"P",
    "gn:feature_code":"PPL",
    "gn:name":"Sialoukro",
    "gn:population":0,
    "gn:timezone":"Africa/Abidjan",
    "iso:country":"CI",
    "wof:name":"Sialoukro",
    "wof:placetype":"locality"
},
  "geometry": {"coordinates":[-4.43928,7.2513],"type":"Point"}
}