{
  "type": "Feature",
  "properties": {
    "gn:admin1_code":"96",
    "gn:asciiname":"Kroukouamissou",
    "gn:country_code":"CI",
    "gn:dem":215,
    "gn:feature_class":"P",
    "gn:feature_code":"PPL",
    "gn:name":"Kroukouamissou",
    "gn:population":0,
    "gn:timezone":"Africa/Abidjan",
    "iso:country":"CI",
    "name:und_x_variant":[
        "Kroukouamessou",
        "Kroukouamissou"
    ],
    "wof:name":"Kroukouamissou",
    "wof:placetype":"locality"
},
  "geometry": {"coordinates":[-5.73638,7.46005],"type":"Point"}
}