{
  "type": "Feature",
  "properties": {
    "gn:admin1_code":"0.0",
    "gn:asciiname":"Doropo",
    "gn:country_code":"CI",
    "gn:dem":341,
    "gn:feature_class":"P",
    "gn:feature_code":"PPL",
    "gn:name":"Doropo",
    "gn:population":0,
    "gn:timezone":"Africa/Abidjan",
    "iso:country":"CI",
    "wof:name":"Doropo",
    "wof:placetype":"locality"
},
  "geometry": {"coordinates":[-3.34577,9.80955],"type":"Point"}
}