{
  "type": "Feature",
  "properties": {
    "gn:admin1_code":"81.0",
    "gn:asciiname":"Boua Kouassikro",
    "gn:country_code":"CI",
    "gn:dem":213,
    "gn:feature_class":"P",
    "gn:feature_code":"PPL",
    "gn:name":"Boua Kouassikro",
    "gn:population":0,
    "gn:timezone":"Africa/Abidjan",
    "iso:country":"CI",
    "wof:name":"Boua Kouassikro",
    "wof:placetype":"locality"
},
  "geometry": {"coordinates":[-4.70366,7.24052],"type":"Point"}
}