{
  "type": "Feature",
  "properties": {
    "gn:admin1_code":"87",
    "gn:asciiname":"Nassian",
    "gn:country_code":"CI",
    "gn:dem":268,
    "gn:feature_class":"P",
    "gn:feature_code":"PPL",
    "gn:name":"Nassian",
    "gn:population":0,
    "gn:timezone":"Africa/Abidjan",
    "iso:country":"CI",
    "name:fra_x_preferred":[
        "Nassian"
    ],
    "name:ita_x_preferred":[
        "Nassian"
    ],
    "name:msa_x_preferred":[
        "Nassian"
    ],
    "name:spa_x_preferred":[
        "Nassian"
    ],
    "name:und_x_variant":[
        "Nasian"
    ],
    "wof:name":"Nassian",
    "wof:placetype":"locality"
},
  "geometry": {"coordinates":[-4.47993,9.39755],"type":"Point"}
}