{
  "type": "Feature",
  "properties": {
    "gn:admin1_code":"87.0",
    "gn:asciiname":"Febiasso",
    "gn:country_code":"CI",
    "gn:dem":375,
    "gn:feature_class":"P",
    "gn:feature_code":"PPL",
    "gn:name":"F\u00e9biasso",
    "gn:population":0,
    "gn:timezone":"Africa/Abidjan",
    "iso:country":"CI",
    "wof:name":"Febiasso",
    "wof:placetype":"locality"
},
  "geometry": {"coordinates":[-6.53819,10.30945],"type":"Point"}
}