{
  "type": "Feature",
  "properties": {
    "gn:admin1_code":"82.0",
    "gn:asciiname":"Anno",
    "gn:country_code":"CI",
    "gn:dem":63,
    "gn:feature_class":"P",
    "gn:feature_code":"PPL",
    "gn:name":"Anno",
    "gn:population":0,
    "gn:timezone":"Africa/Abidjan",
    "iso:country":"CI",
    "name:und_x_variant":[
        "Ano",
        "Anno"
    ],
    "wof:name":"Anno",
    "wof:placetype":"locality"
},
  "geometry": {"coordinates":[-4.37902,5.85952],"type":"Point"}
}