{
  "type": "Feature",
  "properties": {
    "gn:admin1_code":"95.0",
    "gn:asciiname":"Ketasso",
    "gn:country_code":"CI",
    "gn:dem":47,
    "gn:feature_class":"P",
    "gn:feature_code":"PPL",
    "gn:name":"K\u00e9tasso",
    "gn:population":0,
    "gn:timezone":"Africa/Abidjan",
    "iso:country":"CI",
    "name:und_x_variant":[
        "K\u00e9taso",
        "K\u00e9tasso"
    ],
    "wof:name":"Ketasso",
    "wof:placetype":"locality"
},
  "geometry": {"coordinates":[-5.03378,5.75869],"type":"Point"}
}