{
  "type": "Feature",
  "properties": {
    "gn:admin1_code":"92.0",
    "gn:asciiname":"Dakro",
    "gn:country_code":"CI",
    "gn:dem":164,
    "gn:feature_class":"P",
    "gn:feature_code":"PPL",
    "gn:name":"Dakro",
    "gn:population":0,
    "gn:timezone":"Africa/Abidjan",
    "iso:country":"CI",
    "name:und_x_variant":[
        "N\u2019Dakro",
        "Dakro"
    ],
    "wof:name":"Dakro",
    "wof:placetype":"locality"
},
  "geometry": {"coordinates":[-3.3734,7.3625],"type":"Point"}
}