{
  "type": "Feature",
  "properties": {
    "gn:admin1_code":"78.0",
    "gn:asciiname":"Gotouo",
    "gn:country_code":"CI",
    "gn:dem":280,
    "gn:feature_class":"P",
    "gn:feature_code":"PPL",
    "gn:name":"Gotouo",
    "gn:population":0,
    "gn:timezone":"Africa/Abidjan",
    "iso:country":"CI",
    "wof:name":"Gotouo",
    "wof:placetype":"locality"
},
  "geometry": {"coordinates":[-8.06053,6.94364],"type":"Point"}
}