{
  "type": "Feature",
  "properties": {
    "gn:admin1_code":"96",
    "gn:asciiname":"Kouleyo",
    "gn:country_code":"CI",
    "gn:dem":228,
    "gn:feature_class":"P",
    "gn:feature_code":"PPL",
    "gn:name":"Koul\u00e9yo",
    "gn:population":0,
    "gn:timezone":"Africa/Abidjan",
    "iso:country":"CI",
    "wof:name":"Kouleyo",
    "wof:placetype":"locality"
},
  "geometry": {"coordinates":[-6.67211,7.16738],"type":"Point"}
}