{
  "type": "Feature",
  "properties": {
    "gn:admin1_code":"90",
    "gn:asciiname":"Lassoro",
    "gn:country_code":"CI",
    "gn:dem":253,
    "gn:feature_class":"P",
    "gn:feature_code":"PPL",
    "gn:name":"Lassoro",
    "gn:population":0,
    "gn:timezone":"Africa/Abidjan",
    "iso:country":"CI",
    "name:und_x_variant":[
        "Lassorho",
        "Lassogoto",
        "Lassoro"
    ],
    "wof:name":"Lassoro",
    "wof:placetype":"locality"
},
  "geometry": {"coordinates":[-4.19031,8.25602],"type":"Point"}
}