{
  "type": "Feature",
  "properties": {
    "gn:admin1_code":"76",
    "gn:asciiname":"Oulidie",
    "gn:country_code":"CI",
    "gn:dem":35,
    "gn:feature_class":"P",
    "gn:feature_code":"PPL",
    "gn:name":"Oulidi\u00e9",
    "gn:population":0,
    "gn:timezone":"Africa/Abidjan",
    "iso:country":"CI",
    "wof:name":"Oulidie",
    "wof:placetype":"locality"
},
  "geometry": {"coordinates":[-7.19157,4.57146],"type":"Point"}
}