{
  "type": "Feature",
  "properties": {
    "gn:admin1_code":"96.0",
    "gn:asciiname":"Diafla",
    "gn:country_code":"CI",
    "gn:dem":275,
    "gn:feature_class":"P",
    "gn:feature_code":"PPL",
    "gn:name":"Diafla",
    "gn:population":0,
    "gn:timezone":"Africa/Abidjan",
    "iso:country":"CI",
    "name:und_x_variant":[
        "Dyafla",
        "Diafla"
    ],
    "wof:name":"Diafla",
    "wof:placetype":"locality"
},
  "geometry": {"coordinates":[-6.86751,7.42124],"type":"Point"}
}