{
  "type": "Feature",
  "properties": {
    "gn:admin1_code":"90.0",
    "gn:asciiname":"Boka Kouamikro",
    "gn:country_code":"CI",
    "gn:dem":262,
    "gn:feature_class":"P",
    "gn:feature_code":"PPL",
    "gn:name":"Boka Kouamikro",
    "gn:population":0,
    "gn:timezone":"Africa/Abidjan",
    "iso:country":"CI",
    "wof:name":"Boka Kouamikro",
    "wof:placetype":"locality"
},
  "geometry": {"coordinates":[-4.72048,7.70641],"type":"Point"}
}