{
  "type": "Feature",
  "properties": {
    "gn:admin1_code":"95.0",
    "gn:asciiname":"Kappa",
    "gn:country_code":"CI",
    "gn:dem":199,
    "gn:feature_class":"P",
    "gn:feature_code":"PPL",
    "gn:name":"Kappa",
    "gn:population":0,
    "gn:timezone":"Africa/Abidjan",
    "iso:country":"CI",
    "wof:name":"Kappa",
    "wof:placetype":"locality"
},
  "geometry": {"coordinates":[-5.58637,6.43249],"type":"Point"}
}