{
  "type": "Feature",
  "properties": {
    "gn:admin1_code":"90",
    "gn:asciiname":"Ndana",
    "gn:country_code":"CI",
    "gn:dem":273,
    "gn:feature_class":"P",
    "gn:feature_code":"PPL",
    "gn:name":"Ndana",
    "gn:population":0,
    "gn:timezone":"Africa/Abidjan",
    "iso:country":"CI",
    "name:ceb_x_preferred":[
        "Ndana"
    ],
    "name:deu_x_preferred":[
        "Ndana"
    ],
    "name:swe_x_preferred":[
        "Ndana"
    ],
    "wof:name":"Ndana",
    "wof:placetype":"locality"
},
  "geometry": {"coordinates":[-5.0415,8.18399],"type":"Point"}
}