{
  "type": "Feature",
  "properties": {
    "gn:admin1_code":"77",
    "gn:asciiname":"Somotou",
    "gn:country_code":"CI",
    "gn:dem":439,
    "gn:feature_class":"P",
    "gn:feature_code":"PPL",
    "gn:name":"Somotou",
    "gn:population":0,
    "gn:timezone":"Africa/Abidjan",
    "iso:country":"CI",
    "wof:name":"Somotou",
    "wof:placetype":"locality"
},
  "geometry": {"coordinates":[-7.97287,10.10782],"type":"Point"}
}