{
  "type": "Feature",
  "properties": {
    "gn:admin1_code":"78",
    "gn:asciiname":"Zonneu",
    "gn:country_code":"CI",
    "gn:dem":342,
    "gn:feature_class":"P",
    "gn:feature_code":"PPL",
    "gn:name":"Zonneu",
    "gn:population":0,
    "gn:timezone":"Africa/Abidjan",
    "iso:country":"CI",
    "name:fra_x_preferred":[
        "Zonneu"
    ],
    "name:ita_x_preferred":[
        "Zonneu"
    ],
    "name:msa_x_preferred":[
        "Zonneu"
    ],
    "wof:name":"Zonneu",
    "wof:placetype":"locality"
},
  "geometry": {"coordinates":[-8.06675,7.17144],"type":"Point"}
}