{
  "type": "Feature",
  "properties": {
    "gn:admin1_code":"78.0",
    "gn:asciiname":"Vetouo",
    "gn:country_code":"CI",
    "gn:dem":291,
    "gn:feature_class":"P",
    "gn:feature_code":"PPL",
    "gn:name":"V\u00e9touo",
    "gn:population":0,
    "gn:timezone":"Africa/Abidjan",
    "iso:country":"CI",
    "name:und_x_variant":[
        "V\u00e9touo",
        "Veitouo"
    ],
    "wof:name":"Vetouo",
    "wof:placetype":"locality"
},
  "geometry": {"coordinates":[-8.11634,6.96299],"type":"Point"}
}