{
  "type": "Feature",
  "properties": {
    "gn:admin1_code":"90.0",
    "gn:asciiname":"Bokaha",
    "gn:country_code":"CI",
    "gn:dem":271,
    "gn:feature_class":"P",
    "gn:feature_code":"PPL",
    "gn:name":"Bokaha",
    "gn:population":0,
    "gn:timezone":"Africa/Abidjan",
    "iso:country":"CI",
    "wof:name":"Bokaha",
    "wof:placetype":"locality"
},
  "geometry": {"coordinates":[-5.03585,8.0422],"type":"Point"}
}