{
  "type": "Feature",
  "properties": {
    "gn:admin1_code":"90",
    "gn:asciiname":"Koumele",
    "gn:country_code":"CI",
    "gn:dem":218,
    "gn:feature_class":"P",
    "gn:feature_code":"PPL",
    "gn:name":"Koum\u00e9l\u00e9",
    "gn:population":0,
    "gn:timezone":"Africa/Abidjan",
    "iso:country":"CI",
    "wof:name":"Koumele",
    "wof:placetype":"locality"
},
  "geometry": {"coordinates":[-5.37189,7.33236],"type":"Point"}
}