{
  "type": "Feature",
  "properties": {
    "gn:admin1_code":"78.0",
    "gn:asciiname":"Ganhouye",
    "gn:country_code":"CI",
    "gn:dem":229,
    "gn:feature_class":"P",
    "gn:feature_code":"PPL",
    "gn:name":"Ganhouy\u00e9",
    "gn:population":0,
    "gn:timezone":"Africa/Abidjan",
    "iso:country":"CI",
    "name:und_x_variant":[
        "Ganhoul\u00e9",
        "Ganhouy\u00e9"
    ],
    "wof:name":"Ganhouye",
    "wof:placetype":"locality"
},
  "geometry": {"coordinates":[-8.3569,6.75545],"type":"Point"}
}