{
  "type": "Feature",
  "properties": {
    "gn:admin1_code":"76.0",
    "gn:asciiname":"Kedigbo",
    "gn:country_code":"CI",
    "gn:dem":82,
    "gn:feature_class":"P",
    "gn:feature_code":"PPL",
    "gn:name":"K\u00e9digbo",
    "gn:population":0,
    "gn:timezone":"Africa/Abidjan",
    "iso:country":"CI",
    "name:und_x_variant":[
        "Gu\u00e9dikopo",
        "K\u00e9digbo"
    ],
    "wof:name":"Kedigbo",
    "wof:placetype":"locality"
},
  "geometry": {"coordinates":[-5.92564,5.29061],"type":"Point"}
}