{
  "type": "Feature",
  "properties": {
    "gn:admin1_code":"97.0",
    "gn:asciiname":"Katyali",
    "gn:country_code":"CI",
    "gn:dem":345,
    "gn:feature_class":"P",
    "gn:feature_code":"PPL",
    "gn:name":"Katyali",
    "gn:population":0,
    "gn:timezone":"Africa/Abidjan",
    "iso:country":"CI",
    "name:und_x_variant":[
        "Katiali",
        "Katyali"
    ],
    "wof:name":"Katyali",
    "wof:placetype":"locality"
},
  "geometry": {"coordinates":[-6.2711,8.86638],"type":"Point"}
}