{
  "type": "Feature",
  "properties": {
    "gn:admin1_code":"95.0",
    "gn:asciiname":"Hire",
    "gn:country_code":"CI",
    "gn:dem":207,
    "gn:feature_class":"P",
    "gn:feature_code":"PPL",
    "gn:name":"Hir\u00e9",
    "gn:population":0,
    "gn:timezone":"Africa/Abidjan",
    "iso:country":"CI",
    "name:und_x_variant":[
        "Hir\u00e9"
    ],
    "wof:name":"Hire",
    "wof:placetype":"locality"
},
  "geometry": {"coordinates":[-5.29463,6.18878],"type":"Point"}
}