{
  "type": "Feature",
  "properties": {
    "gn:admin1_code":"82.0",
    "gn:asciiname":"Kibimian",
    "gn:country_code":"CI",
    "gn:dem":75,
    "gn:feature_class":"P",
    "gn:feature_code":"PPL",
    "gn:name":"Kibimian",
    "gn:population":0,
    "gn:timezone":"Africa/Abidjan",
    "iso:country":"CI",
    "wof:name":"Kibimian",
    "wof:placetype":"locality"
},
  "geometry": {"coordinates":[-4.33222,5.88515],"type":"Point"}
}