{
  "type": "Feature",
  "properties": {
    "gn:admin1_code":"97",
    "gn:asciiname":"Tiema",
    "gn:country_code":"CI",
    "gn:dem":329,
    "gn:feature_class":"P",
    "gn:feature_code":"PPL",
    "gn:name":"Ti\u00e9ma",
    "gn:population":0,
    "gn:timezone":"Africa/Abidjan",
    "iso:country":"CI",
    "name:fra_x_preferred":[
        "Ti\u00e9ma"
    ],
    "name:und_x_variant":[
        "Ty\u00e9ma",
        "Ty\u00e9mo",
        "Ti\u00e9ma"
    ],
    "wof:name":"Tiema",
    "wof:placetype":"locality"
},
  "geometry": {"coordinates":[-6.10892,8.02044],"type":"Point"}
}