{
  "type": "Feature",
  "properties": {
    "gn:admin1_code":"93.0",
    "gn:asciiname":"Beago",
    "gn:country_code":"CI",
    "gn:dem":5,
    "gn:feature_class":"P",
    "gn:feature_code":"PPL",
    "gn:name":"B\u00e9ago",
    "gn:population":0,
    "gn:timezone":"Africa/Abidjan",
    "iso:country":"CI",
    "wof:name":"Beago",
    "wof:placetype":"locality"
},
  "geometry": {"coordinates":[-4.07007,5.30758],"type":"Point"}
}