{
  "type": "Feature",
  "properties": {
    "gn:admin1_code":"82.0",
    "gn:asciiname":"Diasson",
    "gn:country_code":"CI",
    "gn:dem":91,
    "gn:feature_class":"P",
    "gn:feature_code":"PPL",
    "gn:name":"Diasson",
    "gn:population":0,
    "gn:timezone":"Africa/Abidjan",
    "iso:country":"CI",
    "name:fra_x_preferred":[
        "Diasson"
    ],
    "name:msa_x_preferred":[
        "Diasson"
    ],
    "name:und_x_variant":[
        "Diasso"
    ],
    "wof:name":"Diasson",
    "wof:placetype":"locality"
},
  "geometry": {"coordinates":[-3.72759,5.97152],"type":"Point"}
}