{
  "type": "Feature",
  "properties": {
    "gn:admin1_code":"78.0",
    "gn:asciiname":"Ge",
    "gn:country_code":"CI",
    "gn:dem":319,
    "gn:feature_class":"P",
    "gn:feature_code":"PPL",
    "gn:name":"G\u00e9",
    "gn:population":0,
    "gn:timezone":"Africa/Abidjan",
    "iso:country":"CI",
    "name:ara_x_preferred":[
        "\u062c\u064a \u0625\u064a"
    ],
    "name:fas_x_preferred":[
        "\u06af"
    ],
    "name:nor_x_preferred":[
        "GE"
    ],
    "name:ukr_x_preferred":[
        "Ge"
    ],
    "wof:name":"Ge",
    "wof:placetype":"locality"
},
  "geometry": {"coordinates":[-7.41667,7.03333],"type":"Point"}
}