{
  "type": "Feature",
  "properties": {
    "gn:admin1_code":"82.0",
    "gn:asciiname":"Ahouna Akallou",
    "gn:country_code":"CI",
    "gn:dem":52,
    "gn:feature_class":"P",
    "gn:feature_code":"PPL",
    "gn:name":"Ahouna Akallou",
    "gn:population":0,
    "gn:timezone":"Africa/Abidjan",
    "iso:country":"CI",
    "wof:name":"Ahouna Akallou",
    "wof:placetype":"locality"
},
  "geometry": {"coordinates":[-4.34712,5.83841],"type":"Point"}
}