{
  "type": "Feature",
  "properties": {
    "gn:admin1_code":"89.0",
    "gn:asciiname":"Abiati",
    "gn:country_code":"CI",
    "gn:dem":46,
    "gn:feature_class":"P",
    "gn:feature_code":"PPL",
    "gn:name":"Abiati",
    "gn:population":0,
    "gn:timezone":"Africa/Abidjan",
    "iso:country":"CI",
    "wof:name":"Abiati",
    "wof:placetype":"locality"
},
  "geometry": {"coordinates":[-3.17069,5.28984],"type":"Point"}
}