{
  "type": "Feature",
  "properties": {
    "gn:admin1_code":"82.0",
    "gn:asciiname":"Tiekoura",
    "gn:country_code":"CI",
    "gn:dem":50,
    "gn:feature_class":"P",
    "gn:feature_code":"PPL",
    "gn:name":"Ti\u00e9koura",
    "gn:population":0,
    "gn:timezone":"Africa/Abidjan",
    "iso:country":"CI",
    "wof:name":"Tiekoura",
    "wof:placetype":"locality"
},
  "geometry": {"coordinates":[-4.28786,5.96028],"type":"Point"}
}