{
  "type": "Feature",
  "properties": {
    "gn:admin1_code":"96",
    "gn:asciiname":"Kouinfla",
    "gn:country_code":"CI",
    "gn:dem":240,
    "gn:feature_class":"P",
    "gn:feature_code":"PPL",
    "gn:name":"Kouinfla",
    "gn:population":0,
    "gn:timezone":"Africa/Abidjan",
    "iso:country":"CI",
    "wof:name":"Kouinfla",
    "wof:placetype":"locality"
},
  "geometry": {"coordinates":[-5.96685,7.54141],"type":"Point"}
}