{
  "type": "Feature",
  "properties": {
    "gn:admin1_code":"87",
    "gn:asciiname":"Nyanbelege",
    "gn:country_code":"CI",
    "gn:dem":403,
    "gn:feature_class":"P",
    "gn:feature_code":"PPL",
    "gn:name":"Nyanb\u00e9l\u00e9g\u00e9",
    "gn:population":0,
    "gn:timezone":"Africa/Abidjan",
    "iso:country":"CI",
    "name:und_x_variant":[
        "Nianb\u00e9l\u00e9gu\u00e9",
        "Nyanb\u00e9l\u00e9g\u00e9"
    ],
    "wof:name":"Nyanbelege",
    "wof:placetype":"locality"
},
  "geometry": {"coordinates":[-5.69343,9.46729],"type":"Point"}
}