{
  "type": "Feature",
  "properties": {
    "gn:admin1_code":"87.0",
    "gn:asciiname":"Nyapligue",
    "gn:country_code":"CI",
    "gn:dem":424,
    "gn:feature_class":"P",
    "gn:feature_code":"PPL",
    "gn:name":"Nyapligu\u00e9",
    "gn:population":0,
    "gn:timezone":"Africa/Abidjan",
    "iso:country":"CI",
    "wof:name":"Nyapligue",
    "wof:placetype":"locality"
},
  "geometry": {"coordinates":[-6.54474,9.21991],"type":"Point"}
}