{
  "type": "Feature",
  "properties": {
    "gn:admin1_code":"81.0",
    "gn:asciiname":"Dingbe",
    "gn:country_code":"CI",
    "gn:dem":189,
    "gn:feature_class":"P",
    "gn:feature_code":"PPL",
    "gn:name":"Dingb\u00e9",
    "gn:population":0,
    "gn:timezone":"Africa/Abidjan",
    "iso:country":"CI",
    "wof:name":"Dingbe",
    "wof:placetype":"locality"
},
  "geometry": {"coordinates":[-3.95703,7.07131],"type":"Point"}
}