{
  "type": "Feature",
  "properties": {
    "gn:admin1_code":"98.0",
    "gn:asciiname":"Adaou",
    "gn:country_code":"CI",
    "gn:dem":195,
    "gn:feature_class":"P",
    "gn:feature_code":"PPL",
    "gn:name":"Adaou",
    "gn:population":0,
    "gn:timezone":"Africa/Abidjan",
    "iso:country":"CI",
    "name:fas_x_preferred":[
        "\u0627\u062f\u0627\u0626\u0648"
    ],
    "name:fra_x_preferred":[
        "Adaou"
    ],
    "name:ita_x_preferred":[
        "Adaou"
    ],
    "name:msa_x_preferred":[
        "Adaou"
    ],
    "name:und_x_variant":[
        "Labokro"
    ],
    "wof:name":"Adaou",
    "wof:placetype":"locality"
},
  "geometry": {"coordinates":[-5.04924,6.80119],"type":"Point"}
}