{
  "type": "Feature",
  "properties": {
    "gn:admin1_code":"92.0",
    "gn:asciiname":"Doguina",
    "gn:country_code":"CI",
    "gn:dem":258,
    "gn:feature_class":"P",
    "gn:feature_code":"PPL",
    "gn:name":"Doguina",
    "gn:population":0,
    "gn:timezone":"Africa/Abidjan",
    "iso:country":"CI",
    "wof:name":"Doguina",
    "wof:placetype":"locality"
},
  "geometry": {"coordinates":[-2.75,9.35],"type":"Point"}
}