{
  "type": "Feature",
  "properties": {
    "gn:admin1_code":"76",
    "gn:asciiname":"Weoulo",
    "gn:country_code":"CI",
    "gn:dem":20,
    "gn:feature_class":"P",
    "gn:feature_code":"PPL",
    "gn:name":"W\u00e8oulo",
    "gn:population":0,
    "gn:timezone":"Africa/Abidjan",
    "iso:country":"CI",
    "name:und_x_variant":[
        "Ouabulo",
        "Ouaoulou",
        "Ouaoulo",
        "W\u00e8oulo"
    ],
    "wof:name":"Weoulo",
    "wof:placetype":"locality"
},
  "geometry": {"coordinates":[-7.08061,4.66639],"type":"Point"}
}