{
  "type": "Feature",
  "properties": {
    "gn:admin1_code":"81.0",
    "gn:asciiname":"Bofia",
    "gn:country_code":"CI",
    "gn:dem":159,
    "gn:feature_class":"P",
    "gn:feature_code":"PPL",
    "gn:name":"Bofia",
    "gn:population":0,
    "gn:timezone":"Africa/Abidjan",
    "iso:country":"CI",
    "name:und_x_variant":[
        "Bofla"
    ],
    "wof:name":"Bofia",
    "wof:placetype":"locality"
},
  "geometry": {"coordinates":[-5.00626,6.72004],"type":"Point"}
}