{
  "type": "Feature",
  "properties": {
    "gn:admin1_code":"81.0",
    "gn:asciiname":"Apangokro",
    "gn:country_code":"CI",
    "gn:dem":175,
    "gn:feature_class":"P",
    "gn:feature_code":"PPL",
    "gn:name":"Apangokro",
    "gn:population":0,
    "gn:timezone":"Africa/Abidjan",
    "iso:country":"CI",
    "wof:name":"Apangokro",
    "wof:placetype":"locality"
},
  "geometry": {"coordinates":[-5.01527,6.93212],"type":"Point"}
}