{
  "type": "Feature",
  "properties": {
    "gn:admin1_code":"95.0",
    "gn:asciiname":"Bodossipa",
    "gn:country_code":"CI",
    "gn:dem":251,
    "gn:feature_class":"P",
    "gn:feature_code":"PPL",
    "gn:name":"Bodossipa",
    "gn:population":0,
    "gn:timezone":"Africa/Abidjan",
    "iso:country":"CI",
    "wof:name":"Bodossipa",
    "wof:placetype":"locality"
},
  "geometry": {"coordinates":[-5.95294,6.33652],"type":"Point"}
}