{
  "type": "Feature",
  "properties": {
    "gn:admin1_code":"87",
    "gn:asciiname":"Serifesso",
    "gn:country_code":"CI",
    "gn:dem":288,
    "gn:feature_class":"P",
    "gn:feature_code":"PPL",
    "gn:name":"S\u00e9rifesso",
    "gn:population":0,
    "gn:timezone":"Africa/Abidjan",
    "iso:country":"CI",
    "wof:name":"Serifesso",
    "wof:placetype":"locality"
},
  "geometry": {"coordinates":[-4.61922,9.42683],"type":"Point"}
}