{
  "type": "Feature",
  "properties": {
    "gn:admin1_code":"92",
    "gn:asciiname":"Niobolo",
    "gn:country_code":"CI",
    "gn:dem":329,
    "gn:feature_class":"P",
    "gn:feature_code":"PPL",
    "gn:name":"Niobolo",
    "gn:population":0,
    "gn:timezone":"Africa/Abidjan",
    "iso:country":"CI",
    "wof:name":"Niobolo",
    "wof:placetype":"locality"
},
  "geometry": {"coordinates":[-3.13207,9.80917],"type":"Point"}
}