{
  "type": "Feature",
  "properties": {
    "gn:admin1_code":"93.0",
    "gn:asciiname":"Adiapo-Doume",
    "gn:country_code":"CI",
    "gn:dem":28,
    "gn:feature_class":"P",
    "gn:feature_code":"PPL",
    "gn:name":"Adiapo-Doum\u00e9",
    "gn:population":0,
    "gn:timezone":"Africa/Abidjan",
    "iso:country":"CI",
    "name:und_x_variant":[
        "Adiopo Doum\u00e9",
        "Adiapo-Doum\u00e9"
    ],
    "wof:name":"Adiapo-Doume",
    "wof:placetype":"locality"
},
  "geometry": {"coordinates":[-4.13158,5.34105],"type":"Point"}
}