{
  "type": "Feature",
  "properties": {
    "gn:admin1_code":"92",
    "gn:asciiname":"Sansan",
    "gn:country_code":"CI",
    "gn:dem":332,
    "gn:feature_class":"P",
    "gn:feature_code":"PPL",
    "gn:name":"Sansan",
    "gn:population":0,
    "gn:timezone":"Africa/Abidjan",
    "iso:country":"CI",
    "name:bar_x_preferred":[
        "Sansan"
    ],
    "name:ceb_x_preferred":[
        "Sansan"
    ],
    "name:deu_x_preferred":[
        "Sansan"
    ],
    "name:pol_x_preferred":[
        "Sansan"
    ],
    "name:swe_x_preferred":[
        "Sansan"
    ],
    "wof:name":"Sansan",
    "wof:placetype":"locality"
},
  "geometry": {"coordinates":[-3.0339,9.66038],"type":"Point"}
}