{
  "type": "Feature",
  "properties": {
    "gn:admin1_code":"97.0",
    "gn:asciiname":"Dyoulagbeso",
    "gn:country_code":"CI",
    "gn:dem":551,
    "gn:feature_class":"P",
    "gn:feature_code":"PPL",
    "gn:name":"Dyoulagb\u00e9so",
    "gn:population":0,
    "gn:timezone":"Africa/Abidjan",
    "iso:country":"CI",
    "wof:name":"Dyoulagbeso",
    "wof:placetype":"locality"
},
  "geometry": {"coordinates":[-7.91421,8.83542],"type":"Point"}
}