{
  "type": "Feature",
  "properties": {
    "gn:admin1_code":"94",
    "gn:asciiname":"Zebenou",
    "gn:country_code":"CI",
    "gn:dem":206,
    "gn:feature_class":"P",
    "gn:feature_code":"PPL",
    "gn:name":"Z\u00e9b\u00e9nou",
    "gn:population":0,
    "gn:timezone":"Africa/Abidjan",
    "iso:country":"CI",
    "name:und_x_variant":[
        "Zob\u00e9nou",
        "Z\u00e9b\u00e9nou"
    ],
    "wof:name":"Zebenou",
    "wof:placetype":"locality"
},
  "geometry": {"coordinates":[-3.56757,6.82131],"type":"Point"}
}