{
  "type": "Feature",
  "properties": {
    "gn:admin1_code":"87",
    "gn:asciiname":"Sekonkaha",
    "gn:country_code":"CI",
    "gn:dem":342,
    "gn:feature_class":"P",
    "gn:feature_code":"PPL",
    "gn:name":"S\u00e9konkaha",
    "gn:population":0,
    "gn:timezone":"Africa/Abidjan",
    "iso:country":"CI",
    "wof:name":"Sekonkaha",
    "wof:placetype":"locality"
},
  "geometry": {"coordinates":[-5.41433,9.32868],"type":"Point"}
}