{
  "type": "Feature",
  "properties": {
    "iso:country":"CI",
    "name:ceb_x_preferred":[
        "Tabou"
    ],
    "name:fra_x_preferred":[
        "Tabou"
    ],
    "name:ita_x_preferred":[
        "Tabou"
    ],
    "name:msa_x_preferred":[
        "Tabou"
    ],
    "name:swa_x_preferred":[
        "Tabou"
    ],
    "name:swe_x_preferred":[
        "Tabou"
    ],
    "name:unk_x_variant":[
        "Tabu"
    ],
    "qs:gn_country":"CI",
    "qs:gn_fcode":"PPL",
    "qs:gn_pop":17134,
    "qs:name":"Tabou",
    "qs:name_adm0":"C\u00f4te d\u00b4Ivoire",
    "qs:name_adm1":"Bas-Sassandra",
    "qs:photos":0,
    "qs:photos_1k":0,
    "qs:photos_9k":0,
    "qs:photos_9r":0,
    "qs:photos_all":0,
    "qs:photos_sr":0,
    "qs:placetype":"Town",
    "qs:pop_sr":"6",
    "qs:woe_adm0":23424854,
    "wd:wordcount":38,
    "wof:name":"Tabou",
    "wof:placetype":"locality",
    "wof:population":17134
},
  "geometry": {"coordinates":[-7.3528,4.42295],"type":"Point"}
}