{
  "type": "Feature",
  "properties": {
    "gn:admin1_code":"90.0",
    "gn:asciiname":"Bende Kouassikro",
    "gn:country_code":"CI",
    "gn:dem":314,
    "gn:feature_class":"P",
    "gn:feature_code":"PPL",
    "gn:name":"Bend\u00e9 Kouassikro",
    "gn:population":0,
    "gn:timezone":"Africa/Abidjan",
    "iso:country":"CI",
    "name:und_x_variant":[
        "Bend\u00e9 Kouassikro",
        "Blind\u00e9 Koussikro"
    ],
    "wof:name":"Bende Kouassikro",
    "wof:placetype":"locality"
},
  "geometry": {"coordinates":[-5.14505,7.66667],"type":"Point"}
}