{
  "type": "Feature",
  "properties": {
    "gn:admin1_code":"81.0",
    "gn:asciiname":"Asounmakro",
    "gn:country_code":"CI",
    "gn:dem":199,
    "gn:feature_class":"P",
    "gn:feature_code":"PPL",
    "gn:name":"Asounmakro",
    "gn:population":0,
    "gn:timezone":"Africa/Abidjan",
    "iso:country":"CI",
    "wof:name":"Asounmakro",
    "wof:placetype":"locality"
},
  "geometry": {"coordinates":[-4.10968,7.48758],"type":"Point"}
}