{
  "type": "Feature",
  "properties": {
    "gn:admin1_code":"82.0",
    "gn:asciiname":"Bodo",
    "gn:country_code":"CI",
    "gn:dem":66,
    "gn:feature_class":"P",
    "gn:feature_code":"PPL",
    "gn:name":"Bodo",
    "gn:population":0,
    "gn:timezone":"Africa/Abidjan",
    "iso:country":"CI",
    "wof:name":"Bodo",
    "wof:placetype":"locality"
},
  "geometry": {"coordinates":[-4.68498,5.90955],"type":"Point"}
}