{
  "type": "Feature",
  "properties": {
    "gn:admin1_code":"77",
    "gn:asciiname":"Masadougou",
    "gn:country_code":"CI",
    "gn:dem":392,
    "gn:feature_class":"P",
    "gn:feature_code":"PPL",
    "gn:name":"Masadougou",
    "gn:population":0,
    "gn:timezone":"Africa/Abidjan",
    "iso:country":"CI",
    "name:und_x_variant":[
        "Moussadougou",
        "Masadougou"
    ],
    "wof:name":"Masadougou",
    "wof:placetype":"locality"
},
  "geometry": {"coordinates":[-7.37455,9.10237],"type":"Point"}
}