{
  "type": "Feature",
  "properties": {
    "gn:admin1_code":"95.0",
    "gn:asciiname":"Gareko",
    "gn:country_code":"CI",
    "gn:dem":246,
    "gn:feature_class":"P",
    "gn:feature_code":"PPL",
    "gn:name":"Gar\u00e9ko",
    "gn:population":0,
    "gn:timezone":"Africa/Abidjan",
    "iso:country":"CI",
    "wof:name":"Gareko",
    "wof:placetype":"locality"
},
  "geometry": {"coordinates":[-5.70359,6.07084],"type":"Point"}
}