{
  "type": "Feature",
  "properties": {
    "gn:admin1_code":"77",
    "gn:asciiname":"Korhoyere",
    "gn:country_code":"CI",
    "gn:dem":443,
    "gn:feature_class":"P",
    "gn:feature_code":"PPL",
    "gn:name":"Korhoy\u00e9r\u00e9",
    "gn:population":0,
    "gn:timezone":"Africa/Abidjan",
    "iso:country":"CI",
    "wof:name":"Korhoyere",
    "wof:placetype":"locality"
},
  "geometry": {"coordinates":[-6.89391,9.80391],"type":"Point"}
}