{
  "type": "Feature",
  "properties": {
    "gn:admin1_code":"81.0",
    "gn:asciiname":"Assadue",
    "gn:country_code":"CI",
    "gn:dem":199,
    "gn:feature_class":"P",
    "gn:feature_code":"PPL",
    "gn:name":"Assadu\u00e9",
    "gn:population":0,
    "gn:timezone":"Africa/Abidjan",
    "iso:country":"CI",
    "wof:name":"Assadue",
    "wof:placetype":"locality"
},
  "geometry": {"coordinates":[-4.02884,7.98082],"type":"Point"}
}