{
  "type": "Feature",
  "properties": {
    "gn:admin1_code":"97.0",
    "gn:asciiname":"Gouetifla",
    "gn:country_code":"CI",
    "gn:dem":308,
    "gn:feature_class":"P",
    "gn:feature_code":"PPL",
    "gn:name":"Gou\u00e9tifla",
    "gn:population":0,
    "gn:timezone":"Africa/Abidjan",
    "iso:country":"CI",
    "wof:name":"Gouetifla",
    "wof:placetype":"locality"
},
  "geometry": {"coordinates":[-5.8886,7.73097],"type":"Point"}
}