{
  "type": "Feature",
  "properties": {
    "gn:admin1_code":"97",
    "gn:asciiname":"Sabodougou",
    "gn:country_code":"CI",
    "gn:dem":573,
    "gn:feature_class":"P",
    "gn:feature_code":"PPL",
    "gn:name":"Sabodougou",
    "gn:population":0,
    "gn:timezone":"Africa/Abidjan",
    "iso:country":"CI",
    "name:fra_x_preferred":[
        "Saboudougou"
    ],
    "name:ita_x_preferred":[
        "Saboudougou"
    ],
    "name:msa_x_preferred":[
        "Saboudougou"
    ],
    "name:und_x_variant":[
        "Sobodougou",
        "Sabadougou",
        "Saboudougou",
        "Sabodougou"
    ],
    "name:urd_x_preferred":[
        "\u0633\u0628\u0648\u062f\u0648\u06af\u0648"
    ],
    "wof:name":"Sabodougou",
    "wof:placetype":"locality"
},
  "geometry": {"coordinates":[-8.12249,8.37147],"type":"Point"}
}