{
  "type": "Feature",
  "properties": {
    "gn:admin1_code":"95.0",
    "gn:asciiname":"Doka",
    "gn:country_code":"CI",
    "gn:dem":171,
    "gn:feature_class":"P",
    "gn:feature_code":"PPL",
    "gn:name":"Doka",
    "gn:population":0,
    "gn:timezone":"Africa/Abidjan",
    "iso:country":"CI",
    "name:ceb_x_preferred":[
        "Doka"
    ],
    "name:deu_x_preferred":[
        "Doka"
    ],
    "name:swe_x_preferred":[
        "Doka"
    ],
    "wof:name":"Doka",
    "wof:placetype":"locality"
},
  "geometry": {"coordinates":[-5.35685,6.3206],"type":"Point"}
}