{
  "type": "Feature",
  "properties": {
    "gn:admin1_code":"82.0",
    "gn:asciiname":"Nguessan Yao",
    "gn:country_code":"CI",
    "gn:dem":101,
    "gn:feature_class":"P",
    "gn:feature_code":"PPL",
    "gn:name":"Nguessan Yao",
    "gn:population":0,
    "gn:timezone":"Africa/Abidjan",
    "iso:country":"CI",
    "wof:name":"Nguessan Yao",
    "wof:placetype":"locality"
},
  "geometry": {"coordinates":[-4.48135,5.74789],"type":"Point"}
}