{
  "type": "Feature",
  "properties": {
    "gn:admin1_code":"82.0",
    "gn:asciiname":"Gbesse",
    "gn:country_code":"CI",
    "gn:dem":34,
    "gn:feature_class":"P",
    "gn:feature_code":"PPL",
    "gn:name":"Gb\u00e9ss\u00e9",
    "gn:population":0,
    "gn:timezone":"Africa/Abidjan",
    "iso:country":"CI",
    "name:und_x_variant":[
        "Gb\u00e9ss\u00e9",
        "B\u00e9ss\u00e9"
    ],
    "wof:name":"Gbesse",
    "wof:placetype":"locality"
},
  "geometry": {"coordinates":[-4.29264,5.8394],"type":"Point"}
}