{
  "type": "Feature",
  "properties": {
    "gn:admin1_code":"94.0",
    "gn:asciiname":"Siriki Diara",
    "gn:country_code":"CI",
    "gn:dem":13,
    "gn:feature_class":"P",
    "gn:feature_code":"PPL",
    "gn:name":"Siriki Diara",
    "gn:population":0,
    "gn:timezone":"Africa/Abidjan",
    "iso:country":"CI",
    "wof:name":"Siriki Diara",
    "wof:placetype":"locality"
},
  "geometry": {"coordinates":[-3.80415,5.25484],"type":"Point"}
}