{
  "type": "Feature",
  "properties": {
    "gn:admin1_code":"82.0",
    "gn:asciiname":"Adou",
    "gn:country_code":"CI",
    "gn:dem":66,
    "gn:feature_class":"P",
    "gn:feature_code":"PPL",
    "gn:name":"Adou",
    "gn:population":0,
    "gn:timezone":"Africa/Abidjan",
    "iso:country":"CI",
    "wof:name":"Adou",
    "wof:placetype":"locality"
},
  "geometry": {"coordinates":[-3.71212,5.66055],"type":"Point"}
}