{
  "type": "Feature",
  "properties": {
    "gn:admin1_code":"90",
    "gn:asciiname":"Pambassou",
    "gn:country_code":"CI",
    "gn:dem":224,
    "gn:feature_class":"P",
    "gn:feature_code":"PPL",
    "gn:name":"Pambassou",
    "gn:population":0,
    "gn:timezone":"Africa/Abidjan",
    "iso:country":"CI",
    "name:und_x_variant":[
        "Pambasou"
    ],
    "wof:name":"Pambassou",
    "wof:placetype":"locality"
},
  "geometry": {"coordinates":[-5.48189,7.52264],"type":"Point"}
}