{
  "type": "Feature",
  "properties": {
    "gn:admin1_code":"82",
    "gn:asciiname":"Lauzoua",
    "gn:country_code":"CI",
    "gn:dem":7,
    "gn:feature_class":"P",
    "gn:feature_code":"PPL",
    "gn:name":"Lauzoua",
    "gn:population":0,
    "gn:timezone":"Africa/Abidjan",
    "iso:country":"CI",
    "name:und_x_variant":[
        "Lozoua",
        "Lauzoua"
    ],
    "wof:name":"Lauzoua",
    "wof:placetype":"locality"
},
  "geometry": {"coordinates":[-5.31013,5.20327],"type":"Point"}
}