{
  "type": "Feature",
  "properties": {
    "gn:admin1_code":"78.0",
    "gn:asciiname":"Dio",
    "gn:country_code":"CI",
    "gn:dem":513,
    "gn:feature_class":"P",
    "gn:feature_code":"PPL",
    "gn:name":"Dio",
    "gn:population":0,
    "gn:timezone":"Africa/Abidjan",
    "iso:country":"CI",
    "wof:name":"Dio",
    "wof:placetype":"locality"
},
  "geometry": {"coordinates":[-7.57678,7.78107],"type":"Point"}
}