{
  "type": "Feature",
  "properties": {
    "gn:admin1_code":"76.0",
    "gn:asciiname":"Badahinou",
    "gn:country_code":"CI",
    "gn:dem":201,
    "gn:feature_class":"P",
    "gn:feature_code":"PPL",
    "gn:name":"Badahinou",
    "gn:population":0,
    "gn:timezone":"Africa/Abidjan",
    "iso:country":"CI",
    "wof:name":"Badahinou",
    "wof:placetype":"locality"
},
  "geometry": {"coordinates":[-7.09534,6.41019],"type":"Point"}
}