{
  "type": "Feature",
  "properties": {
    "gn:admin1_code":"82.0",
    "gn:asciiname":"Joamo",
    "gn:country_code":"CI",
    "gn:dem":84,
    "gn:feature_class":"P",
    "gn:feature_code":"PPL",
    "gn:name":"Joamo",
    "gn:population":0,
    "gn:timezone":"Africa/Abidjan",
    "iso:country":"CI",
    "wof:name":"Joamo",
    "wof:placetype":"locality"
},
  "geometry": {"coordinates":[-4.47705,5.9872],"type":"Point"}
}