{
  "type": "Feature",
  "properties": {
    "gn:admin1_code":"77",
    "gn:asciiname":"Limbouriko",
    "gn:country_code":"CI",
    "gn:dem":303,
    "gn:feature_class":"P",
    "gn:feature_code":"PPL",
    "gn:name":"Limbouriko",
    "gn:population":0,
    "gn:timezone":"Africa/Abidjan",
    "iso:country":"CI",
    "name:und_x_variant":[
        "Sangabadougou",
        "Limbouriko"
    ],
    "wof:name":"Limbouriko",
    "wof:placetype":"locality"
},
  "geometry": {"coordinates":[-7.2153,8.70401],"type":"Point"}
}