{
  "type": "Feature",
  "properties": {
    "gn:admin1_code":"87",
    "gn:asciiname":"Nimbiasso",
    "gn:country_code":"CI",
    "gn:dem":362,
    "gn:feature_class":"P",
    "gn:feature_code":"PPL",
    "gn:name":"Nimbiasso",
    "gn:population":0,
    "gn:timezone":"Africa/Abidjan",
    "iso:country":"CI",
    "name:und_x_variant":[
        "N\u00e9b\u00e9kan",
        "Ninbiasso",
        "Nimbiasso"
    ],
    "wof:name":"Nimbiasso",
    "wof:placetype":"locality"
},
  "geometry": {"coordinates":[-6.43333,9.96667],"type":"Point"}
}