{
  "type": "Feature",
  "properties": {
    "gn:admin1_code":"97",
    "gn:asciiname":"Kologo",
    "gn:country_code":"CI",
    "gn:dem":401,
    "gn:feature_class":"P",
    "gn:feature_code":"PPL",
    "gn:name":"Kologo",
    "gn:population":0,
    "gn:timezone":"Africa/Abidjan",
    "iso:country":"CI",
    "wof:name":"Kologo",
    "wof:placetype":"locality"
},
  "geometry": {"coordinates":[-6.88667,8.97583],"type":"Point"}
}