{
  "type": "Feature",
  "properties": {
    "gn:admin1_code":"87",
    "gn:asciiname":"Nyoroninge",
    "gn:country_code":"CI",
    "gn:dem":331,
    "gn:feature_class":"P",
    "gn:feature_code":"PPL",
    "gn:name":"Nyoroning\u00e9",
    "gn:population":0,
    "gn:timezone":"Africa/Abidjan",
    "iso:country":"CI",
    "name:und_x_variant":[
        "Nioroningu\u00e9",
        "Nyoroning\u00e9"
    ],
    "wof:name":"Nyoroninge",
    "wof:placetype":"locality"
},
  "geometry": {"coordinates":[-5.22131,9.98227],"type":"Point"}
}