{
  "type": "Feature",
  "properties": {
    "gn:admin1_code":"96",
    "gn:asciiname":"Trafla",
    "gn:country_code":"CI",
    "gn:dem":273,
    "gn:feature_class":"P",
    "gn:feature_code":"PPL",
    "gn:name":"Trafla",
    "gn:population":0,
    "gn:timezone":"Africa/Abidjan",
    "iso:country":"CI",
    "wof:name":"Trafla",
    "wof:placetype":"locality"
},
  "geometry": {"coordinates":[-6.37645,7.50388],"type":"Point"}
}