{
  "type": "Feature",
  "properties": {
    "gn:admin1_code":"76",
    "gn:asciiname":"Sotowate",
    "gn:country_code":"CI",
    "gn:dem":42,
    "gn:feature_class":"P",
    "gn:feature_code":"PPL",
    "gn:name":"Sotowat\u00e9",
    "gn:population":0,
    "gn:timezone":"Africa/Abidjan",
    "iso:country":"CI",
    "name:und_x_variant":[
        "Soto Ouat\u00e9",
        "Soto Wat\u00e9",
        "Sotowat\u00e9"
    ],
    "wof:name":"Sotowate",
    "wof:placetype":"locality"
},
  "geometry": {"coordinates":[-7.52569,4.91459],"type":"Point"}
}