{
  "type": "Feature",
  "properties": {
    "gn:admin1_code":"81.0",
    "gn:asciiname":"Boli",
    "gn:country_code":"CI",
    "gn:dem":194,
    "gn:feature_class":"P",
    "gn:feature_code":"PPL",
    "gn:name":"Boli",
    "gn:population":0,
    "gn:timezone":"Africa/Abidjan",
    "iso:country":"CI",
    "name:ara_x_preferred":[
        "\u0628\u0648\u0644\u064a"
    ],
    "name:bar_x_preferred":[
        "Boli"
    ],
    "name:ben_x_preferred":[
        "\u09ac\u09cb\u09b2\u09bf"
    ],
    "name:ceb_x_preferred":[
        "Boli"
    ],
    "name:deu_x_preferred":[
        "Boli"
    ],
    "name:ell_x_preferred":[
        "\u039c\u03c0\u03cc\u03bb\u03b9"
    ],
    "name:fas_x_preferred":[
        "\u0628\u0648\u0644\u06cc"
    ],
    "name:fin_x_preferred":[
        "Boli"
    ],
    "name:fra_x_preferred":[
        "Boli"
    ],
    "name:heb_x_preferred":[
        "\u05d1\u05d5\u05dc\u05d9"
    ],
    "name:hin_x_preferred":[
        "\u092c\u094b\u0932\u0940"
    ],
    "name:hun_x_preferred":[
        "Boli"
    ],
    "name:ind_x_preferred":[
        "Boli"
    ],
    "name:ita_x_preferred":[
        "Boli"
    ],
    "name:jpn_x_preferred":[
        "\u52c3\u5229"
    ],
    "name:kor_x_preferred":[
        "\ubcfc\ub9ac"
    ],
    "name:nld_x_preferred":[
        "Boli"
    ],
    "name:pol_x_preferred":[
        "Boli"
    ],
    "name:rus_x_preferred":[
        "\u0411\u043e\u043b\u0438"
    ],
    "name:spa_x_preferred":[
        "Boli"
    ],
    "name:srp_x_preferred":[
        "\u0411\u043e\u043b\u0438"
    ],
    "name:swe_x_preferred":[
        "Boli"
    ],
    "name:tur_x_preferred":[
        "Boli"
    ],
    "name:ukr_x_preferred":[
        "\u0411\u043e\u043b\u0456"
    ],
    "name:urd_x_preferred":[
        "\u0628\u0648\u0644\u06cc"
    ],
    "name:vie_x_preferred":[
        "B\u1ed9t L\u1ee3i"
    ],
    "name:zho_cn_x_preferred":[
        "\u52c3\u5229\u53bf"
    ],
    "name:zho_tw_x_preferred":[
        "\u52c3\u5229"
    ],
    "wof:name":"Boli",
    "wof:placetype":"locality"
},
  "geometry": {"coordinates":[-4.80666,7.22648],"type":"Point"}
}