{
  "type": "Feature",
  "properties": {
    "gn:admin1_code":"81.0",
    "gn:asciiname":"Boli",
    "gn:country_code":"CI",
    "gn:dem":194,
    "gn:feature_class":"P",
    "gn:feature_code":"PPL",
    "gn:name":"Boli",
    "gn:population":0,
    "gn:timezone":"Africa/Abidjan",
    "iso:country":"CI",
    "wof:name":"Boli",
    "wof:placetype":"locality"
},
  "geometry": {"coordinates":[-4.80666,7.22648],"type":"Point"}
}