{
  "type": "Feature",
  "properties": {
    "gn:admin1_code":"94.0",
    "gn:asciiname":"Roa",
    "gn:country_code":"CI",
    "gn:dem":33,
    "gn:feature_class":"P",
    "gn:feature_code":"PPL",
    "gn:name":"Roa",
    "gn:population":0,
    "gn:timezone":"Africa/Abidjan",
    "iso:country":"CI",
    "wof:name":"Roa",
    "wof:placetype":"locality"
},
  "geometry": {"coordinates":[-3.33048,5.29763],"type":"Point"}
}