{
  "type": "Feature",
  "properties": {
    "gn:admin1_code":"94.0",
    "gn:asciiname":"Roa",
    "gn:country_code":"CI",
    "gn:dem":33,
    "gn:feature_class":"P",
    "gn:feature_code":"PPL",
    "gn:name":"Roa",
    "gn:population":0,
    "gn:timezone":"Africa/Abidjan",
    "iso:country":"CI",
    "name:ceb_x_preferred":[
        "Roa"
    ],
    "name:fra_x_preferred":[
        "Roa"
    ],
    "name:heb_x_preferred":[
        "\u05e8\u05d5\u05d0\u05d4"
    ],
    "name:por_x_preferred":[
        "Roa"
    ],
    "name:spa_x_preferred":[
        "Roa"
    ],
    "name:srp_x_preferred":[
        "\u0420\u043e\u0430"
    ],
    "name:swe_x_preferred":[
        "Roa"
    ],
    "wof:name":"Roa",
    "wof:placetype":"locality"
},
  "geometry": {"coordinates":[-3.33048,5.29763],"type":"Point"}
}