{
  "type": "Feature",
  "properties": {
    "gn:admin1_code":"92.0",
    "gn:asciiname":"Kanguele",
    "gn:country_code":"CI",
    "gn:dem":316,
    "gn:feature_class":"P",
    "gn:feature_code":"PPL",
    "gn:name":"Kangu\u00e9l\u00e9",
    "gn:population":0,
    "gn:timezone":"Africa/Abidjan",
    "iso:country":"CI",
    "name:und_x_variant":[
        "Kien-Guel\u00e9",
        "Kangu\u00e9l\u00e9"
    ],
    "wof:name":"Kanguele",
    "wof:placetype":"locality"
},
  "geometry": {"coordinates":[-3.60952,8.41488],"type":"Point"}
}