{
  "type": "Feature",
  "properties": {
    "gn:admin1_code":"92",
    "gn:asciiname":"Tintiouvri",
    "gn:country_code":"CI",
    "gn:dem":309,
    "gn:feature_class":"P",
    "gn:feature_code":"PPL",
    "gn:name":"Tintiouvri",
    "gn:population":0,
    "gn:timezone":"Africa/Abidjan",
    "iso:country":"CI",
    "wof:name":"Tintiouvri",
    "wof:placetype":"locality"
},
  "geometry": {"coordinates":[-3.40058,9.84134],"type":"Point"}
}