{
  "type": "Feature",
  "properties": {
    "gn:admin1_code":"78.0",
    "gn:asciiname":"Klaon",
    "gn:country_code":"CI",
    "gn:dem":236,
    "gn:feature_class":"P",
    "gn:feature_code":"PPL",
    "gn:name":"Klaon",
    "gn:population":0,
    "gn:timezone":"Africa/Abidjan",
    "iso:country":"CI",
    "wof:name":"Klaon",
    "wof:placetype":"locality"
},
  "geometry": {"coordinates":[-8.52765,6.58526],"type":"Point"}
}