{
  "type": "Feature",
  "properties": {
    "gn:admin1_code":"94.0",
    "gn:asciiname":"Ehania-V6",
    "gn:country_code":"CI",
    "gn:dem":101,
    "gn:feature_class":"P",
    "gn:feature_code":"PPL",
    "gn:name":"Ehania-V6",
    "gn:population":0,
    "gn:timezone":"Africa/Abidjan",
    "iso:country":"CI",
    "wof:name":"Ehania-V6",
    "wof:placetype":"locality"
},
  "geometry": {"coordinates":[-2.98144,5.33867],"type":"Point"}
}