{
  "type": "Feature",
  "properties": {
    "gn:admin1_code":"95.0",
    "gn:asciiname":"Barigueparehoin",
    "gn:country_code":"CI",
    "gn:dem":249,
    "gn:feature_class":"P",
    "gn:feature_code":"PPL",
    "gn:name":"Barigu\u00e9par\u00e9hoin",
    "gn:population":0,
    "gn:timezone":"Africa/Abidjan",
    "iso:country":"CI",
    "name:und_x_variant":[
        "Barigu\u00e9par\u00e9hoin",
        "Bar\u00e9guipar\u00e9hoin"
    ],
    "wof:name":"Barigueparehoin",
    "wof:placetype":"locality"
},
  "geometry": {"coordinates":[-5.74287,6.02193],"type":"Point"}
}