{
  "type": "Feature",
  "properties": {
    "gn:admin1_code":"93.0",
    "gn:asciiname":"Seydou Tchefi",
    "gn:country_code":"CI",
    "gn:dem":11,
    "gn:feature_class":"P",
    "gn:feature_code":"PPL",
    "gn:name":"Seydou Tchefi",
    "gn:population":0,
    "gn:timezone":"Africa/Abidjan",
    "iso:country":"CI",
    "wof:name":"Seydou Tchefi",
    "wof:placetype":"locality"
},
  "geometry": {"coordinates":[-3.78695,5.2808],"type":"Point"}
}