{
  "type": "Feature",
  "properties": {
    "gn:admin1_code":"82.0",
    "gn:asciiname":"Assade Pafou",
    "gn:country_code":"CI",
    "gn:dem":77,
    "gn:feature_class":"P",
    "gn:feature_code":"PPL",
    "gn:name":"Assad\u00e9 Pafou",
    "gn:population":0,
    "gn:timezone":"Africa/Abidjan",
    "iso:country":"CI",
    "wof:name":"Assade Pafou",
    "wof:placetype":"locality"
},
  "geometry": {"coordinates":[-4.4023,5.91688],"type":"Point"}
}