{
  "type": "Feature",
  "properties": {
    "gn:admin1_code":"82",
    "gn:asciiname":"Kong",
    "gn:country_code":"CI",
    "gn:dem":104,
    "gn:feature_class":"P",
    "gn:feature_code":"PPL",
    "gn:name":"Kong",
    "gn:population":0,
    "gn:timezone":"Africa/Abidjan",
    "iso:country":"CI",
    "wof:name":"Kong",
    "wof:placetype":"locality"
},
  "geometry": {"coordinates":[-3.64849,6.11391],"type":"Point"}
}