{
  "type": "Feature",
  "properties": {
    "gn:admin1_code":"87.0",
    "gn:asciiname":"Katonon",
    "gn:country_code":"CI",
    "gn:dem":376,
    "gn:feature_class":"P",
    "gn:feature_code":"PPL",
    "gn:name":"Katonon",
    "gn:population":0,
    "gn:timezone":"Africa/Abidjan",
    "iso:country":"CI",
    "wof:name":"Katonon",
    "wof:placetype":"locality"
},
  "geometry": {"coordinates":[-5.61363,10.03596],"type":"Point"}
}