{
  "type": "Feature",
  "properties": {
    "gn:admin1_code":"76",
    "gn:asciiname":"Neheno",
    "gn:country_code":"CI",
    "gn:dem":12,
    "gn:feature_class":"P",
    "gn:feature_code":"PPL",
    "gn:name":"N\u00e9h\u00e9no",
    "gn:population":0,
    "gn:timezone":"Africa/Abidjan",
    "iso:country":"CI",
    "wof:name":"Neheno",
    "wof:placetype":"locality"
},
  "geometry": {"coordinates":[-7.55347,4.54126],"type":"Point"}
}