{
  "type": "Feature",
  "properties": {
    "gn:admin1_code":"96",
    "gn:asciiname":"Okabo",
    "gn:country_code":"CI",
    "gn:dem":210,
    "gn:feature_class":"P",
    "gn:feature_code":"PPL",
    "gn:name":"Okabo",
    "gn:population":0,
    "gn:timezone":"Africa/Abidjan",
    "iso:country":"CI",
    "name:und_x_variant":[
        "Okouabo",
        "Pangbakouam\u00e9kro",
        "Okabo",
        "Pangban Kouam\u00e9kro",
        "Pangbankouam\u00e9kro"
    ],
    "wof:name":"Okabo",
    "wof:placetype":"locality"
},
  "geometry": {"coordinates":[-5.78102,7.19109],"type":"Point"}
}