{
  "type": "Feature",
  "properties": {
    "gn:admin1_code":"97",
    "gn:asciiname":"Sokoro",
    "gn:country_code":"CI",
    "gn:dem":609,
    "gn:feature_class":"P",
    "gn:feature_code":"PPL",
    "gn:name":"Sokoro",
    "gn:population":0,
    "gn:timezone":"Africa/Abidjan",
    "iso:country":"CI",
    "name:fra_x_preferred":[
        "Sokoro"
    ],
    "name:ita_x_preferred":[
        "Sokoro"
    ],
    "name:msa_x_preferred":[
        "Sokoro"
    ],
    "name:und_x_variant":[
        "S\u00e9koro",
        "Sokoro"
    ],
    "wof:name":"Sokoro",
    "wof:placetype":"locality"
},
  "geometry": {"coordinates":[-7.84214,8.9307],"type":"Point"}
}