{
  "type": "Feature",
  "properties": {
    "gn:admin1_code":"78.0",
    "gn:asciiname":"Klatouo",
    "gn:country_code":"CI",
    "gn:dem":331,
    "gn:feature_class":"P",
    "gn:feature_code":"PPL",
    "gn:name":"Klatouo",
    "gn:population":0,
    "gn:timezone":"Africa/Abidjan",
    "iso:country":"CI",
    "wof:name":"Klatouo",
    "wof:placetype":"locality"
},
  "geometry": {"coordinates":[-8.20836,7.25167],"type":"Point"}
}