{
  "type": "Feature",
  "properties": {
    "gn:admin1_code":"76.0",
    "gn:asciiname":"Klo",
    "gn:country_code":"CI",
    "gn:dem":34,
    "gn:feature_class":"P",
    "gn:feature_code":"PPL",
    "gn:name":"Klo",
    "gn:population":0,
    "gn:timezone":"Africa/Abidjan",
    "iso:country":"CI",
    "wof:name":"Klo",
    "wof:placetype":"locality"
},
  "geometry": {"coordinates":[-7.09119,4.70913],"type":"Point"}
}