{
  "type": "Feature",
  "properties": {
    "gn:admin1_code":"95.0",
    "gn:asciiname":"Bogueoa",
    "gn:country_code":"CI",
    "gn:dem":238,
    "gn:feature_class":"P",
    "gn:feature_code":"PPL",
    "gn:name":"Bogu\u00e9oa",
    "gn:population":0,
    "gn:timezone":"Africa/Abidjan",
    "iso:country":"CI",
    "name:und_x_variant":[
        "Bogu\u00e9oa",
        "Bogu\u00e9hoa"
    ],
    "wof:name":"Bogueoa",
    "wof:placetype":"locality"
},
  "geometry": {"coordinates":[-6.21296,6.31759],"type":"Point"}
}