{
  "type": "Feature",
  "properties": {
    "gn:admin1_code":"87",
    "gn:asciiname":"Nabanavogo",
    "gn:country_code":"CI",
    "gn:dem":349,
    "gn:feature_class":"P",
    "gn:feature_code":"PPL",
    "gn:name":"Nabanavogo",
    "gn:population":0,
    "gn:timezone":"Africa/Abidjan",
    "iso:country":"CI",
    "wof:name":"Nabanavogo",
    "wof:placetype":"locality"
},
  "geometry": {"coordinates":[-5.55478,9.65457],"type":"Point"}
}