{
  "type": "Feature",
  "properties": {
    "gn:admin1_code":"90",
    "gn:asciiname":"Kouarabo",
    "gn:country_code":"CI",
    "gn:dem":215,
    "gn:feature_class":"P",
    "gn:feature_code":"PPL",
    "gn:name":"Kouarabo",
    "gn:population":0,
    "gn:timezone":"Africa/Abidjan",
    "iso:country":"CI",
    "name:und_x_variant":[
        "Kouyaroto"
    ],
    "wof:name":"Kouarabo",
    "wof:placetype":"locality"
},
  "geometry": {"coordinates":[-5.69796,7.80487],"type":"Point"}
}