{
  "type": "Feature",
  "properties": {
    "gn:admin1_code":"78.0",
    "gn:asciiname":"Kebli",
    "gn:country_code":"CI",
    "gn:dem":309,
    "gn:feature_class":"P",
    "gn:feature_code":"PPL",
    "gn:name":"K\u00e9bli",
    "gn:population":0,
    "gn:timezone":"Africa/Abidjan",
    "iso:country":"CI",
    "wof:name":"Kebli",
    "wof:placetype":"locality"
},
  "geometry": {"coordinates":[-7.42349,7.42502],"type":"Point"}
}