{
  "type": "Feature",
  "properties": {
    "gn:admin1_code":"90.0",
    "gn:asciiname":"Gbadougou",
    "gn:country_code":"CI",
    "gn:dem":229,
    "gn:feature_class":"P",
    "gn:feature_code":"PPL",
    "gn:name":"Gbadougou",
    "gn:population":0,
    "gn:timezone":"Africa/Abidjan",
    "iso:country":"CI",
    "wof:name":"Gbadougou",
    "wof:placetype":"locality"
},
  "geometry": {"coordinates":[-4.33524,8.32118],"type":"Point"}
}