{
  "type": "Feature",
  "properties": {
    "gn:admin1_code":"82.0",
    "gn:asciiname":"Ahiroa",
    "gn:country_code":"CI",
    "gn:dem":82,
    "gn:feature_class":"P",
    "gn:feature_code":"PPL",
    "gn:name":"Ahiroa",
    "gn:population":0,
    "gn:timezone":"Africa/Abidjan",
    "iso:country":"CI",
    "name:und_x_variant":[
        "Ahirou",
        "Ahiroa"
    ],
    "wof:name":"Ahiroa",
    "wof:placetype":"locality"
},
  "geometry": {"coordinates":[-4.63357,6.17474],"type":"Point"}
}