{
  "type": "Feature",
  "properties": {
    "gn:admin1_code":"92",
    "gn:asciiname":"Sepere",
    "gn:country_code":"CI",
    "gn:dem":319,
    "gn:feature_class":"P",
    "gn:feature_code":"PPL",
    "gn:name":"S\u00e9per\u00e9",
    "gn:population":0,
    "gn:timezone":"Africa/Abidjan",
    "iso:country":"CI",
    "wof:name":"Sepere",
    "wof:placetype":"locality"
},
  "geometry": {"coordinates":[-3.18026,9.39375],"type":"Point"}
}