{
  "type": "Feature",
  "properties": {
    "gn:admin1_code":"78.0",
    "gn:asciiname":"Gourene",
    "gn:country_code":"CI",
    "gn:dem":741,
    "gn:feature_class":"P",
    "gn:feature_code":"PPL",
    "gn:name":"Gour\u00e9n\u00e9",
    "gn:population":0,
    "gn:timezone":"Africa/Abidjan",
    "iso:country":"CI",
    "wof:name":"Gourene",
    "wof:placetype":"locality"
},
  "geometry": {"coordinates":[-7.38576,7.67165],"type":"Point"}
}