{
  "type": "Feature",
  "properties": {
    "gn:admin1_code":"95",
    "gn:asciiname":"Lagaze",
    "gn:country_code":"CI",
    "gn:dem":171,
    "gn:feature_class":"P",
    "gn:feature_code":"PPL",
    "gn:name":"Lagaz\u00e9",
    "gn:population":0,
    "gn:timezone":"Africa/Abidjan",
    "iso:country":"CI",
    "wof:name":"Lagaze",
    "wof:placetype":"locality"
},
  "geometry": {"coordinates":[-5.45689,5.90569],"type":"Point"}
}