{
  "type": "Feature",
  "properties": {
    "gn:admin1_code":"87",
    "gn:asciiname":"Tyenekaha",
    "gn:country_code":"CI",
    "gn:dem":322,
    "gn:feature_class":"P",
    "gn:feature_code":"PPL",
    "gn:name":"Ty\u00e8nekaha",
    "gn:population":0,
    "gn:timezone":"Africa/Abidjan",
    "iso:country":"CI",
    "wof:name":"Tyenekaha",
    "wof:placetype":"locality"
},
  "geometry": {"coordinates":[-5.3498,9.50054],"type":"Point"}
}