{
  "type": "Feature",
  "properties": {
    "gn:admin1_code":"96",
    "gn:asciiname":"Tadea",
    "gn:country_code":"CI",
    "gn:dem":256,
    "gn:feature_class":"P",
    "gn:feature_code":"PPL",
    "gn:name":"Tad\u00e9a",
    "gn:population":0,
    "gn:timezone":"Africa/Abidjan",
    "iso:country":"CI",
    "name:und_x_variant":[
        "Tad\u00e9a",
        "Tadia"
    ],
    "wof:name":"Tadea",
    "wof:placetype":"locality"
},
  "geometry": {"coordinates":[-6.49358,6.81191],"type":"Point"}
}