{
  "type": "Feature",
  "properties": {
    "gn:admin1_code":"93.0",
    "gn:asciiname":"Zako",
    "gn:country_code":"CI",
    "gn:dem":76,
    "gn:feature_class":"P",
    "gn:feature_code":"PPL",
    "gn:name":"Zako",
    "gn:population":0,
    "gn:timezone":"Africa/Abidjan",
    "iso:country":"CI",
    "wof:name":"Zako",
    "wof:placetype":"locality"
},
  "geometry": {"coordinates":[-3.98835,5.45001],"type":"Point"}
}