{
  "type": "Feature",
  "properties": {
    "gn:admin1_code":"78.0",
    "gn:asciiname":"Gouekangouine",
    "gn:country_code":"CI",
    "gn:dem":321,
    "gn:feature_class":"P",
    "gn:feature_code":"PPL",
    "gn:name":"Gou\u00e9kangouin\u00e9",
    "gn:population":0,
    "gn:timezone":"Africa/Abidjan",
    "iso:country":"CI",
    "name:und_x_variant":[
        "Gou\u00e9kangoui",
        "Gou\u00e9kangouin\u00e9"
    ],
    "wof:name":"Gouekangouine",
    "wof:placetype":"locality"
},
  "geometry": {"coordinates":[-7.65424,7.24071],"type":"Point"}
}