{
  "type": "Feature",
  "properties": {
    "gn:admin1_code":"82.0",
    "gn:asciiname":"Lorn Bobo",
    "gn:country_code":"CI",
    "gn:dem":52,
    "gn:feature_class":"P",
    "gn:feature_code":"PPL",
    "gn:name":"Lorn Bobo",
    "gn:population":0,
    "gn:timezone":"Africa/Abidjan",
    "iso:country":"CI",
    "wof:name":"Lorn Bobo",
    "wof:placetype":"locality"
},
  "geometry": {"coordinates":[-4.40546,5.50621],"type":"Point"}
}