{
  "type": "Feature",
  "properties": {
    "gn:admin1_code":"97.0",
    "gn:asciiname":"Boroso",
    "gn:country_code":"CI",
    "gn:dem":528,
    "gn:feature_class":"P",
    "gn:feature_code":"PPL",
    "gn:name":"Boroso",
    "gn:population":0,
    "gn:timezone":"Africa/Abidjan",
    "iso:country":"CI",
    "wof:name":"Boroso",
    "wof:placetype":"locality"
},
  "geometry": {"coordinates":[-7.92326,8.18882],"type":"Point"}
}