{
  "type": "Feature",
  "properties": {
    "gn:admin1_code":"87.0",
    "gn:asciiname":"Doromanivogo",
    "gn:country_code":"CI",
    "gn:dem":376,
    "gn:feature_class":"P",
    "gn:feature_code":"PPL",
    "gn:name":"Doromanivogo",
    "gn:population":0,
    "gn:timezone":"Africa/Abidjan",
    "iso:country":"CI",
    "wof:name":"Doromanivogo",
    "wof:placetype":"locality"
},
  "geometry": {"coordinates":[-5.78333,9.53333],"type":"Point"}
}