{
  "type": "Feature",
  "properties": {
    "gn:admin1_code":"76.0",
    "gn:asciiname":"Buyo",
    "gn:country_code":"CI",
    "gn:dem":229,
    "gn:feature_class":"P",
    "gn:feature_code":"PPLA3",
    "gn:name":"Buyo",
    "gn:population":0,
    "gn:timezone":"Africa/Abidjan",
    "iso:country":"CI",
    "name:ceb_x_preferred":[
        "Buyo"
    ],
    "name:deu_x_preferred":[
        "Buyo"
    ],
    "name:fra_x_preferred":[
        "Buyo"
    ],
    "name:rus_x_preferred":[
        "\u0411\u0443\u0439\u043e"
    ],
    "name:tgl_x_preferred":[
        "Buyo"
    ],
    "name:und_x_variant":[
        "Bouyo",
        "Lagoguh\u00e9"
    ],
    "wof:name":"Buyo",
    "wof:placetype":"locality"
},
  "geometry": {"coordinates":[-6.99704,6.27534],"type":"Point"}
}