{
  "type": "Feature",
  "properties": {
    "gn:admin1_code":"92.0",
    "gn:asciiname":"Baloun",
    "gn:country_code":"CI",
    "gn:dem":287,
    "gn:feature_class":"P",
    "gn:feature_code":"PPL",
    "gn:name":"Baloun",
    "gn:population":0,
    "gn:timezone":"Africa/Abidjan",
    "iso:country":"CI",
    "wof:name":"Baloun",
    "wof:placetype":"locality"
},
  "geometry": {"coordinates":[-3.04046,9.57928],"type":"Point"}
}