{
  "type": "Feature",
  "properties": {
    "gn:admin1_code":"97.0",
    "gn:asciiname":"Banjo",
    "gn:country_code":"CI",
    "gn:dem":313,
    "gn:feature_class":"P",
    "gn:feature_code":"PPL",
    "gn:name":"Banjo",
    "gn:population":0,
    "gn:timezone":"Africa/Abidjan",
    "iso:country":"CI",
    "name:ara_x_preferred":[
        "\u0628\u0627\u0646\u062c\u0648"
    ],
    "name:bel_x_preferred":[
        "\u0411\u0430\u043d\u0434\u0436\u0430"
    ],
    "name:bul_x_preferred":[
        "\u0411\u0430\u043d\u0434\u0436\u043e"
    ],
    "name:cat_x_preferred":[
        "Banjo"
    ],
    "name:ces_x_preferred":[
        "Banjo"
    ],
    "name:cym_x_preferred":[
        "Banjo"
    ],
    "name:dan_x_preferred":[
        "Banjo"
    ],
    "name:deu_x_preferred":[
        "Banjo"
    ],
    "name:epo_x_preferred":[
        "Ban\u011do"
    ],
    "name:est_x_preferred":[
        "Band\u017eo"
    ],
    "name:eus_x_preferred":[
        "Banjo"
    ],
    "name:fas_x_preferred":[
        "\u0628\u0627\u0646\u062c\u0648"
    ],
    "name:fin_x_preferred":[
        "Banjo"
    ],
    "name:fra_x_preferred":[
        "Banjo"
    ],
    "name:gla_x_preferred":[
        "Bainsi\u00f2"
    ],
    "name:gle_x_preferred":[
        "Bainse\u00f3"
    ],
    "name:glg_x_preferred":[
        "Banjo"
    ],
    "name:heb_x_preferred":[
        "\u05d1\u05e0\u05d2'\u05d5"
    ],
    "name:hrv_x_preferred":[
        "Bend\u017eo"
    ],
    "name:hun_x_preferred":[
        "Bendzs\u00f3"
    ],
    "name:hye_x_preferred":[
        "\u0532\u0561\u0576\u057b\u0578"
    ],
    "name:ind_x_preferred":[
        "Banjo"
    ],
    "name:ita_x_preferred":[
        "Banjo"
    ],
    "name:jpn_x_preferred":[
        "\u30d0\u30f3\u30b8\u30e7\u30fc"
    ],
    "name:kat_x_preferred":[
        "\u10d1\u10d0\u10dc\u10ef\u10dd"
    ],
    "name:kir_x_preferred":[
        "\u0411\u0430\u043d\u0434\u0436\u043e"
    ],
    "name:lat_x_preferred":[
        "Banio"
    ],
    "name:lav_x_preferred":[
        "Band\u017eo"
    ],
    "name:lit_x_preferred":[
        "Band\u017ea"
    ],
    "name:mkd_x_preferred":[
        "\u0411\u0435\u043d\u045f\u043e"
    ],
    "name:mya_x_preferred":[
        "\u1018\u1004\u103a\u1002\u103b\u102d\u102f"
    ],
    "name:nds_x_preferred":[
        "Banjo"
    ],
    "name:nld_x_preferred":[
        "Banjo"
    ],
    "name:nno_x_preferred":[
        "Banjo"
    ],
    "name:nor_x_preferred":[
        "Banjo"
    ],
    "name:oci_x_preferred":[
        "Banjo"
    ],
    "name:oss_x_preferred":[
        "\u0411\u0430\u043d\u0434\u0436\u043e"
    ],
    "name:pol_x_preferred":[
        "Banjo"
    ],
    "name:por_x_preferred":[
        "Banjo"
    ],
    "name:ron_x_preferred":[
        "Banjo"
    ],
    "name:rus_x_preferred":[
        "\u0411\u0430\u043d\u0434\u0436\u043e"
    ],
    "name:sco_x_preferred":[
        "Banjo"
    ],
    "name:slk_x_preferred":[
        "Bend\u017eo"
    ],
    "name:slv_x_preferred":[
        "Banjo"
    ],
    "name:spa_x_preferred":[
        "Banyo"
    ],
    "name:srp_x_preferred":[
        "\u0411\u0435\u043d\u045f\u043e"
    ],
    "name:swe_x_preferred":[
        "Banjo"
    ],
    "name:tgl_x_preferred":[
        "Bandyo"
    ],
    "name:tur_x_preferred":[
        "Banjo"
    ],
    "name:ukr_x_preferred":[
        "\u0411\u0430\u043d\u0434\u0436\u043e"
    ],
    "name:uzb_x_preferred":[
        "Banjo"
    ],
    "name:vie_x_preferred":[
        "B\u0103ng c\u1ea7m"
    ],
    "name:zho_x_preferred":[
        "\u73ed\u5353\u7434"
    ],
    "wof:name":"Banjo",
    "wof:placetype":"locality"
},
  "geometry": {"coordinates":[-7.21398,8.33736],"type":"Point"}
}