{
  "type": "Feature",
  "properties": {
    "gn:admin1_code":"95.0",
    "gn:asciiname":"Bolilie",
    "gn:country_code":"CI",
    "gn:dem":174,
    "gn:feature_class":"P",
    "gn:feature_code":"PPL",
    "gn:name":"Bolili\u00e9",
    "gn:population":0,
    "gn:timezone":"Africa/Abidjan",
    "iso:country":"CI",
    "wof:name":"Bolilie",
    "wof:placetype":"locality"
},
  "geometry": {"coordinates":[-5.41676,5.9899],"type":"Point"}
}