{
  "type": "Feature",
  "properties": {
    "gn:admin1_code":"93.0",
    "gn:asciiname":"Ladji",
    "gn:country_code":"CI",
    "gn:dem":16,
    "gn:feature_class":"P",
    "gn:feature_code":"PPL",
    "gn:name":"Ladji",
    "gn:population":0,
    "gn:timezone":"Africa/Abidjan",
    "iso:country":"CI",
    "wof:name":"Ladji",
    "wof:placetype":"locality"
},
  "geometry": {"coordinates":[-4.22729,5.24718],"type":"Point"}
}