{
  "type": "Feature",
  "properties": {
    "gn:admin1_code":"87",
    "gn:asciiname":"Nanvakaha",
    "gn:country_code":"CI",
    "gn:dem":341,
    "gn:feature_class":"P",
    "gn:feature_code":"PPL",
    "gn:name":"Nanvakaha",
    "gn:population":0,
    "gn:timezone":"Africa/Abidjan",
    "iso:country":"CI",
    "wof:name":"Nanvakaha",
    "wof:placetype":"locality"
},
  "geometry": {"coordinates":[-5.4302,9.3513],"type":"Point"}
}