{
  "type": "Feature",
  "properties": {
    "gn:admin1_code":"94.0",
    "gn:asciiname":"Ebotiam",
    "gn:country_code":"CI",
    "gn:dem":10,
    "gn:feature_class":"P",
    "gn:feature_code":"PPL",
    "gn:name":"Ebotiam",
    "gn:population":0,
    "gn:timezone":"Africa/Abidjan",
    "iso:country":"CI",
    "wof:name":"Ebotiam",
    "wof:placetype":"locality"
},
  "geometry": {"coordinates":[-3.4296,5.15341],"type":"Point"}
}