{
  "type": "Feature",
  "properties": {
    "gn:admin1_code":"96",
    "gn:asciiname":"Tiahouo",
    "gn:country_code":"CI",
    "gn:dem":288,
    "gn:feature_class":"P",
    "gn:feature_code":"PPL",
    "gn:name":"Tiahouo",
    "gn:population":0,
    "gn:timezone":"Africa/Abidjan",
    "iso:country":"CI",
    "name:und_x_variant":[
        "Tiaouo",
        "Tyaouo",
        "Tiahouo"
    ],
    "wof:name":"Tiahouo",
    "wof:placetype":"locality"
},
  "geometry": {"coordinates":[-6.50595,7.48796],"type":"Point"}
}