{
  "type": "Feature",
  "properties": {
    "gn:admin1_code":"92",
    "gn:asciiname":"Sanguehi",
    "gn:country_code":"CI",
    "gn:dem":214,
    "gn:feature_class":"P",
    "gn:feature_code":"PPL",
    "gn:name":"Sangu\u00e9hi",
    "gn:population":0,
    "gn:timezone":"Africa/Abidjan",
    "iso:country":"CI",
    "wof:name":"Sanguehi",
    "wof:placetype":"locality"
},
  "geometry": {"coordinates":[-3.648,8.11476],"type":"Point"}
}