{
  "type": "Feature",
  "properties": {
    "gn:admin1_code":"97.0",
    "gn:asciiname":"Dyorofa",
    "gn:country_code":"CI",
    "gn:dem":419,
    "gn:feature_class":"P",
    "gn:feature_code":"PPL",
    "gn:name":"Dyorofa",
    "gn:population":0,
    "gn:timezone":"Africa/Abidjan",
    "iso:country":"CI",
    "wof:name":"Dyorofa",
    "wof:placetype":"locality"
},
  "geometry": {"coordinates":[-6.94344,8.7092],"type":"Point"}
}