{
  "type": "Feature",
  "properties": {
    "gn:admin1_code":"76",
    "gn:asciiname":"Nero-Brousse",
    "gn:country_code":"CI",
    "gn:dem":30,
    "gn:feature_class":"P",
    "gn:feature_code":"PPL",
    "gn:name":"Nero-Brousse",
    "gn:population":0,
    "gn:timezone":"Africa/Abidjan",
    "iso:country":"CI",
    "wof:name":"Nero-Brousse",
    "wof:placetype":"locality"
},
  "geometry": {"coordinates":[-6.92561,4.80636],"type":"Point"}
}