{
  "type": "Feature",
  "properties": {
    "gn:admin1_code":"78.0",
    "gn:asciiname":"Gueya",
    "gn:country_code":"CI",
    "gn:dem":283,
    "gn:feature_class":"P",
    "gn:feature_code":"PPL",
    "gn:name":"Gu\u00e9ya",
    "gn:population":0,
    "gn:timezone":"Africa/Abidjan",
    "iso:country":"CI",
    "wof:name":"Gueya",
    "wof:placetype":"locality"
},
  "geometry": {"coordinates":[-8.48372,6.5456],"type":"Point"}
}