{
  "type": "Feature",
  "properties": {
    "gn:admin1_code":"96",
    "gn:asciiname":"Tenefero",
    "gn:country_code":"CI",
    "gn:dem":334,
    "gn:feature_class":"P",
    "gn:feature_code":"PPL",
    "gn:name":"T\u00e9n\u00e9fero",
    "gn:population":0,
    "gn:timezone":"Africa/Abidjan",
    "iso:country":"CI",
    "name:und_x_variant":[
        "T\u00e9f\u00e9nero",
        "T\u00e9n\u00e9f\u00e9re",
        "T\u00e9n\u00e9fi\u00e9",
        "T\u00e9n\u00e9foro",
        "T\u00e9n\u00e9fero"
    ],
    "wof:name":"Tenefero",
    "wof:placetype":"locality"
},
  "geometry": {"coordinates":[-6.59461,7.76032],"type":"Point"}
}