{
  "type": "Feature",
  "properties": {
    "gn:admin1_code":"92",
    "gn:asciiname":"Minda",
    "gn:country_code":"CI",
    "gn:dem":318,
    "gn:feature_class":"P",
    "gn:feature_code":"PPL",
    "gn:name":"Minda",
    "gn:population":0,
    "gn:timezone":"Africa/Abidjan",
    "iso:country":"CI",
    "wof:name":"Minda",
    "wof:placetype":"locality"
},
  "geometry": {"coordinates":[-3.75,9.71667],"type":"Point"}
}