{
  "type": "Feature",
  "properties": {
    "gn:admin1_code":"82.0",
    "gn:asciiname":"Boudepe",
    "gn:country_code":"CI",
    "gn:dem":111,
    "gn:feature_class":"P",
    "gn:feature_code":"PPL",
    "gn:name":"Boud\u00e9p\u00e9",
    "gn:population":0,
    "gn:timezone":"Africa/Abidjan",
    "iso:country":"CI",
    "name:fra_x_preferred":[
        "Boud\u00e9p\u00e9"
    ],
    "name:msa_x_preferred":[
        "Boud\u00e9p\u00e9"
    ],
    "name:ron_x_preferred":[
        "Boud\u00e9p\u00e9"
    ],
    "wof:name":"Boudepe",
    "wof:placetype":"locality"
},
  "geometry": {"coordinates":[-3.98698,5.98392],"type":"Point"}
}