{
  "type": "Feature",
  "properties": {
    "gn:admin1_code":"76",
    "gn:asciiname":"Koziayo II",
    "gn:country_code":"CI",
    "gn:dem":182,
    "gn:feature_class":"P",
    "gn:feature_code":"PPL",
    "gn:name":"Koziayo II",
    "gn:population":0,
    "gn:timezone":"Africa/Abidjan",
    "iso:country":"CI",
    "wof:name":"Koziayo II",
    "wof:placetype":"locality"
},
  "geometry": {"coordinates":[-6.34379,5.92426],"type":"Point"}
}