{
  "type": "Feature",
  "properties": {
    "gn:admin1_code":"95.0",
    "gn:asciiname":"Balouepalenyoa",
    "gn:country_code":"CI",
    "gn:dem":190,
    "gn:feature_class":"P",
    "gn:feature_code":"PPL",
    "gn:name":"Balouepal\u00e9nyoa",
    "gn:population":0,
    "gn:timezone":"Africa/Abidjan",
    "iso:country":"CI",
    "name:und_x_variant":[
        "Balou\u00e9pal\u00e9gnoa",
        "Balouepal\u00e9nyoa"
    ],
    "wof:name":"Balouepalenyoa",
    "wof:placetype":"locality"
},
  "geometry": {"coordinates":[-5.98444,5.91389],"type":"Point"}
}