{
  "type": "Feature",
  "properties": {
    "gn:admin1_code":"81.0",
    "gn:asciiname":"Bokakro",
    "gn:country_code":"CI",
    "gn:dem":238,
    "gn:feature_class":"P",
    "gn:feature_code":"PPL",
    "gn:name":"Bokakro",
    "gn:population":0,
    "gn:timezone":"Africa/Abidjan",
    "iso:country":"CI",
    "wof:name":"Bokakro",
    "wof:placetype":"locality"
},
  "geometry": {"coordinates":[-4.03333,7.13333],"type":"Point"}
}