{
  "type": "Feature",
  "properties": {
    "gn:admin1_code":"76",
    "gn:asciiname":"Zadieguhe",
    "gn:country_code":"CI",
    "gn:dem":233,
    "gn:feature_class":"P",
    "gn:feature_code":"PPL",
    "gn:name":"Zadi\u00e9guh\u00e9",
    "gn:population":0,
    "gn:timezone":"Africa/Abidjan",
    "iso:country":"CI",
    "name:und_x_variant":[
        "Zadigu\u00e9",
        "Zadi\u00e9guh\u00e9"
    ],
    "wof:name":"Zadieguhe",
    "wof:placetype":"locality"
},
  "geometry": {"coordinates":[-6.53444,6.12972],"type":"Point"}
}