{
  "type": "Feature",
  "properties": {
    "gn:admin1_code":"81",
    "gn:asciiname":"Konandiekro",
    "gn:country_code":"CI",
    "gn:dem":201,
    "gn:feature_class":"P",
    "gn:feature_code":"PPL",
    "gn:name":"Konandi\u00e9kro",
    "gn:population":0,
    "gn:timezone":"Africa/Abidjan",
    "iso:country":"CI",
    "wof:name":"Konandiekro",
    "wof:placetype":"locality"
},
  "geometry": {"coordinates":[-4.78917,7.24194],"type":"Point"}
}