{
  "type": "Feature",
  "properties": {
    "gn:admin1_code":"96",
    "gn:asciiname":"Tibeita",
    "gn:country_code":"CI",
    "gn:dem":205,
    "gn:feature_class":"P",
    "gn:feature_code":"PPL",
    "gn:name":"Tib\u00e9ita",
    "gn:population":0,
    "gn:timezone":"Africa/Abidjan",
    "iso:country":"CI",
    "name:fra_x_preferred":[
        "Tib\u00e9ita"
    ],
    "name:ita_x_preferred":[
        "Tib\u00e9ita"
    ],
    "name:msa_x_preferred":[
        "Tib\u00e9ita"
    ],
    "wof:name":"Tibeita",
    "wof:placetype":"locality"
},
  "geometry": {"coordinates":[-5.82323,7.18271],"type":"Point"}
}