{
  "type": "Feature",
  "properties": {
    "gn:admin1_code":"78",
    "gn:asciiname":"Pouzigui",
    "gn:country_code":"CI",
    "gn:dem":302,
    "gn:feature_class":"P",
    "gn:feature_code":"PPL",
    "gn:name":"Pouzigui",
    "gn:population":0,
    "gn:timezone":"Africa/Abidjan",
    "iso:country":"CI",
    "name:und_x_variant":[
        "Pizigui",
        "Pizigi",
        "Pouzigui"
    ],
    "wof:name":"Pouzigui",
    "wof:placetype":"locality"
},
  "geometry": {"coordinates":[-7.89587,7.1607],"type":"Point"}
}