{
  "type": "Feature",
  "properties": {
    "gn:admin1_code":"77",
    "gn:asciiname":"Sanangourani",
    "gn:country_code":"CI",
    "gn:dem":414,
    "gn:feature_class":"P",
    "gn:feature_code":"PPL",
    "gn:name":"Sanangourani",
    "gn:population":0,
    "gn:timezone":"Africa/Abidjan",
    "iso:country":"CI",
    "wof:name":"Sanangourani",
    "wof:placetype":"locality"
},
  "geometry": {"coordinates":[-7.81021,9.71984],"type":"Point"}
}