{
  "type": "Feature",
  "properties": {
    "gn:admin1_code":"81.0",
    "gn:asciiname":"Esseyakro",
    "gn:country_code":"CI",
    "gn:dem":108,
    "gn:feature_class":"P",
    "gn:feature_code":"PPL",
    "gn:name":"Ess\u00e9yakro",
    "gn:population":0,
    "gn:timezone":"Africa/Abidjan",
    "iso:country":"CI",
    "name:und_x_variant":[
        "Ess\u00e9yakro",
        "Ess\u00e9akro"
    ],
    "wof:name":"Esseyakro",
    "wof:placetype":"locality"
},
  "geometry": {"coordinates":[-4.4783,6.79558],"type":"Point"}
}