{
  "type": "Feature",
  "properties": {
    "gn:admin1_code":"82.0",
    "gn:asciiname":"Yao",
    "gn:country_code":"CI",
    "gn:dem":57,
    "gn:feature_class":"P",
    "gn:feature_code":"PPL",
    "gn:name":"Yao",
    "gn:population":0,
    "gn:timezone":"Africa/Abidjan",
    "iso:country":"CI",
    "name:bul_x_preferred":[
        "\u042f\u043e"
    ],
    "name:cat_x_preferred":[
        "Yao"
    ],
    "name:ceb_x_preferred":[
        "Yao"
    ],
    "name:deu_x_preferred":[
        "Yao"
    ],
    "name:fra_x_preferred":[
        "Yao"
    ],
    "name:heb_x_preferred":[
        "\u05d9\u05d0\u05d5"
    ],
    "name:mlg_x_preferred":[
        "Yao"
    ],
    "name:nld_x_preferred":[
        "Yao"
    ],
    "name:nno_x_preferred":[
        "Yao"
    ],
    "name:nor_x_preferred":[
        "Yao"
    ],
    "name:pol_x_preferred":[
        "Yao"
    ],
    "name:por_x_preferred":[
        "Yao"
    ],
    "name:ron_x_preferred":[
        "Yao"
    ],
    "name:srp_x_preferred":[
        "\u0408\u0430\u043e"
    ],
    "name:swe_x_preferred":[
        "Yao"
    ],
    "name:tgl_x_preferred":[
        "Yao"
    ],
    "name:tur_x_preferred":[
        "Yao"
    ],
    "wof:name":"Yao",
    "wof:placetype":"locality"
},
  "geometry": {"coordinates":[-4.26032,5.91933],"type":"Point"}
}