{
  "type": "Feature",
  "properties": {
    "gn:admin1_code":"82.0",
    "gn:asciiname":"Akrou",
    "gn:country_code":"CI",
    "gn:dem":10,
    "gn:feature_class":"P",
    "gn:feature_code":"PPL",
    "gn:name":"Akrou",
    "gn:population":0,
    "gn:timezone":"Africa/Abidjan",
    "iso:country":"CI",
    "wof:name":"Akrou",
    "wof:placetype":"locality"
},
  "geometry": {"coordinates":[-4.3572,5.20814],"type":"Point"}
}