{
  "type": "Feature",
  "properties": {
    "gn:admin1_code":"90",
    "gn:asciiname":"Soungbonon-Bambarasso",
    "gn:country_code":"CI",
    "gn:dem":394,
    "gn:feature_class":"P",
    "gn:feature_code":"PPL",
    "gn:name":"Soungbonon-Bambarasso",
    "gn:population":0,
    "gn:timezone":"Africa/Abidjan",
    "iso:country":"CI",
    "name:und_x_variant":[
        "Soungbono",
        "Sougbono",
        "Soungbonon-Bambarasso"
    ],
    "wof:name":"Soungbonon-Bambarasso",
    "wof:placetype":"locality"
},
  "geometry": {"coordinates":[-4.55,8.53333],"type":"Point"}
}