{
  "type": "Feature",
  "properties": {
    "gn:admin1_code":"97",
    "gn:asciiname":"Modougou",
    "gn:country_code":"CI",
    "gn:dem":565,
    "gn:feature_class":"P",
    "gn:feature_code":"PPL",
    "gn:name":"Modougou",
    "gn:population":0,
    "gn:timezone":"Africa/Abidjan",
    "iso:country":"CI",
    "wof:name":"Modougou",
    "wof:placetype":"locality"
},
  "geometry": {"coordinates":[-7.8401,8.95308],"type":"Point"}
}