{
  "type": "Feature",
  "properties": {
    "gn:admin1_code":"90",
    "gn:asciiname":"Konakro",
    "gn:country_code":"CI",
    "gn:dem":274,
    "gn:feature_class":"P",
    "gn:feature_code":"PPL",
    "gn:name":"Konakro",
    "gn:population":0,
    "gn:timezone":"Africa/Abidjan",
    "iso:country":"CI",
    "wof:name":"Konakro",
    "wof:placetype":"locality"
},
  "geometry": {"coordinates":[-5.026,7.45989],"type":"Point"}
}