{
  "type": "Feature",
  "properties": {
    "gn:admin1_code":"96.0",
    "gn:asciiname":"Boboniessoko",
    "gn:country_code":"CI",
    "gn:dem":237,
    "gn:feature_class":"P",
    "gn:feature_code":"PPL",
    "gn:name":"Boboniessoko",
    "gn:population":0,
    "gn:timezone":"Africa/Abidjan",
    "iso:country":"CI",
    "name:und_x_variant":[
        "Bobo Niassoko",
        "Bobo-Niasoko",
        "Bobo",
        "Boboniessoko"
    ],
    "wof:name":"Boboniessoko",
    "wof:placetype":"locality"
},
  "geometry": {"coordinates":[-6.65652,6.96589],"type":"Point"}
}