{
  "type": "Feature",
  "properties": {
    "gn:admin1_code":"90.0",
    "gn:asciiname":"Bendekro",
    "gn:country_code":"CI",
    "gn:dem":207,
    "gn:feature_class":"P",
    "gn:feature_code":"PPL",
    "gn:name":"Bend\u00e9kro",
    "gn:population":0,
    "gn:timezone":"Africa/Abidjan",
    "iso:country":"CI",
    "wof:name":"Bendekro",
    "wof:placetype":"locality"
},
  "geometry": {"coordinates":[-5.62861,7.90134],"type":"Point"}
}