{
  "type": "Feature",
  "properties": {
    "gn:admin1_code":"81.0",
    "gn:asciiname":"Abiguy",
    "gn:country_code":"CI",
    "gn:dem":177,
    "gn:feature_class":"P",
    "gn:feature_code":"PPL",
    "gn:name":"Abiguy",
    "gn:population":0,
    "gn:timezone":"Africa/Abidjan",
    "iso:country":"CI",
    "name:und_x_variant":[
        "Abigou"
    ],
    "wof:name":"Abiguy",
    "wof:placetype":"locality"
},
  "geometry": {"coordinates":[-5.01509,6.94211],"type":"Point"}
}