{
  "type": "Feature",
  "properties": {
    "gn:admin1_code":"94.0",
    "gn:asciiname":"Kalfadougou",
    "gn:country_code":"CI",
    "gn:dem":33,
    "gn:feature_class":"P",
    "gn:feature_code":"PPL",
    "gn:name":"Kalfadougou",
    "gn:population":0,
    "gn:timezone":"Africa/Abidjan",
    "iso:country":"CI",
    "wof:name":"Kalfadougou",
    "wof:placetype":"locality"
},
  "geometry": {"coordinates":[-3.34088,5.47846],"type":"Point"}
}