{
  "type": "Feature",
  "properties": {
    "gn:admin1_code":"82.0",
    "gn:asciiname":"Bakriokronou",
    "gn:country_code":"CI",
    "gn:dem":42,
    "gn:feature_class":"P",
    "gn:feature_code":"PPL",
    "gn:name":"Bakriokronou",
    "gn:population":0,
    "gn:timezone":"Africa/Abidjan",
    "iso:country":"CI",
    "wof:name":"Bakriokronou",
    "wof:placetype":"locality"
},
  "geometry": {"coordinates":[-4.44226,5.57839],"type":"Point"}
}