{
  "type": "Feature",
  "properties": {
    "gn:admin1_code":"98.0",
    "gn:asciiname":"Attiegouakro",
    "gn:country_code":"CI",
    "gn:dem":212,
    "gn:feature_class":"P",
    "gn:feature_code":"PPLA3",
    "gn:name":"Atti\u00e9gouakro",
    "gn:population":0,
    "gn:timezone":"Africa/Abidjan",
    "iso:country":"CI",
    "name:und_x_variant":[
        "Atti\u00e9gouakro"
    ],
    "wof:name":"Attiegouakro",
    "wof:placetype":"locality"
},
  "geometry": {"coordinates":[-5.11411,6.77402],"type":"Point"}
}