{
  "type": "Feature",
  "properties": {
    "gn:admin1_code":"94.0",
    "gn:asciiname":"Elobenieni",
    "gn:country_code":"CI",
    "gn:dem":74,
    "gn:feature_class":"P",
    "gn:feature_code":"PPL",
    "gn:name":"\u00c9lob\u00e9ni\u00e9ni",
    "gn:population":0,
    "gn:timezone":"Africa/Abidjan",
    "iso:country":"CI",
    "wof:name":"Elobenieni",
    "wof:placetype":"locality"
},
  "geometry": {"coordinates":[-3.52497,5.167],"type":"Point"}
}