{
  "type": "Feature",
  "properties": {
    "gn:admin1_code":"92.0",
    "gn:asciiname":"Guinanboum",
    "gn:country_code":"CI",
    "gn:dem":292,
    "gn:feature_class":"P",
    "gn:feature_code":"PPL",
    "gn:name":"Guinanboum",
    "gn:population":0,
    "gn:timezone":"Africa/Abidjan",
    "iso:country":"CI",
    "wof:name":"Guinanboum",
    "wof:placetype":"locality"
},
  "geometry": {"coordinates":[-3.00911,9.56132],"type":"Point"}
}