{
  "type": "Feature",
  "properties": {
    "gn:admin1_code":"81",
    "gn:asciiname":"Kpouebo",
    "gn:country_code":"CI",
    "gn:dem":96,
    "gn:feature_class":"P",
    "gn:feature_code":"PPL",
    "gn:name":"Kpou\u00e9bo",
    "gn:population":0,
    "gn:timezone":"Africa/Abidjan",
    "iso:country":"CI",
    "name:fra_x_preferred":[
        "Kpou\u00e8bo"
    ],
    "name:ita_x_preferred":[
        "Kpou\u00e8bo"
    ],
    "name:msa_x_preferred":[
        "Kpou\u00e8bo"
    ],
    "name:und_x_variant":[
        "Kpou\u00e9bo"
    ],
    "wof:name":"Kpouebo",
    "wof:placetype":"locality"
},
  "geometry": {"coordinates":[-4.85618,6.33441],"type":"Point"}
}