{
  "type": "Feature",
  "properties": {
    "gn:admin1_code":"76.0",
    "gn:asciiname":"Gougoueoua",
    "gn:country_code":"CI",
    "gn:dem":203,
    "gn:feature_class":"P",
    "gn:feature_code":"PPL",
    "gn:name":"Gougou\u00e9oua",
    "gn:population":0,
    "gn:timezone":"Africa/Abidjan",
    "iso:country":"CI",
    "name:und_x_variant":[
        "Gogouahiouroua",
        "Gougouh\u00e9oua",
        "Gougou\u00e9oua"
    ],
    "wof:name":"Gougoueoua",
    "wof:placetype":"locality"
},
  "geometry": {"coordinates":[-6.52139,6.1175],"type":"Point"}
}