{
  "type": "Feature",
  "properties": {
    "gn:admin1_code":"78",
    "gn:asciiname":"Soupleu",
    "gn:country_code":"CI",
    "gn:dem":336,
    "gn:feature_class":"P",
    "gn:feature_code":"PPL",
    "gn:name":"Soupleu",
    "gn:population":0,
    "gn:timezone":"Africa/Abidjan",
    "iso:country":"CI",
    "wof:name":"Soupleu",
    "wof:placetype":"locality"
},
  "geometry": {"coordinates":[-7.58322,7.27033],"type":"Point"}
}