{
  "type": "Feature",
  "properties": {
    "gn:admin1_code":"81",
    "gn:asciiname":"Kora-Akissikro",
    "gn:country_code":"CI",
    "gn:dem":175,
    "gn:feature_class":"P",
    "gn:feature_code":"PPL",
    "gn:name":"Kora-Akissikro",
    "gn:population":0,
    "gn:timezone":"Africa/Abidjan",
    "iso:country":"CI",
    "wof:name":"Kora-Akissikro",
    "wof:placetype":"locality"
},
  "geometry": {"coordinates":[-4.50333,7.49056],"type":"Point"}
}