{
  "type": "Feature",
  "properties": {
    "gn:admin1_code":"81.0",
    "gn:asciiname":"Ngouan Te",
    "gn:country_code":"CI",
    "gn:dem":162,
    "gn:feature_class":"P",
    "gn:feature_code":"PPL",
    "gn:name":"Ngouan T\u00e9",
    "gn:population":0,
    "gn:timezone":"Africa/Abidjan",
    "iso:country":"CI",
    "wof:name":"Ngouan Te",
    "wof:placetype":"locality"
},
  "geometry": {"coordinates":[-4.70915,7.03423],"type":"Point"}
}