{
  "type": "Feature",
  "properties": {
    "gn:admin1_code":"97.0",
    "gn:asciiname":"Bayakala",
    "gn:country_code":"CI",
    "gn:dem":286,
    "gn:feature_class":"P",
    "gn:feature_code":"PPL",
    "gn:name":"Bayakala",
    "gn:population":0,
    "gn:timezone":"Africa/Abidjan",
    "iso:country":"CI",
    "wof:name":"Bayakala",
    "wof:placetype":"locality"
},
  "geometry": {"coordinates":[-5.96667,8.13333],"type":"Point"}
}