{
  "type": "Feature",
  "properties": {
    "gn:admin1_code":"78.0",
    "gn:asciiname":"Nizahon II",
    "gn:country_code":"CI",
    "gn:dem":243,
    "gn:feature_class":"P",
    "gn:feature_code":"PPL",
    "gn:name":"Nizahon II",
    "gn:population":0,
    "gn:timezone":"Africa/Abidjan",
    "iso:country":"CI",
    "wof:name":"Nizahon II",
    "wof:placetype":"locality"
},
  "geometry": {"coordinates":[-7.39891,6.37222],"type":"Point"}
}