{
  "type": "Feature",
  "properties": {
    "gn:admin1_code":"95.0",
    "gn:asciiname":"Daligoulilie",
    "gn:country_code":"CI",
    "gn:dem":236,
    "gn:feature_class":"P",
    "gn:feature_code":"PPL",
    "gn:name":"Daligoulili\u00e9",
    "gn:population":0,
    "gn:timezone":"Africa/Abidjan",
    "iso:country":"CI",
    "wof:name":"Daligoulilie",
    "wof:placetype":"locality"
},
  "geometry": {"coordinates":[-5.73834,5.85895],"type":"Point"}
}