{
  "type": "Feature",
  "properties": {
    "gn:admin1_code":"76",
    "gn:asciiname":"Nani",
    "gn:country_code":"CI",
    "gn:dem":39,
    "gn:feature_class":"P",
    "gn:feature_code":"PPL",
    "gn:name":"Nani",
    "gn:population":0,
    "gn:timezone":"Africa/Abidjan",
    "iso:country":"CI",
    "name:und_x_variant":[
        "Ngani",
        "Nani"
    ],
    "wof:name":"Nani",
    "wof:placetype":"locality"
},
  "geometry": {"coordinates":[-6.36347,4.95418],"type":"Point"}
}