{
  "type": "Feature",
  "properties": {
    "gn:admin1_code":"87",
    "gn:asciiname":"Koro",
    "gn:country_code":"CI",
    "gn:dem":388,
    "gn:feature_class":"P",
    "gn:feature_code":"PPL",
    "gn:name":"Koro",
    "gn:population":0,
    "gn:timezone":"Africa/Abidjan",
    "iso:country":"CI",
    "wof:name":"Koro",
    "wof:placetype":"locality"
},
  "geometry": {"coordinates":[-6.59756,9.89498],"type":"Point"}
}