{
  "type": "Feature",
  "properties": {
    "gn:admin1_code":"90.0",
    "gn:asciiname":"Gberekoro-Noumousso",
    "gn:country_code":"CI",
    "gn:dem":261,
    "gn:feature_class":"P",
    "gn:feature_code":"PPL",
    "gn:name":"Gb\u00e9r\u00e9koro-Noumousso",
    "gn:population":0,
    "gn:timezone":"Africa/Abidjan",
    "iso:country":"CI",
    "name:und_x_variant":[
        "Gb\u00e9r\u00e9koro-Noumousso",
        "Gb\u00e9r\u00e9koro"
    ],
    "wof:name":"Gberekoro-Noumousso",
    "wof:placetype":"locality"
},
  "geometry": {"coordinates":[-4.299,8.27305],"type":"Point"}
}